Workbook
Name Adjusted_Gross_Income: [1]Calc1!$N$66:INDEX([1]Calc1!$N$66:$HH$66,COUNTIF([1]Calc1!$N$66:$HH$66,”<>”&””))
Name AgeAdult: [1]Lists!$F$10:$F$60
Name AgeChild: [1]Lists!$H$10:$H$29
Name CCA_RateCategoryEntireCol: INDEX([1]!CCA_RateCategory[#Data],,CCA_RateCategoryStateColNum)
Name CCA_RateCategoryLookup: INDEX([1]!CCA_RateCategory[#Data],1,CCA_RateCategoryStateColNum):INDEX([1]!CCA_RateCategory[#Data],COUNTA(CCA_RateCategoryEntireCol),CCA_RateCategoryStateColNum)
Name CCA_RateCategoryStateColNum: MATCH(InputStateName,[1]!CCA_RateCategory[#Headers],0)
Name CCA_SettingsEntireCol: INDEX([1]!CCA_Settings[#Data],,CCA_SettingsStateColNum)
Name CCA_SettingsLookup: INDEX([1]!CCA_Settings[#Data],1,CCA_SettingsStateColNum):INDEX([1]!CCA_Settings[#Data],COUNTA(CCA_SettingsEntireCol),CCA_SettingsStateColNum)
Name CCA_SettingsStateColNum: MATCH(InputStateName,[1]!CCA_Settings[#Headers],0)
Name CHIP_GroupLookup1: [1]Calc1!$C$384:$G$391
Name CompareAlabamaAdjusted_Gross_Income: [1]Calc1!$N$66:INDEX([1]Calc1!$N$66:$HH$66,COUNTIF([1]Calc1!$N$66:$HH$66,”<>”&””))
Name CompareAlabamaHousehold_Annual_Earned_Income: [1]Calc1!$N$46:INDEX([1]Calc1!$N$46:$HH$46,COUNTIF([1]Calc1!$N$46:$HH$46,”<>”&””))
Name CompareAlabamaHousehold_Annual_Income: [1]Calc1!$N$50:INDEX([1]Calc1!$N$50:$HH$50,COUNTIF([1]Calc1!$N$50:$HH$50,”<>”&””))
Name CompareAlabamaHousehold_Annual_Unearned_Income: [1]Calc1!$N$48:INDEX([1]Calc1!$N$48:$HH$48,COUNTIF([1]Calc1!$N$48:$HH$48,”<>”&””))
Name CompareAlabamaHousehold_Monthly_Earned_Income: [1]Calc1!$N$45:INDEX([1]Calc1!$N$45:$HH$45,COUNTIF([1]Calc1!$N$45:$HH$45,”<>”&””))
Name CompareAlabamaHousehold_Monthly_Income: [1]Calc1!$N$49:INDEX([1]Calc1!$N$49:$HH$49,COUNTIF([1]Calc1!$N$49:$HH$49,”<>”&””))
Name CompareAlabamaHousehold_Monthly_Unearned_Income: [1]Calc1!$N$47:INDEX([1]Calc1!$N$47:$HH$47,COUNTIF([1]Calc1!$N$47:$HH$47,”<>”&””))
Name CompareAlabamaOutputACTC: [1]Calc1!$N$140:$HF$140
Name CompareAlabamaOutputChildCareSubsidyFinal: [1]Calc1!$N$588:$HF$588
Name CompareAlabamaOutputCHIP: [1]Calc1!$N$419:$HF$419
Name CompareAlabamaOutputComboCashAssistance: CompareAlabamaOutputTANF + CompareAlabamaOutputSSI +CompareAlabamaOutputLIHEAP
Name CompareAlabamaOutputComboFoodAssistance: CompareAlabamaOutputSNAP + CompareAlabamaOutputWIC + CompareAlabamaOutputSubsidizedSchoolMeals
Name CompareAlabamaOutputComboMedicalAssistance: CompareAlabamaOutputMedicaid + CompareAlabamaOutputCHIP + CompareAlabamaOutputHIXPTC
Name CompareAlabamaOutputComboNetEarnings: CompareAlabamaAdjusted_Gross_Income - CompareAlabamaOutputFICA - CompareAlabamaOutputFedTax - CompareAlabamaOutputStateTax
Name CompareAlabamaOutputComboRefundableTaxCredits: CompareAlabamaOutputEITC + CompareAlabamaOutputACTC + CompareAlabamaOutputStateEITC + CompareAlabamaOutputCTC
Name CompareAlabamaOutputCTC: [1]Calc1!$N$108:$HF$108
Name CompareAlabamaOutputEITC: [1]Calc1!$N$122:$HF$122
Name CompareAlabamaOutputFedTax: [1]Calc1!$N$102:$HF$102
Name CompareAlabamaOutputFICA: [1]Calc1!$N$54:$HF$54
Name CompareAlabamaOutputHIXPTC: [1]Calc1!$N$462:$HF$462
Name CompareAlabamaOutputInterval: [1]Calc1!$N$2:$HF$2
Name CompareAlabamaOutputLIHEAP: [1]Calc1!$N$711:$HF$711
Name CompareAlabamaOutputMedicaid: [1]Calc1!$N$375:$HF$375
Name CompareAlabamaOutputMedicaidAndCHIP: CompareAlabamaOutputMedicaid + CompareAlabamaOutputCHIP
Name CompareAlabamaOutputMomHourlyWage: [1]Calc1!$N$10:$HF$10
Name CompareAlabamaOutputMomWeeklyHours: [1]Calc1!$N$5:$HF$5
Name CompareAlabamaOutputSec8Entry: [1]Calc1!$N$685:$HF$685
Name CompareAlabamaOutputSec8Extended: [1]Calc1!$N$690:$HF$690
Name CompareAlabamaOutputSec8Final: [1]Calc1!$N$688:$HF$688
Name CompareAlabamaOutputSNAP: [1]Calc1!$N$313:$HF$313
Name CompareAlabamaOutputSSI: [1]Calc1!$N$280:$HF$280
Name CompareAlabamaOutputStackPlusCashAssistance: CompareAlabamaOutputStackPlusRefundableTaxCredits + CompareAlabamaOutputComboCashAssistance
Name CompareAlabamaOutputStackPlusChildCareFinal: CompareAlabamaOutputStackPlusMedicalAssistance + CompareAlabamaOutputChildCareSubsidyFinal
Name CompareAlabamaOutputStackPlusFoodAssistance: CompareAlabamaOutputStackPlusCashAssistance + CompareAlabamaOutputComboFoodAssistance
Name CompareAlabamaOutputStackPlusHIXPTC: CompareAlabamaOutputStackPlusMedicaidAndCHIP + CompareAlabamaOutputHIXPTC
Name CompareAlabamaOutputStackPlusMedicaidAndCHIP: CompareAlabamaOutputStackPlusFoodAssistance + CompareAlabamaOutputMedicaid + CompareAlabamaOutputCHIP
Name CompareAlabamaOutputStackPlusMedicalAssistance: CompareAlabamaOutputStackPlusFoodAssistance + CompareAlabamaOutputComboMedicalAssistance
Name CompareAlabamaOutputStackPlusRefundableTaxCredits: CompareAlabamaOutputComboNetEarnings+CompareAlabamaOutputComboRefundableTaxCredits
Name CompareAlabamaOutputStackPlusSec8Entry: CompareAlabamaOutputStackPlusChildCareFinal + CompareAlabamaOutputSec8Entry
Name CompareAlabamaOutputStackPlusSec8Entry_Graph: CompareAlabamaOutputStackPlusChildCareFinal + CompareAlabamaOutputSec8Final
Name CompareAlabamaOutputStackPlusSec8Extended: CompareAlabamaOutputStackPlusSec8Entry + CompareAlabamaOutputSec8Extended
Name CompareAlabamaOutputStateEITC: [1]Calc1!$N$221:$HF$221
Name CompareAlabamaOutputStateTax: [1]Calc1!$N$206:$HF$206
Name CompareAlabamaOutputSubsidizedSchoolMeals: [1]Calc1!$N$346:$HF$346
Name CompareAlabamaOutputTANF: [1]Calc1!$N$267:$HF$267
Name CompareAlabamaOutputWIC: [1]Calc1!$N$335:$HF$335
Name CompareFloridaAdjusted_Gross_Income: [1]Calc1!$N$66:INDEX([1]Calc1!$N$66:$HH$66,COUNTIF([1]Calc1!$N$66:$HH$66,”<>”&””))
Name CompareFloridaHousehold_Annual_Earned_Income: [1]Calc1!$N$46:INDEX([1]Calc1!$N$46:$HH$46,COUNTIF([1]Calc1!$N$46:$HH$46,”<>”&””))
Name CompareFloridaHousehold_Annual_Income: [1]Calc1!$N$50:INDEX([1]Calc1!$N$50:$HH$50,COUNTIF([1]Calc1!$N$50:$HH$50,”<>”&””))
Name CompareFloridaHousehold_Annual_Unearned_Income: [1]Calc1!$N$48:INDEX([1]Calc1!$N$48:$HH$48,COUNTIF([1]Calc1!$N$48:$HH$48,”<>”&””))

Sheet BLS Data
A1: Chained Consumer Price Index for All Urban Consumers (C-CPI-U): U.S. city average | R1: Chained Consumer Price Index for All Urban Consumers (C-CPI-U): U.S. city average
A2: Original Data Value | R2: Original Data Value
A4: Series Id: | B4: SUUR0000SAM2 | R4: Series Id: | S4: SUUR0000SAM
A5: Not Seasonally Adjusted | R5: Not Seasonally Adjusted
A6: Series Title: | B6: Medical care services in U.S. city average, all urban consumers, chained, not seasonally adjusted | R6: Series Title: | S6: Medical care in U.S. city average, all urban consumers, chained, not seasonally adjusted
A7: Area: | B7: U.S. city average | R7: Area: | S7: U.S. city average
A8: Item: | B8: Medical care services | R8: Item: | S8: Medical care
A9: Base Period: | B9: DECEMBER 1999=100 | R9: Base Period: | S9: DECEMBER 1999=100
A10: Years: | B10: 2014 to 2024 | R10: Years: | S10: 2014 to 2024
A12: Year | B12: Jan | C12: Feb | D12: Mar | E12: Apr | F12: May | G12: Jun | H12: Jul | I12: Aug | J12: Sep | K12: Oct | L12: Nov | M12: Dec | O12: average | R12: Year | S12: Jan | T12: Feb | U12: Mar | V12: Apr | W12: May | X12: Jun | Y12: Jul | Z12: Aug | AA12: Sep | AB12: Oct | AC12: Nov | AD12: Dec
A13: 2014 | B13: 175.801 | C13: 177.026 | D13: 177.383 | E13: 177.591 | F13: 177.864 | G13: 177.776 | H13: 177.864 | I13: 177.683 | J13: 177.877 | K13: 178.116 | L13: 178.616 | M13: 178.971 | R13: 2014 | S13: 166.347 | T13: 167.597 | U13: 167.763 | V13: 168.027 | W13: 168.332 | X13: 168.445 | Y13: 168.638 | Z13: 168.514 | AA13: 168.83 | AB13: 169.01 | AC13: 169.508 | AD13: 169.993
A14: 2015 | B14: 179.709 | C14: 179.793 | D14: 180.654 | E14: 182.094 | F14: 182.266 | G14: 181.666 | H14: 181.737 | I14: 181.491 | J14: 182.003 | K14: 183.585 | L14: 184.206 | M14: 184.243 | R14: 2015 | S14: 170.609 | T14: 171.039 | U14: 171.719 | V14: 172.838 | W14: 172.991 | X14: 172.506 | Y14: 172.628 | Z14: 172.579 | AA14: 172.909 | AB14: 174.109 | AC14: 174.612 | AD14: 174.5
A15: 2016 | B15: 185.643 | C15: 187.13 | D15: 187.256 | E15: 187.711 | F15: 188.724 | G15: 188.842 | H15: 189.511 | I15: 190.87 | J15: 190.979 | K15: 190.989 | L15: 191.338 | M15: 191.41 | R15: 2016 | S15: 175.772 | T15: 177.273 | U15: 177.437 | V15: 177.869 | W15: 178.388 | X15: 178.74 | Y15: 179.489 | Z15: 181.028 | AA15: 181.294 | AB15: 181.302 | AC15: 181.35 | AD15: 181.416
A16: 2017 | B16: 192.249 | C16: 193.405 | D16: 193.393 | E16: 193.209 | F16: 193.121 | G16: 193.094 | H16: 193.442 | I16: 193.81 | J16: 194.081 | K16: 194.454 | L16: 194.305 | M16: 194.34 | R16: 2017 | S16: 182.282 | T16: 183.309 | U16: 183.328 | V16: 182.9 | W16: 182.86 | X16: 183.042 | Y16: 183.624 | Z16: 183.999 | AA16: 183.942 | AB16: 184.159 | AC16: 184.147 | AD16: 184.317
A17: 2018 | B17: 195.67 | C17: 196.37 | D17: 196.971 | E17: 197.158 | F17: 197.064 | G17: 197.44 | H17: 197.346 | I17: 196.741 | J17: 197.173 | K17: 197.547 | L17: 198.14 | M17: 198.677 | R17: 2018 | S17: 185.361 | T17: 186.032 | U17: 186.483 | V17: 186.525 | W17: 186.736 | X17: 187.148 | Y17: 186.798 | Z17: 186.317 | AA17: 186.506 | AB17: 186.73 | AC17: 187.271 | AD17: 187.441
A18: 2019 | B18: 199.81 | C18: 200.645 | D18: 200.906 | E18: 201.088 | F18: 201.919 | G18: 202.404 | H18: 203.241 | I18: 204.427 | J18: 205.033 | K18: 206.483 | L18: 207.155 | M18: 207.516 | R18: 2019 | S18: 188.415 | T18: 188.896 | U18: 189.21 | V18: 189.513 | W18: 190.157 | X18: 190.43 | Y18: 191.158 | Z18: 192.296 | AA18: 192.449 | AB18: 193.749 | AC18: 194.233 | AD18: 194.678
A19: 2020 | B19: 208.707 | C19: 209.641 | D19: 210.279 | E19: 210.883 | F19: 211.658 | G19: 212.323 | H19: 213.148 | I19: 213.237 | J19: 213.369 | K19: 212.915 | L19: 212.842 | M19: 212.575 | P19: Factor | R19: 2020 | S19: 195.414 | T19: 196.045 | U19: 196.531 | V19: 196.899 | W19: 197.531 | X19: 198.025 | Y19: 198.661 | Z19: 198.805 | AA19: 198.674 | AB19: 198.093 | AC19: 197.832 | AD19: 197.529 | AG19: Factor | AH19: FFY | AI19: CY | AJ19: Factor
A20: 2021 | B20: 214.466 | C20: 216.05 | D20: 216.423 | E20: 216.131 | F20: 215.874 | G20: 215.69 | H20: 216.346 | I20: 216.926 | J20: 216.643 | K20: 217.606 | L20: 218.099 | M20: 218.536 | O20: =AVERAGE(B20:M20) -> 216.56583 | R20: 2021 | S20: 198.949 | T20: 199.923 | U20: 200.211 | V20: 200.139 | W20: 199.982 | X20: 199.718 | Y20: 200.284 | Z20: 200.66 | AA20: 200.573 | AB20: 201.478 | AC20: 201.882 | AD20: 202.283 | AF20: =AVERAGE(S18:AD18) -> 191.26533 | AH20: =AVERAGE(AB17:AD17,S18:AA18) -> 189.49717 | AI20: =AVERAGE(S18:AD18) -> 191.26533 | AJ20: =AI20/AH$22 -> 0.95876633 | AK20: 2019
A21: 2022 | B21: 220.691 | C21: 221.538 | D21: 222.771 | E21: 223.611 | F21: 224.479 | G21: 225.725 | H21: 226.769 | I21: 228.648 | J21: 230.049 | K21: 228.914 | L21: 227.214 | M21: 226.996 | O21: =AVERAGE(B21:M21) -> 225.61708 | R21: 2022 | S21: 204.148 | T21: 204.917 | U21: 205.993 | V21: 206.67 | W21: 207.439 | X21: 208.532 | Y21: 209.562 | Z21: 211.077 | AA21: 212.052 | AB21: 211.173 | AC21: 209.973 | AD21: 209.862 | AF21: =AVERAGE(S19:AD19) -> 197.50325 | AH21: =AVERAGE(AB18:AD18,S19:AA19) -> 196.60375 | AI21: =AVERAGE(S19:AD19) -> 197.50325 | AJ21: =AI21/AH$22 -> 0.99003548 | AK21: 2020
A22: 2023 | B22: 226.763 | C22: 225.502 | D22: 223.901 | E22: 223.119 | F22: 222.705 | G22: 222.378 | H22: 221.638 | I22: 221.872 | J22: 222.017 | K22: 222.399 | L22: 223.184 | M22: 224.051 | O22: =AVERAGE(B22:M22) -> 223.29408 | P22: =O22/O20 -> 1.0310679 | R22: 2023 | S22: 210.103 | T22: 209.225 | U22: 208.283 | V22: 207.907 | W22: 207.908 | X22: 207.813 | Y22: 207.439 | Z22: 207.827 | AA22: 207.814 | AB22: 208.256 | AC22: 209.022 | AD22: 209.637 | AF22: =AVERAGE(S20:AD20) -> 200.50683 | AH22: =AVERAGE(AB19:AD19,S20:AA20) -> 199.49108 | AI22: =AVERAGE(S20:AD20) -> 200.50683 | AJ22: =AI22/AH$22 -> 1.0050917 | AK22: 2021
A23: 2024 | B23: 226.252 | C23: 226.175 | D23: 227.485 | E23: 228.095 | F23: 228.74 | G23: 229.161 | R23: 2024 | S23: 211.079 | T23: 211.052 | U23: 212.119 | V23: 212.753 | W23: 213.741 | X23: 214.134 | AF23: =AVERAGE(S21:AD21) -> 208.44983 | AI23: =AVERAGE(S21:AD21) -> 208.44983 | AJ23: =AI23/AH$22 -> 1.044908 | AK23: 2022
AF24: =AVERAGE(S22:AD22) -> 208.43617 | AG24: =AF24/AF22 -> 1.0395464 | AI24: =AVERAGE(S22:AD22) -> 208.43617 | AJ24: =AI24/AH$22 -> 1.0448395 | AK24: 2023
AH25: Projected | AI25: =(X23/S23)^(1/6) -> 1.0023978 | AJ25: =AI25^12*AJ24 -> 1.0753028 | AK25: 2024

Sheet Mcaid
A1: Mcaid | B1: Medicaid
B3: Statute
C4: 42 U.S. Code Chapter 7 - Social Secuirty Subchapter XIX— Grants to States for Medical Assistance Programs
C5: https://www.law.cornell.edu/uscode/text/42/chapter-7/subchapter-XIX
B7: Federal Administration
C8: U.S. Department of Health and Human Services
C9: Center for Medicare and Medicaid Services (CMS)
C10: Medicaid.Gov
C11: https://www.medicaid.gov | F11: 2019 | G11: 2020 | H11: 2021 | I11: 2022 | J11: 2023
E12: Effective Date | F12: 43556 | G12: 43556 | H12: 44105 | I12: 44743 | J12: 44743
B13: Lookup Table: MedicaidIncomeEligibility
C15: State | D15: Year | E15: Children Medicaid Ages 0 | F15: Children Medicaid Ages 1-5 | G15: Children Medicaid Ages 6-18 | H15: Children Separate CHIP | I15: Pregnant Women Medicaid | J15: Pregnant Women CHIP | K15: Adults (Medicaid) Parent/Caretaker | L15: Adults (Medicaid) Expansion to Adults
C16: Alabama | D16: 2019 | E16: 1.41 | F16: 1.41 | G16: 1.41 | H16: 3.12 | I16: 1.41 | J16: N/A | K16: 0.13 | L16: No
C17: Alaska | D17: 2019 | E17: 2.03 | F17: 2.03 | G17: 2.03 | H17: N/A | I17: 2 | J17: N/A | K17: 1.35 | L17: 1.33
C18: Arizona | D18: 2019 | E18: 1.47 | F18: 1.41 | G18: 1.33 | H18: 2 | I18: 1.56 | J18: N/A | K18: 1.06 | L18: 1.33
C19: Arkansas | D19: 2019 | E19: 1.42 | F19: 1.42 | G19: 1.42 | H19: 2.11 | I19: 2.09 | J19: N/A | K19: 0.17 | L19: 1.33
C20: California | D20: 2019 | E20: 2.61 | F20: 2.61 | G20: 2.61 | H20: N/A | I20: 2.08 | J20: N/A | K20: 1.09 | L20: 1.33
C21: Colorado | D21: 2019 | E21: 1.42 | F21: 1.42 | G21: 1.42 | H21: 2.6 | I21: 1.95 | J21: 2.6 | K21: 0.68 | L21: 1.33
C22: Connecticut | D22: 2019 | E22: 1.96 | F22: 1.96 | G22: 1.96 | H22: 3.18 | I22: 2.58 | J22: N/A | K22: 1.5 | L22: 1.33
C23: Delaware | D23: 2019 | E23: 2.12 | F23: 1.42 | G23: 1.33 | H23: 2.12 | I23: 2.12 | J23: N/A | K23: 0.87 | L23: 1.33
C24: District of Columbia | D24: 2019 | E24: 3.19 | F24: 3.19 | G24: 3.19 | H24: N/A | I24: 3.19 | J24: N/A | K24: 2.16 | L24: 2.1
C25: Florida | D25: 2019 | E25: 2.06 | F25: 1.4 | G25: 1.33 | H25: 2.1 | I25: 1.91 | J25: N/A | K25: 0.28 | L25: No
C26: Georgia | D26: 2019 | E26: 2.05 | F26: 1.49 | G26: 1.33 | H26: 2.47 | I26: 2.2 | J26: N/A | K26: 0.32 | L26: No
C27: Hawaii | D27: 2019 | E27: 3.08 | F27: 3.08 | G27: 3.08 | H27: N/A | I27: 1.91 | J27: N/A | K27: 1.05 | L27: 1.33
C28: Idaho | D28: 2019 | E28: 1.42 | F28: 1.42 | G28: 1.33 | H28: 1.85 | I28: 1.33 | J28: N/A | K28: 0.23 | L28: No
C29: Illinois | D29: 2019 | E29: 1.42 | F29: 1.42 | G29: 1.42 | H29: 3.13 | I29: 2.08 | J29: N/A | K29: 1.33 | L29: 1.33
C30: Indiana | D30: 2019 | E30: 2.08 | F30: 1.58 | G30: 1.58 | H30: 2.5 | I30: 2.08 | J30: N/A | K30: 0.19 | L30: 1.33
C31: Iowa | D31: 2019 | E31: 3.75 | F31: 1.67 | G31: 1.67 | H31: 3.02 | I31: 3.75 | J31: N/A | K31: 0.51 | L31: 1.33
C32: Kansas | D32: 2019 | E32: 1.66 | F32: 1.49 | G32: 1.33 | H32: 2.3 | I32: 1.66 | J32: N/A | K32: 0.33 | L32: No
C33: Kentucky | D33: 2019 | E33: 1.95 | F33: 1.59 | G33: 1.59 | H33: 2.13 | I33: 1.95 | J33: N/A | K33: 0.24 | L33: 1.33
C34: Louisiana | D34: 2019 | E34: 2.12 | F34: 2.12 | G34: 2.12 | H34: 2.5 | I34: 1.33 | J34: N/A | K34: 0.19 | L34: 1.33
C35: Maine | D35: 2019 | E35: 1.91 | F35: 1.57 | G35: 1.57 | H35: 2.08 | I35: 2.09 | J35: N/A | K35: 1 | L35: Yes
C36: Maryland | D36: 2019 | E36: 3.17 | F36: 3.17 | G36: 3.17 | H36: N/A | I36: 2.59 | J36: N/A | K36: 1.23 | L36: 1.33
C37: Massachusetts | D37: 2019 | E37: 2 | F37: 1.5 | G37: 1.5 | H37: 3 | I37: 2 | J37: N/A | K37: 1.33 | L37: 1.33
C38: Michigan | D38: 2019 | E38: 2.12 | F38: 2.12 | G38: 2.12 | H38: N/A | I38: 1.95 | J38: N/A | K38: 0.54 | L38: 1.33
C39: Minnesota | D39: 2019 | E39: 2.83 | F39: 2.75 | G39: 2.75 | H39: N/A | I39: 2.78 | J39: N/A | K39: 1.33 | L39: 2
C40: Mississippi | D40: 2019 | E40: 1.94 | F40: 1.43 | G40: 1.33 | H40: 2.09 | I40: 1.94 | J40: N/A | K40: 0.23 | L40: No
C41: Missouri | D41: 2019 | E41: 1.96 | F41: 1.5 | G41: 1.5 | H41: 3 | I41: 1.96 | J41: 3 | K41: 0.17 | L41: No
C42: Montana | D42: 2019 | E42: 1.43 | F42: 1.43 | G42: 1.43 | H42: 2.61 | I42: 1.57 | J42: N/A | K42: 0.24 | L42: 1.33
C43: Nebraska | D43: 2019 | E43: 2.13 | F43: 2.13 | G43: 2.13 | H43: N/A | I43: 1.94 | J43: N/A | K43: 0.58 | L43: No
C44: Nevada | D44: 2019 | E44: 1.6 | F44: 1.6 | G44: 1.33 | H44: 2 | I44: 1.6 | J44: N/A | K44: 0.31 | L44: 1.33
C45: New Hampshire | D45: 2019 | E45: 3.18 | F45: 3.18 | G45: 3.18 | H45: N/A | I45: 1.96 | J45: N/A | K45: 0.64 | L45: 1.33
C46: New Jersey | D46: 2019 | E46: 1.94 | F46: 1.42 | G46: 1.42 | H46: 3.5 | I46: 1.94 | J46: 2 | K46: 0.3 | L46: 1.33
C47: New Mexico | D47: 2019 | E47: 3 | F47: 3 | G47: 2.4 | H47: N/A | I47: 2.5 | J47: N/A | K47: 0.43 | L47: 1.33
C48: New York | D48: 2019 | E48: 2.18 | F48: 1.49 | G48: 1.49 | H48: 4 | I48: 2.18 | J48: N/A | K48: 1.33 | L48: 2
C49: North Carolina | D49: 2019 | E49: 2.1 | F49: 2.1 | G49: 1.33 | H49: 2.11 | I49: 1.96 | J49: N/A | K49: 0.42 | L49: No
C50: North Dakota | D50: 2019 | E50: 1.47 | F50: 1.47 | G50: 1.33 | H50: 1.7 | I50: 1.47 | J50: N/A | K50: 0.5 | L50: 1.33
C51: Ohio | D51: 2019 | E51: 2.06 | F51: 2.06 | G51: 2.06 | H51: N/A | I51: 2 | J51: N/A | K51: 0.9 | L51: 1.33
C52: Oklahoma | D52: 2019 | E52: 2.05 | F52: 2.05 | G52: 2.05 | H52: N/A | I52: 1.33 | J52: N/A | K52: 0.39 | L52: No
C53: Oregon | D53: 2019 | E53: 1.85 | F53: 1.33 | G53: 1.33 | H53: 3 | I53: 1.85 | J53: N/A | K53: 0.38 | L53: 1.33
C54: Pennsylvania | D54: 2019 | E54: 2.15 | F54: 1.57 | G54: 1.33 | H54: 3.14 | I54: 2.15 | J54: N/A | K54: 0.33 | L54: 1.33
C55: Rhode Island | D55: 2019 | E55: 2.61 | F55: 2.61 | G55: 2.61 | H55: N/A | I55: 1.9 | J55: 2.53 | K55: 1.16 | L55: 1.33
C56: South Carolina | D56: 2019 | E56: 2.08 | F56: 2.08 | G56: 2.08 | H56: N/A | I56: 1.94 | J56: N/A | K56: 0.62 | L56: No
C57: South Dakota | D57: 2019 | E57: 1.82 | F57: 1.82 | G57: 1.82 | H57: 2.04 | I57: 1.33 | J57: N/A | K57: 0.54 | L57: No
C58: Tennessee | D58: 2019 | E58: 1.95 | F58: 1.42 | G58: 1.33 | H58: 2.5 | I58: 1.95 | J58: N/A | K58: 0.98 | L58: No
C59: Texas | D59: 2019 | E59: 1.98 | F59: 1.44 | G59: 1.33 | H59: 2.01 | I59: 1.98 | J59: N/A | K59: 0.15 | L59: No
C60: Utah | D60: 2019 | E60: 1.39 | F60: 1.39 | G60: 1.33 | H60: 2 | I60: 1.39 | J60: N/A | K60: 0.42 | L60: 0.95
C61: Vermont | D61: 2019 | E61: 3.12 | F61: 3.12 | G61: 3.12 | H61: N/A | I61: 2.08 | J61: N/A | K61: 0.52 | L61: 1.33
C62: Virginia | D62: 2019 | E62: 1.43 | F62: 1.43 | G62: 1.43 | H62: 2 | I62: 1.43 | J62: 2 | K62: 0.47 | L62: Yes
C63: Washington | D63: 2019 | E63: 2.1 | F63: 2.1 | G63: 2.1 | H63: 3.12 | I63: 1.93 | J63: N/A | K63: 0.4 | L63: 1.33
C64: West Virginia | D64: 2019 | E64: 1.58 | F64: 1.41 | G64: 1.33 | H64: 3 | I64: 1.58 | J64: N/A | K64: 0.18 | L64: 1.33
C65: Wisconsin | D65: 2019 | E65: 3.01 | F65: 1.86 | G65: 1.51 | H65: 3.01 | I65: 3.01 | J65: N/A | K65: 0.95 | L65: No
C66: Wyoming | D66: 2019 | E66: 1.54 | F66: 1.54 | G66: 1.33 | H66: 2 | I66: 1.54 | J66: N/A | K66: 0.52 | L66: No
C67: United States | D67: 2019 | E67: 2.13 | F67: 1.855 | G67: 1.791 | H67: 1.861 | I67: 2.023 | J67: N/A | K67: 0.719 | L67: 1.33
C68: Alabama | D68: 2020 | E68: 1.41 | F68: 1.41 | G68: 1.41 | H68: 3.12 | I68: 1.41 | J68: N/A | K68: 0.13 | L68: No
C69: Alaska | D69: 2020 | E69: 2.03 | F69: 2.03 | G69: 2.03 | H69: N/A | I69: 2 | J69: N/A | K69: 1.35 | L69: 1.33
C70: Arizona | D70: 2020 | E70: 1.47 | F70: 1.41 | G70: 1.33 | H70: 2 | I70: 1.56 | J70: N/A | K70: 1.06 | L70: 1.33
C71: Arkansas | D71: 2020 | E71: 1.42 | F71: 1.42 | G71: 1.42 | H71: 2.11 | I71: 2.09 | J71: N/A | K71: 0.17 | L71: 1.33
C72: California | D72: 2020 | E72: 2.61 | F72: 2.61 | G72: 2.61 | H72: N/A | I72: 2.08 | J72: N/A | K72: 1.09 | L72: 1.33
C73: Colorado | D73: 2020 | E73: 1.42 | F73: 1.42 | G73: 1.42 | H73: 2.6 | I73: 1.95 | J73: 2.6 | K73: 0.68 | L73: 1.33
C74: Connecticut | D74: 2020 | E74: 1.96 | F74: 1.96 | G74: 1.96 | H74: 3.18 | I74: 2.58 | J74: N/A | K74: 1.5 | L74: 1.33
C75: Delaware | D75: 2020 | E75: 2.12 | F75: 1.42 | G75: 1.33 | H75: 2.12 | I75: 2.12 | J75: N/A | K75: 0.87 | L75: 1.33
C76: District of Columbia | D76: 2020 | E76: 3.19 | F76: 3.19 | G76: 3.19 | H76: N/A | I76: 3.19 | J76: N/A | K76: 2.16 | L76: 2.1
C77: Florida | D77: 2020 | E77: 2.06 | F77: 1.4 | G77: 1.33 | H77: 2.1 | I77: 1.91 | J77: N/A | K77: 0.28 | L77: No
C78: Georgia | D78: 2020 | E78: 2.05 | F78: 1.49 | G78: 1.33 | H78: 2.47 | I78: 2.2 | J78: N/A | K78: 0.32 | L78: No
C79: Hawaii | D79: 2020 | E79: 3.08 | F79: 3.08 | G79: 3.08 | H79: N/A | I79: 1.91 | J79: N/A | K79: 1.05 | L79: 1.33
C80: Idaho | D80: 2020 | E80: 1.42 | F80: 1.42 | G80: 1.33 | H80: 1.85 | I80: 1.33 | J80: N/A | K80: 0.23 | L80: No
C81: Illinois | D81: 2020 | E81: 1.42 | F81: 1.42 | G81: 1.42 | H81: 3.13 | I81: 2.08 | J81: N/A | K81: 1.33 | L81: 1.33
C82: Indiana | D82: 2020 | E82: 2.08 | F82: 1.58 | G82: 1.58 | H82: 2.5 | I82: 2.08 | J82: N/A | K82: 0.19 | L82: 1.33
C83: Iowa | D83: 2020 | E83: 3.75 | F83: 1.67 | G83: 1.67 | H83: 3.02 | I83: 3.75 | J83: N/A | K83: 0.51 | L83: 1.33
C84: Kansas | D84: 2020 | E84: 1.66 | F84: 1.49 | G84: 1.33 | H84: 2.3 | I84: 1.66 | J84: N/A | K84: 0.33 | L84: No
C85: Kentucky | D85: 2020 | E85: 1.95 | F85: 1.59 | G85: 1.59 | H85: 2.13 | I85: 1.95 | J85: N/A | K85: 0.24 | L85: 1.33
C86: Louisiana | D86: 2020 | E86: 2.12 | F86: 2.12 | G86: 2.12 | H86: 2.5 | I86: 1.33 | J86: N/A | K86: 0.19 | L86: 1.33
C87: Maine | D87: 2020 | E87: 1.91 | F87: 1.57 | G87: 1.57 | H87: 2.08 | I87: 2.09 | J87: N/A | K87: 1 | L87: Yes
C88: Maryland | D88: 2020 | E88: 3.17 | F88: 3.17 | G88: 3.17 | H88: N/A | I88: 2.59 | J88: N/A | K88: 1.23 | L88: 1.33
C89: Massachusetts | D89: 2020 | E89: 2 | F89: 1.5 | G89: 1.5 | H89: 3 | I89: 2 | J89: N/A | K89: 1.33 | L89: 1.33
C90: Michigan | D90: 2020 | E90: 2.12 | F90: 2.12 | G90: 2.12 | H90: N/A | I90: 1.95 | J90: N/A | K90: 0.54 | L90: 1.33
C91: Minnesota | D91: 2020 | E91: 2.83 | F91: 2.75 | G91: 2.75 | H91: N/A | I91: 2.78 | J91: N/A | K91: 1.33 | L91: 2
C92: Mississippi | D92: 2020 | E92: 1.94 | F92: 1.43 | G92: 1.33 | H92: 2.09 | I92: 1.94 | J92: N/A | K92: 0.21 | L92: No
C93: Missouri | D93: 2020 | E93: 1.96 | F93: 1.5 | G93: 1.5 | H93: 3 | I93: 1.96 | J93: 3 | K93: 0.17 | L93: No
C94: Montana | D94: 2020 | E94: 1.43 | F94: 1.43 | G94: 1.43 | H94: 2.61 | I94: 1.57 | J94: N/A | K94: 0.24 | L94: 1.33
C95: Nebraska | D95: 2020 | E95: 2.13 | F95: 2.13 | G95: 2.13 | H95: N/A | I95: 1.94 | J95: N/A | K95: 0.58 | L95: No
C96: Nevada | D96: 2020 | E96: 1.6 | F96: 1.6 | G96: 1.33 | H96: 2 | I96: 1.6 | J96: N/A | K96: 0.31 | L96: 1.33
C97: New Hampshire | D97: 2020 | E97: 3.18 | F97: 3.18 | G97: 3.18 | H97: N/A | I97: 1.96 | J97: N/A | K97: 0.64 | L97: 1.33
C98: New Jersey | D98: 2020 | E98: 1.94 | F98: 1.42 | G98: 1.42 | H98: 3.5 | I98: 1.94 | J98: 2 | K98: 0.3 | L98: 1.33
C99: New Mexico | D99: 2020 | E99: 3 | F99: 3 | G99: 2.4 | H99: N/A | I99: 2.5 | J99: N/A | K99: 0.43 | L99: 1.33
C100: New York | D100: 2020 | E100: 2.18 | F100: 1.49 | G100: 1.49 | H100: 4 | I100: 2.18 | J100: N/A | K100: 1.33 | L100: 2
C101: North Carolina | D101: 2020 | E101: 2.1 | F101: 2.1 | G101: 1.33 | H101: 2.11 | I101: 1.96 | J101: N/A | K101: 0.42 | L101: No
C102: North Dakota | D102: 2020 | E102: 1.47 | F102: 1.47 | G102: 1.33 | H102: 1.7 | I102: 1.47 | J102: N/A | K102: 0.5 | L102: 1.33
C103: Ohio | D103: 2020 | E103: 2.06 | F103: 2.06 | G103: 2.06 | H103: N/A | I103: 2 | J103: N/A | K103: 0.9 | L103: 1.33
...

Sheet Cliff WB PMPM
A1: State | B1: Year | C1: Total | D1: Child | E1: Expansion Adults | F1: Adults | G1: Disabled | H1: Aged
A2: National | B2: 2019 | C2: =ROUND(C54/'BLS Data'!$AJ$20,2) -> 809.61 | D2: =ROUND(D54/'BLS Data'!$AJ$20,2) -> 316.84 | E2: =ROUND(E54/'BLS Data'!$AJ$20,2) -> 662.48 | F2: =ROUND(F54/'BLS Data'!$AJ$20,2) -> 563.71 | G2: =ROUND(G54/'BLS Data'!$AJ$20,2) -> 2361.43 | H2: =ROUND(H54/'BLS Data'!$AJ$20,2) -> 2139.49
A3: Alabama | B3: 2019 | C3: =ROUND(C55/'BLS Data'!$AJ$20,2) -> 604.27 | D3: =ROUND(D55/'BLS Data'!$AJ$20,2) -> 233.01 | E3: N/A | F3: =ROUND(F55/'BLS Data'!$AJ$20,2) -> 444.05 | G3: =ROUND(G55/'BLS Data'!$AJ$20,2) -> 1540.14 | H3: =ROUND(H55/'BLS Data'!$AJ$20,2) -> 2139.49
A4: Alaska | B4: 2019 | C4: =ROUND(C56/'BLS Data'!$AJ$20,2) -> 801.46 | D4: =ROUND(D56/'BLS Data'!$AJ$20,2) -> 450.9 | E4: =ROUND(E56/'BLS Data'!$AJ$20,2) -> 724.02 | F4: =ROUND(F56/'BLS Data'!$AJ$20,2) -> 625.87 | G4: =ROUND(G56/'BLS Data'!$AJ$20,2) -> 2885.2 | H4: =ROUND(H56/'BLS Data'!$AJ$20,2) -> 2010.88
A5: Arizona | B5: 2019 | C5: =ROUND(C57/'BLS Data'!$AJ$20,2) -> 787.15 | D5: =ROUND(D57/'BLS Data'!$AJ$20,2) -> 316.23 | E5: =ROUND(E57/'BLS Data'!$AJ$20,2) -> 848.25 | F5: =ROUND(F57/'BLS Data'!$AJ$20,2) -> 611.47 | G5: =ROUND(G57/'BLS Data'!$AJ$20,2) -> 2793.45 | H5: =ROUND(H57/'BLS Data'!$AJ$20,2) -> 1101.61
A6: Arkansas | B6: 2019 | C6: =ROUND(C58/'BLS Data'!$AJ$20,2) -> 692.68 | D6: =ROUND(D58/'BLS Data'!$AJ$20,2) -> 358.37 | E6: =ROUND(E58/'BLS Data'!$AJ$20,2) -> 634.47 | F6: =ROUND(F58/'BLS Data'!$AJ$20,2) -> 525.61 | G6: =ROUND(G58/'BLS Data'!$AJ$20,2) -> 1651.02 | H6: =ROUND(H58/'BLS Data'!$AJ$20,2) -> 1929.05
A7: California | B7: 2019 | C7: =ROUND(C59/'BLS Data'!$AJ$20,2) -> 777.49 | D7: =ROUND(D59/'BLS Data'!$AJ$20,2) -> 324.22 | E7: =ROUND(E59/'BLS Data'!$AJ$20,2) -> 549.06 | F7: =ROUND(F59/'BLS Data'!$AJ$20,2) -> 578.98 | G7: =ROUND(G59/'BLS Data'!$AJ$20,2) -> 2792.66 | H7: =ROUND(H59/'BLS Data'!$AJ$20,2) -> 1527.49
A8: Colorado | B8: 2019 | C8: =ROUND(C60/'BLS Data'!$AJ$20,2) -> 673.19 | D8: =ROUND(D60/'BLS Data'!$AJ$20,2) -> 273.12 | E8: =ROUND(E60/'BLS Data'!$AJ$20,2) -> 506.73 | F8: =ROUND(F60/'BLS Data'!$AJ$20,2) -> 505.76 | G8: =ROUND(G60/'BLS Data'!$AJ$20,2) -> 2957.89 | H8: =ROUND(H60/'BLS Data'!$AJ$20,2) -> 2711.11
A9: Connecticut | B9: 2019 | C9: =ROUND(C61/'BLS Data'!$AJ$20,2) -> 816.12 | D9: =ROUND(D61/'BLS Data'!$AJ$20,2) -> 314.74 | E9: =ROUND(E61/'BLS Data'!$AJ$20,2) -> 646.32 | F9: =ROUND(F61/'BLS Data'!$AJ$20,2) -> 510.86 | G9: =ROUND(G61/'BLS Data'!$AJ$20,2) -> 4940.59 | H9: =ROUND(H61/'BLS Data'!$AJ$20,2) -> 3845.56
A10: Delaware | B10: 2019 | C10: =ROUND(C62/'BLS Data'!$AJ$20,2) -> 871.52 | D10: =ROUND(D62/'BLS Data'!$AJ$20,2) -> 401.12 | E10: =ROUND(E62/'BLS Data'!$AJ$20,2) -> 708.66 | F10: =ROUND(F62/'BLS Data'!$AJ$20,2) -> 821.73 | G10: =ROUND(G62/'BLS Data'!$AJ$20,2) -> 3008.99 | H10: =ROUND(H62/'BLS Data'!$AJ$20,2) -> 3363.23
A11: District of Columbia | B11: 2019 | C11: =ROUND(C63/'BLS Data'!$AJ$20,2) -> 1135.76 | D11: =ROUND(D63/'BLS Data'!$AJ$20,2) -> 414.55 | E11: =ROUND(E63/'BLS Data'!$AJ$20,2) -> 635.79 | F11: =ROUND(F63/'BLS Data'!$AJ$20,2) -> 622.01 | G11: =ROUND(G63/'BLS Data'!$AJ$20,2) -> 3793.32 | H11: =ROUND(H63/'BLS Data'!$AJ$20,2) -> 3437.24
A12: Florida | B12: 2019 | C12: =ROUND(C64/'BLS Data'!$AJ$20,2) -> 540.36 | D12: =ROUND(D64/'BLS Data'!$AJ$20,2) -> 221.32 | E12: N/A | F12: =ROUND(F64/'BLS Data'!$AJ$20,2) -> 336.51 | G12: =ROUND(G64/'BLS Data'!$AJ$20,2) -> 1593.51 | H12: =ROUND(H64/'BLS Data'!$AJ$20,2) -> 1539.26
A13: Georgia | B13: 2019 | C13: =ROUND(C65/'BLS Data'!$AJ$20,2) -> 514.45 | D13: =ROUND(D65/'BLS Data'!$AJ$20,2) -> 217.99 | E13: N/A | F13: =ROUND(F65/'BLS Data'!$AJ$20,2) -> 431.86 | G13: =ROUND(G65/'BLS Data'!$AJ$20,2) -> 1450.85 | H13: =ROUND(H65/'BLS Data'!$AJ$20,2) -> 1837.31
A14: Hawaii | B14: 2019 | C14: =ROUND(C66/'BLS Data'!$AJ$20,2) -> 639.48 | D14: =ROUND(D66/'BLS Data'!$AJ$20,2) -> 321.58 | E14: =ROUND(E66/'BLS Data'!$AJ$20,2) -> 545.11 | F14: =ROUND(F66/'BLS Data'!$AJ$20,2) -> 481.89 | G14: =ROUND(G66/'BLS Data'!$AJ$20,2) -> 2419.56 | H14: =ROUND(H66/'BLS Data'!$AJ$20,2) -> 1439.27
A15: Idaho | B15: 2019 | C15: =ROUND(C67/'BLS Data'!$AJ$20,2) -> 690.66 | D15: =ROUND(D67/'BLS Data'!$AJ$20,2) -> 277.25 | E15: =ROUND(E67/'BLS Data'!$AJ$20,2) -> 539.39 | F15: =ROUND(F67/'BLS Data'!$AJ$20,2) -> 561.61 | G15: =ROUND(G67/'BLS Data'!$AJ$20,2) -> 2294.79 | H15: =ROUND(H67/'BLS Data'!$AJ$20,2) -> 1852.41
A16: Illinois | B16: 2019 | C16: =ROUND(C68/'BLS Data'!$AJ$20,2) -> 770.38 | D16: =ROUND(D68/'BLS Data'!$AJ$20,2) -> 364.69 | E16: =ROUND(E68/'BLS Data'!$AJ$20,2) -> 690.22 | F16: =ROUND(F68/'BLS Data'!$AJ$20,2) -> 533.95 | G16: =ROUND(G68/'BLS Data'!$AJ$20,2) -> 1529.34 | H16: =ROUND(H68/'BLS Data'!$AJ$20,2) -> 1936.52
A17: Indiana | B17: 2019 | C17: =ROUND(C69/'BLS Data'!$AJ$20,2) -> 828.59 | D17: =ROUND(D69/'BLS Data'!$AJ$20,2) -> 257.76 | E17: =ROUND(E69/'BLS Data'!$AJ$20,2) -> 804 | F17: =ROUND(F69/'BLS Data'!$AJ$20,2) -> 939.02 | G17: =ROUND(G69/'BLS Data'!$AJ$20,2) -> 1997.18 | H17: =ROUND(H69/'BLS Data'!$AJ$20,2) -> 2952.71
A18: Iowa | B18: 2019 | C18: =ROUND(C70/'BLS Data'!$AJ$20,2) -> 749.13 | D18: =ROUND(D70/'BLS Data'!$AJ$20,2) -> 273.04 | E18: =ROUND(E70/'BLS Data'!$AJ$20,2) -> 577.76 | F18: =ROUND(F70/'BLS Data'!$AJ$20,2) -> 555.55 | G18: =ROUND(G70/'BLS Data'!$AJ$20,2) -> 2383.47 | H18: =ROUND(H70/'BLS Data'!$AJ$20,2) -> 2694.51
A19: Kansas | B19: 2019 | C19: =ROUND(C71/'BLS Data'!$AJ$20,2) -> 890.82 | D19: =ROUND(D71/'BLS Data'!$AJ$20,2) -> 320.7 | E19: N/A | F19: =ROUND(F71/'BLS Data'!$AJ$20,2) -> 572.5 | G19: =ROUND(G71/'BLS Data'!$AJ$20,2) -> 2480.56 | H19: =ROUND(H71/'BLS Data'!$AJ$20,2) -> 2881.07
A20: Kentucky | B20: 2019 | C20: =ROUND(C72/'BLS Data'!$AJ$20,2) -> 824.37 | D20: =ROUND(D72/'BLS Data'!$AJ$20,2) -> 403.58 | E20: =ROUND(E72/'BLS Data'!$AJ$20,2) -> 707.35 | F20: =ROUND(F72/'BLS Data'!$AJ$20,2) -> 721.39 | G20: =ROUND(G72/'BLS Data'!$AJ$20,2) -> 2073.3 | H20: =ROUND(H72/'BLS Data'!$AJ$20,2) -> 2083.12
A21: Louisiana | B21: 2019 | C21: =ROUND(C73/'BLS Data'!$AJ$20,2) -> 675.64 | D21: =ROUND(D73/'BLS Data'!$AJ$20,2) -> 283.22 | E21: =ROUND(E73/'BLS Data'!$AJ$20,2) -> 628.5 | F21: =ROUND(F73/'BLS Data'!$AJ$20,2) -> 592.16 | G21: =ROUND(G73/'BLS Data'!$AJ$20,2) -> 1691.23 | H21: =ROUND(H73/'BLS Data'!$AJ$20,2) -> 1630.21
A22: Maine | B22: 2019 | C22: =ROUND(C74/'BLS Data'!$AJ$20,2) -> 950.52 | D22: =ROUND(D74/'BLS Data'!$AJ$20,2) -> 431.86 | E22: =ROUND(E74/'BLS Data'!$AJ$20,2) -> 579.95 | F22: =ROUND(F74/'BLS Data'!$AJ$20,2) -> 500.33 | G22: =ROUND(G74/'BLS Data'!$AJ$20,2) -> 2322.28 | H22: =ROUND(H74/'BLS Data'!$AJ$20,2) -> 2167.5
A23: Maryland | B23: 2019 | C23: =ROUND(C75/'BLS Data'!$AJ$20,2) -> 843.16 | D23: =ROUND(D75/'BLS Data'!$AJ$20,2) -> 314.12 | E23: =ROUND(E75/'BLS Data'!$AJ$20,2) -> 769.76 | F23: =ROUND(F75/'BLS Data'!$AJ$20,2) -> 569.08 | G23: =ROUND(G75/'BLS Data'!$AJ$20,2) -> 3034.36 | H23: =ROUND(H75/'BLS Data'!$AJ$20,2) -> 3194.83
A24: Massachusetts | B24: 2019 | C24: =ROUND(C76/'BLS Data'!$AJ$20,2) -> 1048.15 | D24: =ROUND(D76/'BLS Data'!$AJ$20,2) -> 396.56 | E24: =ROUND(E76/'BLS Data'!$AJ$20,2) -> 707.61 | F24: =ROUND(F76/'BLS Data'!$AJ$20,2) -> 536.68 | G24: =ROUND(G76/'BLS Data'!$AJ$20,2) -> 1918.96 | H24: =ROUND(H76/'BLS Data'!$AJ$20,2) -> 2438.34
A25: Michigan | B25: 2019 | C25: =ROUND(C77/'BLS Data'!$AJ$20,2) -> 666.87 | D25: =ROUND(D77/'BLS Data'!$AJ$20,2) -> 243.89 | E25: =ROUND(E77/'BLS Data'!$AJ$20,2) -> 572.5 | F25: =ROUND(F77/'BLS Data'!$AJ$20,2) -> 465.2 | G25: =ROUND(G77/'BLS Data'!$AJ$20,2) -> 1734.51 | H25: =ROUND(H77/'BLS Data'!$AJ$20,2) -> 2055.57
A26: Minnesota | B26: 2019 | C26: =ROUND(C78/'BLS Data'!$AJ$20,2) -> 1091.26 | D26: =ROUND(D78/'BLS Data'!$AJ$20,2) -> 349.5 | E26: =ROUND(E78/'BLS Data'!$AJ$20,2) -> 932.88 | F26: =ROUND(F78/'BLS Data'!$AJ$20,2) -> 636.23 | G26: =ROUND(G78/'BLS Data'!$AJ$20,2) -> 4432.27 | H26: =ROUND(H78/'BLS Data'!$AJ$20,2) -> 3430.66
A27: Mississippi | B27: 2019 | C27: =ROUND(C79/'BLS Data'!$AJ$20,2) -> 709.8 | D27: =ROUND(D79/'BLS Data'!$AJ$20,2) -> 294.72 | E27: N/A | F27: =ROUND(F79/'BLS Data'!$AJ$20,2) -> 578.56 | G27: =ROUND(G79/'BLS Data'!$AJ$20,2) -> 1671.83 | H27: =ROUND(H79/'BLS Data'!$AJ$20,2) -> 2095.68
A28: Missouri | B28: 2019 | C28: =ROUND(C80/'BLS Data'!$AJ$20,2) -> 872.57 | D28: =ROUND(D80/'BLS Data'!$AJ$20,2) -> 380.23 | E28: =ROUND(E80/'BLS Data'!$AJ$20,2) -> 532.47 | F28: =ROUND(F80/'BLS Data'!$AJ$20,2) -> 547.3 | G28: =ROUND(G80/'BLS Data'!$AJ$20,2) -> 2465.28 | H28: =ROUND(H80/'BLS Data'!$AJ$20,2) -> 1982.69
A29: Montana | B29: 2019 | C29: =ROUND(C81/'BLS Data'!$AJ$20,2) -> 744.04 | D29: =ROUND(D81/'BLS Data'!$AJ$20,2) -> 374.26 | E29: =ROUND(E81/'BLS Data'!$AJ$20,2) -> 707.09 | F29: =ROUND(F81/'BLS Data'!$AJ$20,2) -> 676.26 | G29: =ROUND(G81/'BLS Data'!$AJ$20,2) -> 2049.59 | H29: =ROUND(H81/'BLS Data'!$AJ$20,2) -> 2198.22
A30: Nebraska | B30: 2019 | C30: =ROUND(C82/'BLS Data'!$AJ$20,2) -> 940.07 | D30: =ROUND(D82/'BLS Data'!$AJ$20,2) -> 322.03 | E30: =ROUND(E82/'BLS Data'!$AJ$20,2) -> 860.27 | F30: =ROUND(F82/'BLS Data'!$AJ$20,2) -> 707.61 | G30: =ROUND(G82/'BLS Data'!$AJ$20,2) -> 2685.12 | H30: =ROUND(H82/'BLS Data'!$AJ$20,2) -> 2801.09
A31: Nevada | B31: 2019 | C31: =ROUND(C83/'BLS Data'!$AJ$20,2) -> 541.85 | D31: =ROUND(D83/'BLS Data'!$AJ$20,2) -> 222.56 | E31: =ROUND(E83/'BLS Data'!$AJ$20,2) -> 568.8 | F31: =ROUND(F83/'BLS Data'!$AJ$20,2) -> 445.19 | G31: =ROUND(G83/'BLS Data'!$AJ$20,2) -> 2032.82 | H31: =ROUND(H83/'BLS Data'!$AJ$20,2) -> 1855.75
A32: New Hampshire | B32: 2019 | C32: =ROUND(C84/'BLS Data'!$AJ$20,2) -> 916.2 | D32: =ROUND(D84/'BLS Data'!$AJ$20,2) -> 399.01 | E32: =ROUND(E84/'BLS Data'!$AJ$20,2) -> 634.03 | F32: =ROUND(F84/'BLS Data'!$AJ$20,2) -> 591.54 | G32: =ROUND(G84/'BLS Data'!$AJ$20,2) -> 2779.32 | H32: =ROUND(H84/'BLS Data'!$AJ$20,2) -> 3893.04
A33: New Jersey | B33: 2019 | C33: =ROUND(C85/'BLS Data'!$AJ$20,2) -> 900.14 | D33: =ROUND(D85/'BLS Data'!$AJ$20,2) -> 316.31 | E33: =ROUND(E85/'BLS Data'!$AJ$20,2) -> 632.28 | F33: =ROUND(F85/'BLS Data'!$AJ$20,2) -> 650.72 | G33: =ROUND(G85/'BLS Data'!$AJ$20,2) -> 3152.35 | H33: =ROUND(H85/'BLS Data'!$AJ$20,2) -> 2235.98
A34: New Mexico | B34: 2019 | C34: =ROUND(C86/'BLS Data'!$AJ$20,2) -> 735.16 | D34: =ROUND(D86/'BLS Data'!$AJ$20,2) -> 378.29 | E34: =ROUND(E86/'BLS Data'!$AJ$20,2) -> 649.4 | F34: =ROUND(F86/'BLS Data'!$AJ$20,2) -> 638.08 | G34: =ROUND(G86/'BLS Data'!$AJ$20,2) -> 2641.31 | H34: =ROUND(H86/'BLS Data'!$AJ$20,2) -> 2428.41
A35: New York | B35: 2019 | C35: =ROUND(C87/'BLS Data'!$AJ$20,2) -> 960.35 | D35: =ROUND(D87/'BLS Data'!$AJ$20,2) -> 293.48 | E35: =ROUND(E87/'BLS Data'!$AJ$20,2) -> 614.89 | F35: =ROUND(F87/'BLS Data'!$AJ$20,2) -> 526.93 | G35: =ROUND(G87/'BLS Data'!$AJ$20,2) -> 3149.19 | H35: =ROUND(H87/'BLS Data'!$AJ$20,2) -> 2896.88
A36: North Carolina | B36: 2019 | C36: =ROUND(C88/'BLS Data'!$AJ$20,2) -> 783.63 | D36: =ROUND(D88/'BLS Data'!$AJ$20,2) -> 304.46 | E36: N/A | F36: =ROUND(F88/'BLS Data'!$AJ$20,2) -> 577.14 | G36: =ROUND(G88/'BLS Data'!$AJ$20,2) -> 1996.47 | H36: =ROUND(H88/'BLS Data'!$AJ$20,2) -> 1840.55
A37: North Dakota | B37: 2019 | C37: =ROUND(C89/'BLS Data'!$AJ$20,2) -> 1106.1 | D37: =ROUND(D89/'BLS Data'!$AJ$20,2) -> 372.42 | E37: =ROUND(E89/'BLS Data'!$AJ$20,2) -> 122.55 | F37: =ROUND(F89/'BLS Data'!$AJ$20,2) -> 493.22 | G37: =ROUND(G89/'BLS Data'!$AJ$20,2) -> 4218.32 | H37: =ROUND(H89/'BLS Data'!$AJ$20,2) -> 5548.29
A38: Ohio | B38: 2019 | C38: =ROUND(C90/'BLS Data'!$AJ$20,2) -> 838.93 | D38: =ROUND(D90/'BLS Data'!$AJ$20,2) -> 313.86 | E38: =ROUND(E90/'BLS Data'!$AJ$20,2) -> 702.77 | F38: =ROUND(F90/'BLS Data'!$AJ$20,2) -> 541.95 | G38: =ROUND(G90/'BLS Data'!$AJ$20,2) -> 2391.72 | H38: =ROUND(H90/'BLS Data'!$AJ$20,2) -> 2696.18
A39: Oklahoma | B39: 2019 | C39: =ROUND(C91/'BLS Data'!$AJ$20,2) -> 616.48 | D39: =ROUND(D91/'BLS Data'!$AJ$20,2) -> 341.07 | E39: =ROUND(E91/'BLS Data'!$AJ$20,2) -> 480.48 | F39: =ROUND(F91/'BLS Data'!$AJ$20,2) -> 464.15 | G39: =ROUND(G91/'BLS Data'!$AJ$20,2) -> 1666.46 | H39: =ROUND(H91/'BLS Data'!$AJ$20,2) -> 1503.53
A40: Oregon | B40: 2019 | C40: =ROUND(C92/'BLS Data'!$AJ$20,2) -> 967.91 | D40: =ROUND(D92/'BLS Data'!$AJ$20,2) -> 373.81 | E40: =ROUND(E92/'BLS Data'!$AJ$20,2) -> 709.97 | F40: =ROUND(F92/'BLS Data'!$AJ$20,2) -> 943.41 | G40: =ROUND(G92/'BLS Data'!$AJ$20,2) -> 2697.5 | H40: =ROUND(H92/'BLS Data'!$AJ$20,2) -> 4570.89
A41: Pennsylvania | B41: 2019 | C41: =ROUND(C93/'BLS Data'!$AJ$20,2) -> 1067.9 | D41: =ROUND(D93/'BLS Data'!$AJ$20,2) -> 382.42 | E41: =ROUND(E93/'BLS Data'!$AJ$20,2) -> 666.69 | F41: =ROUND(F93/'BLS Data'!$AJ$20,2) -> 609.01 | G41: =ROUND(G93/'BLS Data'!$AJ$20,2) -> 2388.3 | H41: =ROUND(H93/'BLS Data'!$AJ$20,2) -> 3030.94
A42: Rhode Island | B42: 2019 | C42: =ROUND(C94/'BLS Data'!$AJ$20,2) -> 817.44 | D42: =ROUND(D94/'BLS Data'!$AJ$20,2) -> 608.84 | E42: =ROUND(E94/'BLS Data'!$AJ$20,2) -> 655.62 | F42: =ROUND(F94/'BLS Data'!$AJ$20,2) -> 463.28 | G42: =ROUND(G94/'BLS Data'!$AJ$20,2) -> 2116.31 | H42: =ROUND(H94/'BLS Data'!$AJ$20,2) -> 1173.86
A43: South Carolina | B43: 2019 | C43: =ROUND(C95/'BLS Data'!$AJ$20,2) -> 542.63 | D43: =ROUND(D95/'BLS Data'!$AJ$20,2) -> 226.95 | E43: N/A | F43: =ROUND(F95/'BLS Data'!$AJ$20,2) -> 411.93 | G43: =ROUND(G95/'BLS Data'!$AJ$20,2) -> 1495.37 | H43: =ROUND(H95/'BLS Data'!$AJ$20,2) -> 1220.66
A44: South Dakota | B44: 2019 | C44: =ROUND(C96/'BLS Data'!$AJ$20,2) -> 778.63 | D44: =ROUND(D96/'BLS Data'!$AJ$20,2) -> 255.56 | E44: N/A | F44: =ROUND(F96/'BLS Data'!$AJ$20,2) -> 545.19 | G44: =ROUND(G96/'BLS Data'!$AJ$20,2) -> 2557.12 | H44: =ROUND(H96/'BLS Data'!$AJ$20,2) -> 2471.78
A45: Tennessee | B45: 2019 | C45: =ROUND(C97/'BLS Data'!$AJ$20,2) -> 611.73 | D45: =ROUND(D97/'BLS Data'!$AJ$20,2) -> 323.77 | E45: N/A | F45: =ROUND(F97/'BLS Data'!$AJ$20,2) -> 454.58 | G45: =ROUND(G97/'BLS Data'!$AJ$20,2) -> 1482.62 | H45: =ROUND(H97/'BLS Data'!$AJ$20,2) -> 2149.15
A46: Texas | B46: 2019 | C46: =ROUND(C98/'BLS Data'!$AJ$20,2) -> 739.38 | D46: =ROUND(D98/'BLS Data'!$AJ$20,2) -> 326.5 | E46: =ROUND(E98/'BLS Data'!$AJ$20,2) -> 248.54 | F46: =ROUND(F98/'BLS Data'!$AJ$20,2) -> 739.56 | G46: =ROUND(G98/'BLS Data'!$AJ$20,2) -> 2331.06 | H46: =ROUND(H98/'BLS Data'!$AJ$20,2) -> 2210.6
A47: Utah | B47: 2019 | C47: =ROUND(C99/'BLS Data'!$AJ$20,2) -> 799.69 | D47: =ROUND(D99/'BLS Data'!$AJ$20,2) -> 323.25 | E47: =ROUND(E99/'BLS Data'!$AJ$20,2) -> 736.13 | F47: =ROUND(F99/'BLS Data'!$AJ$20,2) -> 668.71 | G47: =ROUND(G99/'BLS Data'!$AJ$20,2) -> 2532.71 | H47: =ROUND(H99/'BLS Data'!$AJ$20,2) -> 1970.05
A48: Vermont | B48: 2019 | C48: =ROUND(C100/'BLS Data'!$AJ$20,2) -> 0 | D48: =ROUND(D100/'BLS Data'!$AJ$20,2) -> 0 | E48: =ROUND(E100/'BLS Data'!$AJ$20,2) -> 0 | F48: =ROUND(F100/'BLS Data'!$AJ$20,2) -> 0 | G48: =ROUND(G100/'BLS Data'!$AJ$20,2) -> 0 | H48: =ROUND(H100/'BLS Data'!$AJ$20,2) -> 0
A49: Virginia | B49: 2019 | C49: =ROUND(C101/'BLS Data'!$AJ$20,2) -> 896.88 | D49: =ROUND(D101/'BLS Data'!$AJ$20,2) -> 334.3 | E49: =ROUND(E101/'BLS Data'!$AJ$20,2) -> 740.17 | F49: =ROUND(F101/'BLS Data'!$AJ$20,2) -> 500.07 | G49: =ROUND(G101/'BLS Data'!$AJ$20,2) -> 3189.48 | H49: =ROUND(H101/'BLS Data'!$AJ$20,2) -> 2363.88
A50: Washington | B50: 2019 | C50: =ROUND(C102/'BLS Data'!$AJ$20,2) -> 994.59 | D50: =ROUND(D102/'BLS Data'!$AJ$20,2) -> 373.21 | E50: =ROUND(E102/'BLS Data'!$AJ$20,2) -> 960.45 | F50: =ROUND(F102/'BLS Data'!$AJ$20,2) -> 906.88 | G50: =ROUND(G102/'BLS Data'!$AJ$20,2) -> 3293.87 | H50: =ROUND(H102/'BLS Data'!$AJ$20,2) -> 2807.76
A51: West Virginia | B51: 2019 | C51: =ROUND(C103/'BLS Data'!$AJ$20,2) -> 727.71 | D51: =ROUND(D103/'BLS Data'!$AJ$20,2) -> 308.94 | E51: =ROUND(E103/'BLS Data'!$AJ$20,2) -> 570.47 | F51: =ROUND(F103/'BLS Data'!$AJ$20,2) -> 606.21 | G51: =ROUND(G103/'BLS Data'!$AJ$20,2) -> 1517.66 | H51: =ROUND(H103/'BLS Data'!$AJ$20,2) -> 2982.03
A52: Wisconsin | B52: 2019 | C52: =ROUND(C104/'BLS Data'!$AJ$20,2) -> 721.74 | D52: =ROUND(D104/'BLS Data'!$AJ$20,2) -> 271.1 | E52: N/A | F52: =ROUND(F104/'BLS Data'!$AJ$20,2) -> 466.44 | G52: =ROUND(G104/'BLS Data'!$AJ$20,2) -> 2006.58 | H52: =ROUND(H104/'BLS Data'!$AJ$20,2) -> 1456.65
A53: Wyoming | B53: 2019 | C53: =ROUND(C105/'BLS Data'!$AJ$20,2) -> 793.81 | D53: =ROUND(D105/'BLS Data'!$AJ$20,2) -> 287.53 | E53: N/A | F53: =ROUND(F105/'BLS Data'!$AJ$20,2) -> 547.21 | G53: =ROUND(G105/'BLS Data'!$AJ$20,2) -> 2342.65 | H53: =ROUND(H105/'BLS Data'!$AJ$20,2) -> 3057.97
A54: National | B54: 2020 | C54: =ROUND(C106/'BLS Data'!$AJ$21,2) -> 776.23 | D54: =ROUND(D106/'BLS Data'!$AJ$21,2) -> 303.78 | E54: =ROUND(E106/'BLS Data'!$AJ$21,2) -> 635.16 | F54: =ROUND(F106/'BLS Data'!$AJ$21,2) -> 540.47 | G54: =ROUND(G106/'BLS Data'!$AJ$21,2) -> 2264.06 | H54: =ROUND(H106/'BLS Data'!$AJ$21,2) -> 2051.27 | J54: =PMPM[[#This Row],[ Total]]*'BLS Data'!$AJ$21 -> 768.49524 | K54: =PMPM[[#This Row],[Child]]*'BLS Data'!$AJ$21 -> 300.75298 | L54: =PMPM[[#This Row],[Expansion Adults]]*'BLS Data'!$AJ$21 -> 628.83093 | M54: =PMPM[[#This Row],[Adults]]*'BLS Data'!$AJ$21 -> 535.08447 | N54: =PMPM[[#This Row],[ Disabled]]*'BLS Data'!$AJ$21 -> 2241.4997 | O54: =PMPM[[#This Row],[ Aged]]*'BLS Data'!$AJ$21 -> 2030.8301
A55: Alabama | B55: 2020 | C55: =ROUND(C107/'BLS Data'!$AJ$21,2) -> 579.35 | D55: =ROUND(D107/'BLS Data'!$AJ$21,2) -> 223.4 | E55: N/A | F55: =ROUND(F107/'BLS Data'!$AJ$21,2) -> 425.74 | G55: =ROUND(G107/'BLS Data'!$AJ$21,2) -> 1476.63 | H55: =ROUND(H107/'BLS Data'!$AJ$21,2) -> 2051.27
A56: Alaska | B56: 2020 | C56: =ROUND(C108/'BLS Data'!$AJ$21,2) -> 768.41 | D56: =ROUND(D108/'BLS Data'!$AJ$21,2) -> 432.31 | E56: =ROUND(E108/'BLS Data'!$AJ$21,2) -> 694.17 | F56: =ROUND(F108/'BLS Data'!$AJ$21,2) -> 600.06 | G56: =ROUND(G108/'BLS Data'!$AJ$21,2) -> 2766.23 | H56: =ROUND(H108/'BLS Data'!$AJ$21,2) -> 1927.96 | J56: X* | K56: ='BLS Data'!AJ21 -> 0.99003548 | L56: =C106 -> 768.5
A57: Arizona | B57: 2020 | C57: =ROUND(C109/'BLS Data'!$AJ$21,2) -> 754.69 | D57: =ROUND(D109/'BLS Data'!$AJ$21,2) -> 303.19 | E57: =ROUND(E109/'BLS Data'!$AJ$21,2) -> 813.27 | F57: =ROUND(F109/'BLS Data'!$AJ$21,2) -> 586.26 | G57: =ROUND(G109/'BLS Data'!$AJ$21,2) -> 2678.27 | H57: =ROUND(H109/'BLS Data'!$AJ$21,2) -> 1056.19
A58: Arkansas | B58: 2020 | C58: =ROUND(C110/'BLS Data'!$AJ$21,2) -> 664.12 | D58: =ROUND(D110/'BLS Data'!$AJ$21,2) -> 343.59 | E58: =ROUND(E110/'BLS Data'!$AJ$21,2) -> 608.31 | F58: =ROUND(F110/'BLS Data'!$AJ$21,2) -> 503.94 | G58: =ROUND(G110/'BLS Data'!$AJ$21,2) -> 1582.94 | H58: =ROUND(H110/'BLS Data'!$AJ$21,2) -> 1849.51
A59: California | B59: 2020 | C59: =ROUND(C111/'BLS Data'!$AJ$21,2) -> 745.43 | D59: =ROUND(D111/'BLS Data'!$AJ$21,2) -> 310.85 | E59: =ROUND(E111/'BLS Data'!$AJ$21,2) -> 526.42 | F59: =ROUND(F111/'BLS Data'!$AJ$21,2) -> 555.11 | G59: =ROUND(G111/'BLS Data'!$AJ$21,2) -> 2677.51 | H59: =ROUND(H111/'BLS Data'!$AJ$21,2) -> 1464.51
A60: Colorado | B60: 2020 | C60: =ROUND(C112/'BLS Data'!$AJ$21,2) -> 645.43 | D60: =ROUND(D112/'BLS Data'!$AJ$21,2) -> 261.86 | E60: =ROUND(E112/'BLS Data'!$AJ$21,2) -> 485.84 | F60: =ROUND(F112/'BLS Data'!$AJ$21,2) -> 484.91 | G60: =ROUND(G112/'BLS Data'!$AJ$21,2) -> 2835.93 | H60: =ROUND(H112/'BLS Data'!$AJ$21,2) -> 2599.32
A61: Connecticut | B61: 2020 | C61: =ROUND(C113/'BLS Data'!$AJ$21,2) -> 782.47 | D61: =ROUND(D113/'BLS Data'!$AJ$21,2) -> 301.76 | E61: =ROUND(E113/'BLS Data'!$AJ$21,2) -> 619.67 | F61: =ROUND(F113/'BLS Data'!$AJ$21,2) -> 489.8 | G61: =ROUND(G113/'BLS Data'!$AJ$21,2) -> 4736.87 | H61: =ROUND(H113/'BLS Data'!$AJ$21,2) -> 3686.99
A62: Delaware | B62: 2020 | C62: =ROUND(C114/'BLS Data'!$AJ$21,2) -> 835.58 | D62: =ROUND(D114/'BLS Data'!$AJ$21,2) -> 384.58 | E62: =ROUND(E114/'BLS Data'!$AJ$21,2) -> 679.44 | F62: =ROUND(F114/'BLS Data'!$AJ$21,2) -> 787.85 | G62: =ROUND(G114/'BLS Data'!$AJ$21,2) -> 2884.92 | H62: =ROUND(H114/'BLS Data'!$AJ$21,2) -> 3224.55
A63: District of Columbia | B63: 2020 | C63: =ROUND(C115/'BLS Data'!$AJ$21,2) -> 1088.93 | D63: =ROUND(D115/'BLS Data'!$AJ$21,2) -> 397.46 | E63: =ROUND(E115/'BLS Data'!$AJ$21,2) -> 609.57 | F63: =ROUND(F115/'BLS Data'!$AJ$21,2) -> 596.36 | G63: =ROUND(G115/'BLS Data'!$AJ$21,2) -> 3636.91 | H63: =ROUND(H115/'BLS Data'!$AJ$21,2) -> 3295.51
A64: Florida | B64: 2020 | C64: =ROUND(C116/'BLS Data'!$AJ$21,2) -> 518.08 | D64: =ROUND(D116/'BLS Data'!$AJ$21,2) -> 212.19 | E64: N/A | F64: =ROUND(F116/'BLS Data'!$AJ$21,2) -> 322.63 | G64: =ROUND(G116/'BLS Data'!$AJ$21,2) -> 1527.8 | H64: =ROUND(H116/'BLS Data'!$AJ$21,2) -> 1475.79
A65: Georgia | B65: 2020 | C65: =ROUND(C117/'BLS Data'!$AJ$21,2) -> 493.24 | D65: =ROUND(D117/'BLS Data'!$AJ$21,2) -> 209 | E65: N/A | F65: =ROUND(F117/'BLS Data'!$AJ$21,2) -> 414.05 | G65: =ROUND(G117/'BLS Data'!$AJ$21,2) -> 1391.03 | H65: =ROUND(H117/'BLS Data'!$AJ$21,2) -> 1761.55
A66: Hawaii | B66: 2020 | C66: =ROUND(C118/'BLS Data'!$AJ$21,2) -> 613.11 | D66: =ROUND(D118/'BLS Data'!$AJ$21,2) -> 308.32 | E66: =ROUND(E118/'BLS Data'!$AJ$21,2) -> 522.63 | F66: =ROUND(F118/'BLS Data'!$AJ$21,2) -> 462.02 | G66: =ROUND(G118/'BLS Data'!$AJ$21,2) -> 2319.79 | H66: =ROUND(H118/'BLS Data'!$AJ$21,2) -> 1379.92
A67: Idaho | B67: 2020 | C67: =ROUND(C119/'BLS Data'!$AJ$21,2) -> 662.18 | D67: =ROUND(D119/'BLS Data'!$AJ$21,2) -> 265.82 | E67: =ROUND(E119/'BLS Data'!$AJ$21,2) -> 517.15 | F67: =ROUND(F119/'BLS Data'!$AJ$21,2) -> 538.45 | G67: =ROUND(G119/'BLS Data'!$AJ$21,2) -> 2200.17 | H67: =ROUND(H119/'BLS Data'!$AJ$21,2) -> 1776.03
A68: Illinois | B68: 2020 | C68: =ROUND(C120/'BLS Data'!$AJ$21,2) -> 738.61 | D68: =ROUND(D120/'BLS Data'!$AJ$21,2) -> 349.65 | E68: =ROUND(E120/'BLS Data'!$AJ$21,2) -> 661.76 | F68: =ROUND(F120/'BLS Data'!$AJ$21,2) -> 511.93 | G68: =ROUND(G120/'BLS Data'!$AJ$21,2) -> 1466.28 | H68: =ROUND(H120/'BLS Data'!$AJ$21,2) -> 1856.67
A69: Indiana | B69: 2020 | C69: =ROUND(C121/'BLS Data'!$AJ$21,2) -> 794.42 | D69: =ROUND(D121/'BLS Data'!$AJ$21,2) -> 247.13 | E69: =ROUND(E121/'BLS Data'!$AJ$21,2) -> 770.85 | F69: =ROUND(F121/'BLS Data'!$AJ$21,2) -> 900.3 | G69: =ROUND(G121/'BLS Data'!$AJ$21,2) -> 1914.83 | H69: =ROUND(H121/'BLS Data'!$AJ$21,2) -> 2830.96
A70: Iowa | B70: 2020 | C70: =ROUND(C122/'BLS Data'!$AJ$21,2) -> 718.24 | D70: =ROUND(D122/'BLS Data'!$AJ$21,2) -> 261.78 | E70: =ROUND(E122/'BLS Data'!$AJ$21,2) -> 553.94 | F70: =ROUND(F122/'BLS Data'!$AJ$21,2) -> 532.64 | G70: =ROUND(G122/'BLS Data'!$AJ$21,2) -> 2285.19 | H70: =ROUND(H122/'BLS Data'!$AJ$21,2) -> 2583.41
A71: Kansas | B71: 2020 | C71: =ROUND(C123/'BLS Data'!$AJ$21,2) -> 854.09 | D71: =ROUND(D123/'BLS Data'!$AJ$21,2) -> 307.48 | E71: N/A | F71: =ROUND(F123/'BLS Data'!$AJ$21,2) -> 548.89 | G71: =ROUND(G123/'BLS Data'!$AJ$21,2) -> 2378.28 | H71: =ROUND(H123/'BLS Data'!$AJ$21,2) -> 2762.27
A72: Kentucky | B72: 2020 | C72: =ROUND(C124/'BLS Data'!$AJ$21,2) -> 790.38 | D72: =ROUND(D124/'BLS Data'!$AJ$21,2) -> 386.94 | E72: =ROUND(E124/'BLS Data'!$AJ$21,2) -> 678.18 | F72: =ROUND(F124/'BLS Data'!$AJ$21,2) -> 691.64 | G72: =ROUND(G124/'BLS Data'!$AJ$21,2) -> 1987.81 | H72: =ROUND(H124/'BLS Data'!$AJ$21,2) -> 1997.23
A73: Louisiana | B73: 2020 | C73: =ROUND(C125/'BLS Data'!$AJ$21,2) -> 647.78 | D73: =ROUND(D125/'BLS Data'!$AJ$21,2) -> 271.54 | E73: =ROUND(E125/'BLS Data'!$AJ$21,2) -> 602.58 | F73: =ROUND(F125/'BLS Data'!$AJ$21,2) -> 567.74 | G73: =ROUND(G125/'BLS Data'!$AJ$21,2) -> 1621.49 | H73: =ROUND(H125/'BLS Data'!$AJ$21,2) -> 1562.99
A74: Maine | B74: 2020 | C74: =ROUND(C126/'BLS Data'!$AJ$21,2) -> 911.33 | D74: =ROUND(D126/'BLS Data'!$AJ$21,2) -> 414.05 | E74: =ROUND(E126/'BLS Data'!$AJ$21,2) -> 556.04 | F74: =ROUND(F126/'BLS Data'!$AJ$21,2) -> 479.7 | G74: =ROUND(G126/'BLS Data'!$AJ$21,2) -> 2226.52 | H74: =ROUND(H126/'BLS Data'!$AJ$21,2) -> 2078.13
A75: Maryland | B75: 2020 | C75: =ROUND(C127/'BLS Data'!$AJ$21,2) -> 808.39 | D75: =ROUND(D127/'BLS Data'!$AJ$21,2) -> 301.17 | E75: =ROUND(E127/'BLS Data'!$AJ$21,2) -> 738.02 | F75: =ROUND(F127/'BLS Data'!$AJ$21,2) -> 545.61 | G75: =ROUND(G127/'BLS Data'!$AJ$21,2) -> 2909.24 | H75: =ROUND(H127/'BLS Data'!$AJ$21,2) -> 3063.1
A76: Massachusetts | B76: 2020 | C76: =ROUND(C128/'BLS Data'!$AJ$21,2) -> 1004.93 | D76: =ROUND(D128/'BLS Data'!$AJ$21,2) -> 380.21 | E76: =ROUND(E128/'BLS Data'!$AJ$21,2) -> 678.43 | F76: =ROUND(F128/'BLS Data'!$AJ$21,2) -> 514.55 | G76: =ROUND(G128/'BLS Data'!$AJ$21,2) -> 1839.83 | H76: =ROUND(H128/'BLS Data'!$AJ$21,2) -> 2337.8
A77: Michigan | B77: 2020 | C77: =ROUND(C129/'BLS Data'!$AJ$21,2) -> 639.37 | D77: =ROUND(D129/'BLS Data'!$AJ$21,2) -> 233.83 | E77: =ROUND(E129/'BLS Data'!$AJ$21,2) -> 548.89 | F77: =ROUND(F129/'BLS Data'!$AJ$21,2) -> 446.02 | G77: =ROUND(G129/'BLS Data'!$AJ$21,2) -> 1662.99 | H77: =ROUND(H129/'BLS Data'!$AJ$21,2) -> 1970.81
A78: Minnesota | B78: 2020 | C78: =ROUND(C130/'BLS Data'!$AJ$21,2) -> 1046.26 | D78: =ROUND(D130/'BLS Data'!$AJ$21,2) -> 335.09 | E78: =ROUND(E130/'BLS Data'!$AJ$21,2) -> 894.41 | F78: =ROUND(F130/'BLS Data'!$AJ$21,2) -> 610 | G78: =ROUND(G130/'BLS Data'!$AJ$21,2) -> 4249.51 | H78: =ROUND(H130/'BLS Data'!$AJ$21,2) -> 3289.2
A79: Mississippi | B79: 2020 | C79: =ROUND(C131/'BLS Data'!$AJ$21,2) -> 680.53 | D79: =ROUND(D131/'BLS Data'!$AJ$21,2) -> 282.57 | E79: N/A | F79: =ROUND(F131/'BLS Data'!$AJ$21,2) -> 554.7 | G79: =ROUND(G131/'BLS Data'!$AJ$21,2) -> 1602.89 | H79: =ROUND(H131/'BLS Data'!$AJ$21,2) -> 2009.27
A80: Missouri | B80: 2020 | C80: =ROUND(C132/'BLS Data'!$AJ$21,2) -> 836.59 | D80: =ROUND(D132/'BLS Data'!$AJ$21,2) -> 364.55 | E80: =ROUND(E132/'BLS Data'!$AJ$21,2) -> 510.51 | F80: =ROUND(F132/'BLS Data'!$AJ$21,2) -> 524.73 | G80: =ROUND(G132/'BLS Data'!$AJ$21,2) -> 2363.63 | H80: =ROUND(H132/'BLS Data'!$AJ$21,2) -> 1900.94
A81: Montana | B81: 2020 | C81: =ROUND(C133/'BLS Data'!$AJ$21,2) -> 713.36 | D81: =ROUND(D133/'BLS Data'!$AJ$21,2) -> 358.83 | E81: =ROUND(E133/'BLS Data'!$AJ$21,2) -> 677.93 | F81: =ROUND(F133/'BLS Data'!$AJ$21,2) -> 648.38 | G81: =ROUND(G133/'BLS Data'!$AJ$21,2) -> 1965.08 | H81: =ROUND(H133/'BLS Data'!$AJ$21,2) -> 2107.58
A82: Nebraska | B82: 2020 | C82: =ROUND(C134/'BLS Data'!$AJ$21,2) -> 901.31 | D82: =ROUND(D134/'BLS Data'!$AJ$21,2) -> 308.75 | E82: =ROUND(E134/'BLS Data'!$AJ$21,2) -> 824.8 | F82: =ROUND(F134/'BLS Data'!$AJ$21,2) -> 678.43 | G82: =ROUND(G134/'BLS Data'!$AJ$21,2) -> 2574.4 | H82: =ROUND(H134/'BLS Data'!$AJ$21,2) -> 2685.59
A83: Nevada | B83: 2020 | C83: =ROUND(C135/'BLS Data'!$AJ$21,2) -> 519.51 | D83: =ROUND(D135/'BLS Data'!$AJ$21,2) -> 213.38 | E83: =ROUND(E135/'BLS Data'!$AJ$21,2) -> 545.35 | F83: =ROUND(F135/'BLS Data'!$AJ$21,2) -> 426.83 | G83: =ROUND(G135/'BLS Data'!$AJ$21,2) -> 1949 | H83: =ROUND(H135/'BLS Data'!$AJ$21,2) -> 1779.23
A84: New Hampshire | B84: 2020 | C84: =ROUND(C136/'BLS Data'!$AJ$21,2) -> 878.42 | D84: =ROUND(D136/'BLS Data'!$AJ$21,2) -> 382.56 | E84: =ROUND(E136/'BLS Data'!$AJ$21,2) -> 607.89 | F84: =ROUND(F136/'BLS Data'!$AJ$21,2) -> 567.15 | G84: =ROUND(G136/'BLS Data'!$AJ$21,2) -> 2664.72 | H84: =ROUND(H136/'BLS Data'!$AJ$21,2) -> 3732.52
A85: New Jersey | B85: 2020 | C85: =ROUND(C137/'BLS Data'!$AJ$21,2) -> 863.02 | D85: =ROUND(D137/'BLS Data'!$AJ$21,2) -> 303.27 | E85: =ROUND(E137/'BLS Data'!$AJ$21,2) -> 606.21 | F85: =ROUND(F137/'BLS Data'!$AJ$21,2) -> 623.89 | G85: =ROUND(G137/'BLS Data'!$AJ$21,2) -> 3022.37 | H85: =ROUND(H137/'BLS Data'!$AJ$21,2) -> 2143.78
A86: New Mexico | B86: 2020 | C86: =ROUND(C138/'BLS Data'!$AJ$21,2) -> 704.85 | D86: =ROUND(D138/'BLS Data'!$AJ$21,2) -> 362.69 | E86: =ROUND(E138/'BLS Data'!$AJ$21,2) -> 622.62 | F86: =ROUND(F138/'BLS Data'!$AJ$21,2) -> 611.77 | G86: =ROUND(G138/'BLS Data'!$AJ$21,2) -> 2532.4 | H86: =ROUND(H138/'BLS Data'!$AJ$21,2) -> 2328.28
A87: New York | B87: 2020 | C87: =ROUND(C139/'BLS Data'!$AJ$21,2) -> 920.75 | D87: =ROUND(D139/'BLS Data'!$AJ$21,2) -> 281.38 | E87: =ROUND(E139/'BLS Data'!$AJ$21,2) -> 589.54 | F87: =ROUND(F139/'BLS Data'!$AJ$21,2) -> 505.2 | G87: =ROUND(G139/'BLS Data'!$AJ$21,2) -> 3019.34 | H87: =ROUND(H139/'BLS Data'!$AJ$21,2) -> 2777.43
A88: North Carolina | B88: 2020 | C88: =ROUND(C140/'BLS Data'!$AJ$21,2) -> 751.32 | D88: =ROUND(D140/'BLS Data'!$AJ$21,2) -> 291.91 | E88: N/A | F88: =ROUND(F140/'BLS Data'!$AJ$21,2) -> 553.34 | G88: =ROUND(G140/'BLS Data'!$AJ$21,2) -> 1914.15 | H88: =ROUND(H140/'BLS Data'!$AJ$21,2) -> 1764.66
A89: North Dakota | B89: 2020 | C89: =ROUND(C141/'BLS Data'!$AJ$21,2) -> 1060.49 | D89: =ROUND(D141/'BLS Data'!$AJ$21,2) -> 357.06 | E89: =ROUND(E141/'BLS Data'!$AJ$21,2) -> 117.5 | F89: =ROUND(F141/'BLS Data'!$AJ$21,2) -> 472.88 | G89: =ROUND(G141/'BLS Data'!$AJ$21,2) -> 4044.38 | H89: =ROUND(H141/'BLS Data'!$AJ$21,2) -> 5319.51
A90: Ohio | B90: 2020 | C90: =ROUND(C142/'BLS Data'!$AJ$21,2) -> 804.34 | D90: =ROUND(D142/'BLS Data'!$AJ$21,2) -> 300.92 | E90: =ROUND(E142/'BLS Data'!$AJ$21,2) -> 673.79 | F90: =ROUND(F142/'BLS Data'!$AJ$21,2) -> 519.6 | G90: =ROUND(G142/'BLS Data'!$AJ$21,2) -> 2293.1 | H90: =ROUND(H142/'BLS Data'!$AJ$21,2) -> 2585.01
A91: Oklahoma | B91: 2020 | C91: =ROUND(C143/'BLS Data'!$AJ$21,2) -> 591.06 | D91: =ROUND(D143/'BLS Data'!$AJ$21,2) -> 327.01 | E91: =ROUND(E143/'BLS Data'!$AJ$21,2) -> 460.67 | F91: =ROUND(F143/'BLS Data'!$AJ$21,2) -> 445.01 | G91: =ROUND(G143/'BLS Data'!$AJ$21,2) -> 1597.75 | H91: =ROUND(H143/'BLS Data'!$AJ$21,2) -> 1441.53
A92: Oregon | B92: 2020 | C92: =ROUND(C144/'BLS Data'!$AJ$21,2) -> 928 | D92: =ROUND(D144/'BLS Data'!$AJ$21,2) -> 358.4 | E92: =ROUND(E144/'BLS Data'!$AJ$21,2) -> 680.7 | F92: =ROUND(F144/'BLS Data'!$AJ$21,2) -> 904.51 | G92: =ROUND(G144/'BLS Data'!$AJ$21,2) -> 2586.27 | H92: =ROUND(H144/'BLS Data'!$AJ$21,2) -> 4382.42
A93: Pennsylvania | B93: 2020 | C93: =ROUND(C145/'BLS Data'!$AJ$21,2) -> 1023.87 | D93: =ROUND(D145/'BLS Data'!$AJ$21,2) -> 366.65 | E93: =ROUND(E145/'BLS Data'!$AJ$21,2) -> 639.2 | F93: =ROUND(F145/'BLS Data'!$AJ$21,2) -> 583.9 | G93: =ROUND(G145/'BLS Data'!$AJ$21,2) -> 2289.82 | H93: =ROUND(H145/'BLS Data'!$AJ$21,2) -> 2905.96
A94: Rhode Island | B94: 2020 | C94: =ROUND(C146/'BLS Data'!$AJ$21,2) -> 783.73 | D94: =ROUND(D146/'BLS Data'!$AJ$21,2) -> 583.74 | E94: =ROUND(E146/'BLS Data'!$AJ$21,2) -> 628.59 | F94: =ROUND(F146/'BLS Data'!$AJ$21,2) -> 444.18 | G94: =ROUND(G146/'BLS Data'!$AJ$21,2) -> 2029.05 | H94: =ROUND(H146/'BLS Data'!$AJ$21,2) -> 1125.46
A95: South Carolina | B95: 2020 | C95: =ROUND(C147/'BLS Data'!$AJ$21,2) -> 520.26 | D95: =ROUND(D147/'BLS Data'!$AJ$21,2) -> 217.59 | E95: N/A | F95: =ROUND(F147/'BLS Data'!$AJ$21,2) -> 394.94 | G95: =ROUND(G147/'BLS Data'!$AJ$21,2) -> 1433.71 | H95: =ROUND(H147/'BLS Data'!$AJ$21,2) -> 1170.33
A96: South Dakota | B96: 2020 | C96: =ROUND(C148/'BLS Data'!$AJ$21,2) -> 746.52 | D96: =ROUND(D148/'BLS Data'!$AJ$21,2) -> 245.02 | E96: N/A | F96: =ROUND(F148/'BLS Data'!$AJ$21,2) -> 522.71 | G96: =ROUND(G148/'BLS Data'!$AJ$21,2) -> 2451.68 | H96: =ROUND(H148/'BLS Data'!$AJ$21,2) -> 2369.86
A97: Tennessee | B97: 2020 | C97: =ROUND(C149/'BLS Data'!$AJ$21,2) -> 586.51 | D97: =ROUND(D149/'BLS Data'!$AJ$21,2) -> 310.42 | E97: N/A | F97: =ROUND(F149/'BLS Data'!$AJ$21,2) -> 435.84 | G97: =ROUND(G149/'BLS Data'!$AJ$21,2) -> 1421.49 | H97: =ROUND(H149/'BLS Data'!$AJ$21,2) -> 2060.53
A98: Texas | B98: 2020 | C98: =ROUND(C150/'BLS Data'!$AJ$21,2) -> 708.89 | D98: =ROUND(D150/'BLS Data'!$AJ$21,2) -> 313.04 | E98: =ROUND(E150/'BLS Data'!$AJ$21,2) -> 238.29 | F98: =ROUND(F150/'BLS Data'!$AJ$21,2) -> 709.07 | G98: =ROUND(G150/'BLS Data'!$AJ$21,2) -> 2234.94 | H98: =ROUND(H150/'BLS Data'!$AJ$21,2) -> 2119.45
A99: Utah | B99: 2020 | C99: =ROUND(C151/'BLS Data'!$AJ$21,2) -> 766.72 | D99: =ROUND(D151/'BLS Data'!$AJ$21,2) -> 309.92 | E99: =ROUND(E151/'BLS Data'!$AJ$21,2) -> 705.78 | F99: =ROUND(F151/'BLS Data'!$AJ$21,2) -> 641.14 | G99: =ROUND(G151/'BLS Data'!$AJ$21,2) -> 2428.28 | H99: =ROUND(H151/'BLS Data'!$AJ$21,2) -> 1888.82
A100: Vermont | B100: 2020 | C100: =ROUND(C152/'BLS Data'!$AJ$21,2) -> 0 | D100: =ROUND(D152/'BLS Data'!$AJ$21,2) -> 0 | E100: =ROUND(E152/'BLS Data'!$AJ$21,2) -> 0 | F100: =ROUND(F152/'BLS Data'!$AJ$21,2) -> 0 | G100: =ROUND(G152/'BLS Data'!$AJ$21,2) -> 0 | H100: =ROUND(H152/'BLS Data'!$AJ$21,2) -> 0
...

Sheet Sheet1
