Workbook
Name ACTC: '[1]State Comparison Data'!#REF!
Name ActiveState: [1]Calc1!$D$3
Name Adjusted_Gross_Income: [1]Calc1!$R$58:INDEX([1]Calc1!$R$58:$HJ$58,COUNTIF([1]Calc1!$R$58:$HJ$58,”<>”&””))
Name Adjusted_Gross_Income: [1]Calc1!$R$58:INDEX([1]Calc1!$R$58:$HJ$58,COUNTIF([1]Calc1!$R$58:$HJ$58,”<>”&””))
Name Adjusted_Gross_Income: [1]Calc1!$R$58:INDEX([1]Calc1!$R$58:$HJ$58,COUNTIF([1]Calc1!$R$58:$HJ$58,”<>”&””))
Name Adjusted_Gross_Income: [1]Calc1!$R$58:INDEX([1]Calc1!$R$58:$HJ$58,COUNTIF([1]Calc1!$R$58:$HJ$58,”<>”&””))
Name Adjusted_Gross_Income: [1]Calc1!$R$58:INDEX([1]Calc1!$R$58:$HJ$58,COUNTIF([1]Calc1!$R$58:$HJ$58,”<>”&””))
Name Adjusted_Gross_Income: [1]Calc1!$R$58:INDEX([1]Calc1!$R$58:$HJ$58,COUNTIF([1]Calc1!$R$58:$HJ$58,”<>”&””))
Name Adjusted_Gross_Income: [1]Calc1!$R$58:INDEX([1]Calc1!$R$58:$HJ$58,COUNTIF([1]Calc1!$R$58:$HJ$58,”<>”&””))
Name Adjusted_Gross_Income: [1]Calc1!$R$58:INDEX([1]Calc1!$R$58:$HJ$58,COUNTIF([1]Calc1!$R$58:$HJ$58,”<>”&””))
Name Adjusted_Gross_Income: [1]Calc1!$R$58:INDEX([1]Calc1!$R$58:$HJ$58,COUNTIF([1]Calc1!$R$58:$HJ$58,”<>”&””))
Name AgeAdult: [1]Lists!$F$10:$F$59
Name AgeChild: [1]Lists!$H$10:$H$33
Name Apply: [1]MarriagePenalties!$B$30
Name CalculatorNewHours: [1]Inputs!$R$7
Name CalculatorNewWage: [1]Inputs!$Q$7
Name CCA_RateCategoryEntireCol: INDEX([1]!CCA_RateCategoryStates[#Data],,CHIP!CCA_RateCategoryStateColNum)
Name CCA_RateCategoryEntireCol: INDEX([1]!CCA_RateCategoryStates[#Data],,FPIG!CCA_RateCategoryStateColNum)
Name CCA_RateCategoryEntireCol: INDEX([1]!CCA_RateCategoryStates[#Data],,Mcaid!CCA_RateCategoryStateColNum)
Name CCA_RateCategoryEntireCol: INDEX([1]!CCA_RateCategoryStates[#Data],,CCA_RateCategoryStateColNum)
Name CCA_RateCategoryLookup: INDEX([1]!CCA_RateCategoryStates[#Data],1,CHIP!CCA_RateCategoryStateColNum):INDEX([1]!CCA_RateCategoryStates[#Data],COUNTA(CHIP!CCA_RateCategoryEntireCol),CHIP!CCA_RateCategoryStateColNum)
Name CCA_RateCategoryLookup: INDEX([1]!CCA_RateCategoryStates[#Data],1,FPIG!CCA_RateCategoryStateColNum):INDEX([1]!CCA_RateCategoryStates[#Data],COUNTA(FPIG!CCA_RateCategoryEntireCol),FPIG!CCA_RateCategoryStateColNum)
Name CCA_RateCategoryLookup: INDEX([1]!CCA_RateCategoryStates[#Data],1,Mcaid!CCA_RateCategoryStateColNum):INDEX([1]!CCA_RateCategoryStates[#Data],COUNTA(Mcaid!CCA_RateCategoryEntireCol),Mcaid!CCA_RateCategoryStateColNum)
Name CCA_RateCategoryLookup: INDEX([1]!CCA_RateCategoryStates[#Data],1,CCA_RateCategoryStateColNum):INDEX([1]!CCA_RateCategoryStates[#Data],COUNTA(CCA_RateCategoryEntireCol),CCA_RateCategoryStateColNum)
Name CCA_RateCategoryStateColNum: MATCH(InputStateName,[1]!CCA_RateCategoryStates[#Headers],0)
Name CCA_RateCategoryStateColNum: MATCH(InputStateName,[1]!CCA_RateCategoryStates[#Headers],0)
Name CCA_RateCategoryStateColNum: MATCH(InputStateName,[1]!CCA_RateCategoryStates[#Headers],0)
Name CCA_RateCategoryStateColNum: MATCH(InputStateName,[1]!CCA_RateCategoryStates[#Headers],0)
Name CCA_RateCategoryStatesEntireCol: INDEX([1]!CCA_RateCategoryStates[#Data],,CHIP!CCA_RateCategoryStatesStateColNum)
Name CCA_RateCategoryStatesEntireCol: INDEX([1]!CCA_RateCategoryStates[#Data],,FPIG!CCA_RateCategoryStatesStateColNum)
Name CCA_RateCategoryStatesEntireCol: INDEX([1]!CCA_RateCategoryStates[#Data],,Mcaid!CCA_RateCategoryStatesStateColNum)
Name CCA_RateCategoryStatesEntireCol: INDEX([1]!CCA_RateCategoryStates[#Data],,CCA_RateCategoryStatesStateColNum)
Name CCA_RateCategoryStatesStateColNum: MATCH(InputStateName,[1]!CCA_RateCategoryStates[#Headers],0)
Name CCA_RateCategoryStatesStateColNum: MATCH(InputStateName,[1]!CCA_RateCategoryStates[#Headers],0)
Name CCA_RateCategoryStatesStateColNum: MATCH(InputStateName,[1]!CCA_RateCategoryStates[#Headers],0)
Name CCA_RateCategoryStatesStateColNum: MATCH(InputStateName,[1]!CCA_RateCategoryStates[#Headers],0)
Name CCA_SettingsEntireCol: INDEX([1]!CCA_SettingsStates[#Data],,CHIP!CCA_SettingsStateColNum)
Name CCA_SettingsEntireCol: INDEX([1]!CCA_SettingsStates[#Data],,FPIG!CCA_SettingsStateColNum)
Name CCA_SettingsEntireCol: INDEX([1]!CCA_SettingsStates[#Data],,Mcaid!CCA_SettingsStateColNum)
Name CCA_SettingsEntireCol: INDEX([1]!CCA_SettingsStates[#Data],,CCA_SettingsStateColNum)
Name CCA_SettingsLookup: INDEX([1]!CCA_SettingsStates[#Data],1,CHIP!CCA_SettingsStateColNum):INDEX([1]!CCA_SettingsStates[#Data],COUNTA(CHIP!CCA_SettingsEntireCol),CHIP!CCA_SettingsStateColNum)
Name CCA_SettingsLookup: INDEX([1]!CCA_SettingsStates[#Data],1,FPIG!CCA_SettingsStateColNum):INDEX([1]!CCA_SettingsStates[#Data],COUNTA(FPIG!CCA_SettingsEntireCol),FPIG!CCA_SettingsStateColNum)
Name CCA_SettingsLookup: INDEX([1]!CCA_SettingsStates[#Data],1,Mcaid!CCA_SettingsStateColNum):INDEX([1]!CCA_SettingsStates[#Data],COUNTA(Mcaid!CCA_SettingsEntireCol),Mcaid!CCA_SettingsStateColNum)
Name CCA_SettingsLookup: INDEX([1]!CCA_SettingsStates[#Data],1,CCA_SettingsStateColNum):INDEX([1]!CCA_SettingsStates[#Data],COUNTA(CCA_SettingsEntireCol),CCA_SettingsStateColNum)
Name CCA_SettingsStateColNum: MATCH(InputStateName,[1]!CCA_SettingsStates[#Headers],0)
Name CCA_SettingsStateColNum: MATCH(InputStateName,[1]!CCA_SettingsStates[#Headers],0)
Name CCA_SettingsStateColNum: MATCH(InputStateName,[1]!CCA_SettingsStates[#Headers],0)
Name CCA_SettingsStateColNum: MATCH(InputStateName,[1]!CCA_SettingsStates[#Headers],0)
Name CCA_SettingsStatesEntireCol: INDEX([1]!CCA_SettingsStates[#Data],,CHIP!CCA_SettingsStatesStateColNum)
Name CCA_SettingsStatesEntireCol: INDEX([1]!CCA_SettingsStates[#Data],,FPIG!CCA_SettingsStatesStateColNum)
Name CCA_SettingsStatesEntireCol: INDEX([1]!CCA_SettingsStates[#Data],,Mcaid!CCA_SettingsStatesStateColNum)
Name CCA_SettingsStatesEntireCol: INDEX([1]!CCA_SettingsStates[#Data],,CCA_SettingsStatesStateColNum)
Name CCA_SettingsStatesLookup: INDEX([1]!CCA_SettingsStates[#Data],1,CHIP!CCA_SettingsStatesStateColNum):INDEX([1]!CCA_SettingsStates[#Data],COUNTA(CHIP!CCA_SettingsStatesEntireCol),CHIP!CCA_SettingsStatesStateColNum)
Name CCA_SettingsStatesLookup: INDEX([1]!CCA_SettingsStates[#Data],1,FPIG!CCA_SettingsStatesStateColNum):INDEX([1]!CCA_SettingsStates[#Data],COUNTA(FPIG!CCA_SettingsStatesEntireCol),FPIG!CCA_SettingsStatesStateColNum)
Name CCA_SettingsStatesLookup: INDEX([1]!CCA_SettingsStates[#Data],1,Mcaid!CCA_SettingsStatesStateColNum):INDEX([1]!CCA_SettingsStates[#Data],COUNTA(Mcaid!CCA_SettingsStatesEntireCol),Mcaid!CCA_SettingsStatesStateColNum)
Name CCA_SettingsStatesLookup: INDEX([1]!CCA_SettingsStates[#Data],1,CCA_SettingsStatesStateColNum):INDEX([1]!CCA_SettingsStates[#Data],COUNTA(CCA_SettingsStatesEntireCol),CCA_SettingsStatesStateColNum)
Name CCA_SettingsStatesStateColNum: MATCH(InputStateName,[1]!CCA_SettingsStates[#Headers],0)
Name CCA_SettingsStatesStateColNum: MATCH(InputStateName,[1]!CCA_SettingsStates[#Headers],0)
Name CCA_SettingsStatesStateColNum: MATCH(InputStateName,[1]!CCA_SettingsStates[#Headers],0)
Name CCA_SettingsStatesStateColNum: MATCH(InputStateName,[1]!CCA_SettingsStates[#Headers],0)

Sheet Results (2)
A1: Results For USE with UTAH Demonstration Project PowerPoint
B2: Income Eligibility Rules
C3: Children Medicaid Ages 0-1 | D3: Children Medicaid Ages 1-5 | E3: Children Medicaid Ages 6-18 | F3: Children Separate CHIP | G3: Pregnant Women Medicaid | H3: Pregnant Women CHIP | I3: Adults (Medicaid) Parent/ Caretaker | J3: Adults (Medicaid) Expansion to Adults
B4: Eligiblity (FPIG) | C4: ='Eligibility 2024'!S7 -> 2.21 | D4: ='Eligibility 2024'!T7 -> 1.943 | E4: ='Eligibility 2024'!U7 -> 1.899 | F4: ='Eligibility 2024'!V7 -> 2.847 | G4: ='Eligibility 2024'!W7 -> 2.035 | H4: ='Eligibility 2024'!X7 -> N/A | I4: ='Eligibility 2024'!Y7 -> 0.706 | J4: ='Eligibility 2024'!Z7 -> 1.33
B5: Utah | C5: ='Eligibility 2024'!E55 -> 1.39 | D5: ='Eligibility 2024'!G55 -> 1.39 | E5: ='Eligibility 2024'!H55 -> 1.33 | F5: ='Eligibility 2024'!I55 -> 2 | G5: ='Eligibility 2024'!K55 -> 1.39 | J5: 1.33
C7: Per Member Expenditures (Estimated 2024 Data): Full Benefits
D8: All | E8: Seniors | F8: Individuals with Disabilities | G8: Adults | H8: Children | I8: ACA Expansion Adults
C9: National | D9: ='PMPA-MACPAC'!D11 -> 9866 | E9: ='PMPA-MACPAC'!N10 -> 25334 | F9: ='PMPA-MACPAC'!L10 -> 27962 | G9: ='PMPA-MACPAC'!J10 -> 6674 | H9: ='PMPA-MACPAC'!F10 -> 3752 | I9: ='PMPA-MACPAC'!H10 -> 7845
C10: Utah | D10: ='PMPA-MACPAC'!CG61 -> 9745 | E10: ='PMPA-MACPAC'!CP61 -> 23301 | F10: ='PMPA-MACPAC'!CO61 -> 30864 | G10: ='PMPA-MACPAC'!CM61 -> 8149 | H10: ='PMPA-MACPAC'!CI61 -> 3939 | I10: ='PMPA-MACPAC'!CK61 -> 8971
A12: Use this one | B12: MACPAC Data- Full only
C14: U.S. Average | D14: Utah
B15: Children Medicaid Ages 0-1 | C15: 2.21 | D15: 1.39
B16: Children Medicaid Ages 1-5 | C16: 1.943 | D16: 1.39
B17: Children Medicaid Ages 6-18 | C17: 1.899 | D17: 1.33
B18: Children Separate CHIP | C18: 2.123 | D18: 2
B19: Pregnant Women Medicaid | C19: 2.035 | D19: 1.39
B20: Adults (Medicaid) Parent/ Caretaker | C20: 0.706 | D20: 0.36
B21: Adults (Medicaid) Expansion to Adults | C21: 1.33 | D21: 1.33

Sheet Sources
B3: Last downloaded July 31, 2024
B4: CMS
C5: https://data.medicaid.gov/dataset/6165f45b-ca93-5bb5-9d06-db29c692a360/data?conditions%5B0%5D%5Bproperty%5D=report_date&conditions%5B0%5D%5Bvalue%5D=2021-04-01&conditions%5B0%5D%5Boperator%5D=%3D&conditions%5B1%5D%5Bproperty%5D=preliminary_updated&conditions%5B1%5D%5Bvalue%5D=U&conditions%5B1%5D%5Boperator%5D=%3D
C6: https://data.medicaid.gov/dataset/6165f45b-ca93-5bb5-9d06-db29c692a360/data
C7: Back to State Medicaid and CHIP Applications, Eligibility Determinations, and Enrollment Data
C8: State Medicaid and CHIP Applications, Eligibility Determinations, and Enrollment Data
C10: Medicaid, Children's Health Insurance Program, & Basic Health Program Eligibility Levels
D11: Path: Home > Medicaid Program Information > Medicaid & CHIP Eligibility Levels
D12: https://www.medicaid.gov/medicaid/national-medicaid-chip-program-information/medicaid-childrens-health-insurance-program-basic-health-program-eligibility-levels/index.html
D13: Includes summary table of eligibility
B15: KFF
D16: Medicaid Spending per Enrollee (Full or Partial Benefit) by Enrollment Group
D17: https://www.kff.org/medicaid/state-indicator/medicaid-spending-per-enrollee/
D18: Accessed August 2, 2024
D20: Medicaid and CHIP Eligibility, Enrollment, and Cost Sharing Policies as of January 2020: Findings from a 50-State Survey
D21: https://files.kff.org/attachment/Report-Medicaid-and-CHIP-Eligibility,-Enrollment-and-Cost-Sharing-Policies-as-of-January-2020.pdf
D22: Prepared by: Tricia Brooks and Lauren Roygardner Georgetown University Center for Children and Families and Samantha Artiga, Olivia Pham, and Rachel Dolan KFF
E23: Table 14 : Premiums and Enrollment Fees for Children at Selected Income Levels, January 2020: p64
D24: website: | E24: https://www.kff.org/medicaid/report/medicaid-and-chip-eligibility-enrollment-and-cost-sharing-policies-as-of-january-2019-findings-from-a-50-state-survey/
B29: BLS | C29: Bureau of Labor Statistics
D30: Series Id: | E30: SUUR0000SAM2
D31: Not Seasonally Adjusted
D32: Series Title: | E32: Medical care services in U.S. city average, all urban consumers, chained, not seasonally adjusted
D33: Area: | E33: U.S. city average
D34: Item: | E34: Medical care services
D35: Base Period: | E35: DECEMBER 1999=100
D37: Series Id: | E37: SUUR0000SAM
D38: Not Seasonally Adjusted
D39: Series Title: | E39: Medical care in U.S. city average, all urban consumers, chained, not seasonally adjusted
D40: Area: | E40: U.S. city average
D41: Item: | E41: Medical care
D42: Base Period: | E42: DECEMBER 1999=100
D43: Years: | E43: 2014 to 2024
B45: MACPAC | C45: Medicaid and CHIP Payment and Access Commission
D46: MACStats: Medicaid and CHIP Data Book
D47: 45261
D48: https://www.macpac.gov/publication/macstats-medicaid-and-chip-data-book-2/
E49: The Medicaid and CHIP Payment and Access Commission (MACPAC) is a non-partisan legislative branch agency that provides policy and data analysis and makes recommendations to Congress, the Secretary of the U.S. Department of Health and Human Services, and the states on a wide array of issues affecting Medicaid and the State Children’s Health Insurance Program (CHIP). The U.S. Comptroller General appoints MACPAC’s 17 commissioners, who come from diverse regions across the United States and bring broad expertise and a wide range of perspectives on Medicaid and CHIP.
B51: CMS
C52: Income Counting
C53: https://www.medicaid.gov/state-reCsource-center/mac-learning-collaboratives/downloads/part-2-income.pdf

Sheet Results
A1: Results
B2: Income Eligibility Rules
D3: Children Medicaid Ages 0-1 | E3: Children Medicaid Ages 1-5 | F3: Children Medicaid Ages 6-18 | G3: Children Separate CHIP | H3: Pregnant Women Medicaid | I3: Pregnant Women CHIP | J3: Adults (Medicaid) Parent/ Caretaker | K3: Adults (Medicaid) Expansion to Adults
A4: Use this one | B4: Eligibility (FPIG) | D4: ='Eligibility 2024'!S7 -> 2.21 | E4: ='Eligibility 2024'!T7 -> 1.943 | F4: ='Eligibility 2024'!U7 -> 1.899 | G4: ='Eligibility 2024'!V7 -> 2.847 | H4: ='Eligibility 2024'!W7 -> 2.035 | I4: ='Eligibility 2024'!X7 -> N/A | J4: ='Eligibility 2024'!Y7 -> 0.706 | K4: ='Eligibility 2024'!Z7 -> 1.33
B5: Notes | J5: ='Eligibility 2024'!Y8 -> uses % | K5: yes, expanded
B7: Per Member Expenditures (2023)
D8: All Full or Partial Benefit Enrollees | E8: Seniors | F8: Individuals with Disabilities | G8: Adults | H8: Children | I8: ACA Expansion Adults
B9: KFF Data | C9: FY 2021 converted to CY 2023 | D9: ='PMPA-KFF'!B6 -> 7403 | E9: ='PMPA-KFF'!C6 -> 15344 | F9: ='PMPA-KFF'!D6 -> 17734 | G9: ='PMPA-KFF'!E6 -> 4731 | H9: ='PMPA-KFF'!F6 -> 3143 | I9: ='PMPA-KFF'!G6 -> 6678
B12: MACPAC Data- All | C12: FY 2021 | D12: ='PMPA-MACPAC'!C16 -> 8651 | E12: ='PMPA-MACPAC'!M16 -> 18514 | F12: ='PMPA-MACPAC'!K16 -> 23935 | G12: ='PMPA-MACPAC'!I16 -> 5462 | H12: ='PMPA-MACPAC'!E16 -> 3584 | I12: ='PMPA-MACPAC'!G16 -> 7486
B13: MACPAC Data- Full only | C13: FY 2021 | D13: ='PMPA-MACPAC'!D16 -> 9175 | E13: ='PMPA-MACPAC'!N16 -> 24247 | F13: ='PMPA-MACPAC'!L16 -> 26762 | G13: ='PMPA-MACPAC'!J16 -> 6388 | H13: ='PMPA-MACPAC'!F16 -> 3591 | I13: ='PMPA-MACPAC'!H16 -> 7508
B14: MACPAC Data- All | C14: FY 2021 converted to CY 2023 | D14: ='PMPA-MACPAC'!C10 -> 9039 | E14: ='PMPA-MACPAC'!M10 -> 19344 | F14: ='PMPA-MACPAC'!K10 -> 25008 | G14: ='PMPA-MACPAC'!I10 -> 5707 | H14: ='PMPA-MACPAC'!E10 -> 3745 | I14: ='PMPA-MACPAC'!G10 -> 7822
A15: Use this one | B15: MACPAC Data- Full only | C15: FY 2021 converted to CY 2023 | D15: ='PMPA-MACPAC'!D10 -> 9586 | E15: ='PMPA-MACPAC'!N10 -> 25334 | F15: ='PMPA-MACPAC'!L10 -> 27962 | G15: ='PMPA-MACPAC'!J10 -> 6674 | H15: ='PMPA-MACPAC'!F10 -> 3752 | I15: ='PMPA-MACPAC'!H10 -> 7845
C17: Premium Shares for Children
D18: FPL | E18: Annual Cost Per Child
C19: Group 1 | D19: ='KFF Premium Cost Sharing'!Q3 -> 1.51 | E19: ='KFF Premium Cost Sharing'!Q8 -> 37.51
C20: Group 2 | D20: ='KFF Premium Cost Sharing'!S3 -> 2.01 | E20: ='KFF Premium Cost Sharing'!S8 -> 139.34
C21: Group 3 | D21: ='KFF Premium Cost Sharing'!U3 -> 2.51 | E21: ='KFF Premium Cost Sharing'!U8 -> 332.76
C22: Group 4 | D22: ='KFF Premium Cost Sharing'!W3 -> 3.01 | E22: ='KFF Premium Cost Sharing'!W8 -> 463.34
C23: [Group 5--Not needed*] | D23: ='KFF Premium Cost Sharing'!Y3 -> 3.51 | E23: ='KFF Premium Cost Sharing'!Y8 -> 514.43
C24: *Exceeds maximum eligibility of 285% FPL
C25: Interpretation: maximum FPL for annual cost per child.
C26: Use these annual cost for when child comes off Medicaid until 285% FPL when they become ineligible.
B32: IMAGES
B71: Note:
B72: Don't count EITC or SSI as income

Sheet Weighting
B2: Select Enrollment Type = | C2: Total Medicaid and CHIP Enrollment
B3: Preliminary or Updated = | C3: U | F3: Number missing =
B4: Final Report = | C4: Y | F4: =COUNTIF(F7:F57,0) -> 0 | G4: =COUNTIF(G7:G57,0) -> 0 | H4: =COUNTIF(H7:H57,0) -> 0 | I4: =COUNTIF(I7:I57,0) -> 0 | J4: =COUNTIF(J7:J57,0) -> 0 | K4: =COUNTIF(K7:K57,0) -> 0 | L4: =COUNTIF(L7:L57,0) -> 0 | M4: =COUNTIF(M7:M57,0) -> 0 | ... Q4: =COUNTIF(Q7:Q57,0) -> 0
D5: State Expanded Medicaid
B6: Post Code | C6: State | D6: 44927 | E6: 45261 | F6: 44927 | G6: 44958 | H6: 44986 | I6: 45017 | J6: 45047 | K6: 45078 | L6: 45108 | M6: 45139 | N6: 45170 | O6: 45200 | P6: 45231 | Q6: 45261 | R6: average | U6: Enrollment Type | V6: Preliminary or Updated | W6: Final Report
A7: 1 | B7: AL | C7: Alabama | D7: {=INDEX(MData[],MATCH(1,(MData[State Abbreviation]=$B7)*(MData[Report Date]=D$6)*(MData[Preliminary or Updated]=$C$3)*(MData[Final Report]=$C$4),0),MATCH($D$5,MData[#Headers],0))} -> N | E7: {=INDEX(MData[],MATCH(1,(MData[State Abbreviation]=$B7)*(MData[Report Date]=E$6)*(MData[Preliminary or Updated]=$C$3)*(MData[Final Report]=$C$4),0),MATCH($D$5,MData[#Headers],0))} -> N | F7: {=INDEX(MData[],MATCH(1,(MData[State Abbreviation]=$B7)*(MData[Report Date]=F$6)*(MData[Preliminary or Updated]=$C$3)*(MData[Final Report]=$C$4),0),MATCH($C$2,MData[#Headers],0))} -> 1178842 | G7: {=INDEX(MData[],MATCH(1,(MData[State Abbreviation]=$B7)*(MData[Report Date]=G$6)*(MData[Preliminary or Updated]=$C$3)*(MData[Final Report]=$C$4),0),MATCH($C$2,MData[#Headers],0))} -> 1197673 | H7: {=INDEX(MData[],MATCH(1,(MData[State Abbreviation]=$B7)*(MData[Report Date]=H$6)*(MData[Preliminary or Updated]=$C$3)*(MData[Final Report]=$C$4),0),MATCH($C$2,MData[#Headers],0))} -> 1205375 | I7: {=INDEX(MData[],MATCH(1,(MData[State Abbreviation]=$B7)*(MData[Report Date]=I$6)*(MData[Preliminary or Updated]=$C$3)*(MData[Final Report]=$C$4),0),MATCH($C$2,MData[#Headers],0))} -> 1210198 | J7: {=INDEX(MData[],MATCH(1,(MData[State Abbreviation]=$B7)*(MData[Report Date]=J$6)*(MData[Preliminary or Updated]=$C$3)*(MData[Final Report]=$C$4),0),MATCH($C$2,MData[#Headers],0))} -> 1207604 | K7: {=INDEX(MData[],MATCH(1,(MData[State Abbreviation]=$B7)*(MData[Report Date]=K$6)*(MData[Preliminary or Updated]=$C$3)*(MData[Final Report]=$C$4),0),MATCH($C$2,MData[#Headers],0))} -> 1213189 | L7: {=INDEX(MData[],MATCH(1,(MData[State Abbreviation]=$B7)*(MData[Report Date]=L$6)*(MData[Preliminary or Updated]=$C$3)*(MData[Final Report]=$C$4),0),MATCH($C$2,MData[#Headers],0))} -> 1192748 | M7: {=INDEX(MData[],MATCH(1,(MData[State Abbreviation]=$B7)*(MData[Report Date]=M$6)*(MData[Preliminary or Updated]=$C$3)*(MData[Final Report]=$C$4),0),MATCH($C$2,MData[#Headers],0))} -> 1170429 | ... Q7: {=INDEX(MData[],MATCH(1,(MData[State Abbreviation]=$B7)*(MData[Report Date]=Q$6)*(MData[Preliminary or Updated]=$C$3)*(MData[Final Report]=$C$4),0),MATCH($C$2,MData[#Headers],0))} -> 1093532 | R7: =AVERAGE(F7:Q7) -> 1171764.9 | U7: Total Medicaid and CHIP Enrollment | V7: P | W7: Y
A8: 2 | B8: AK | C8: Alaska | D8: {=INDEX(MData[],MATCH(1,(MData[State Abbreviation]=$B8)*(MData[Report Date]=D$6)*(MData[Preliminary or Updated]=$C$3)*(MData[Final Report]=$C$4),0),MATCH($D$5,MData[#Headers],0))} -> Y | E8: {=INDEX(MData[],MATCH(1,(MData[State Abbreviation]=$B8)*(MData[Report Date]=E$6)*(MData[Preliminary or Updated]=$C$3)*(MData[Final Report]=$C$4),0),MATCH($D$5,MData[#Headers],0))} -> Y | F8: {=INDEX(MData[],MATCH(1,(MData[State Abbreviation]=$B8)*(MData[Report Date]=F$6)*(MData[Preliminary or Updated]=$C$3)*(MData[Final Report]=$C$4),0),MATCH($C$2,MData[#Headers],0))} -> 265528 | G8: {=INDEX(MData[],MATCH(1,(MData[State Abbreviation]=$B8)*(MData[Report Date]=G$6)*(MData[Preliminary or Updated]=$C$3)*(MData[Final Report]=$C$4),0),MATCH($C$2,MData[#Headers],0))} -> 266213 | H8: {=INDEX(MData[],MATCH(1,(MData[State Abbreviation]=$B8)*(MData[Report Date]=H$6)*(MData[Preliminary or Updated]=$C$3)*(MData[Final Report]=$C$4),0),MATCH($C$2,MData[#Headers],0))} -> 267278 | I8: {=INDEX(MData[],MATCH(1,(MData[State Abbreviation]=$B8)*(MData[Report Date]=I$6)*(MData[Preliminary or Updated]=$C$3)*(MData[Final Report]=$C$4),0),MATCH($C$2,MData[#Headers],0))} -> 268069 | J8: {=INDEX(MData[],MATCH(1,(MData[State Abbreviation]=$B8)*(MData[Report Date]=J$6)*(MData[Preliminary or Updated]=$C$3)*(MData[Final Report]=$C$4),0),MATCH($C$2,MData[#Headers],0))} -> 266917 | K8: {=INDEX(MData[],MATCH(1,(MData[State Abbreviation]=$B8)*(MData[Report Date]=K$6)*(MData[Preliminary or Updated]=$C$3)*(MData[Final Report]=$C$4),0),MATCH($C$2,MData[#Headers],0))} -> 265952 | L8: {=INDEX(MData[],MATCH(1,(MData[State Abbreviation]=$B8)*(MData[Report Date]=L$6)*(MData[Preliminary or Updated]=$C$3)*(MData[Final Report]=$C$4),0),MATCH($C$2,MData[#Headers],0))} -> 262806 | M8: {=INDEX(MData[],MATCH(1,(MData[State Abbreviation]=$B8)*(MData[Report Date]=M$6)*(MData[Preliminary or Updated]=$C$3)*(MData[Final Report]=$C$4),0),MATCH($C$2,MData[#Headers],0))} -> 256543 | ... Q8: {=INDEX(MData[],MATCH(1,(MData[State Abbreviation]=$B8)*(MData[Report Date]=Q$6)*(MData[Preliminary or Updated]=$C$3)*(MData[Final Report]=$C$4),0),MATCH($C$2,MData[#Headers],0))} -> 242860 | R8: =AVERAGE(F8:Q8) -> 258266.83 | U8: Medicaid and CHIP Child Enrollment | V8: U | W8: N
A9: 3 | B9: AZ | C9: Arizona | D9: {=INDEX(MData[],MATCH(1,(MData[State Abbreviation]=$B9)*(MData[Report Date]=D$6)*(MData[Preliminary or Updated]=$C$3)*(MData[Final Report]=$C$4),0),MATCH($D$5,MData[#Headers],0))} -> Y | E9: {=INDEX(MData[],MATCH(1,(MData[State Abbreviation]=$B9)*(MData[Report Date]=E$6)*(MData[Preliminary or Updated]=$C$3)*(MData[Final Report]=$C$4),0),MATCH($D$5,MData[#Headers],0))} -> Y | F9: {=INDEX(MData[],MATCH(1,(MData[State Abbreviation]=$B9)*(MData[Report Date]=F$6)*(MData[Preliminary or Updated]=$C$3)*(MData[Final Report]=$C$4),0),MATCH($C$2,MData[#Headers],0))} -> 2309576 | G9: {=INDEX(MData[],MATCH(1,(MData[State Abbreviation]=$B9)*(MData[Report Date]=G$6)*(MData[Preliminary or Updated]=$C$3)*(MData[Final Report]=$C$4),0),MATCH($C$2,MData[#Headers],0))} -> 2319692 | H9: {=INDEX(MData[],MATCH(1,(MData[State Abbreviation]=$B9)*(MData[Report Date]=H$6)*(MData[Preliminary or Updated]=$C$3)*(MData[Final Report]=$C$4),0),MATCH($C$2,MData[#Headers],0))} -> 2332111 | I9: {=INDEX(MData[],MATCH(1,(MData[State Abbreviation]=$B9)*(MData[Report Date]=I$6)*(MData[Preliminary or Updated]=$C$3)*(MData[Final Report]=$C$4),0),MATCH($C$2,MData[#Headers],0))} -> 2303620 | J9: {=INDEX(MData[],MATCH(1,(MData[State Abbreviation]=$B9)*(MData[Report Date]=J$6)*(MData[Preliminary or Updated]=$C$3)*(MData[Final Report]=$C$4),0),MATCH($C$2,MData[#Headers],0))} -> 2283588 | K9: {=INDEX(MData[],MATCH(1,(MData[State Abbreviation]=$B9)*(MData[Report Date]=K$6)*(MData[Preliminary or Updated]=$C$3)*(MData[Final Report]=$C$4),0),MATCH($C$2,MData[#Headers],0))} -> 2181664 | L9: {=INDEX(MData[],MATCH(1,(MData[State Abbreviation]=$B9)*(MData[Report Date]=L$6)*(MData[Preliminary or Updated]=$C$3)*(MData[Final Report]=$C$4),0),MATCH($C$2,MData[#Headers],0))} -> 2134921 | M9: {=INDEX(MData[],MATCH(1,(MData[State Abbreviation]=$B9)*(MData[Report Date]=M$6)*(MData[Preliminary or Updated]=$C$3)*(MData[Final Report]=$C$4),0),MATCH($C$2,MData[#Headers],0))} -> 2108891 | ... Q9: {=INDEX(MData[],MATCH(1,(MData[State Abbreviation]=$B9)*(MData[Report Date]=Q$6)*(MData[Preliminary or Updated]=$C$3)*(MData[Final Report]=$C$4),0),MATCH($C$2,MData[#Headers],0))} -> 2037255 | R9: =AVERAGE(F9:Q9) -> 2176738.6 | U9: Total Medicaid Enrollment
A10: 4 | B10: AR | C10: Arkansas | D10: {=INDEX(MData[],MATCH(1,(MData[State Abbreviation]=$B10)*(MData[Report Date]=D$6)*(MData[Preliminary or Updated]=$C$3)*(MData[Final Report]=$C$4),0),MATCH($D$5,MData[#Headers],0))} -> Y | E10: {=INDEX(MData[],MATCH(1,(MData[State Abbreviation]=$B10)*(MData[Report Date]=E$6)*(MData[Preliminary or Updated]=$C$3)*(MData[Final Report]=$C$4),0),MATCH($D$5,MData[#Headers],0))} -> Y | F10: {=INDEX(MData[],MATCH(1,(MData[State Abbreviation]=$B10)*(MData[Report Date]=F$6)*(MData[Preliminary or Updated]=$C$3)*(MData[Final Report]=$C$4),0),MATCH($C$2,MData[#Headers],0))} -> 1048216 | G10: {=INDEX(MData[],MATCH(1,(MData[State Abbreviation]=$B10)*(MData[Report Date]=G$6)*(MData[Preliminary or Updated]=$C$3)*(MData[Final Report]=$C$4),0),MATCH($C$2,MData[#Headers],0))} -> 1047297 | H10: {=INDEX(MData[],MATCH(1,(MData[State Abbreviation]=$B10)*(MData[Report Date]=H$6)*(MData[Preliminary or Updated]=$C$3)*(MData[Final Report]=$C$4),0),MATCH($C$2,MData[#Headers],0))} -> 1049471 | I10: {=INDEX(MData[],MATCH(1,(MData[State Abbreviation]=$B10)*(MData[Report Date]=I$6)*(MData[Preliminary or Updated]=$C$3)*(MData[Final Report]=$C$4),0),MATCH($C$2,MData[#Headers],0))} -> 1041808 | J10: {=INDEX(MData[],MATCH(1,(MData[State Abbreviation]=$B10)*(MData[Report Date]=J$6)*(MData[Preliminary or Updated]=$C$3)*(MData[Final Report]=$C$4),0),MATCH($C$2,MData[#Headers],0))} -> 991620 | K10: {=INDEX(MData[],MATCH(1,(MData[State Abbreviation]=$B10)*(MData[Report Date]=K$6)*(MData[Preliminary or Updated]=$C$3)*(MData[Final Report]=$C$4),0),MATCH($C$2,MData[#Headers],0))} -> 947122 | L10: {=INDEX(MData[],MATCH(1,(MData[State Abbreviation]=$B10)*(MData[Report Date]=L$6)*(MData[Preliminary or Updated]=$C$3)*(MData[Final Report]=$C$4),0),MATCH($C$2,MData[#Headers],0))} -> 898622 | M10: {=INDEX(MData[],MATCH(1,(MData[State Abbreviation]=$B10)*(MData[Report Date]=M$6)*(MData[Preliminary or Updated]=$C$3)*(MData[Final Report]=$C$4),0),MATCH($C$2,MData[#Headers],0))} -> 851992 | ... Q10: {=INDEX(MData[],MATCH(1,(MData[State Abbreviation]=$B10)*(MData[Report Date]=Q$6)*(MData[Preliminary or Updated]=$C$3)*(MData[Final Report]=$C$4),0),MATCH($C$2,MData[#Headers],0))} -> 783091 | R10: =AVERAGE(F10:Q10) -> 926134 | U10: Total CHIP Enrollment
A11: 5 | B11: CA | C11: California | D11: {=INDEX(MData[],MATCH(1,(MData[State Abbreviation]=$B11)*(MData[Report Date]=D$6)*(MData[Preliminary or Updated]=$C$3)*(MData[Final Report]=$C$4),0),MATCH($D$5,MData[#Headers],0))} -> Y | E11: {=INDEX(MData[],MATCH(1,(MData[State Abbreviation]=$B11)*(MData[Report Date]=E$6)*(MData[Preliminary or Updated]=$C$3)*(MData[Final Report]=$C$4),0),MATCH($D$5,MData[#Headers],0))} -> Y | F11: {=INDEX(MData[],MATCH(1,(MData[State Abbreviation]=$B11)*(MData[Report Date]=F$6)*(MData[Preliminary or Updated]=$C$3)*(MData[Final Report]=$C$4),0),MATCH($C$2,MData[#Headers],0))} -> 14176618 | G11: {=INDEX(MData[],MATCH(1,(MData[State Abbreviation]=$B11)*(MData[Report Date]=G$6)*(MData[Preliminary or Updated]=$C$3)*(MData[Final Report]=$C$4),0),MATCH($C$2,MData[#Headers],0))} -> 14218802 | H11: {=INDEX(MData[],MATCH(1,(MData[State Abbreviation]=$B11)*(MData[Report Date]=H$6)*(MData[Preliminary or Updated]=$C$3)*(MData[Final Report]=$C$4),0),MATCH($C$2,MData[#Headers],0))} -> 14285643 | I11: {=INDEX(MData[],MATCH(1,(MData[State Abbreviation]=$B11)*(MData[Report Date]=I$6)*(MData[Preliminary or Updated]=$C$3)*(MData[Final Report]=$C$4),0),MATCH($C$2,MData[#Headers],0))} -> 14344876 | J11: {=INDEX(MData[],MATCH(1,(MData[State Abbreviation]=$B11)*(MData[Report Date]=J$6)*(MData[Preliminary or Updated]=$C$3)*(MData[Final Report]=$C$4),0),MATCH($C$2,MData[#Headers],0))} -> 14401941 | K11: {=INDEX(MData[],MATCH(1,(MData[State Abbreviation]=$B11)*(MData[Report Date]=K$6)*(MData[Preliminary or Updated]=$C$3)*(MData[Final Report]=$C$4),0),MATCH($C$2,MData[#Headers],0))} -> 14462560 | L11: {=INDEX(MData[],MATCH(1,(MData[State Abbreviation]=$B11)*(MData[Report Date]=L$6)*(MData[Preliminary or Updated]=$C$3)*(MData[Final Report]=$C$4),0),MATCH($C$2,MData[#Headers],0))} -> 14399877 | M11: {=INDEX(MData[],MATCH(1,(MData[State Abbreviation]=$B11)*(MData[Report Date]=M$6)*(MData[Preliminary or Updated]=$C$3)*(MData[Final Report]=$C$4),0),MATCH($C$2,MData[#Headers],0))} -> 14397473 | ... Q11: {=INDEX(MData[],MATCH(1,(MData[State Abbreviation]=$B11)*(MData[Report Date]=Q$6)*(MData[Preliminary or Updated]=$C$3)*(MData[Final Report]=$C$4),0),MATCH($C$2,MData[#Headers],0))} -> 13805628 | R11: =AVERAGE(F11:Q11) -> 14231316
A12: 6 | B12: CO | C12: Colorado | D12: {=INDEX(MData[],MATCH(1,(MData[State Abbreviation]=$B12)*(MData[Report Date]=D$6)*(MData[Preliminary or Updated]=$C$3)*(MData[Final Report]=$C$4),0),MATCH($D$5,MData[#Headers],0))} -> Y | E12: {=INDEX(MData[],MATCH(1,(MData[State Abbreviation]=$B12)*(MData[Report Date]=E$6)*(MData[Preliminary or Updated]=$C$3)*(MData[Final Report]=$C$4),0),MATCH($D$5,MData[#Headers],0))} -> Y | F12: {=INDEX(MData[],MATCH(1,(MData[State Abbreviation]=$B12)*(MData[Report Date]=F$6)*(MData[Preliminary or Updated]=$C$3)*(MData[Final Report]=$C$4),0),MATCH($C$2,MData[#Headers],0))} -> 1712273 | G12: {=INDEX(MData[],MATCH(1,(MData[State Abbreviation]=$B12)*(MData[Report Date]=G$6)*(MData[Preliminary or Updated]=$C$3)*(MData[Final Report]=$C$4),0),MATCH($C$2,MData[#Headers],0))} -> 1722639 | H12: {=INDEX(MData[],MATCH(1,(MData[State Abbreviation]=$B12)*(MData[Report Date]=H$6)*(MData[Preliminary or Updated]=$C$3)*(MData[Final Report]=$C$4),0),MATCH($C$2,MData[#Headers],0))} -> 1705007 | I12: {=INDEX(MData[],MATCH(1,(MData[State Abbreviation]=$B12)*(MData[Report Date]=I$6)*(MData[Preliminary or Updated]=$C$3)*(MData[Final Report]=$C$4),0),MATCH($C$2,MData[#Headers],0))} -> 1713809 | J12: {=INDEX(MData[],MATCH(1,(MData[State Abbreviation]=$B12)*(MData[Report Date]=J$6)*(MData[Preliminary or Updated]=$C$3)*(MData[Final Report]=$C$4),0),MATCH($C$2,MData[#Headers],0))} -> 1722323 | K12: {=INDEX(MData[],MATCH(1,(MData[State Abbreviation]=$B12)*(MData[Report Date]=K$6)*(MData[Preliminary or Updated]=$C$3)*(MData[Final Report]=$C$4),0),MATCH($C$2,MData[#Headers],0))} -> 1689842 | L12: {=INDEX(MData[],MATCH(1,(MData[State Abbreviation]=$B12)*(MData[Report Date]=L$6)*(MData[Preliminary or Updated]=$C$3)*(MData[Final Report]=$C$4),0),MATCH($C$2,MData[#Headers],0))} -> 1649658 | M12: {=INDEX(MData[],MATCH(1,(MData[State Abbreviation]=$B12)*(MData[Report Date]=M$6)*(MData[Preliminary or Updated]=$C$3)*(MData[Final Report]=$C$4),0),MATCH($C$2,MData[#Headers],0))} -> 1608510 | ... Q12: {=INDEX(MData[],MATCH(1,(MData[State Abbreviation]=$B12)*(MData[Report Date]=Q$6)*(MData[Preliminary or Updated]=$C$3)*(MData[Final Report]=$C$4),0),MATCH($C$2,MData[#Headers],0))} -> 1420075 | R12: =AVERAGE(F12:Q12) -> 1626985.6
A13: 7 | B13: CT | C13: Connecticut | D13: {=INDEX(MData[],MATCH(1,(MData[State Abbreviation]=$B13)*(MData[Report Date]=D$6)*(MData[Preliminary or Updated]=$C$3)*(MData[Final Report]=$C$4),0),MATCH($D$5,MData[#Headers],0))} -> Y | E13: {=INDEX(MData[],MATCH(1,(MData[State Abbreviation]=$B13)*(MData[Report Date]=E$6)*(MData[Preliminary or Updated]=$C$3)*(MData[Final Report]=$C$4),0),MATCH($D$5,MData[#Headers],0))} -> Y | F13: {=INDEX(MData[],MATCH(1,(MData[State Abbreviation]=$B13)*(MData[Report Date]=F$6)*(MData[Preliminary or Updated]=$C$3)*(MData[Final Report]=$C$4),0),MATCH($C$2,MData[#Headers],0))} -> 1012131 | G13: {=INDEX(MData[],MATCH(1,(MData[State Abbreviation]=$B13)*(MData[Report Date]=G$6)*(MData[Preliminary or Updated]=$C$3)*(MData[Final Report]=$C$4),0),MATCH($C$2,MData[#Headers],0))} -> 1016060 | H13: {=INDEX(MData[],MATCH(1,(MData[State Abbreviation]=$B13)*(MData[Report Date]=H$6)*(MData[Preliminary or Updated]=$C$3)*(MData[Final Report]=$C$4),0),MATCH($C$2,MData[#Headers],0))} -> 1020137 | I13: {=INDEX(MData[],MATCH(1,(MData[State Abbreviation]=$B13)*(MData[Report Date]=I$6)*(MData[Preliminary or Updated]=$C$3)*(MData[Final Report]=$C$4),0),MATCH($C$2,MData[#Headers],0))} -> 1021298 | J13: {=INDEX(MData[],MATCH(1,(MData[State Abbreviation]=$B13)*(MData[Report Date]=J$6)*(MData[Preliminary or Updated]=$C$3)*(MData[Final Report]=$C$4),0),MATCH($C$2,MData[#Headers],0))} -> 1008465 | K13: {=INDEX(MData[],MATCH(1,(MData[State Abbreviation]=$B13)*(MData[Report Date]=K$6)*(MData[Preliminary or Updated]=$C$3)*(MData[Final Report]=$C$4),0),MATCH($C$2,MData[#Headers],0))} -> 1000711 | L13: {=INDEX(MData[],MATCH(1,(MData[State Abbreviation]=$B13)*(MData[Report Date]=L$6)*(MData[Preliminary or Updated]=$C$3)*(MData[Final Report]=$C$4),0),MATCH($C$2,MData[#Headers],0))} -> 996632 | M13: {=INDEX(MData[],MATCH(1,(MData[State Abbreviation]=$B13)*(MData[Report Date]=M$6)*(MData[Preliminary or Updated]=$C$3)*(MData[Final Report]=$C$4),0),MATCH($C$2,MData[#Headers],0))} -> 976859 | ... Q13: {=INDEX(MData[],MATCH(1,(MData[State Abbreviation]=$B13)*(MData[Report Date]=Q$6)*(MData[Preliminary or Updated]=$C$3)*(MData[Final Report]=$C$4),0),MATCH($C$2,MData[#Headers],0))} -> 980628 | R13: =AVERAGE(F13:Q13) -> 995265.25
A14: 8 | B14: DE | C14: Delaware | D14: {=INDEX(MData[],MATCH(1,(MData[State Abbreviation]=$B14)*(MData[Report Date]=D$6)*(MData[Preliminary or Updated]=$C$3)*(MData[Final Report]=$C$4),0),MATCH($D$5,MData[#Headers],0))} -> Y | E14: {=INDEX(MData[],MATCH(1,(MData[State Abbreviation]=$B14)*(MData[Report Date]=E$6)*(MData[Preliminary or Updated]=$C$3)*(MData[Final Report]=$C$4),0),MATCH($D$5,MData[#Headers],0))} -> Y | F14: {=INDEX(MData[],MATCH(1,(MData[State Abbreviation]=$B14)*(MData[Report Date]=F$6)*(MData[Preliminary or Updated]=$C$3)*(MData[Final Report]=$C$4),0),MATCH($C$2,MData[#Headers],0))} -> 303192 | G14: {=INDEX(MData[],MATCH(1,(MData[State Abbreviation]=$B14)*(MData[Report Date]=G$6)*(MData[Preliminary or Updated]=$C$3)*(MData[Final Report]=$C$4),0),MATCH($C$2,MData[#Headers],0))} -> 305292 | H14: {=INDEX(MData[],MATCH(1,(MData[State Abbreviation]=$B14)*(MData[Report Date]=H$6)*(MData[Preliminary or Updated]=$C$3)*(MData[Final Report]=$C$4),0),MATCH($C$2,MData[#Headers],0))} -> 306822 | I14: {=INDEX(MData[],MATCH(1,(MData[State Abbreviation]=$B14)*(MData[Report Date]=I$6)*(MData[Preliminary or Updated]=$C$3)*(MData[Final Report]=$C$4),0),MATCH($C$2,MData[#Headers],0))} -> 308105 | J14: {=INDEX(MData[],MATCH(1,(MData[State Abbreviation]=$B14)*(MData[Report Date]=J$6)*(MData[Preliminary or Updated]=$C$3)*(MData[Final Report]=$C$4),0),MATCH($C$2,MData[#Headers],0))} -> 309636 | K14: {=INDEX(MData[],MATCH(1,(MData[State Abbreviation]=$B14)*(MData[Report Date]=K$6)*(MData[Preliminary or Updated]=$C$3)*(MData[Final Report]=$C$4),0),MATCH($C$2,MData[#Headers],0))} -> 309753 | L14: {=INDEX(MData[],MATCH(1,(MData[State Abbreviation]=$B14)*(MData[Report Date]=L$6)*(MData[Preliminary or Updated]=$C$3)*(MData[Final Report]=$C$4),0),MATCH($C$2,MData[#Headers],0))} -> 310479 | M14: {=INDEX(MData[],MATCH(1,(MData[State Abbreviation]=$B14)*(MData[Report Date]=M$6)*(MData[Preliminary or Updated]=$C$3)*(MData[Final Report]=$C$4),0),MATCH($C$2,MData[#Headers],0))} -> 303388 | ... Q14: {=INDEX(MData[],MATCH(1,(MData[State Abbreviation]=$B14)*(MData[Report Date]=Q$6)*(MData[Preliminary or Updated]=$C$3)*(MData[Final Report]=$C$4),0),MATCH($C$2,MData[#Headers],0))} -> 289484 | R14: =AVERAGE(F14:Q14) -> 302669.42
A15: 9 | B15: DC | C15: District of Columbia | D15: {=INDEX(MData[],MATCH(1,(MData[State Abbreviation]=$B15)*(MData[Report Date]=D$6)*(MData[Preliminary or Updated]=$C$3)*(MData[Final Report]=$C$4),0),MATCH($D$5,MData[#Headers],0))} -> Y | E15: {=INDEX(MData[],MATCH(1,(MData[State Abbreviation]=$B15)*(MData[Report Date]=E$6)*(MData[Preliminary or Updated]=$C$3)*(MData[Final Report]=$C$4),0),MATCH($D$5,MData[#Headers],0))} -> Y | F15: {=INDEX(MData[],MATCH(1,(MData[State Abbreviation]=$B15)*(MData[Report Date]=F$6)*(MData[Preliminary or Updated]=$C$3)*(MData[Final Report]=$C$4),0),MATCH($C$2,MData[#Headers],0))} -> 293970 | G15: {=INDEX(MData[],MATCH(1,(MData[State Abbreviation]=$B15)*(MData[Report Date]=G$6)*(MData[Preliminary or Updated]=$C$3)*(MData[Final Report]=$C$4),0),MATCH($C$2,MData[#Headers],0))} -> 295152 | H15: {=INDEX(MData[],MATCH(1,(MData[State Abbreviation]=$B15)*(MData[Report Date]=H$6)*(MData[Preliminary or Updated]=$C$3)*(MData[Final Report]=$C$4),0),MATCH($C$2,MData[#Headers],0))} -> 296412 | I15: {=INDEX(MData[],MATCH(1,(MData[State Abbreviation]=$B15)*(MData[Report Date]=I$6)*(MData[Preliminary or Updated]=$C$3)*(MData[Final Report]=$C$4),0),MATCH($C$2,MData[#Headers],0))} -> 297053 | J15: {=INDEX(MData[],MATCH(1,(MData[State Abbreviation]=$B15)*(MData[Report Date]=J$6)*(MData[Preliminary or Updated]=$C$3)*(MData[Final Report]=$C$4),0),MATCH($C$2,MData[#Headers],0))} -> 297395 | K15: {=INDEX(MData[],MATCH(1,(MData[State Abbreviation]=$B15)*(MData[Report Date]=K$6)*(MData[Preliminary or Updated]=$C$3)*(MData[Final Report]=$C$4),0),MATCH($C$2,MData[#Headers],0))} -> 295185 | L15: {=INDEX(MData[],MATCH(1,(MData[State Abbreviation]=$B15)*(MData[Report Date]=L$6)*(MData[Preliminary or Updated]=$C$3)*(MData[Final Report]=$C$4),0),MATCH($C$2,MData[#Headers],0))} -> 292976 | M15: {=INDEX(MData[],MATCH(1,(MData[State Abbreviation]=$B15)*(MData[Report Date]=M$6)*(MData[Preliminary or Updated]=$C$3)*(MData[Final Report]=$C$4),0),MATCH($C$2,MData[#Headers],0))} -> 290845 | ... Q15: {=INDEX(MData[],MATCH(1,(MData[State Abbreviation]=$B15)*(MData[Report Date]=Q$6)*(MData[Preliminary or Updated]=$C$3)*(MData[Final Report]=$C$4),0),MATCH($C$2,MData[#Headers],0))} -> 277511 | R15: =AVERAGE(F15:Q15) -> 290836.67
A16: 10 | B16: FL | C16: Florida | D16: {=INDEX(MData[],MATCH(1,(MData[State Abbreviation]=$B16)*(MData[Report Date]=D$6)*(MData[Preliminary or Updated]=$C$3)*(MData[Final Report]=$C$4),0),MATCH($D$5,MData[#Headers],0))} -> N | E16: {=INDEX(MData[],MATCH(1,(MData[State Abbreviation]=$B16)*(MData[Report Date]=E$6)*(MData[Preliminary or Updated]=$C$3)*(MData[Final Report]=$C$4),0),MATCH($D$5,MData[#Headers],0))} -> N | F16: {=INDEX(MData[],MATCH(1,(MData[State Abbreviation]=$B16)*(MData[Report Date]=F$6)*(MData[Preliminary or Updated]=$C$3)*(MData[Final Report]=$C$4),0),MATCH($C$2,MData[#Headers],0))} -> 4924826 | G16: {=INDEX(MData[],MATCH(1,(MData[State Abbreviation]=$B16)*(MData[Report Date]=G$6)*(MData[Preliminary or Updated]=$C$3)*(MData[Final Report]=$C$4),0),MATCH($C$2,MData[#Headers],0))} -> 4949019 | H16: {=INDEX(MData[],MATCH(1,(MData[State Abbreviation]=$B16)*(MData[Report Date]=H$6)*(MData[Preliminary or Updated]=$C$3)*(MData[Final Report]=$C$4),0),MATCH($C$2,MData[#Headers],0))} -> 4978001 | I16: {=INDEX(MData[],MATCH(1,(MData[State Abbreviation]=$B16)*(MData[Report Date]=I$6)*(MData[Preliminary or Updated]=$C$3)*(MData[Final Report]=$C$4),0),MATCH($C$2,MData[#Headers],0))} -> 5007292 | J16: {=INDEX(MData[],MATCH(1,(MData[State Abbreviation]=$B16)*(MData[Report Date]=J$6)*(MData[Preliminary or Updated]=$C$3)*(MData[Final Report]=$C$4),0),MATCH($C$2,MData[#Headers],0))} -> 4751303 | K16: {=INDEX(MData[],MATCH(1,(MData[State Abbreviation]=$B16)*(MData[Report Date]=K$6)*(MData[Preliminary or Updated]=$C$3)*(MData[Final Report]=$C$4),0),MATCH($C$2,MData[#Headers],0))} -> 4606431 | L16: {=INDEX(MData[],MATCH(1,(MData[State Abbreviation]=$B16)*(MData[Report Date]=L$6)*(MData[Preliminary or Updated]=$C$3)*(MData[Final Report]=$C$4),0),MATCH($C$2,MData[#Headers],0))} -> 4521012 | M16: {=INDEX(MData[],MATCH(1,(MData[State Abbreviation]=$B16)*(MData[Report Date]=M$6)*(MData[Preliminary or Updated]=$C$3)*(MData[Final Report]=$C$4),0),MATCH($C$2,MData[#Headers],0))} -> 4394460 | ... Q16: {=INDEX(MData[],MATCH(1,(MData[State Abbreviation]=$B16)*(MData[Report Date]=Q$6)*(MData[Preliminary or Updated]=$C$3)*(MData[Final Report]=$C$4),0),MATCH($C$2,MData[#Headers],0))} -> 4155117 | R16: =AVERAGE(F16:Q16) -> 4575955.5
A17: 11 | B17: GA | C17: Georgia | D17: {=INDEX(MData[],MATCH(1,(MData[State Abbreviation]=$B17)*(MData[Report Date]=D$6)*(MData[Preliminary or Updated]=$C$3)*(MData[Final Report]=$C$4),0),MATCH($D$5,MData[#Headers],0))} -> N | E17: {=INDEX(MData[],MATCH(1,(MData[State Abbreviation]=$B17)*(MData[Report Date]=E$6)*(MData[Preliminary or Updated]=$C$3)*(MData[Final Report]=$C$4),0),MATCH($D$5,MData[#Headers],0))} -> N | F17: {=INDEX(MData[],MATCH(1,(MData[State Abbreviation]=$B17)*(MData[Report Date]=F$6)*(MData[Preliminary or Updated]=$C$3)*(MData[Final Report]=$C$4),0),MATCH($C$2,MData[#Headers],0))} -> 2491677 | G17: {=INDEX(MData[],MATCH(1,(MData[State Abbreviation]=$B17)*(MData[Report Date]=G$6)*(MData[Preliminary or Updated]=$C$3)*(MData[Final Report]=$C$4),0),MATCH($C$2,MData[#Headers],0))} -> 2502475 | H17: {=INDEX(MData[],MATCH(1,(MData[State Abbreviation]=$B17)*(MData[Report Date]=H$6)*(MData[Preliminary or Updated]=$C$3)*(MData[Final Report]=$C$4),0),MATCH($C$2,MData[#Headers],0))} -> 2511599 | I17: {=INDEX(MData[],MATCH(1,(MData[State Abbreviation]=$B17)*(MData[Report Date]=I$6)*(MData[Preliminary or Updated]=$C$3)*(MData[Final Report]=$C$4),0),MATCH($C$2,MData[#Headers],0))} -> 2542085 | J17: {=INDEX(MData[],MATCH(1,(MData[State Abbreviation]=$B17)*(MData[Report Date]=J$6)*(MData[Preliminary or Updated]=$C$3)*(MData[Final Report]=$C$4),0),MATCH($C$2,MData[#Headers],0))} -> 2552798 | K17: {=INDEX(MData[],MATCH(1,(MData[State Abbreviation]=$B17)*(MData[Report Date]=K$6)*(MData[Preliminary or Updated]=$C$3)*(MData[Final Report]=$C$4),0),MATCH($C$2,MData[#Headers],0))} -> 2548372 | L17: {=INDEX(MData[],MATCH(1,(MData[State Abbreviation]=$B17)*(MData[Report Date]=L$6)*(MData[Preliminary or Updated]=$C$3)*(MData[Final Report]=$C$4),0),MATCH($C$2,MData[#Headers],0))} -> 2539809 | M17: {=INDEX(MData[],MATCH(1,(MData[State Abbreviation]=$B17)*(MData[Report Date]=M$6)*(MData[Preliminary or Updated]=$C$3)*(MData[Final Report]=$C$4),0),MATCH($C$2,MData[#Headers],0))} -> 2408413 | ... Q17: {=INDEX(MData[],MATCH(1,(MData[State Abbreviation]=$B17)*(MData[Report Date]=Q$6)*(MData[Preliminary or Updated]=$C$3)*(MData[Final Report]=$C$4),0),MATCH($C$2,MData[#Headers],0))} -> 2151282 | R17: =AVERAGE(F17:Q17) -> 2428986.7
A18: 12 | B18: HI | C18: Hawaii | D18: {=INDEX(MData[],MATCH(1,(MData[State Abbreviation]=$B18)*(MData[Report Date]=D$6)*(MData[Preliminary or Updated]=$C$3)*(MData[Final Report]=$C$4),0),MATCH($D$5,MData[#Headers],0))} -> Y | E18: {=INDEX(MData[],MATCH(1,(MData[State Abbreviation]=$B18)*(MData[Report Date]=E$6)*(MData[Preliminary or Updated]=$C$3)*(MData[Final Report]=$C$4),0),MATCH($D$5,MData[#Headers],0))} -> Y | F18: {=INDEX(MData[],MATCH(1,(MData[State Abbreviation]=$B18)*(MData[Report Date]=F$6)*(MData[Preliminary or Updated]=$C$3)*(MData[Final Report]=$C$4),0),MATCH($C$2,MData[#Headers],0))} -> 461990 | G18: {=INDEX(MData[],MATCH(1,(MData[State Abbreviation]=$B18)*(MData[Report Date]=G$6)*(MData[Preliminary or Updated]=$C$3)*(MData[Final Report]=$C$4),0),MATCH($C$2,MData[#Headers],0))} -> 463842 | H18: {=INDEX(MData[],MATCH(1,(MData[State Abbreviation]=$B18)*(MData[Report Date]=H$6)*(MData[Preliminary or Updated]=$C$3)*(MData[Final Report]=$C$4),0),MATCH($C$2,MData[#Headers],0))} -> 465474 | I18: {=INDEX(MData[],MATCH(1,(MData[State Abbreviation]=$B18)*(MData[Report Date]=I$6)*(MData[Preliminary or Updated]=$C$3)*(MData[Final Report]=$C$4),0),MATCH($C$2,MData[#Headers],0))} -> 461504 | J18: {=INDEX(MData[],MATCH(1,(MData[State Abbreviation]=$B18)*(MData[Report Date]=J$6)*(MData[Preliminary or Updated]=$C$3)*(MData[Final Report]=$C$4),0),MATCH($C$2,MData[#Headers],0))} -> 461349 | K18: {=INDEX(MData[],MATCH(1,(MData[State Abbreviation]=$B18)*(MData[Report Date]=K$6)*(MData[Preliminary or Updated]=$C$3)*(MData[Final Report]=$C$4),0),MATCH($C$2,MData[#Headers],0))} -> 443621 | L18: {=INDEX(MData[],MATCH(1,(MData[State Abbreviation]=$B18)*(MData[Report Date]=L$6)*(MData[Preliminary or Updated]=$C$3)*(MData[Final Report]=$C$4),0),MATCH($C$2,MData[#Headers],0))} -> 438194 | M18: {=INDEX(MData[],MATCH(1,(MData[State Abbreviation]=$B18)*(MData[Report Date]=M$6)*(MData[Preliminary or Updated]=$C$3)*(MData[Final Report]=$C$4),0),MATCH($C$2,MData[#Headers],0))} -> 437390 | ... Q18: {=INDEX(MData[],MATCH(1,(MData[State Abbreviation]=$B18)*(MData[Report Date]=Q$6)*(MData[Preliminary or Updated]=$C$3)*(MData[Final Report]=$C$4),0),MATCH($C$2,MData[#Headers],0))} -> 469301 | R18: =AVERAGE(F18:Q18) -> 457257.58
A19: 13 | B19: ID | C19: Idaho | D19: {=INDEX(MData[],MATCH(1,(MData[State Abbreviation]=$B19)*(MData[Report Date]=D$6)*(MData[Preliminary or Updated]=$C$3)*(MData[Final Report]=$C$4),0),MATCH($D$5,MData[#Headers],0))} -> Y | E19: {=INDEX(MData[],MATCH(1,(MData[State Abbreviation]=$B19)*(MData[Report Date]=E$6)*(MData[Preliminary or Updated]=$C$3)*(MData[Final Report]=$C$4),0),MATCH($D$5,MData[#Headers],0))} -> Y | F19: {=INDEX(MData[],MATCH(1,(MData[State Abbreviation]=$B19)*(MData[Report Date]=F$6)*(MData[Preliminary or Updated]=$C$3)*(MData[Final Report]=$C$4),0),MATCH($C$2,MData[#Headers],0))} -> 455548 | G19: {=INDEX(MData[],MATCH(1,(MData[State Abbreviation]=$B19)*(MData[Report Date]=G$6)*(MData[Preliminary or Updated]=$C$3)*(MData[Final Report]=$C$4),0),MATCH($C$2,MData[#Headers],0))} -> 457355 | H19: {=INDEX(MData[],MATCH(1,(MData[State Abbreviation]=$B19)*(MData[Report Date]=H$6)*(MData[Preliminary or Updated]=$C$3)*(MData[Final Report]=$C$4),0),MATCH($C$2,MData[#Headers],0))} -> 460085 | I19: {=INDEX(MData[],MATCH(1,(MData[State Abbreviation]=$B19)*(MData[Report Date]=I$6)*(MData[Preliminary or Updated]=$C$3)*(MData[Final Report]=$C$4),0),MATCH($C$2,MData[#Headers],0))} -> 443371 | J19: {=INDEX(MData[],MATCH(1,(MData[State Abbreviation]=$B19)*(MData[Report Date]=J$6)*(MData[Preliminary or Updated]=$C$3)*(MData[Final Report]=$C$4),0),MATCH($C$2,MData[#Headers],0))} -> 432712 | K19: {=INDEX(MData[],MATCH(1,(MData[State Abbreviation]=$B19)*(MData[Report Date]=K$6)*(MData[Preliminary or Updated]=$C$3)*(MData[Final Report]=$C$4),0),MATCH($C$2,MData[#Headers],0))} -> 385133 | L19: {=INDEX(MData[],MATCH(1,(MData[State Abbreviation]=$B19)*(MData[Report Date]=L$6)*(MData[Preliminary or Updated]=$C$3)*(MData[Final Report]=$C$4),0),MATCH($C$2,MData[#Headers],0))} -> 363567 | M19: {=INDEX(MData[],MATCH(1,(MData[State Abbreviation]=$B19)*(MData[Report Date]=M$6)*(MData[Preliminary or Updated]=$C$3)*(MData[Final Report]=$C$4),0),MATCH($C$2,MData[#Headers],0))} -> 344660 | ... Q19: {=INDEX(MData[],MATCH(1,(MData[State Abbreviation]=$B19)*(MData[Report Date]=Q$6)*(MData[Preliminary or Updated]=$C$3)*(MData[Final Report]=$C$4),0),MATCH($C$2,MData[#Headers],0))} -> 338380 | R19: =AVERAGE(F19:Q19) -> 387596.58
A20: 14 | B20: IL | C20: Illinois | D20: {=INDEX(MData[],MATCH(1,(MData[State Abbreviation]=$B20)*(MData[Report Date]=D$6)*(MData[Preliminary or Updated]=$C$3)*(MData[Final Report]=$C$4),0),MATCH($D$5,MData[#Headers],0))} -> Y | E20: {=INDEX(MData[],MATCH(1,(MData[State Abbreviation]=$B20)*(MData[Report Date]=E$6)*(MData[Preliminary or Updated]=$C$3)*(MData[Final Report]=$C$4),0),MATCH($D$5,MData[#Headers],0))} -> Y | F20: {=INDEX(MData[],MATCH(1,(MData[State Abbreviation]=$B20)*(MData[Report Date]=F$6)*(MData[Preliminary or Updated]=$C$3)*(MData[Final Report]=$C$4),0),MATCH($C$2,MData[#Headers],0))} -> 3808385 | G20: {=INDEX(MData[],MATCH(1,(MData[State Abbreviation]=$B20)*(MData[Report Date]=G$6)*(MData[Preliminary or Updated]=$C$3)*(MData[Final Report]=$C$4),0),MATCH($C$2,MData[#Headers],0))} -> 3818769 | H20: {=INDEX(MData[],MATCH(1,(MData[State Abbreviation]=$B20)*(MData[Report Date]=H$6)*(MData[Preliminary or Updated]=$C$3)*(MData[Final Report]=$C$4),0),MATCH($C$2,MData[#Headers],0))} -> 3826461 | I20: {=INDEX(MData[],MATCH(1,(MData[State Abbreviation]=$B20)*(MData[Report Date]=I$6)*(MData[Preliminary or Updated]=$C$3)*(MData[Final Report]=$C$4),0),MATCH($C$2,MData[#Headers],0))} -> 3839112 | J20: {=INDEX(MData[],MATCH(1,(MData[State Abbreviation]=$B20)*(MData[Report Date]=J$6)*(MData[Preliminary or Updated]=$C$3)*(MData[Final Report]=$C$4),0),MATCH($C$2,MData[#Headers],0))} -> 3851907 | K20: {=INDEX(MData[],MATCH(1,(MData[State Abbreviation]=$B20)*(MData[Report Date]=K$6)*(MData[Preliminary or Updated]=$C$3)*(MData[Final Report]=$C$4),0),MATCH($C$2,MData[#Headers],0))} -> 3866234 | L20: {=INDEX(MData[],MATCH(1,(MData[State Abbreviation]=$B20)*(MData[Report Date]=L$6)*(MData[Preliminary or Updated]=$C$3)*(MData[Final Report]=$C$4),0),MATCH($C$2,MData[#Headers],0))} -> 3872945 | M20: {=INDEX(MData[],MATCH(1,(MData[State Abbreviation]=$B20)*(MData[Report Date]=M$6)*(MData[Preliminary or Updated]=$C$3)*(MData[Final Report]=$C$4),0),MATCH($C$2,MData[#Headers],0))} -> 3846699 | ... Q20: {=INDEX(MData[],MATCH(1,(MData[State Abbreviation]=$B20)*(MData[Report Date]=Q$6)*(MData[Preliminary or Updated]=$C$3)*(MData[Final Report]=$C$4),0),MATCH($C$2,MData[#Headers],0))} -> 3664724 | R20: =AVERAGE(F20:Q20) -> 3806069.2
A21: 15 | B21: IN | C21: Indiana | D21: {=INDEX(MData[],MATCH(1,(MData[State Abbreviation]=$B21)*(MData[Report Date]=D$6)*(MData[Preliminary or Updated]=$C$3)*(MData[Final Report]=$C$4),0),MATCH($D$5,MData[#Headers],0))} -> Y | E21: {=INDEX(MData[],MATCH(1,(MData[State Abbreviation]=$B21)*(MData[Report Date]=E$6)*(MData[Preliminary or Updated]=$C$3)*(MData[Final Report]=$C$4),0),MATCH($D$5,MData[#Headers],0))} -> Y | F21: {=INDEX(MData[],MATCH(1,(MData[State Abbreviation]=$B21)*(MData[Report Date]=F$6)*(MData[Preliminary or Updated]=$C$3)*(MData[Final Report]=$C$4),0),MATCH($C$2,MData[#Headers],0))} -> 2025386 | G21: {=INDEX(MData[],MATCH(1,(MData[State Abbreviation]=$B21)*(MData[Report Date]=G$6)*(MData[Preliminary or Updated]=$C$3)*(MData[Final Report]=$C$4),0),MATCH($C$2,MData[#Headers],0))} -> 2038189 | H21: {=INDEX(MData[],MATCH(1,(MData[State Abbreviation]=$B21)*(MData[Report Date]=H$6)*(MData[Preliminary or Updated]=$C$3)*(MData[Final Report]=$C$4),0),MATCH($C$2,MData[#Headers],0))} -> 2048631 | I21: {=INDEX(MData[],MATCH(1,(MData[State Abbreviation]=$B21)*(MData[Report Date]=I$6)*(MData[Preliminary or Updated]=$C$3)*(MData[Final Report]=$C$4),0),MATCH($C$2,MData[#Headers],0))} -> 2059657 | J21: {=INDEX(MData[],MATCH(1,(MData[State Abbreviation]=$B21)*(MData[Report Date]=J$6)*(MData[Preliminary or Updated]=$C$3)*(MData[Final Report]=$C$4),0),MATCH($C$2,MData[#Headers],0))} -> 2056226 | K21: {=INDEX(MData[],MATCH(1,(MData[State Abbreviation]=$B21)*(MData[Report Date]=K$6)*(MData[Preliminary or Updated]=$C$3)*(MData[Final Report]=$C$4),0),MATCH($C$2,MData[#Headers],0))} -> 2012845 | L21: {=INDEX(MData[],MATCH(1,(MData[State Abbreviation]=$B21)*(MData[Report Date]=L$6)*(MData[Preliminary or Updated]=$C$3)*(MData[Final Report]=$C$4),0),MATCH($C$2,MData[#Headers],0))} -> 1978780 | M21: {=INDEX(MData[],MATCH(1,(MData[State Abbreviation]=$B21)*(MData[Report Date]=M$6)*(MData[Preliminary or Updated]=$C$3)*(MData[Final Report]=$C$4),0),MATCH($C$2,MData[#Headers],0))} -> 1950151 | ... Q21: {=INDEX(MData[],MATCH(1,(MData[State Abbreviation]=$B21)*(MData[Report Date]=Q$6)*(MData[Preliminary or Updated]=$C$3)*(MData[Final Report]=$C$4),0),MATCH($C$2,MData[#Headers],0))} -> 1861409 | R21: =AVERAGE(F21:Q21) -> 1978495.8
A22: 16 | B22: IA | C22: Iowa | D22: {=INDEX(MData[],MATCH(1,(MData[State Abbreviation]=$B22)*(MData[Report Date]=D$6)*(MData[Preliminary or Updated]=$C$3)*(MData[Final Report]=$C$4),0),MATCH($D$5,MData[#Headers],0))} -> Y | E22: {=INDEX(MData[],MATCH(1,(MData[State Abbreviation]=$B22)*(MData[Report Date]=E$6)*(MData[Preliminary or Updated]=$C$3)*(MData[Final Report]=$C$4),0),MATCH($D$5,MData[#Headers],0))} -> Y | F22: {=INDEX(MData[],MATCH(1,(MData[State Abbreviation]=$B22)*(MData[Report Date]=F$6)*(MData[Preliminary or Updated]=$C$3)*(MData[Final Report]=$C$4),0),MATCH($C$2,MData[#Headers],0))} -> 855602 | G22: {=INDEX(MData[],MATCH(1,(MData[State Abbreviation]=$B22)*(MData[Report Date]=G$6)*(MData[Preliminary or Updated]=$C$3)*(MData[Final Report]=$C$4),0),MATCH($C$2,MData[#Headers],0))} -> 859437 | H22: {=INDEX(MData[],MATCH(1,(MData[State Abbreviation]=$B22)*(MData[Report Date]=H$6)*(MData[Preliminary or Updated]=$C$3)*(MData[Final Report]=$C$4),0),MATCH($C$2,MData[#Headers],0))} -> 862577 | I22: {=INDEX(MData[],MATCH(1,(MData[State Abbreviation]=$B22)*(MData[Report Date]=I$6)*(MData[Preliminary or Updated]=$C$3)*(MData[Final Report]=$C$4),0),MATCH($C$2,MData[#Headers],0))} -> 866496 | J22: {=INDEX(MData[],MATCH(1,(MData[State Abbreviation]=$B22)*(MData[Report Date]=J$6)*(MData[Preliminary or Updated]=$C$3)*(MData[Final Report]=$C$4),0),MATCH($C$2,MData[#Headers],0))} -> 860981 | K22: {=INDEX(MData[],MATCH(1,(MData[State Abbreviation]=$B22)*(MData[Report Date]=K$6)*(MData[Preliminary or Updated]=$C$3)*(MData[Final Report]=$C$4),0),MATCH($C$2,MData[#Headers],0))} -> 830677 | L22: {=INDEX(MData[],MATCH(1,(MData[State Abbreviation]=$B22)*(MData[Report Date]=L$6)*(MData[Preliminary or Updated]=$C$3)*(MData[Final Report]=$C$4),0),MATCH($C$2,MData[#Headers],0))} -> 802222 | M22: {=INDEX(MData[],MATCH(1,(MData[State Abbreviation]=$B22)*(MData[Report Date]=M$6)*(MData[Preliminary or Updated]=$C$3)*(MData[Final Report]=$C$4),0),MATCH($C$2,MData[#Headers],0))} -> 774745 | ... Q22: {=INDEX(MData[],MATCH(1,(MData[State Abbreviation]=$B22)*(MData[Report Date]=Q$6)*(MData[Preliminary or Updated]=$C$3)*(MData[Final Report]=$C$4),0),MATCH($C$2,MData[#Headers],0))} -> 710281 | R22: =AVERAGE(F22:Q22) -> 802633.92
... A57: 51 | B57: WY | C57: Wyoming | D57: {=INDEX(MData[],MATCH(1,(MData[State Abbreviation]=$B57)*(MData[Report Date]=D$6)*(MData[Preliminary or Updated]=$C$3)*(MData[Final Report]=$C$4),0),MATCH($D$5,MData[#Headers],0))} -> N | E57: {=INDEX(MData[],MATCH(1,(MData[State Abbreviation]=$B57)*(MData[Report Date]=E$6)*(MData[Preliminary or Updated]=$C$3)*(MData[Final Report]=$C$4),0),MATCH($D$5,MData[#Headers],0))} -> N | F57: {=INDEX(MData[],MATCH(1,(MData[State Abbreviation]=$B57)*(MData[Report Date]=F$6)*(MData[Preliminary or Updated]=$C$3)*(MData[Final Report]=$C$4),0),MATCH($C$2,MData[#Headers],0))} -> 83979 | G57: {=INDEX(MData[],MATCH(1,(MData[State Abbreviation]=$B57)*(MData[Report Date]=G$6)*(MData[Preliminary or Updated]=$C$3)*(MData[Final Report]=$C$4),0),MATCH($C$2,MData[#Headers],0))} -> 84746 | H57: {=INDEX(MData[],MATCH(1,(MData[State Abbreviation]=$B57)*(MData[Report Date]=H$6)*(MData[Preliminary or Updated]=$C$3)*(MData[Final Report]=$C$4),0),MATCH($C$2,MData[#Headers],0))} -> 85018 | I57: {=INDEX(MData[],MATCH(1,(MData[State Abbreviation]=$B57)*(MData[Report Date]=I$6)*(MData[Preliminary or Updated]=$C$3)*(MData[Final Report]=$C$4),0),MATCH($C$2,MData[#Headers],0))} -> 85281 | J57: {=INDEX(MData[],MATCH(1,(MData[State Abbreviation]=$B57)*(MData[Report Date]=J$6)*(MData[Preliminary or Updated]=$C$3)*(MData[Final Report]=$C$4),0),MATCH($C$2,MData[#Headers],0))} -> 85193 | K57: {=INDEX(MData[],MATCH(1,(MData[State Abbreviation]=$B57)*(MData[Report Date]=K$6)*(MData[Preliminary or Updated]=$C$3)*(MData[Final Report]=$C$4),0),MATCH($C$2,MData[#Headers],0))} -> 84816 | L57: {=INDEX(MData[],MATCH(1,(MData[State Abbreviation]=$B57)*(MData[Report Date]=L$6)*(MData[Preliminary or Updated]=$C$3)*(MData[Final Report]=$C$4),0),MATCH($C$2,MData[#Headers],0))} -> 85818 | M57: {=INDEX(MData[],MATCH(1,(MData[State Abbreviation]=$B57)*(MData[Report Date]=M$6)*(MData[Preliminary or Updated]=$C$3)*(MData[Final Report]=$C$4),0),MATCH($C$2,MData[#Headers],0))} -> 76785 | ... Q57: {=INDEX(MData[],MATCH(1,(MData[State Abbreviation]=$B57)*(MData[Report Date]=Q$6)*(MData[Preliminary or Updated]=$C$3)*(MData[Final Report]=$C$4),0),MATCH($C$2,MData[#Headers],0))} -> 75000 | R57: =AVERAGE(F57:Q57) -> 81218.917
D58: State Expanded Medicaid
B59: Post Code | C59: State | D59: 44562 | E59: 44896 | F59: 44562 | G59: 44593 | H59: 44621 | I59: 44652 | J59: 44682 | K59: 44713 | L59: 44743 | M59: 44774 | N59: 44805 | O59: 44835 | P59: 44866 | Q59: 44896 | R59: average
A60: 1 | B60: AL | C60: Alabama | D60: {=INDEX(MData[],MATCH(1,(MData[State Abbreviation]=$B60)*(MData[Report Date]=D$6)*(MData[Preliminary or Updated]=$C$3)*(MData[Final Report]=$C$4),0),MATCH($D$5,MData[#Headers],0))} -> N | E60: {=INDEX(MData[],MATCH(1,(MData[State Abbreviation]=$B60)*(MData[Report Date]=E$6)*(MData[Preliminary or Updated]=$C$3)*(MData[Final Report]=$C$4),0),MATCH($D$5,MData[#Headers],0))} -> N | F60: {=INDEX(MData[],MATCH(1,(MData[State Abbreviation]=$B60)*(MData[Report Date]=F$59)*(MData[Preliminary or Updated]=$C$3)*(MData[Final Report]=$C$4),0),MATCH($C$2,MData[#Headers],0))} -> 1099586 | G60: {=INDEX(MData[],MATCH(1,(MData[State Abbreviation]=$B60)*(MData[Report Date]=G$59)*(MData[Preliminary or Updated]=$C$3)*(MData[Final Report]=$C$4),0),MATCH($C$2,MData[#Headers],0))} -> 1105544 | H60: {=INDEX(MData[],MATCH(1,(MData[State Abbreviation]=$B60)*(MData[Report Date]=H$59)*(MData[Preliminary or Updated]=$C$3)*(MData[Final Report]=$C$4),0),MATCH($C$2,MData[#Headers],0))} -> 1111770 | I60: {=INDEX(MData[],MATCH(1,(MData[State Abbreviation]=$B60)*(MData[Report Date]=I$59)*(MData[Preliminary or Updated]=$C$3)*(MData[Final Report]=$C$4),0),MATCH($C$2,MData[#Headers],0))} -> 1117611 | J60: {=INDEX(MData[],MATCH(1,(MData[State Abbreviation]=$B60)*(MData[Report Date]=J$59)*(MData[Preliminary or Updated]=$C$3)*(MData[Final Report]=$C$4),0),MATCH($C$2,MData[#Headers],0))} -> 1124220 | K60: {=INDEX(MData[],MATCH(1,(MData[State Abbreviation]=$B60)*(MData[Report Date]=K$59)*(MData[Preliminary or Updated]=$C$3)*(MData[Final Report]=$C$4),0),MATCH($C$2,MData[#Headers],0))} -> 1131459 | L60: {=INDEX(MData[],MATCH(1,(MData[State Abbreviation]=$B60)*(MData[Report Date]=L$59)*(MData[Preliminary or Updated]=$C$3)*(MData[Final Report]=$C$4),0),MATCH($C$2,MData[#Headers],0))} -> 1138406 | M60: {=INDEX(MData[],MATCH(1,(MData[State Abbreviation]=$B60)*(MData[Report Date]=M$59)*(MData[Preliminary or Updated]=$C$3)*(MData[Final Report]=$C$4),0),MATCH($C$2,MData[#Headers],0))} -> 1145553 | ... Q60: {=INDEX(MData[],MATCH(1,(MData[State Abbreviation]=$B60)*(MData[Report Date]=Q$59)*(MData[Preliminary or Updated]=$C$3)*(MData[Final Report]=$C$4),0),MATCH($C$2,MData[#Headers],0))} -> 1171540 | R60: =AVERAGE(F60:Q60) -> 1135104.8
A61: 2 | B61: AK | C61: Alaska | D61: {=INDEX(MData[],MATCH(1,(MData[State Abbreviation]=$B61)*(MData[Report Date]=D$6)*(MData[Preliminary or Updated]=$C$3)*(MData[Final Report]=$C$4),0),MATCH($D$5,MData[#Headers],0))} -> Y | E61: {=INDEX(MData[],MATCH(1,(MData[State Abbreviation]=$B61)*(MData[Report Date]=E$6)*(MData[Preliminary or Updated]=$C$3)*(MData[Final Report]=$C$4),0),MATCH($D$5,MData[#Headers],0))} -> Y | F61: {=INDEX(MData[],MATCH(1,(MData[State Abbreviation]=$B61)*(MData[Report Date]=F$59)*(MData[Preliminary or Updated]=$C$3)*(MData[Final Report]=$C$4),0),MATCH($C$2,MData[#Headers],0))} -> 257035 | G61: {=INDEX(MData[],MATCH(1,(MData[State Abbreviation]=$B61)*(MData[Report Date]=G$59)*(MData[Preliminary or Updated]=$C$3)*(MData[Final Report]=$C$4),0),MATCH($C$2,MData[#Headers],0))} -> 257691 | H61: {=INDEX(MData[],MATCH(1,(MData[State Abbreviation]=$B61)*(MData[Report Date]=H$59)*(MData[Preliminary or Updated]=$C$3)*(MData[Final Report]=$C$4),0),MATCH($C$2,MData[#Headers],0))} -> 259457 | I61: {=INDEX(MData[],MATCH(1,(MData[State Abbreviation]=$B61)*(MData[Report Date]=I$59)*(MData[Preliminary or Updated]=$C$3)*(MData[Final Report]=$C$4),0),MATCH($C$2,MData[#Headers],0))} -> 259971 | J61: {=INDEX(MData[],MATCH(1,(MData[State Abbreviation]=$B61)*(MData[Report Date]=J$59)*(MData[Preliminary or Updated]=$C$3)*(MData[Final Report]=$C$4),0),MATCH($C$2,MData[#Headers],0))} -> 260768 | K61: {=INDEX(MData[],MATCH(1,(MData[State Abbreviation]=$B61)*(MData[Report Date]=K$59)*(MData[Preliminary or Updated]=$C$3)*(MData[Final Report]=$C$4),0),MATCH($C$2,MData[#Headers],0))} -> 262031 | L61: {=INDEX(MData[],MATCH(1,(MData[State Abbreviation]=$B61)*(MData[Report Date]=L$59)*(MData[Preliminary or Updated]=$C$3)*(MData[Final Report]=$C$4),0),MATCH($C$2,MData[#Headers],0))} -> 261816 | M61: {=INDEX(MData[],MATCH(1,(MData[State Abbreviation]=$B61)*(MData[Report Date]=M$59)*(MData[Preliminary or Updated]=$C$3)*(MData[Final Report]=$C$4),0),MATCH($C$2,MData[#Headers],0))} -> 262417 | ... Q61: {=INDEX(MData[],MATCH(1,(MData[State Abbreviation]=$B61)*(MData[Report Date]=Q$59)*(MData[Preliminary or Updated]=$C$3)*(MData[Final Report]=$C$4),0),MATCH($C$2,MData[#Headers],0))} -> 263656 | R61: =AVERAGE(F61:Q61) -> 261131.75
A62: 3 | B62: AZ | C62: Arizona | D62: {=INDEX(MData[],MATCH(1,(MData[State Abbreviation]=$B62)*(MData[Report Date]=D$6)*(MData[Preliminary or Updated]=$C$3)*(MData[Final Report]=$C$4),0),MATCH($D$5,MData[#Headers],0))} -> Y | E62: {=INDEX(MData[],MATCH(1,(MData[State Abbreviation]=$B62)*(MData[Report Date]=E$6)*(MData[Preliminary or Updated]=$C$3)*(MData[Final Report]=$C$4),0),MATCH($D$5,MData[#Headers],0))} -> Y | F62: {=INDEX(MData[],MATCH(1,(MData[State Abbreviation]=$B62)*(MData[Report Date]=F$59)*(MData[Preliminary or Updated]=$C$3)*(MData[Final Report]=$C$4),0),MATCH($C$2,MData[#Headers],0))} -> 2155732 | G62: {=INDEX(MData[],MATCH(1,(MData[State Abbreviation]=$B62)*(MData[Report Date]=G$59)*(MData[Preliminary or Updated]=$C$3)*(MData[Final Report]=$C$4),0),MATCH($C$2,MData[#Headers],0))} -> 2169228 | H62: {=INDEX(MData[],MATCH(1,(MData[State Abbreviation]=$B62)*(MData[Report Date]=H$59)*(MData[Preliminary or Updated]=$C$3)*(MData[Final Report]=$C$4),0),MATCH($C$2,MData[#Headers],0))} -> 2178981 | I62: {=INDEX(MData[],MATCH(1,(MData[State Abbreviation]=$B62)*(MData[Report Date]=I$59)*(MData[Preliminary or Updated]=$C$3)*(MData[Final Report]=$C$4),0),MATCH($C$2,MData[#Headers],0))} -> 2192656 | J62: {=INDEX(MData[],MATCH(1,(MData[State Abbreviation]=$B62)*(MData[Report Date]=J$59)*(MData[Preliminary or Updated]=$C$3)*(MData[Final Report]=$C$4),0),MATCH($C$2,MData[#Headers],0))} -> 2206792 | K62: {=INDEX(MData[],MATCH(1,(MData[State Abbreviation]=$B62)*(MData[Report Date]=K$59)*(MData[Preliminary or Updated]=$C$3)*(MData[Final Report]=$C$4),0),MATCH($C$2,MData[#Headers],0))} -> 2216371 | L62: {=INDEX(MData[],MATCH(1,(MData[State Abbreviation]=$B62)*(MData[Report Date]=L$59)*(MData[Preliminary or Updated]=$C$3)*(MData[Final Report]=$C$4),0),MATCH($C$2,MData[#Headers],0))} -> 2227971 | M62: {=INDEX(MData[],MATCH(1,(MData[State Abbreviation]=$B62)*(MData[Report Date]=M$59)*(MData[Preliminary or Updated]=$C$3)*(MData[Final Report]=$C$4),0),MATCH($C$2,MData[#Headers],0))} -> 2245107 | ... Q62: {=INDEX(MData[],MATCH(1,(MData[State Abbreviation]=$B62)*(MData[Report Date]=Q$59)*(MData[Preliminary or Updated]=$C$3)*(MData[Final Report]=$C$4),0),MATCH($C$2,MData[#Headers],0))} -> 2291196 | R62: =AVERAGE(F62:Q62) -> 2224415.2
A63: 4 | B63: AR | C63: Arkansas | D63: {=INDEX(MData[],MATCH(1,(MData[State Abbreviation]=$B63)*(MData[Report Date]=D$6)*(MData[Preliminary or Updated]=$C$3)*(MData[Final Report]=$C$4),0),MATCH($D$5,MData[#Headers],0))} -> Y | E63: {=INDEX(MData[],MATCH(1,(MData[State Abbreviation]=$B63)*(MData[Report Date]=E$6)*(MData[Preliminary or Updated]=$C$3)*(MData[Final Report]=$C$4),0),MATCH($D$5,MData[#Headers],0))} -> Y | F63: {=INDEX(MData[],MATCH(1,(MData[State Abbreviation]=$B63)*(MData[Report Date]=F$59)*(MData[Preliminary or Updated]=$C$3)*(MData[Final Report]=$C$4),0),MATCH($C$2,MData[#Headers],0))} -> 974587 | G63: {=INDEX(MData[],MATCH(1,(MData[State Abbreviation]=$B63)*(MData[Report Date]=G$59)*(MData[Preliminary or Updated]=$C$3)*(MData[Final Report]=$C$4),0),MATCH($C$2,MData[#Headers],0))} -> 982319 | H63: {=INDEX(MData[],MATCH(1,(MData[State Abbreviation]=$B63)*(MData[Report Date]=H$59)*(MData[Preliminary or Updated]=$C$3)*(MData[Final Report]=$C$4),0),MATCH($C$2,MData[#Headers],0))} -> 990124 | I63: {=INDEX(MData[],MATCH(1,(MData[State Abbreviation]=$B63)*(MData[Report Date]=I$59)*(MData[Preliminary or Updated]=$C$3)*(MData[Final Report]=$C$4),0),MATCH($C$2,MData[#Headers],0))} -> 998943 | J63: {=INDEX(MData[],MATCH(1,(MData[State Abbreviation]=$B63)*(MData[Report Date]=J$59)*(MData[Preliminary or Updated]=$C$3)*(MData[Final Report]=$C$4),0),MATCH($C$2,MData[#Headers],0))} -> 1004038 | K63: {=INDEX(MData[],MATCH(1,(MData[State Abbreviation]=$B63)*(MData[Report Date]=K$59)*(MData[Preliminary or Updated]=$C$3)*(MData[Final Report]=$C$4),0),MATCH($C$2,MData[#Headers],0))} -> 1008791 | L63: {=INDEX(MData[],MATCH(1,(MData[State Abbreviation]=$B63)*(MData[Report Date]=L$59)*(MData[Preliminary or Updated]=$C$3)*(MData[Final Report]=$C$4),0),MATCH($C$2,MData[#Headers],0))} -> 1012769 | M63: {=INDEX(MData[],MATCH(1,(MData[State Abbreviation]=$B63)*(MData[Report Date]=M$59)*(MData[Preliminary or Updated]=$C$3)*(MData[Final Report]=$C$4),0),MATCH($C$2,MData[#Headers],0))} -> 1019232 | ... Q63: {=INDEX(MData[],MATCH(1,(MData[State Abbreviation]=$B63)*(MData[Report Date]=Q$59)*(MData[Preliminary or Updated]=$C$3)*(MData[Final Report]=$C$4),0),MATCH($C$2,MData[#Headers],0))} -> 1041085 | R63: =AVERAGE(F63:Q63) -> 1009895.6
A64: 5 | B64: CA | C64: California | D64: {=INDEX(MData[],MATCH(1,(MData[State Abbreviation]=$B64)*(MData[Report Date]=D$6)*(MData[Preliminary or Updated]=$C$3)*(MData[Final Report]=$C$4),0),MATCH($D$5,MData[#Headers],0))} -> Y | E64: {=INDEX(MData[],MATCH(1,(MData[State Abbreviation]=$B64)*(MData[Report Date]=E$6)*(MData[Preliminary or Updated]=$C$3)*(MData[Final Report]=$C$4),0),MATCH($D$5,MData[#Headers],0))} -> Y | F64: {=INDEX(MData[],MATCH(1,(MData[State Abbreviation]=$B64)*(MData[Report Date]=F$59)*(MData[Preliminary or Updated]=$C$3)*(MData[Final Report]=$C$4),0),MATCH($C$2,MData[#Headers],0))} -> 13368893 | G64: {=INDEX(MData[],MATCH(1,(MData[State Abbreviation]=$B64)*(MData[Report Date]=G$59)*(MData[Preliminary or Updated]=$C$3)*(MData[Final Report]=$C$4),0),MATCH($C$2,MData[#Headers],0))} -> 13411356 | H64: {=INDEX(MData[],MATCH(1,(MData[State Abbreviation]=$B64)*(MData[Report Date]=H$59)*(MData[Preliminary or Updated]=$C$3)*(MData[Final Report]=$C$4),0),MATCH($C$2,MData[#Headers],0))} -> 13482237 | I64: {=INDEX(MData[],MATCH(1,(MData[State Abbreviation]=$B64)*(MData[Report Date]=I$59)*(MData[Preliminary or Updated]=$C$3)*(MData[Final Report]=$C$4),0),MATCH($C$2,MData[#Headers],0))} -> 13534548 | J64: {=INDEX(MData[],MATCH(1,(MData[State Abbreviation]=$B64)*(MData[Report Date]=J$59)*(MData[Preliminary or Updated]=$C$3)*(MData[Final Report]=$C$4),0),MATCH($C$2,MData[#Headers],0))} -> 13625983 | K64: {=INDEX(MData[],MATCH(1,(MData[State Abbreviation]=$B64)*(MData[Report Date]=K$59)*(MData[Preliminary or Updated]=$C$3)*(MData[Final Report]=$C$4),0),MATCH($C$2,MData[#Headers],0))} -> 13688202 | L64: {=INDEX(MData[],MATCH(1,(MData[State Abbreviation]=$B64)*(MData[Report Date]=L$59)*(MData[Preliminary or Updated]=$C$3)*(MData[Final Report]=$C$4),0),MATCH($C$2,MData[#Headers],0))} -> 13744043 | M64: {=INDEX(MData[],MATCH(1,(MData[State Abbreviation]=$B64)*(MData[Report Date]=M$59)*(MData[Preliminary or Updated]=$C$3)*(MData[Final Report]=$C$4),0),MATCH($C$2,MData[#Headers],0))} -> 13820824 | ... Q64: {=INDEX(MData[],MATCH(1,(MData[State Abbreviation]=$B64)*(MData[Report Date]=Q$59)*(MData[Preliminary or Updated]=$C$3)*(MData[Final Report]=$C$4),0),MATCH($C$2,MData[#Headers],0))} -> 14078007 | R64: =AVERAGE(F64:Q64) -> 13715734
A65: 6 | B65: CO | C65: Colorado | D65: {=INDEX(MData[],MATCH(1,(MData[State Abbreviation]=$B65)*(MData[Report Date]=D$6)*(MData[Preliminary or Updated]=$C$3)*(MData[Final Report]=$C$4),0),MATCH($D$5,MData[#Headers],0))} -> Y | E65: {=INDEX(MData[],MATCH(1,(MData[State Abbreviation]=$B65)*(MData[Report Date]=E$6)*(MData[Preliminary or Updated]=$C$3)*(MData[Final Report]=$C$4),0),MATCH($D$5,MData[#Headers],0))} -> Y | F65: {=INDEX(MData[],MATCH(1,(MData[State Abbreviation]=$B65)*(MData[Report Date]=F$59)*(MData[Preliminary or Updated]=$C$3)*(MData[Final Report]=$C$4),0),MATCH($C$2,MData[#Headers],0))} -> 1598614 | G65: {=INDEX(MData[],MATCH(1,(MData[State Abbreviation]=$B65)*(MData[Report Date]=G$59)*(MData[Preliminary or Updated]=$C$3)*(MData[Final Report]=$C$4),0),MATCH($C$2,MData[#Headers],0))} -> 1604957 | H65: {=INDEX(MData[],MATCH(1,(MData[State Abbreviation]=$B65)*(MData[Report Date]=H$59)*(MData[Preliminary or Updated]=$C$3)*(MData[Final Report]=$C$4),0),MATCH($C$2,MData[#Headers],0))} -> 1613405 | I65: {=INDEX(MData[],MATCH(1,(MData[State Abbreviation]=$B65)*(MData[Report Date]=I$59)*(MData[Preliminary or Updated]=$C$3)*(MData[Final Report]=$C$4),0),MATCH($C$2,MData[#Headers],0))} -> 1620385 | J65: {=INDEX(MData[],MATCH(1,(MData[State Abbreviation]=$B65)*(MData[Report Date]=J$59)*(MData[Preliminary or Updated]=$C$3)*(MData[Final Report]=$C$4),0),MATCH($C$2,MData[#Headers],0))} -> 1625864 | K65: {=INDEX(MData[],MATCH(1,(MData[State Abbreviation]=$B65)*(MData[Report Date]=K$59)*(MData[Preliminary or Updated]=$C$3)*(MData[Final Report]=$C$4),0),MATCH($C$2,MData[#Headers],0))} -> 1635385 | L65: {=INDEX(MData[],MATCH(1,(MData[State Abbreviation]=$B65)*(MData[Report Date]=L$59)*(MData[Preliminary or Updated]=$C$3)*(MData[Final Report]=$C$4),0),MATCH($C$2,MData[#Headers],0))} -> 1646836 | M65: {=INDEX(MData[],MATCH(1,(MData[State Abbreviation]=$B65)*(MData[Report Date]=M$59)*(MData[Preliminary or Updated]=$C$3)*(MData[Final Report]=$C$4),0),MATCH($C$2,MData[#Headers],0))} -> 1656830 | ... Q65: {=INDEX(MData[],MATCH(1,(MData[State Abbreviation]=$B65)*(MData[Report Date]=Q$59)*(MData[Preliminary or Updated]=$C$3)*(MData[Final Report]=$C$4),0),MATCH($C$2,MData[#Headers],0))} -> 1699630 | R65: =AVERAGE(F65:Q65) -> 1644331.1
A66: 7 | B66: CT | C66: Connecticut | D66: {=INDEX(MData[],MATCH(1,(MData[State Abbreviation]=$B66)*(MData[Report Date]=D$6)*(MData[Preliminary or Updated]=$C$3)*(MData[Final Report]=$C$4),0),MATCH($D$5,MData[#Headers],0))} -> Y | E66: {=INDEX(MData[],MATCH(1,(MData[State Abbreviation]=$B66)*(MData[Report Date]=E$6)*(MData[Preliminary or Updated]=$C$3)*(MData[Final Report]=$C$4),0),MATCH($D$5,MData[#Headers],0))} -> Y | F66: {=INDEX(MData[],MATCH(1,(MData[State Abbreviation]=$B66)*(MData[Report Date]=F$59)*(MData[Preliminary or Updated]=$C$3)*(MData[Final Report]=$C$4),0),MATCH($C$2,MData[#Headers],0))} -> 969817 | G66: {=INDEX(MData[],MATCH(1,(MData[State Abbreviation]=$B66)*(MData[Report Date]=G$59)*(MData[Preliminary or Updated]=$C$3)*(MData[Final Report]=$C$4),0),MATCH($C$2,MData[#Headers],0))} -> 971179 | H66: {=INDEX(MData[],MATCH(1,(MData[State Abbreviation]=$B66)*(MData[Report Date]=H$59)*(MData[Preliminary or Updated]=$C$3)*(MData[Final Report]=$C$4),0),MATCH($C$2,MData[#Headers],0))} -> 971185 | I66: {=INDEX(MData[],MATCH(1,(MData[State Abbreviation]=$B66)*(MData[Report Date]=I$59)*(MData[Preliminary or Updated]=$C$3)*(MData[Final Report]=$C$4),0),MATCH($C$2,MData[#Headers],0))} -> 971354 | J66: {=INDEX(MData[],MATCH(1,(MData[State Abbreviation]=$B66)*(MData[Report Date]=J$59)*(MData[Preliminary or Updated]=$C$3)*(MData[Final Report]=$C$4),0),MATCH($C$2,MData[#Headers],0))} -> 974428 | K66: {=INDEX(MData[],MATCH(1,(MData[State Abbreviation]=$B66)*(MData[Report Date]=K$59)*(MData[Preliminary or Updated]=$C$3)*(MData[Final Report]=$C$4),0),MATCH($C$2,MData[#Headers],0))} -> 974747 | L66: {=INDEX(MData[],MATCH(1,(MData[State Abbreviation]=$B66)*(MData[Report Date]=L$59)*(MData[Preliminary or Updated]=$C$3)*(MData[Final Report]=$C$4),0),MATCH($C$2,MData[#Headers],0))} -> 979293 | M66: {=INDEX(MData[],MATCH(1,(MData[State Abbreviation]=$B66)*(MData[Report Date]=M$59)*(MData[Preliminary or Updated]=$C$3)*(MData[Final Report]=$C$4),0),MATCH($C$2,MData[#Headers],0))} -> 985813 | ... Q66: {=INDEX(MData[],MATCH(1,(MData[State Abbreviation]=$B66)*(MData[Report Date]=Q$59)*(MData[Preliminary or Updated]=$C$3)*(MData[Final Report]=$C$4),0),MATCH($C$2,MData[#Headers],0))} -> 1008718 | R66: =AVERAGE(F66:Q66) -> 983379.42
A67: 8 | B67: DE | C67: Delaware | D67: {=INDEX(MData[],MATCH(1,(MData[State Abbreviation]=$B67)*(MData[Report Date]=D$6)*(MData[Preliminary or Updated]=$C$3)*(MData[Final Report]=$C$4),0),MATCH($D$5,MData[#Headers],0))} -> Y | E67: {=INDEX(MData[],MATCH(1,(MData[State Abbreviation]=$B67)*(MData[Report Date]=E$6)*(MData[Preliminary or Updated]=$C$3)*(MData[Final Report]=$C$4),0),MATCH($D$5,MData[#Headers],0))} -> Y | F67: {=INDEX(MData[],MATCH(1,(MData[State Abbreviation]=$B67)*(MData[Report Date]=F$59)*(MData[Preliminary or Updated]=$C$3)*(MData[Final Report]=$C$4),0),MATCH($C$2,MData[#Headers],0))} -> 280153 | G67: {=INDEX(MData[],MATCH(1,(MData[State Abbreviation]=$B67)*(MData[Report Date]=G$59)*(MData[Preliminary or Updated]=$C$3)*(MData[Final Report]=$C$4),0),MATCH($C$2,MData[#Headers],0))} -> 282299 | H67: {=INDEX(MData[],MATCH(1,(MData[State Abbreviation]=$B67)*(MData[Report Date]=H$59)*(MData[Preliminary or Updated]=$C$3)*(MData[Final Report]=$C$4),0),MATCH($C$2,MData[#Headers],0))} -> 283950 | I67: {=INDEX(MData[],MATCH(1,(MData[State Abbreviation]=$B67)*(MData[Report Date]=I$59)*(MData[Preliminary or Updated]=$C$3)*(MData[Final Report]=$C$4),0),MATCH($C$2,MData[#Headers],0))} -> 285541 | J67: {=INDEX(MData[],MATCH(1,(MData[State Abbreviation]=$B67)*(MData[Report Date]=J$59)*(MData[Preliminary or Updated]=$C$3)*(MData[Final Report]=$C$4),0),MATCH($C$2,MData[#Headers],0))} -> 287300 | K67: {=INDEX(MData[],MATCH(1,(MData[State Abbreviation]=$B67)*(MData[Report Date]=K$59)*(MData[Preliminary or Updated]=$C$3)*(MData[Final Report]=$C$4),0),MATCH($C$2,MData[#Headers],0))} -> 289032 | L67: {=INDEX(MData[],MATCH(1,(MData[State Abbreviation]=$B67)*(MData[Report Date]=L$59)*(MData[Preliminary or Updated]=$C$3)*(MData[Final Report]=$C$4),0),MATCH($C$2,MData[#Headers],0))} -> 290979 | M67: {=INDEX(MData[],MATCH(1,(MData[State Abbreviation]=$B67)*(MData[Report Date]=M$59)*(MData[Preliminary or Updated]=$C$3)*(MData[Final Report]=$C$4),0),MATCH($C$2,MData[#Headers],0))} -> 293136 | ... Q67: {=INDEX(MData[],MATCH(1,(MData[State Abbreviation]=$B67)*(MData[Report Date]=Q$59)*(MData[Preliminary or Updated]=$C$3)*(MData[Final Report]=$C$4),0),MATCH($C$2,MData[#Headers],0))} -> 300480 | R67: =AVERAGE(F67:Q67) -> 290238.17
A68: 9 | B68: DC | C68: District of Columbia | D68: {=INDEX(MData[],MATCH(1,(MData[State Abbreviation]=$B68)*(MData[Report Date]=D$6)*(MData[Preliminary or Updated]=$C$3)*(MData[Final Report]=$C$4),0),MATCH($D$5,MData[#Headers],0))} -> Y | E68: {=INDEX(MData[],MATCH(1,(MData[State Abbreviation]=$B68)*(MData[Report Date]=E$6)*(MData[Preliminary or Updated]=$C$3)*(MData[Final Report]=$C$4),0),MATCH($D$5,MData[#Headers],0))} -> Y | F68: {=INDEX(MData[],MATCH(1,(MData[State Abbreviation]=$B68)*(MData[Report Date]=F$59)*(MData[Preliminary or Updated]=$C$3)*(MData[Final Report]=$C$4),0),MATCH($C$2,MData[#Headers],0))} -> 277586 | G68: {=INDEX(MData[],MATCH(1,(MData[State Abbreviation]=$B68)*(MData[Report Date]=G$59)*(MData[Preliminary or Updated]=$C$3)*(MData[Final Report]=$C$4),0),MATCH($C$2,MData[#Headers],0))} -> 278984 | H68: {=INDEX(MData[],MATCH(1,(MData[State Abbreviation]=$B68)*(MData[Report Date]=H$59)*(MData[Preliminary or Updated]=$C$3)*(MData[Final Report]=$C$4),0),MATCH($C$2,MData[#Headers],0))} -> 279965 | I68: {=INDEX(MData[],MATCH(1,(MData[State Abbreviation]=$B68)*(MData[Report Date]=I$59)*(MData[Preliminary or Updated]=$C$3)*(MData[Final Report]=$C$4),0),MATCH($C$2,MData[#Headers],0))} -> 283267 | J68: {=INDEX(MData[],MATCH(1,(MData[State Abbreviation]=$B68)*(MData[Report Date]=J$59)*(MData[Preliminary or Updated]=$C$3)*(MData[Final Report]=$C$4),0),MATCH($C$2,MData[#Headers],0))} -> 285248 | K68: {=INDEX(MData[],MATCH(1,(MData[State Abbreviation]=$B68)*(MData[Report Date]=K$59)*(MData[Preliminary or Updated]=$C$3)*(MData[Final Report]=$C$4),0),MATCH($C$2,MData[#Headers],0))} -> 286000 | L68: {=INDEX(MData[],MATCH(1,(MData[State Abbreviation]=$B68)*(MData[Report Date]=L$59)*(MData[Preliminary or Updated]=$C$3)*(MData[Final Report]=$C$4),0),MATCH($C$2,MData[#Headers],0))} -> 286672 | M68: {=INDEX(MData[],MATCH(1,(MData[State Abbreviation]=$B68)*(MData[Report Date]=M$59)*(MData[Preliminary or Updated]=$C$3)*(MData[Final Report]=$C$4),0),MATCH($C$2,MData[#Headers],0))} -> 287984 | ... Q68: {=INDEX(MData[],MATCH(1,(MData[State Abbreviation]=$B68)*(MData[Report Date]=Q$59)*(MData[Preliminary or Updated]=$C$3)*(MData[Final Report]=$C$4),0),MATCH($C$2,MData[#Headers],0))} -> 292727 | R68: =AVERAGE(F68:Q68) -> 285803
A69: 10 | B69: FL | C69: Florida | D69: {=INDEX(MData[],MATCH(1,(MData[State Abbreviation]=$B69)*(MData[Report Date]=D$6)*(MData[Preliminary or Updated]=$C$3)*(MData[Final Report]=$C$4),0),MATCH($D$5,MData[#Headers],0))} -> N | E69: {=INDEX(MData[],MATCH(1,(MData[State Abbreviation]=$B69)*(MData[Report Date]=E$6)*(MData[Preliminary or Updated]=$C$3)*(MData[Final Report]=$C$4),0),MATCH($D$5,MData[#Headers],0))} -> N | F69: {=INDEX(MData[],MATCH(1,(MData[State Abbreviation]=$B69)*(MData[Report Date]=F$59)*(MData[Preliminary or Updated]=$C$3)*(MData[Final Report]=$C$4),0),MATCH($C$2,MData[#Headers],0))} -> 4539216 | G69: {=INDEX(MData[],MATCH(1,(MData[State Abbreviation]=$B69)*(MData[Report Date]=G$59)*(MData[Preliminary or Updated]=$C$3)*(MData[Final Report]=$C$4),0),MATCH($C$2,MData[#Headers],0))} -> 4564104 | H69: {=INDEX(MData[],MATCH(1,(MData[State Abbreviation]=$B69)*(MData[Report Date]=H$59)*(MData[Preliminary or Updated]=$C$3)*(MData[Final Report]=$C$4),0),MATCH($C$2,MData[#Headers],0))} -> 4596546 | I69: {=INDEX(MData[],MATCH(1,(MData[State Abbreviation]=$B69)*(MData[Report Date]=I$59)*(MData[Preliminary or Updated]=$C$3)*(MData[Final Report]=$C$4),0),MATCH($C$2,MData[#Headers],0))} -> 4631017 | J69: {=INDEX(MData[],MATCH(1,(MData[State Abbreviation]=$B69)*(MData[Report Date]=J$59)*(MData[Preliminary or Updated]=$C$3)*(MData[Final Report]=$C$4),0),MATCH($C$2,MData[#Headers],0))} -> 4670235 | K69: {=INDEX(MData[],MATCH(1,(MData[State Abbreviation]=$B69)*(MData[Report Date]=K$59)*(MData[Preliminary or Updated]=$C$3)*(MData[Final Report]=$C$4),0),MATCH($C$2,MData[#Headers],0))} -> 4704468 | L69: {=INDEX(MData[],MATCH(1,(MData[State Abbreviation]=$B69)*(MData[Report Date]=L$59)*(MData[Preliminary or Updated]=$C$3)*(MData[Final Report]=$C$4),0),MATCH($C$2,MData[#Headers],0))} -> 4734996 | M69: {=INDEX(MData[],MATCH(1,(MData[State Abbreviation]=$B69)*(MData[Report Date]=M$59)*(MData[Preliminary or Updated]=$C$3)*(MData[Final Report]=$C$4),0),MATCH($C$2,MData[#Headers],0))} -> 4773338 | ... Q69: {=INDEX(MData[],MATCH(1,(MData[State Abbreviation]=$B69)*(MData[Report Date]=Q$59)*(MData[Preliminary or Updated]=$C$3)*(MData[Final Report]=$C$4),0),MATCH($C$2,MData[#Headers],0))} -> 4883951 | R69: =AVERAGE(F69:Q69) -> 4714528.5
A70: 11 | B70: GA | C70: Georgia | D70: {=INDEX(MData[],MATCH(1,(MData[State Abbreviation]=$B70)*(MData[Report Date]=D$6)*(MData[Preliminary or Updated]=$C$3)*(MData[Final Report]=$C$4),0),MATCH($D$5,MData[#Headers],0))} -> N | E70: {=INDEX(MData[],MATCH(1,(MData[State Abbreviation]=$B70)*(MData[Report Date]=E$6)*(MData[Preliminary or Updated]=$C$3)*(MData[Final Report]=$C$4),0),MATCH($D$5,MData[#Headers],0))} -> N | F70: {=INDEX(MData[],MATCH(1,(MData[State Abbreviation]=$B70)*(MData[Report Date]=F$59)*(MData[Preliminary or Updated]=$C$3)*(MData[Final Report]=$C$4),0),MATCH($C$2,MData[#Headers],0))} -> 2320281 | G70: {=INDEX(MData[],MATCH(1,(MData[State Abbreviation]=$B70)*(MData[Report Date]=G$59)*(MData[Preliminary or Updated]=$C$3)*(MData[Final Report]=$C$4),0),MATCH($C$2,MData[#Headers],0))} -> 2335335 | H70: {=INDEX(MData[],MATCH(1,(MData[State Abbreviation]=$B70)*(MData[Report Date]=H$59)*(MData[Preliminary or Updated]=$C$3)*(MData[Final Report]=$C$4),0),MATCH($C$2,MData[#Headers],0))} -> 2349817 | I70: {=INDEX(MData[],MATCH(1,(MData[State Abbreviation]=$B70)*(MData[Report Date]=I$59)*(MData[Preliminary or Updated]=$C$3)*(MData[Final Report]=$C$4),0),MATCH($C$2,MData[#Headers],0))} -> 2358345 | J70: {=INDEX(MData[],MATCH(1,(MData[State Abbreviation]=$B70)*(MData[Report Date]=J$59)*(MData[Preliminary or Updated]=$C$3)*(MData[Final Report]=$C$4),0),MATCH($C$2,MData[#Headers],0))} -> 2373707 | K70: {=INDEX(MData[],MATCH(1,(MData[State Abbreviation]=$B70)*(MData[Report Date]=K$59)*(MData[Preliminary or Updated]=$C$3)*(MData[Final Report]=$C$4),0),MATCH($C$2,MData[#Headers],0))} -> 2388803 | L70: {=INDEX(MData[],MATCH(1,(MData[State Abbreviation]=$B70)*(MData[Report Date]=L$59)*(MData[Preliminary or Updated]=$C$3)*(MData[Final Report]=$C$4),0),MATCH($C$2,MData[#Headers],0))} -> 2405477 | M70: {=INDEX(MData[],MATCH(1,(MData[State Abbreviation]=$B70)*(MData[Report Date]=M$59)*(MData[Preliminary or Updated]=$C$3)*(MData[Final Report]=$C$4),0),MATCH($C$2,MData[#Headers],0))} -> 2423690 | ... Q70: {=INDEX(MData[],MATCH(1,(MData[State Abbreviation]=$B70)*(MData[Report Date]=Q$59)*(MData[Preliminary or Updated]=$C$3)*(MData[Final Report]=$C$4),0),MATCH($C$2,MData[#Headers],0))} -> 2485394 | R70: =AVERAGE(F70:Q70) -> 2400788.9
A71: 12 | B71: HI | C71: Hawaii | D71: {=INDEX(MData[],MATCH(1,(MData[State Abbreviation]=$B71)*(MData[Report Date]=D$6)*(MData[Preliminary or Updated]=$C$3)*(MData[Final Report]=$C$4),0),MATCH($D$5,MData[#Headers],0))} -> Y | E71: {=INDEX(MData[],MATCH(1,(MData[State Abbreviation]=$B71)*(MData[Report Date]=E$6)*(MData[Preliminary or Updated]=$C$3)*(MData[Final Report]=$C$4),0),MATCH($D$5,MData[#Headers],0))} -> Y | F71: {=INDEX(MData[],MATCH(1,(MData[State Abbreviation]=$B71)*(MData[Report Date]=F$59)*(MData[Preliminary or Updated]=$C$3)*(MData[Final Report]=$C$4),0),MATCH($C$2,MData[#Headers],0))} -> 440394 | G71: {=INDEX(MData[],MATCH(1,(MData[State Abbreviation]=$B71)*(MData[Report Date]=G$59)*(MData[Preliminary or Updated]=$C$3)*(MData[Final Report]=$C$4),0),MATCH($C$2,MData[#Headers],0))} -> 441896 | H71: {=INDEX(MData[],MATCH(1,(MData[State Abbreviation]=$B71)*(MData[Report Date]=H$59)*(MData[Preliminary or Updated]=$C$3)*(MData[Final Report]=$C$4),0),MATCH($C$2,MData[#Headers],0))} -> 444463 | I71: {=INDEX(MData[],MATCH(1,(MData[State Abbreviation]=$B71)*(MData[Report Date]=I$59)*(MData[Preliminary or Updated]=$C$3)*(MData[Final Report]=$C$4),0),MATCH($C$2,MData[#Headers],0))} -> 446467 | J71: {=INDEX(MData[],MATCH(1,(MData[State Abbreviation]=$B71)*(MData[Report Date]=J$59)*(MData[Preliminary or Updated]=$C$3)*(MData[Final Report]=$C$4),0),MATCH($C$2,MData[#Headers],0))} -> 448383 | K71: {=INDEX(MData[],MATCH(1,(MData[State Abbreviation]=$B71)*(MData[Report Date]=K$59)*(MData[Preliminary or Updated]=$C$3)*(MData[Final Report]=$C$4),0),MATCH($C$2,MData[#Headers],0))} -> 450481 | L71: {=INDEX(MData[],MATCH(1,(MData[State Abbreviation]=$B71)*(MData[Report Date]=L$59)*(MData[Preliminary or Updated]=$C$3)*(MData[Final Report]=$C$4),0),MATCH($C$2,MData[#Headers],0))} -> 452696 | M71: {=INDEX(MData[],MATCH(1,(MData[State Abbreviation]=$B71)*(MData[Report Date]=M$59)*(MData[Preliminary or Updated]=$C$3)*(MData[Final Report]=$C$4),0),MATCH($C$2,MData[#Headers],0))} -> 454990 | ... Q71: {=INDEX(MData[],MATCH(1,(MData[State Abbreviation]=$B71)*(MData[Report Date]=Q$59)*(MData[Preliminary or Updated]=$C$3)*(MData[Final Report]=$C$4),0),MATCH($C$2,MData[#Headers],0))} -> 459261 | R71: =AVERAGE(F71:Q71) -> 450362.92
... A110: 51 | B110: WY | C110: Wyoming | D110: {=INDEX(MData[],MATCH(1,(MData[State Abbreviation]=$B110)*(MData[Report Date]=D$6)*(MData[Preliminary or Updated]=$C$3)*(MData[Final Report]=$C$4),0),MATCH($D$5,MData[#Headers],0))} -> N | E110: {=INDEX(MData[],MATCH(1,(MData[State Abbreviation]=$B110)*(MData[Report Date]=E$6)*(MData[Preliminary or Updated]=$C$3)*(MData[Final Report]=$C$4),0),MATCH($D$5,MData[#Headers],0))} -> N | F110: {=INDEX(MData[],MATCH(1,(MData[State Abbreviation]=$B110)*(MData[Report Date]=F$59)*(MData[Preliminary or Updated]=$C$3)*(MData[Final Report]=$C$4),0),MATCH($C$2,MData[#Headers],0))} -> 73440 | G110: {=INDEX(MData[],MATCH(1,(MData[State Abbreviation]=$B110)*(MData[Report Date]=G$59)*(MData[Preliminary or Updated]=$C$3)*(MData[Final Report]=$C$4),0),MATCH($C$2,MData[#Headers],0))} -> 74185 | H110: {=INDEX(MData[],MATCH(1,(MData[State Abbreviation]=$B110)*(MData[Report Date]=H$59)*(MData[Preliminary or Updated]=$C$3)*(MData[Final Report]=$C$4),0),MATCH($C$2,MData[#Headers],0))} -> 74832 | I110: {=INDEX(MData[],MATCH(1,(MData[State Abbreviation]=$B110)*(MData[Report Date]=I$59)*(MData[Preliminary or Updated]=$C$3)*(MData[Final Report]=$C$4),0),MATCH($C$2,MData[#Headers],0))} -> 75200 | J110: {=INDEX(MData[],MATCH(1,(MData[State Abbreviation]=$B110)*(MData[Report Date]=J$59)*(MData[Preliminary or Updated]=$C$3)*(MData[Final Report]=$C$4),0),MATCH($C$2,MData[#Headers],0))} -> 76431 | K110: {=INDEX(MData[],MATCH(1,(MData[State Abbreviation]=$B110)*(MData[Report Date]=K$59)*(MData[Preliminary or Updated]=$C$3)*(MData[Final Report]=$C$4),0),MATCH($C$2,MData[#Headers],0))} -> 78132 | L110: {=INDEX(MData[],MATCH(1,(MData[State Abbreviation]=$B110)*(MData[Report Date]=L$59)*(MData[Preliminary or Updated]=$C$3)*(MData[Final Report]=$C$4),0),MATCH($C$2,MData[#Headers],0))} -> 79318 | M110: {=INDEX(MData[],MATCH(1,(MData[State Abbreviation]=$B110)*(MData[Report Date]=M$59)*(MData[Preliminary or Updated]=$C$3)*(MData[Final Report]=$C$4),0),MATCH($C$2,MData[#Headers],0))} -> 80208 | ... Q110: {=INDEX(MData[],MATCH(1,(MData[State Abbreviation]=$B110)*(MData[Report Date]=Q$59)*(MData[Preliminary or Updated]=$C$3)*(MData[Final Report]=$C$4),0),MATCH($C$2,MData[#Headers],0))} -> 83301 | R110: =AVERAGE(F110:Q110) -> 78254.417
D111: State Expanded Medicaid
B112: Post Code | C112: State | D112: 44197 | E112: 44531 | F112: 44197 | G112: 44228 | H112: 44256 | I112: 44287 | J112: 44317 | K112: 44348 | L112: 44378 | M112: 44409 | N112: 44440 | O112: 44470 | P112: 44501 | Q112: 44531 | R112: average
A113: 1 | B113: AL | C113: Alabama | D113: {=INDEX(MData[],MATCH(1,(MData[State Abbreviation]=$B113)*(MData[Report Date]=D$6)*(MData[Preliminary or Updated]=$C$3)*(MData[Final Report]=$C$4),0),MATCH($D$5,MData[#Headers],0))} -> N | E113: {=INDEX(MData[],MATCH(1,(MData[State Abbreviation]=$B113)*(MData[Report Date]=E$6)*(MData[Preliminary or Updated]=$C$3)*(MData[Final Report]=$C$4),0),MATCH($D$5,MData[#Headers],0))} -> N | F113: {=INDEX(MData[],MATCH(1,(MData[State Abbreviation]=$B113)*(MData[Report Date]=F$112)*(MData[Preliminary or Updated]=$C$3)*(MData[Final Report]=$C$4),0),MATCH($C$2,MData[#Headers],0))} -> 1009033 | G113: {=INDEX(MData[],MATCH(1,(MData[State Abbreviation]=$B113)*(MData[Report Date]=G$112)*(MData[Preliminary or Updated]=$C$3)*(MData[Final Report]=$C$4),0),MATCH($C$2,MData[#Headers],0))} -> 1015804 | H113: {=INDEX(MData[],MATCH(1,(MData[State Abbreviation]=$B113)*(MData[Report Date]=H$112)*(MData[Preliminary or Updated]=$C$3)*(MData[Final Report]=$C$4),0),MATCH($C$2,MData[#Headers],0))} -> 1023300 | I113: {=INDEX(MData[],MATCH(1,(MData[State Abbreviation]=$B113)*(MData[Report Date]=I$112)*(MData[Preliminary or Updated]=$C$3)*(MData[Final Report]=$C$4),0),MATCH($C$2,MData[#Headers],0))} -> 1031694 | J113: {=INDEX(MData[],MATCH(1,(MData[State Abbreviation]=$B113)*(MData[Report Date]=J$112)*(MData[Preliminary or Updated]=$C$3)*(MData[Final Report]=$C$4),0),MATCH($C$2,MData[#Headers],0))} -> 1038830 | K113: {=INDEX(MData[],MATCH(1,(MData[State Abbreviation]=$B113)*(MData[Report Date]=K$112)*(MData[Preliminary or Updated]=$C$3)*(MData[Final Report]=$C$4),0),MATCH($C$2,MData[#Headers],0))} -> 1047619 | L113: {=INDEX(MData[],MATCH(1,(MData[State Abbreviation]=$B113)*(MData[Report Date]=L$112)*(MData[Preliminary or Updated]=$C$3)*(MData[Final Report]=$C$4),0),MATCH($C$2,MData[#Headers],0))} -> 1055463 | M113: {=INDEX(MData[],MATCH(1,(MData[State Abbreviation]=$B113)*(MData[Report Date]=M$112)*(MData[Preliminary or Updated]=$C$3)*(MData[Final Report]=$C$4),0),MATCH($C$2,MData[#Headers],0))} -> 1063643 | ... Q113: {=INDEX(MData[],MATCH(1,(MData[State Abbreviation]=$B113)*(MData[Report Date]=Q$112)*(MData[Preliminary or Updated]=$C$3)*(MData[Final Report]=$C$4),0),MATCH($C$2,MData[#Headers],0))} -> 1091996 | R113: =AVERAGE(F113:Q113) -> 1050933.4
A114: 2 | B114: AK | C114: Alaska | D114: {=INDEX(MData[],MATCH(1,(MData[State Abbreviation]=$B114)*(MData[Report Date]=D$6)*(MData[Preliminary or Updated]=$C$3)*(MData[Final Report]=$C$4),0),MATCH($D$5,MData[#Headers],0))} -> Y | E114: {=INDEX(MData[],MATCH(1,(MData[State Abbreviation]=$B114)*(MData[Report Date]=E$6)*(MData[Preliminary or Updated]=$C$3)*(MData[Final Report]=$C$4),0),MATCH($D$5,MData[#Headers],0))} -> Y | F114: {=INDEX(MData[],MATCH(1,(MData[State Abbreviation]=$B114)*(MData[Report Date]=F$112)*(MData[Preliminary or Updated]=$C$3)*(MData[Final Report]=$C$4),0),MATCH($C$2,MData[#Headers],0))} -> 241410 | G114: {=INDEX(MData[],MATCH(1,(MData[State Abbreviation]=$B114)*(MData[Report Date]=G$112)*(MData[Preliminary or Updated]=$C$3)*(MData[Final Report]=$C$4),0),MATCH($C$2,MData[#Headers],0))} -> 242991 | H114: {=INDEX(MData[],MATCH(1,(MData[State Abbreviation]=$B114)*(MData[Report Date]=H$112)*(MData[Preliminary or Updated]=$C$3)*(MData[Final Report]=$C$4),0),MATCH($C$2,MData[#Headers],0))} -> 244860 | I114: {=INDEX(MData[],MATCH(1,(MData[State Abbreviation]=$B114)*(MData[Report Date]=I$112)*(MData[Preliminary or Updated]=$C$3)*(MData[Final Report]=$C$4),0),MATCH($C$2,MData[#Headers],0))} -> 247180 | J114: {=INDEX(MData[],MATCH(1,(MData[State Abbreviation]=$B114)*(MData[Report Date]=J$112)*(MData[Preliminary or Updated]=$C$3)*(MData[Final Report]=$C$4),0),MATCH($C$2,MData[#Headers],0))} -> 248739 | K114: {=INDEX(MData[],MATCH(1,(MData[State Abbreviation]=$B114)*(MData[Report Date]=K$112)*(MData[Preliminary or Updated]=$C$3)*(MData[Final Report]=$C$4),0),MATCH($C$2,MData[#Headers],0))} -> 250285 | L114: {=INDEX(MData[],MATCH(1,(MData[State Abbreviation]=$B114)*(MData[Report Date]=L$112)*(MData[Preliminary or Updated]=$C$3)*(MData[Final Report]=$C$4),0),MATCH($C$2,MData[#Headers],0))} -> 251024 | M114: {=INDEX(MData[],MATCH(1,(MData[State Abbreviation]=$B114)*(MData[Report Date]=M$112)*(MData[Preliminary or Updated]=$C$3)*(MData[Final Report]=$C$4),0),MATCH($C$2,MData[#Headers],0))} -> 251977 | ... Q114: {=INDEX(MData[],MATCH(1,(MData[State Abbreviation]=$B114)*(MData[Report Date]=Q$112)*(MData[Preliminary or Updated]=$C$3)*(MData[Final Report]=$C$4),0),MATCH($C$2,MData[#Headers],0))} -> 255746 | R114: =AVERAGE(F114:Q114) -> 249695.58
A115: 3 | B115: AZ | C115: Arizona | D115: {=INDEX(MData[],MATCH(1,(MData[State Abbreviation]=$B115)*(MData[Report Date]=D$6)*(MData[Preliminary or Updated]=$C$3)*(MData[Final Report]=$C$4),0),MATCH($D$5,MData[#Headers],0))} -> Y | E115: {=INDEX(MData[],MATCH(1,(MData[State Abbreviation]=$B115)*(MData[Report Date]=E$6)*(MData[Preliminary or Updated]=$C$3)*(MData[Final Report]=$C$4),0),MATCH($D$5,MData[#Headers],0))} -> Y | F115: {=INDEX(MData[],MATCH(1,(MData[State Abbreviation]=$B115)*(MData[Report Date]=F$112)*(MData[Preliminary or Updated]=$C$3)*(MData[Final Report]=$C$4),0),MATCH($C$2,MData[#Headers],0))} -> 1981809 | G115: {=INDEX(MData[],MATCH(1,(MData[State Abbreviation]=$B115)*(MData[Report Date]=G$112)*(MData[Preliminary or Updated]=$C$3)*(MData[Final Report]=$C$4),0),MATCH($C$2,MData[#Headers],0))} -> 1998341 | H115: {=INDEX(MData[],MATCH(1,(MData[State Abbreviation]=$B115)*(MData[Report Date]=H$112)*(MData[Preliminary or Updated]=$C$3)*(MData[Final Report]=$C$4),0),MATCH($C$2,MData[#Headers],0))} -> 2011270 | I115: {=INDEX(MData[],MATCH(1,(MData[State Abbreviation]=$B115)*(MData[Report Date]=I$112)*(MData[Preliminary or Updated]=$C$3)*(MData[Final Report]=$C$4),0),MATCH($C$2,MData[#Headers],0))} -> 2027065 | J115: {=INDEX(MData[],MATCH(1,(MData[State Abbreviation]=$B115)*(MData[Report Date]=J$112)*(MData[Preliminary or Updated]=$C$3)*(MData[Final Report]=$C$4),0),MATCH($C$2,MData[#Headers],0))} -> 2044604 | K115: {=INDEX(MData[],MATCH(1,(MData[State Abbreviation]=$B115)*(MData[Report Date]=K$112)*(MData[Preliminary or Updated]=$C$3)*(MData[Final Report]=$C$4),0),MATCH($C$2,MData[#Headers],0))} -> 2059556 | L115: {=INDEX(MData[],MATCH(1,(MData[State Abbreviation]=$B115)*(MData[Report Date]=L$112)*(MData[Preliminary or Updated]=$C$3)*(MData[Final Report]=$C$4),0),MATCH($C$2,MData[#Headers],0))} -> 2072102 | M115: {=INDEX(MData[],MATCH(1,(MData[State Abbreviation]=$B115)*(MData[Report Date]=M$112)*(MData[Preliminary or Updated]=$C$3)*(MData[Final Report]=$C$4),0),MATCH($C$2,MData[#Headers],0))} -> 2088145 | ... Q115: {=INDEX(MData[],MATCH(1,(MData[State Abbreviation]=$B115)*(MData[Report Date]=Q$112)*(MData[Preliminary or Updated]=$C$3)*(MData[Final Report]=$C$4),0),MATCH($C$2,MData[#Headers],0))} -> 2139682 | R115: =AVERAGE(F115:Q115) -> 2063827.5
A116: 4 | B116: AR | C116: Arkansas | D116: {=INDEX(MData[],MATCH(1,(MData[State Abbreviation]=$B116)*(MData[Report Date]=D$6)*(MData[Preliminary or Updated]=$C$3)*(MData[Final Report]=$C$4),0),MATCH($D$5,MData[#Headers],0))} -> Y | E116: {=INDEX(MData[],MATCH(1,(MData[State Abbreviation]=$B116)*(MData[Report Date]=E$6)*(MData[Preliminary or Updated]=$C$3)*(MData[Final Report]=$C$4),0),MATCH($D$5,MData[#Headers],0))} -> Y | F116: {=INDEX(MData[],MATCH(1,(MData[State Abbreviation]=$B116)*(MData[Report Date]=F$112)*(MData[Preliminary or Updated]=$C$3)*(MData[Final Report]=$C$4),0),MATCH($C$2,MData[#Headers],0))} -> 898965 | G116: {=INDEX(MData[],MATCH(1,(MData[State Abbreviation]=$B116)*(MData[Report Date]=G$112)*(MData[Preliminary or Updated]=$C$3)*(MData[Final Report]=$C$4),0),MATCH($C$2,MData[#Headers],0))} -> 903150 | H116: {=INDEX(MData[],MATCH(1,(MData[State Abbreviation]=$B116)*(MData[Report Date]=H$112)*(MData[Preliminary or Updated]=$C$3)*(MData[Final Report]=$C$4),0),MATCH($C$2,MData[#Headers],0))} -> 910463 | I116: {=INDEX(MData[],MATCH(1,(MData[State Abbreviation]=$B116)*(MData[Report Date]=I$112)*(MData[Preliminary or Updated]=$C$3)*(MData[Final Report]=$C$4),0),MATCH($C$2,MData[#Headers],0))} -> 916841 | J116: {=INDEX(MData[],MATCH(1,(MData[State Abbreviation]=$B116)*(MData[Report Date]=J$112)*(MData[Preliminary or Updated]=$C$3)*(MData[Final Report]=$C$4),0),MATCH($C$2,MData[#Headers],0))} -> 920717 | K116: {=INDEX(MData[],MATCH(1,(MData[State Abbreviation]=$B116)*(MData[Report Date]=K$112)*(MData[Preliminary or Updated]=$C$3)*(MData[Final Report]=$C$4),0),MATCH($C$2,MData[#Headers],0))} -> 927247 | L116: {=INDEX(MData[],MATCH(1,(MData[State Abbreviation]=$B116)*(MData[Report Date]=L$112)*(MData[Preliminary or Updated]=$C$3)*(MData[Final Report]=$C$4),0),MATCH($C$2,MData[#Headers],0))} -> 934944 | M116: {=INDEX(MData[],MATCH(1,(MData[State Abbreviation]=$B116)*(MData[Report Date]=M$112)*(MData[Preliminary or Updated]=$C$3)*(MData[Final Report]=$C$4),0),MATCH($C$2,MData[#Headers],0))} -> 941715 | ... Q116: {=INDEX(MData[],MATCH(1,(MData[State Abbreviation]=$B116)*(MData[Report Date]=Q$112)*(MData[Preliminary or Updated]=$C$3)*(MData[Final Report]=$C$4),0),MATCH($C$2,MData[#Headers],0))} -> 965168 | R116: =AVERAGE(F116:Q116) -> 931714.58
A117: 5 | B117: CA | C117: California | D117: {=INDEX(MData[],MATCH(1,(MData[State Abbreviation]=$B117)*(MData[Report Date]=D$6)*(MData[Preliminary or Updated]=$C$3)*(MData[Final Report]=$C$4),0),MATCH($D$5,MData[#Headers],0))} -> Y | E117: {=INDEX(MData[],MATCH(1,(MData[State Abbreviation]=$B117)*(MData[Report Date]=E$6)*(MData[Preliminary or Updated]=$C$3)*(MData[Final Report]=$C$4),0),MATCH($D$5,MData[#Headers],0))} -> Y | F117: {=INDEX(MData[],MATCH(1,(MData[State Abbreviation]=$B117)*(MData[Report Date]=F$112)*(MData[Preliminary or Updated]=$C$3)*(MData[Final Report]=$C$4),0),MATCH($C$2,MData[#Headers],0))} -> 12586999 | G117: {=INDEX(MData[],MATCH(1,(MData[State Abbreviation]=$B117)*(MData[Report Date]=G$112)*(MData[Preliminary or Updated]=$C$3)*(MData[Final Report]=$C$4),0),MATCH($C$2,MData[#Headers],0))} -> 12643124 | H117: {=INDEX(MData[],MATCH(1,(MData[State Abbreviation]=$B117)*(MData[Report Date]=H$112)*(MData[Preliminary or Updated]=$C$3)*(MData[Final Report]=$C$4),0),MATCH($C$2,MData[#Headers],0))} -> 12724578 | I117: {=INDEX(MData[],MATCH(1,(MData[State Abbreviation]=$B117)*(MData[Report Date]=I$112)*(MData[Preliminary or Updated]=$C$3)*(MData[Final Report]=$C$4),0),MATCH($C$2,MData[#Headers],0))} -> 12790804 | J117: {=INDEX(MData[],MATCH(1,(MData[State Abbreviation]=$B117)*(MData[Report Date]=J$112)*(MData[Preliminary or Updated]=$C$3)*(MData[Final Report]=$C$4),0),MATCH($C$2,MData[#Headers],0))} -> 12850229 | K117: {=INDEX(MData[],MATCH(1,(MData[State Abbreviation]=$B117)*(MData[Report Date]=K$112)*(MData[Preliminary or Updated]=$C$3)*(MData[Final Report]=$C$4),0),MATCH($C$2,MData[#Headers],0))} -> 12913441 | L117: {=INDEX(MData[],MATCH(1,(MData[State Abbreviation]=$B117)*(MData[Report Date]=L$112)*(MData[Preliminary or Updated]=$C$3)*(MData[Final Report]=$C$4),0),MATCH($C$2,MData[#Headers],0))} -> 12983442 | M117: {=INDEX(MData[],MATCH(1,(MData[State Abbreviation]=$B117)*(MData[Report Date]=M$112)*(MData[Preliminary or Updated]=$C$3)*(MData[Final Report]=$C$4),0),MATCH($C$2,MData[#Headers],0))} -> 13058458 | ... Q117: {=INDEX(MData[],MATCH(1,(MData[State Abbreviation]=$B117)*(MData[Report Date]=Q$112)*(MData[Preliminary or Updated]=$C$3)*(MData[Final Report]=$C$4),0),MATCH($C$2,MData[#Headers],0))} -> 13292295 | R117: =AVERAGE(F117:Q117) -> 12947026
A118: 6 | B118: CO | C118: Colorado | D118: {=INDEX(MData[],MATCH(1,(MData[State Abbreviation]=$B118)*(MData[Report Date]=D$6)*(MData[Preliminary or Updated]=$C$3)*(MData[Final Report]=$C$4),0),MATCH($D$5,MData[#Headers],0))} -> Y | E118: {=INDEX(MData[],MATCH(1,(MData[State Abbreviation]=$B118)*(MData[Report Date]=E$6)*(MData[Preliminary or Updated]=$C$3)*(MData[Final Report]=$C$4),0),MATCH($D$5,MData[#Headers],0))} -> Y | F118: {=INDEX(MData[],MATCH(1,(MData[State Abbreviation]=$B118)*(MData[Report Date]=F$112)*(MData[Preliminary or Updated]=$C$3)*(MData[Final Report]=$C$4),0),MATCH($C$2,MData[#Headers],0))} -> 1466436 | G118: {=INDEX(MData[],MATCH(1,(MData[State Abbreviation]=$B118)*(MData[Report Date]=G$112)*(MData[Preliminary or Updated]=$C$3)*(MData[Final Report]=$C$4),0),MATCH($C$2,MData[#Headers],0))} -> 1477439 | H118: {=INDEX(MData[],MATCH(1,(MData[State Abbreviation]=$B118)*(MData[Report Date]=H$112)*(MData[Preliminary or Updated]=$C$3)*(MData[Final Report]=$C$4),0),MATCH($C$2,MData[#Headers],0))} -> 1489827 | I118: {=INDEX(MData[],MATCH(1,(MData[State Abbreviation]=$B118)*(MData[Report Date]=I$112)*(MData[Preliminary or Updated]=$C$3)*(MData[Final Report]=$C$4),0),MATCH($C$2,MData[#Headers],0))} -> 1501448 | J118: {=INDEX(MData[],MATCH(1,(MData[State Abbreviation]=$B118)*(MData[Report Date]=J$112)*(MData[Preliminary or Updated]=$C$3)*(MData[Final Report]=$C$4),0),MATCH($C$2,MData[#Headers],0))} -> 1511858 | K118: {=INDEX(MData[],MATCH(1,(MData[State Abbreviation]=$B118)*(MData[Report Date]=K$112)*(MData[Preliminary or Updated]=$C$3)*(MData[Final Report]=$C$4),0),MATCH($C$2,MData[#Headers],0))} -> 1522471 | L118: {=INDEX(MData[],MATCH(1,(MData[State Abbreviation]=$B118)*(MData[Report Date]=L$112)*(MData[Preliminary or Updated]=$C$3)*(MData[Final Report]=$C$4),0),MATCH($C$2,MData[#Headers],0))} -> 1532326 | M118: {=INDEX(MData[],MATCH(1,(MData[State Abbreviation]=$B118)*(MData[Report Date]=M$112)*(MData[Preliminary or Updated]=$C$3)*(MData[Final Report]=$C$4),0),MATCH($C$2,MData[#Headers],0))} -> 1544088 | ... Q118: {=INDEX(MData[],MATCH(1,(MData[State Abbreviation]=$B118)*(MData[Report Date]=Q$112)*(MData[Preliminary or Updated]=$C$3)*(MData[Final Report]=$C$4),0),MATCH($C$2,MData[#Headers],0))} -> 1585726 | R118: =AVERAGE(F118:Q118) -> 1526930.2
A119: 7 | B119: CT | C119: Connecticut | D119: {=INDEX(MData[],MATCH(1,(MData[State Abbreviation]=$B119)*(MData[Report Date]=D$6)*(MData[Preliminary or Updated]=$C$3)*(MData[Final Report]=$C$4),0),MATCH($D$5,MData[#Headers],0))} -> Y | E119: {=INDEX(MData[],MATCH(1,(MData[State Abbreviation]=$B119)*(MData[Report Date]=E$6)*(MData[Preliminary or Updated]=$C$3)*(MData[Final Report]=$C$4),0),MATCH($D$5,MData[#Headers],0))} -> Y | F119: {=INDEX(MData[],MATCH(1,(MData[State Abbreviation]=$B119)*(MData[Report Date]=F$112)*(MData[Preliminary or Updated]=$C$3)*(MData[Final Report]=$C$4),0),MATCH($C$2,MData[#Headers],0))} -> 937667 | G119: {=INDEX(MData[],MATCH(1,(MData[State Abbreviation]=$B119)*(MData[Report Date]=G$112)*(MData[Preliminary or Updated]=$C$3)*(MData[Final Report]=$C$4),0),MATCH($C$2,MData[#Headers],0))} -> 941576 | H119: {=INDEX(MData[],MATCH(1,(MData[State Abbreviation]=$B119)*(MData[Report Date]=H$112)*(MData[Preliminary or Updated]=$C$3)*(MData[Final Report]=$C$4),0),MATCH($C$2,MData[#Headers],0))} -> 948002 | I119: {=INDEX(MData[],MATCH(1,(MData[State Abbreviation]=$B119)*(MData[Report Date]=I$112)*(MData[Preliminary or Updated]=$C$3)*(MData[Final Report]=$C$4),0),MATCH($C$2,MData[#Headers],0))} -> 949551 | J119: {=INDEX(MData[],MATCH(1,(MData[State Abbreviation]=$B119)*(MData[Report Date]=J$112)*(MData[Preliminary or Updated]=$C$3)*(MData[Final Report]=$C$4),0),MATCH($C$2,MData[#Headers],0))} -> 951563 | K119: {=INDEX(MData[],MATCH(1,(MData[State Abbreviation]=$B119)*(MData[Report Date]=K$112)*(MData[Preliminary or Updated]=$C$3)*(MData[Final Report]=$C$4),0),MATCH($C$2,MData[#Headers],0))} -> 961399 | L119: {=INDEX(MData[],MATCH(1,(MData[State Abbreviation]=$B119)*(MData[Report Date]=L$112)*(MData[Preliminary or Updated]=$C$3)*(MData[Final Report]=$C$4),0),MATCH($C$2,MData[#Headers],0))} -> 960844 | M119: {=INDEX(MData[],MATCH(1,(MData[State Abbreviation]=$B119)*(MData[Report Date]=M$112)*(MData[Preliminary or Updated]=$C$3)*(MData[Final Report]=$C$4),0),MATCH($C$2,MData[#Headers],0))} -> 962673 | ... Q119: {=INDEX(MData[],MATCH(1,(MData[State Abbreviation]=$B119)*(MData[Report Date]=Q$112)*(MData[Preliminary or Updated]=$C$3)*(MData[Final Report]=$C$4),0),MATCH($C$2,MData[#Headers],0))} -> 968210 | R119: =AVERAGE(F119:Q119) -> 955636
A120: 8 | B120: DE | C120: Delaware | D120: {=INDEX(MData[],MATCH(1,(MData[State Abbreviation]=$B120)*(MData[Report Date]=D$6)*(MData[Preliminary or Updated]=$C$3)*(MData[Final Report]=$C$4),0),MATCH($D$5,MData[#Headers],0))} -> Y | E120: {=INDEX(MData[],MATCH(1,(MData[State Abbreviation]=$B120)*(MData[Report Date]=E$6)*(MData[Preliminary or Updated]=$C$3)*(MData[Final Report]=$C$4),0),MATCH($D$5,MData[#Headers],0))} -> Y | F120: {=INDEX(MData[],MATCH(1,(MData[State Abbreviation]=$B120)*(MData[Report Date]=F$112)*(MData[Preliminary or Updated]=$C$3)*(MData[Final Report]=$C$4),0),MATCH($C$2,MData[#Headers],0))} -> 260236 | G120: {=INDEX(MData[],MATCH(1,(MData[State Abbreviation]=$B120)*(MData[Report Date]=G$112)*(MData[Preliminary or Updated]=$C$3)*(MData[Final Report]=$C$4),0),MATCH($C$2,MData[#Headers],0))} -> 262185 | H120: {=INDEX(MData[],MATCH(1,(MData[State Abbreviation]=$B120)*(MData[Report Date]=H$112)*(MData[Preliminary or Updated]=$C$3)*(MData[Final Report]=$C$4),0),MATCH($C$2,MData[#Headers],0))} -> 264446 | I120: {=INDEX(MData[],MATCH(1,(MData[State Abbreviation]=$B120)*(MData[Report Date]=I$112)*(MData[Preliminary or Updated]=$C$3)*(MData[Final Report]=$C$4),0),MATCH($C$2,MData[#Headers],0))} -> 265098 | J120: {=INDEX(MData[],MATCH(1,(MData[State Abbreviation]=$B120)*(MData[Report Date]=J$112)*(MData[Preliminary or Updated]=$C$3)*(MData[Final Report]=$C$4),0),MATCH($C$2,MData[#Headers],0))} -> 267045 | K120: {=INDEX(MData[],MATCH(1,(MData[State Abbreviation]=$B120)*(MData[Report Date]=K$112)*(MData[Preliminary or Updated]=$C$3)*(MData[Final Report]=$C$4),0),MATCH($C$2,MData[#Headers],0))} -> 268963 | L120: {=INDEX(MData[],MATCH(1,(MData[State Abbreviation]=$B120)*(MData[Report Date]=L$112)*(MData[Preliminary or Updated]=$C$3)*(MData[Final Report]=$C$4),0),MATCH($C$2,MData[#Headers],0))} -> 271159 | M120: {=INDEX(MData[],MATCH(1,(MData[State Abbreviation]=$B120)*(MData[Report Date]=M$112)*(MData[Preliminary or Updated]=$C$3)*(MData[Final Report]=$C$4),0),MATCH($C$2,MData[#Headers],0))} -> 273386 | ... Q120: {=INDEX(MData[],MATCH(1,(MData[State Abbreviation]=$B120)*(MData[Report Date]=Q$112)*(MData[Preliminary or Updated]=$C$3)*(MData[Final Report]=$C$4),0),MATCH($C$2,MData[#Headers],0))} -> 278171 | R120: =AVERAGE(F120:Q120) -> 270085.42
A121: 9 | B121: DC | C121: District of Columbia | D121: {=INDEX(MData[],MATCH(1,(MData[State Abbreviation]=$B121)*(MData[Report Date]=D$6)*(MData[Preliminary or Updated]=$C$3)*(MData[Final Report]=$C$4),0),MATCH($D$5,MData[#Headers],0))} -> Y | E121: {=INDEX(MData[],MATCH(1,(MData[State Abbreviation]=$B121)*(MData[Report Date]=E$6)*(MData[Preliminary or Updated]=$C$3)*(MData[Final Report]=$C$4),0),MATCH($D$5,MData[#Headers],0))} -> Y | F121: {=INDEX(MData[],MATCH(1,(MData[State Abbreviation]=$B121)*(MData[Report Date]=F$112)*(MData[Preliminary or Updated]=$C$3)*(MData[Final Report]=$C$4),0),MATCH($C$2,MData[#Headers],0))} -> 264086 | G121: {=INDEX(MData[],MATCH(1,(MData[State Abbreviation]=$B121)*(MData[Report Date]=G$112)*(MData[Preliminary or Updated]=$C$3)*(MData[Final Report]=$C$4),0),MATCH($C$2,MData[#Headers],0))} -> 265037 | H121: {=INDEX(MData[],MATCH(1,(MData[State Abbreviation]=$B121)*(MData[Report Date]=H$112)*(MData[Preliminary or Updated]=$C$3)*(MData[Final Report]=$C$4),0),MATCH($C$2,MData[#Headers],0))} -> 266374 | I121: {=INDEX(MData[],MATCH(1,(MData[State Abbreviation]=$B121)*(MData[Report Date]=I$112)*(MData[Preliminary or Updated]=$C$3)*(MData[Final Report]=$C$4),0),MATCH($C$2,MData[#Headers],0))} -> 267598 | J121: {=INDEX(MData[],MATCH(1,(MData[State Abbreviation]=$B121)*(MData[Report Date]=J$112)*(MData[Preliminary or Updated]=$C$3)*(MData[Final Report]=$C$4),0),MATCH($C$2,MData[#Headers],0))} -> 268308 | K121: {=INDEX(MData[],MATCH(1,(MData[State Abbreviation]=$B121)*(MData[Report Date]=K$112)*(MData[Preliminary or Updated]=$C$3)*(MData[Final Report]=$C$4),0),MATCH($C$2,MData[#Headers],0))} -> 269591 | L121: {=INDEX(MData[],MATCH(1,(MData[State Abbreviation]=$B121)*(MData[Report Date]=L$112)*(MData[Preliminary or Updated]=$C$3)*(MData[Final Report]=$C$4),0),MATCH($C$2,MData[#Headers],0))} -> 270938 | M121: {=INDEX(MData[],MATCH(1,(MData[State Abbreviation]=$B121)*(MData[Report Date]=M$112)*(MData[Preliminary or Updated]=$C$3)*(MData[Final Report]=$C$4),0),MATCH($C$2,MData[#Headers],0))} -> 272037 | ... Q121: {=INDEX(MData[],MATCH(1,(MData[State Abbreviation]=$B121)*(MData[Report Date]=Q$112)*(MData[Preliminary or Updated]=$C$3)*(MData[Final Report]=$C$4),0),MATCH($C$2,MData[#Headers],0))} -> 275771 | R121: =AVERAGE(F121:Q121) -> 270103.58
A122: 10 | B122: FL | C122: Florida | D122: {=INDEX(MData[],MATCH(1,(MData[State Abbreviation]=$B122)*(MData[Report Date]=D$6)*(MData[Preliminary or Updated]=$C$3)*(MData[Final Report]=$C$4),0),MATCH($D$5,MData[#Headers],0))} -> N | E122: {=INDEX(MData[],MATCH(1,(MData[State Abbreviation]=$B122)*(MData[Report Date]=E$6)*(MData[Preliminary or Updated]=$C$3)*(MData[Final Report]=$C$4),0),MATCH($D$5,MData[#Headers],0))} -> N | F122: {=INDEX(MData[],MATCH(1,(MData[State Abbreviation]=$B122)*(MData[Report Date]=F$112)*(MData[Preliminary or Updated]=$C$3)*(MData[Final Report]=$C$4),0),MATCH($C$2,MData[#Headers],0))} -> 4144712 | G122: {=INDEX(MData[],MATCH(1,(MData[State Abbreviation]=$B122)*(MData[Report Date]=G$112)*(MData[Preliminary or Updated]=$C$3)*(MData[Final Report]=$C$4),0),MATCH($C$2,MData[#Headers],0))} -> 4169637 | H122: {=INDEX(MData[],MATCH(1,(MData[State Abbreviation]=$B122)*(MData[Report Date]=H$112)*(MData[Preliminary or Updated]=$C$3)*(MData[Final Report]=$C$4),0),MATCH($C$2,MData[#Headers],0))} -> 4213933 | I122: {=INDEX(MData[],MATCH(1,(MData[State Abbreviation]=$B122)*(MData[Report Date]=I$112)*(MData[Preliminary or Updated]=$C$3)*(MData[Final Report]=$C$4),0),MATCH($C$2,MData[#Headers],0))} -> 4249167 | J122: {=INDEX(MData[],MATCH(1,(MData[State Abbreviation]=$B122)*(MData[Report Date]=J$112)*(MData[Preliminary or Updated]=$C$3)*(MData[Final Report]=$C$4),0),MATCH($C$2,MData[#Headers],0))} -> 4281662 | K122: {=INDEX(MData[],MATCH(1,(MData[State Abbreviation]=$B122)*(MData[Report Date]=K$112)*(MData[Preliminary or Updated]=$C$3)*(MData[Final Report]=$C$4),0),MATCH($C$2,MData[#Headers],0))} -> 4316655 | L122: {=INDEX(MData[],MATCH(1,(MData[State Abbreviation]=$B122)*(MData[Report Date]=L$112)*(MData[Preliminary or Updated]=$C$3)*(MData[Final Report]=$C$4),0),MATCH($C$2,MData[#Headers],0))} -> 4350511 | M122: {=INDEX(MData[],MATCH(1,(MData[State Abbreviation]=$B122)*(MData[Report Date]=M$112)*(MData[Preliminary or Updated]=$C$3)*(MData[Final Report]=$C$4),0),MATCH($C$2,MData[#Headers],0))} -> 4396610 | ... Q122: {=INDEX(MData[],MATCH(1,(MData[State Abbreviation]=$B122)*(MData[Report Date]=Q$112)*(MData[Preliminary or Updated]=$C$3)*(MData[Final Report]=$C$4),0),MATCH($C$2,MData[#Headers],0))} -> 4507461 | R122: =AVERAGE(F122:Q122) -> 4333693.7
A123: 11 | B123: GA | C123: Georgia | D123: {=INDEX(MData[],MATCH(1,(MData[State Abbreviation]=$B123)*(MData[Report Date]=D$6)*(MData[Preliminary or Updated]=$C$3)*(MData[Final Report]=$C$4),0),MATCH($D$5,MData[#Headers],0))} -> N | E123: {=INDEX(MData[],MATCH(1,(MData[State Abbreviation]=$B123)*(MData[Report Date]=E$6)*(MData[Preliminary or Updated]=$C$3)*(MData[Final Report]=$C$4),0),MATCH($D$5,MData[#Headers],0))} -> N | F123: {=INDEX(MData[],MATCH(1,(MData[State Abbreviation]=$B123)*(MData[Report Date]=F$112)*(MData[Preliminary or Updated]=$C$3)*(MData[Final Report]=$C$4),0),MATCH($C$2,MData[#Headers],0))} -> 2109497 | G123: {=INDEX(MData[],MATCH(1,(MData[State Abbreviation]=$B123)*(MData[Report Date]=G$112)*(MData[Preliminary or Updated]=$C$3)*(MData[Final Report]=$C$4),0),MATCH($C$2,MData[#Headers],0))} -> 2129693 | H123: {=INDEX(MData[],MATCH(1,(MData[State Abbreviation]=$B123)*(MData[Report Date]=H$112)*(MData[Preliminary or Updated]=$C$3)*(MData[Final Report]=$C$4),0),MATCH($C$2,MData[#Headers],0))} -> 2146602 | I123: {=INDEX(MData[],MATCH(1,(MData[State Abbreviation]=$B123)*(MData[Report Date]=I$112)*(MData[Preliminary or Updated]=$C$3)*(MData[Final Report]=$C$4),0),MATCH($C$2,MData[#Headers],0))} -> 2160406 | J123: {=INDEX(MData[],MATCH(1,(MData[State Abbreviation]=$B123)*(MData[Report Date]=J$112)*(MData[Preliminary or Updated]=$C$3)*(MData[Final Report]=$C$4),0),MATCH($C$2,MData[#Headers],0))} -> 2177156 | K123: {=INDEX(MData[],MATCH(1,(MData[State Abbreviation]=$B123)*(MData[Report Date]=K$112)*(MData[Preliminary or Updated]=$C$3)*(MData[Final Report]=$C$4),0),MATCH($C$2,MData[#Headers],0))} -> 2194346 | L123: {=INDEX(MData[],MATCH(1,(MData[State Abbreviation]=$B123)*(MData[Report Date]=L$112)*(MData[Preliminary or Updated]=$C$3)*(MData[Final Report]=$C$4),0),MATCH($C$2,MData[#Headers],0))} -> 2214237 | M123: {=INDEX(MData[],MATCH(1,(MData[State Abbreviation]=$B123)*(MData[Report Date]=M$112)*(MData[Preliminary or Updated]=$C$3)*(MData[Final Report]=$C$4),0),MATCH($C$2,MData[#Headers],0))} -> 2235830 | ... Q123: {=INDEX(MData[],MATCH(1,(MData[State Abbreviation]=$B123)*(MData[Report Date]=Q$112)*(MData[Preliminary or Updated]=$C$3)*(MData[Final Report]=$C$4),0),MATCH($C$2,MData[#Headers],0))} -> 2305389 | R123: =AVERAGE(F123:Q123) -> 2206783.2
A124: 12 | B124: HI | C124: Hawaii | D124: {=INDEX(MData[],MATCH(1,(MData[State Abbreviation]=$B124)*(MData[Report Date]=D$6)*(MData[Preliminary or Updated]=$C$3)*(MData[Final Report]=$C$4),0),MATCH($D$5,MData[#Headers],0))} -> Y | E124: {=INDEX(MData[],MATCH(1,(MData[State Abbreviation]=$B124)*(MData[Report Date]=E$6)*(MData[Preliminary or Updated]=$C$3)*(MData[Final Report]=$C$4),0),MATCH($D$5,MData[#Headers],0))} -> Y | F124: {=INDEX(MData[],MATCH(1,(MData[State Abbreviation]=$B124)*(MData[Report Date]=F$112)*(MData[Preliminary or Updated]=$C$3)*(MData[Final Report]=$C$4),0),MATCH($C$2,MData[#Headers],0))} -> 400775 | G124: {=INDEX(MData[],MATCH(1,(MData[State Abbreviation]=$B124)*(MData[Report Date]=G$112)*(MData[Preliminary or Updated]=$C$3)*(MData[Final Report]=$C$4),0),MATCH($C$2,MData[#Headers],0))} -> 405238 | H124: {=INDEX(MData[],MATCH(1,(MData[State Abbreviation]=$B124)*(MData[Report Date]=H$112)*(MData[Preliminary or Updated]=$C$3)*(MData[Final Report]=$C$4),0),MATCH($C$2,MData[#Headers],0))} -> 411719 | I124: {=INDEX(MData[],MATCH(1,(MData[State Abbreviation]=$B124)*(MData[Report Date]=I$112)*(MData[Preliminary or Updated]=$C$3)*(MData[Final Report]=$C$4),0),MATCH($C$2,MData[#Headers],0))} -> 415647 | J124: {=INDEX(MData[],MATCH(1,(MData[State Abbreviation]=$B124)*(MData[Report Date]=J$112)*(MData[Preliminary or Updated]=$C$3)*(MData[Final Report]=$C$4),0),MATCH($C$2,MData[#Headers],0))} -> 418088 | K124: {=INDEX(MData[],MATCH(1,(MData[State Abbreviation]=$B124)*(MData[Report Date]=K$112)*(MData[Preliminary or Updated]=$C$3)*(MData[Final Report]=$C$4),0),MATCH($C$2,MData[#Headers],0))} -> 420829 | L124: {=INDEX(MData[],MATCH(1,(MData[State Abbreviation]=$B124)*(MData[Report Date]=L$112)*(MData[Preliminary or Updated]=$C$3)*(MData[Final Report]=$C$4),0),MATCH($C$2,MData[#Headers],0))} -> 424531 | M124: {=INDEX(MData[],MATCH(1,(MData[State Abbreviation]=$B124)*(MData[Report Date]=M$112)*(MData[Preliminary or Updated]=$C$3)*(MData[Final Report]=$C$4),0),MATCH($C$2,MData[#Headers],0))} -> 427508 | ... Q124: {=INDEX(MData[],MATCH(1,(MData[State Abbreviation]=$B124)*(MData[Report Date]=Q$112)*(MData[Preliminary or Updated]=$C$3)*(MData[Final Report]=$C$4),0),MATCH($C$2,MData[#Headers],0))} -> 437335 | R124: =AVERAGE(F124:Q124) -> 421454.5
... A163: 51 | B163: WY | C163: Wyoming | D163: {=INDEX(MData[],MATCH(1,(MData[State Abbreviation]=$B163)*(MData[Report Date]=D$6)*(MData[Preliminary or Updated]=$C$3)*(MData[Final Report]=$C$4),0),MATCH($D$5,MData[#Headers],0))} -> N | E163: {=INDEX(MData[],MATCH(1,(MData[State Abbreviation]=$B163)*(MData[Report Date]=E$6)*(MData[Preliminary or Updated]=$C$3)*(MData[Final Report]=$C$4),0),MATCH($D$5,MData[#Headers],0))} -> N | F163: {=INDEX(MData[],MATCH(1,(MData[State Abbreviation]=$B163)*(MData[Report Date]=F$112)*(MData[Preliminary or Updated]=$C$3)*(MData[Final Report]=$C$4),0),MATCH($C$2,MData[#Headers],0))} -> 65364 | G163: {=INDEX(MData[],MATCH(1,(MData[State Abbreviation]=$B163)*(MData[Report Date]=G$112)*(MData[Preliminary or Updated]=$C$3)*(MData[Final Report]=$C$4),0),MATCH($C$2,MData[#Headers],0))} -> 66510 | H163: {=INDEX(MData[],MATCH(1,(MData[State Abbreviation]=$B163)*(MData[Report Date]=H$112)*(MData[Preliminary or Updated]=$C$3)*(MData[Final Report]=$C$4),0),MATCH($C$2,MData[#Headers],0))} -> 67377 | I163: {=INDEX(MData[],MATCH(1,(MData[State Abbreviation]=$B163)*(MData[Report Date]=I$112)*(MData[Preliminary or Updated]=$C$3)*(MData[Final Report]=$C$4),0),MATCH($C$2,MData[#Headers],0))} -> 68173 | J163: {=INDEX(MData[],MATCH(1,(MData[State Abbreviation]=$B163)*(MData[Report Date]=J$112)*(MData[Preliminary or Updated]=$C$3)*(MData[Final Report]=$C$4),0),MATCH($C$2,MData[#Headers],0))} -> 68855 | K163: {=INDEX(MData[],MATCH(1,(MData[State Abbreviation]=$B163)*(MData[Report Date]=K$112)*(MData[Preliminary or Updated]=$C$3)*(MData[Final Report]=$C$4),0),MATCH($C$2,MData[#Headers],0))} -> 69413 | L163: {=INDEX(MData[],MATCH(1,(MData[State Abbreviation]=$B163)*(MData[Report Date]=L$112)*(MData[Preliminary or Updated]=$C$3)*(MData[Final Report]=$C$4),0),MATCH($C$2,MData[#Headers],0))} -> 70089 | M163: {=INDEX(MData[],MATCH(1,(MData[State Abbreviation]=$B163)*(MData[Report Date]=M$112)*(MData[Preliminary or Updated]=$C$3)*(MData[Final Report]=$C$4),0),MATCH($C$2,MData[#Headers],0))} -> 70811 | ... Q163: {=INDEX(MData[],MATCH(1,(MData[State Abbreviation]=$B163)*(MData[Report Date]=Q$112)*(MData[Preliminary or Updated]=$C$3)*(MData[Final Report]=$C$4),0),MATCH($C$2,MData[#Headers],0))} -> 72773 | R163: =AVERAGE(F163:Q163) -> 69630.417
D164: State Expanded Medicaid
B165: Post Code | C165: State | D165: 43831 | E165: 44166 | F165: 43831 | G165: 43862 | H165: 43891 | I165: 43922 | J165: 43952 | K165: 43983 | L165: 44013 | M165: 44044 | N165: 44075 | O165: 44105 | P165: 44136 | Q165: 44166 | R165: average
A166: 1 | B166: AL | C166: Alabama | D166: {=INDEX(MData[],MATCH(1,(MData[State Abbreviation]=$B166)*(MData[Report Date]=D$6)*(MData[Preliminary or Updated]=$C$3)*(MData[Final Report]=$C$4),0),MATCH($D$5,MData[#Headers],0))} -> N | E166: {=INDEX(MData[],MATCH(1,(MData[State Abbreviation]=$B166)*(MData[Report Date]=E$6)*(MData[Preliminary or Updated]=$C$3)*(MData[Final Report]=$C$4),0),MATCH($D$5,MData[#Headers],0))} -> N | F166: {=INDEX(MData[],MATCH(1,(MData[State Abbreviation]=$B166)*(MData[Report Date]=F$165)*(MData[Preliminary or Updated]=$C$3)*(MData[Final Report]=$C$4),0),MATCH($C$2,MData[#Headers],0))} -> 922592 | G166: {=INDEX(MData[],MATCH(1,(MData[State Abbreviation]=$B166)*(MData[Report Date]=G$165)*(MData[Preliminary or Updated]=$C$3)*(MData[Final Report]=$C$4),0),MATCH($C$2,MData[#Headers],0))} -> 923320 | H166: {=INDEX(MData[],MATCH(1,(MData[State Abbreviation]=$B166)*(MData[Report Date]=H$165)*(MData[Preliminary or Updated]=$C$3)*(MData[Final Report]=$C$4),0),MATCH($C$2,MData[#Headers],0))} -> 922989 | I166: {=INDEX(MData[],MATCH(1,(MData[State Abbreviation]=$B166)*(MData[Report Date]=I$165)*(MData[Preliminary or Updated]=$C$3)*(MData[Final Report]=$C$4),0),MATCH($C$2,MData[#Headers],0))} -> 933842 | J166: {=INDEX(MData[],MATCH(1,(MData[State Abbreviation]=$B166)*(MData[Report Date]=J$165)*(MData[Preliminary or Updated]=$C$3)*(MData[Final Report]=$C$4),0),MATCH($C$2,MData[#Headers],0))} -> 943545 | K166: {=INDEX(MData[],MATCH(1,(MData[State Abbreviation]=$B166)*(MData[Report Date]=K$165)*(MData[Preliminary or Updated]=$C$3)*(MData[Final Report]=$C$4),0),MATCH($C$2,MData[#Headers],0))} -> 951984 | L166: {=INDEX(MData[],MATCH(1,(MData[State Abbreviation]=$B166)*(MData[Report Date]=L$165)*(MData[Preliminary or Updated]=$C$3)*(MData[Final Report]=$C$4),0),MATCH($C$2,MData[#Headers],0))} -> 959675 | M166: {=INDEX(MData[],MATCH(1,(MData[State Abbreviation]=$B166)*(MData[Report Date]=M$165)*(MData[Preliminary or Updated]=$C$3)*(MData[Final Report]=$C$4),0),MATCH($C$2,MData[#Headers],0))} -> 967364 | ... Q166: {=INDEX(MData[],MATCH(1,(MData[State Abbreviation]=$B166)*(MData[Report Date]=Q$165)*(MData[Preliminary or Updated]=$C$3)*(MData[Final Report]=$C$4),0),MATCH($C$2,MData[#Headers],0))} -> 1001444 | R166: =AVERAGE(F166:Q166) -> 956823.08
A167: 2 | B167: AK | C167: Alaska | D167: {=INDEX(MData[],MATCH(1,(MData[State Abbreviation]=$B167)*(MData[Report Date]=D$6)*(MData[Preliminary or Updated]=$C$3)*(MData[Final Report]=$C$4),0),MATCH($D$5,MData[#Headers],0))} -> Y | E167: {=INDEX(MData[],MATCH(1,(MData[State Abbreviation]=$B167)*(MData[Report Date]=E$6)*(MData[Preliminary or Updated]=$C$3)*(MData[Final Report]=$C$4),0),MATCH($D$5,MData[#Headers],0))} -> Y | F167: {=INDEX(MData[],MATCH(1,(MData[State Abbreviation]=$B167)*(MData[Report Date]=F$165)*(MData[Preliminary or Updated]=$C$3)*(MData[Final Report]=$C$4),0),MATCH($C$2,MData[#Headers],0))} -> 223963 | G167: {=INDEX(MData[],MATCH(1,(MData[State Abbreviation]=$B167)*(MData[Report Date]=G$165)*(MData[Preliminary or Updated]=$C$3)*(MData[Final Report]=$C$4),0),MATCH($C$2,MData[#Headers],0))} -> 222941 | H167: {=INDEX(MData[],MATCH(1,(MData[State Abbreviation]=$B167)*(MData[Report Date]=H$165)*(MData[Preliminary or Updated]=$C$3)*(MData[Final Report]=$C$4),0),MATCH($C$2,MData[#Headers],0))} -> 224965 | I167: {=INDEX(MData[],MATCH(1,(MData[State Abbreviation]=$B167)*(MData[Report Date]=I$165)*(MData[Preliminary or Updated]=$C$3)*(MData[Final Report]=$C$4),0),MATCH($C$2,MData[#Headers],0))} -> 228270 | J167: {=INDEX(MData[],MATCH(1,(MData[State Abbreviation]=$B167)*(MData[Report Date]=J$165)*(MData[Preliminary or Updated]=$C$3)*(MData[Final Report]=$C$4),0),MATCH($C$2,MData[#Headers],0))} -> 230043 | K167: {=INDEX(MData[],MATCH(1,(MData[State Abbreviation]=$B167)*(MData[Report Date]=K$165)*(MData[Preliminary or Updated]=$C$3)*(MData[Final Report]=$C$4),0),MATCH($C$2,MData[#Headers],0))} -> 232069 | L167: {=INDEX(MData[],MATCH(1,(MData[State Abbreviation]=$B167)*(MData[Report Date]=L$165)*(MData[Preliminary or Updated]=$C$3)*(MData[Final Report]=$C$4),0),MATCH($C$2,MData[#Headers],0))} -> 233334 | M167: {=INDEX(MData[],MATCH(1,(MData[State Abbreviation]=$B167)*(MData[Report Date]=M$165)*(MData[Preliminary or Updated]=$C$3)*(MData[Final Report]=$C$4),0),MATCH($C$2,MData[#Headers],0))} -> 235261 | ... Q167: {=INDEX(MData[],MATCH(1,(MData[State Abbreviation]=$B167)*(MData[Report Date]=Q$165)*(MData[Preliminary or Updated]=$C$3)*(MData[Final Report]=$C$4),0),MATCH($C$2,MData[#Headers],0))} -> 239981 | R167: =AVERAGE(F167:Q167) -> 231987.33
A168: 3 | B168: AZ | C168: Arizona | D168: {=INDEX(MData[],MATCH(1,(MData[State Abbreviation]=$B168)*(MData[Report Date]=D$6)*(MData[Preliminary or Updated]=$C$3)*(MData[Final Report]=$C$4),0),MATCH($D$5,MData[#Headers],0))} -> Y | E168: {=INDEX(MData[],MATCH(1,(MData[State Abbreviation]=$B168)*(MData[Report Date]=E$6)*(MData[Preliminary or Updated]=$C$3)*(MData[Final Report]=$C$4),0),MATCH($D$5,MData[#Headers],0))} -> Y | F168: {=INDEX(MData[],MATCH(1,(MData[State Abbreviation]=$B168)*(MData[Report Date]=F$165)*(MData[Preliminary or Updated]=$C$3)*(MData[Final Report]=$C$4),0),MATCH($C$2,MData[#Headers],0))} -> 1702632 | G168: {=INDEX(MData[],MATCH(1,(MData[State Abbreviation]=$B168)*(MData[Report Date]=G$165)*(MData[Preliminary or Updated]=$C$3)*(MData[Final Report]=$C$4),0),MATCH($C$2,MData[#Headers],0))} -> 1705789 | H168: {=INDEX(MData[],MATCH(1,(MData[State Abbreviation]=$B168)*(MData[Report Date]=H$165)*(MData[Preliminary or Updated]=$C$3)*(MData[Final Report]=$C$4),0),MATCH($C$2,MData[#Headers],0))} -> 1746744 | I168: {=INDEX(MData[],MATCH(1,(MData[State Abbreviation]=$B168)*(MData[Report Date]=I$165)*(MData[Preliminary or Updated]=$C$3)*(MData[Final Report]=$C$4),0),MATCH($C$2,MData[#Headers],0))} -> 1781233 | J168: {=INDEX(MData[],MATCH(1,(MData[State Abbreviation]=$B168)*(MData[Report Date]=J$165)*(MData[Preliminary or Updated]=$C$3)*(MData[Final Report]=$C$4),0),MATCH($C$2,MData[#Headers],0))} -> 1817362 | K168: {=INDEX(MData[],MATCH(1,(MData[State Abbreviation]=$B168)*(MData[Report Date]=K$165)*(MData[Preliminary or Updated]=$C$3)*(MData[Final Report]=$C$4),0),MATCH($C$2,MData[#Headers],0))} -> 1839932 | L168: {=INDEX(MData[],MATCH(1,(MData[State Abbreviation]=$B168)*(MData[Report Date]=L$165)*(MData[Preliminary or Updated]=$C$3)*(MData[Final Report]=$C$4),0),MATCH($C$2,MData[#Headers],0))} -> 1862408 | M168: {=INDEX(MData[],MATCH(1,(MData[State Abbreviation]=$B168)*(MData[Report Date]=M$165)*(MData[Preliminary or Updated]=$C$3)*(MData[Final Report]=$C$4),0),MATCH($C$2,MData[#Headers],0))} -> 1887382 | ... Q168: {=INDEX(MData[],MATCH(1,(MData[State Abbreviation]=$B168)*(MData[Report Date]=Q$165)*(MData[Preliminary or Updated]=$C$3)*(MData[Final Report]=$C$4),0),MATCH($C$2,MData[#Headers],0))} -> 1963007 | R168: =AVERAGE(F168:Q168) -> 1839783.8
A169: 4 | B169: AR | C169: Arkansas | D169: {=INDEX(MData[],MATCH(1,(MData[State Abbreviation]=$B169)*(MData[Report Date]=D$6)*(MData[Preliminary or Updated]=$C$3)*(MData[Final Report]=$C$4),0),MATCH($D$5,MData[#Headers],0))} -> Y | E169: {=INDEX(MData[],MATCH(1,(MData[State Abbreviation]=$B169)*(MData[Report Date]=E$6)*(MData[Preliminary or Updated]=$C$3)*(MData[Final Report]=$C$4),0),MATCH($D$5,MData[#Headers],0))} -> Y | F169: {=INDEX(MData[],MATCH(1,(MData[State Abbreviation]=$B169)*(MData[Report Date]=F$165)*(MData[Preliminary or Updated]=$C$3)*(MData[Final Report]=$C$4),0),MATCH($C$2,MData[#Headers],0))} -> 808905 | G169: {=INDEX(MData[],MATCH(1,(MData[State Abbreviation]=$B169)*(MData[Report Date]=G$165)*(MData[Preliminary or Updated]=$C$3)*(MData[Final Report]=$C$4),0),MATCH($C$2,MData[#Headers],0))} -> 802939 | H169: {=INDEX(MData[],MATCH(1,(MData[State Abbreviation]=$B169)*(MData[Report Date]=H$165)*(MData[Preliminary or Updated]=$C$3)*(MData[Final Report]=$C$4),0),MATCH($C$2,MData[#Headers],0))} -> 799896 | I169: {=INDEX(MData[],MATCH(1,(MData[State Abbreviation]=$B169)*(MData[Report Date]=I$165)*(MData[Preliminary or Updated]=$C$3)*(MData[Final Report]=$C$4),0),MATCH($C$2,MData[#Headers],0))} -> 813734 | J169: {=INDEX(MData[],MATCH(1,(MData[State Abbreviation]=$B169)*(MData[Report Date]=J$165)*(MData[Preliminary or Updated]=$C$3)*(MData[Final Report]=$C$4),0),MATCH($C$2,MData[#Headers],0))} -> 820544 | K169: {=INDEX(MData[],MATCH(1,(MData[State Abbreviation]=$B169)*(MData[Report Date]=K$165)*(MData[Preliminary or Updated]=$C$3)*(MData[Final Report]=$C$4),0),MATCH($C$2,MData[#Headers],0))} -> 836406 | L169: {=INDEX(MData[],MATCH(1,(MData[State Abbreviation]=$B169)*(MData[Report Date]=L$165)*(MData[Preliminary or Updated]=$C$3)*(MData[Final Report]=$C$4),0),MATCH($C$2,MData[#Headers],0))} -> 843515 | M169: {=INDEX(MData[],MATCH(1,(MData[State Abbreviation]=$B169)*(MData[Report Date]=M$165)*(MData[Preliminary or Updated]=$C$3)*(MData[Final Report]=$C$4),0),MATCH($C$2,MData[#Headers],0))} -> 849875 | ... Q169: {=INDEX(MData[],MATCH(1,(MData[State Abbreviation]=$B169)*(MData[Report Date]=Q$165)*(MData[Preliminary or Updated]=$C$3)*(MData[Final Report]=$C$4),0),MATCH($C$2,MData[#Headers],0))} -> 892423 | R169: =AVERAGE(F169:Q169) -> 840034.08
A170: 5 | B170: CA | C170: California | D170: {=INDEX(MData[],MATCH(1,(MData[State Abbreviation]=$B170)*(MData[Report Date]=D$6)*(MData[Preliminary or Updated]=$C$3)*(MData[Final Report]=$C$4),0),MATCH($D$5,MData[#Headers],0))} -> Y | E170: {=INDEX(MData[],MATCH(1,(MData[State Abbreviation]=$B170)*(MData[Report Date]=E$6)*(MData[Preliminary or Updated]=$C$3)*(MData[Final Report]=$C$4),0),MATCH($D$5,MData[#Headers],0))} -> Y | F170: {=INDEX(MData[],MATCH(1,(MData[State Abbreviation]=$B170)*(MData[Report Date]=F$165)*(MData[Preliminary or Updated]=$C$3)*(MData[Final Report]=$C$4),0),MATCH($C$2,MData[#Headers],0))} -> 11614902 | G170: {=INDEX(MData[],MATCH(1,(MData[State Abbreviation]=$B170)*(MData[Report Date]=G$165)*(MData[Preliminary or Updated]=$C$3)*(MData[Final Report]=$C$4),0),MATCH($C$2,MData[#Headers],0))} -> 11590601 | H170: {=INDEX(MData[],MATCH(1,(MData[State Abbreviation]=$B170)*(MData[Report Date]=H$165)*(MData[Preliminary or Updated]=$C$3)*(MData[Final Report]=$C$4),0),MATCH($C$2,MData[#Headers],0))} -> 11576877 | I170: {=INDEX(MData[],MATCH(1,(MData[State Abbreviation]=$B170)*(MData[Report Date]=I$165)*(MData[Preliminary or Updated]=$C$3)*(MData[Final Report]=$C$4),0),MATCH($C$2,MData[#Headers],0))} -> 11622708 | J170: {=INDEX(MData[],MATCH(1,(MData[State Abbreviation]=$B170)*(MData[Report Date]=J$165)*(MData[Preliminary or Updated]=$C$3)*(MData[Final Report]=$C$4),0),MATCH($C$2,MData[#Headers],0))} -> 11740127 | K170: {=INDEX(MData[],MATCH(1,(MData[State Abbreviation]=$B170)*(MData[Report Date]=K$165)*(MData[Preliminary or Updated]=$C$3)*(MData[Final Report]=$C$4),0),MATCH($C$2,MData[#Headers],0))} -> 11847711 | L170: {=INDEX(MData[],MATCH(1,(MData[State Abbreviation]=$B170)*(MData[Report Date]=L$165)*(MData[Preliminary or Updated]=$C$3)*(MData[Final Report]=$C$4),0),MATCH($C$2,MData[#Headers],0))} -> 12016056 | M170: {=INDEX(MData[],MATCH(1,(MData[State Abbreviation]=$B170)*(MData[Report Date]=M$165)*(MData[Preliminary or Updated]=$C$3)*(MData[Final Report]=$C$4),0),MATCH($C$2,MData[#Headers],0))} -> 12116855 | ... Q170: {=INDEX(MData[],MATCH(1,(MData[State Abbreviation]=$B170)*(MData[Report Date]=Q$165)*(MData[Preliminary or Updated]=$C$3)*(MData[Final Report]=$C$4),0),MATCH($C$2,MData[#Headers],0))} -> 12491149 | R170: =AVERAGE(F170:Q170) -> 11957231
A171: 6 | B171: CO | C171: Colorado | D171: {=INDEX(MData[],MATCH(1,(MData[State Abbreviation]=$B171)*(MData[Report Date]=D$6)*(MData[Preliminary or Updated]=$C$3)*(MData[Final Report]=$C$4),0),MATCH($D$5,MData[#Headers],0))} -> Y | E171: {=INDEX(MData[],MATCH(1,(MData[State Abbreviation]=$B171)*(MData[Report Date]=E$6)*(MData[Preliminary or Updated]=$C$3)*(MData[Final Report]=$C$4),0),MATCH($D$5,MData[#Headers],0))} -> Y | F171: {=INDEX(MData[],MATCH(1,(MData[State Abbreviation]=$B171)*(MData[Report Date]=F$165)*(MData[Preliminary or Updated]=$C$3)*(MData[Final Report]=$C$4),0),MATCH($C$2,MData[#Headers],0))} -> 1272902 | G171: {=INDEX(MData[],MATCH(1,(MData[State Abbreviation]=$B171)*(MData[Report Date]=G$165)*(MData[Preliminary or Updated]=$C$3)*(MData[Final Report]=$C$4),0),MATCH($C$2,MData[#Headers],0))} -> 1266680 | H171: {=INDEX(MData[],MATCH(1,(MData[State Abbreviation]=$B171)*(MData[Report Date]=H$165)*(MData[Preliminary or Updated]=$C$3)*(MData[Final Report]=$C$4),0),MATCH($C$2,MData[#Headers],0))} -> 1259742 | I171: {=INDEX(MData[],MATCH(1,(MData[State Abbreviation]=$B171)*(MData[Report Date]=I$165)*(MData[Preliminary or Updated]=$C$3)*(MData[Final Report]=$C$4),0),MATCH($C$2,MData[#Headers],0))} -> 1296936 | J171: {=INDEX(MData[],MATCH(1,(MData[State Abbreviation]=$B171)*(MData[Report Date]=J$165)*(MData[Preliminary or Updated]=$C$3)*(MData[Final Report]=$C$4),0),MATCH($C$2,MData[#Headers],0))} -> 1316135 | K171: {=INDEX(MData[],MATCH(1,(MData[State Abbreviation]=$B171)*(MData[Report Date]=K$165)*(MData[Preliminary or Updated]=$C$3)*(MData[Final Report]=$C$4),0),MATCH($C$2,MData[#Headers],0))} -> 1336974 | L171: {=INDEX(MData[],MATCH(1,(MData[State Abbreviation]=$B171)*(MData[Report Date]=L$165)*(MData[Preliminary or Updated]=$C$3)*(MData[Final Report]=$C$4),0),MATCH($C$2,MData[#Headers],0))} -> 1357050 | M171: {=INDEX(MData[],MATCH(1,(MData[State Abbreviation]=$B171)*(MData[Report Date]=M$165)*(MData[Preliminary or Updated]=$C$3)*(MData[Final Report]=$C$4),0),MATCH($C$2,MData[#Headers],0))} -> 1377505 | ... Q171: {=INDEX(MData[],MATCH(1,(MData[State Abbreviation]=$B171)*(MData[Report Date]=Q$165)*(MData[Preliminary or Updated]=$C$3)*(MData[Final Report]=$C$4),0),MATCH($C$2,MData[#Headers],0))} -> 1449824 | R171: =AVERAGE(F171:Q171) -> 1348029.8
A172: 7 | B172: CT | C172: Connecticut | D172: {=INDEX(MData[],MATCH(1,(MData[State Abbreviation]=$B172)*(MData[Report Date]=D$6)*(MData[Preliminary or Updated]=$C$3)*(MData[Final Report]=$C$4),0),MATCH($D$5,MData[#Headers],0))} -> Y | E172: {=INDEX(MData[],MATCH(1,(MData[State Abbreviation]=$B172)*(MData[Report Date]=E$6)*(MData[Preliminary or Updated]=$C$3)*(MData[Final Report]=$C$4),0),MATCH($D$5,MData[#Headers],0))} -> Y | F172: {=INDEX(MData[],MATCH(1,(MData[State Abbreviation]=$B172)*(MData[Report Date]=F$165)*(MData[Preliminary or Updated]=$C$3)*(MData[Final Report]=$C$4),0),MATCH($C$2,MData[#Headers],0))} -> 847119 | G172: {=INDEX(MData[],MATCH(1,(MData[State Abbreviation]=$B172)*(MData[Report Date]=G$165)*(MData[Preliminary or Updated]=$C$3)*(MData[Final Report]=$C$4),0),MATCH($C$2,MData[#Headers],0))} -> 844967 | H172: {=INDEX(MData[],MATCH(1,(MData[State Abbreviation]=$B172)*(MData[Report Date]=H$165)*(MData[Preliminary or Updated]=$C$3)*(MData[Final Report]=$C$4),0),MATCH($C$2,MData[#Headers],0))} -> 845434 | I172: {=INDEX(MData[],MATCH(1,(MData[State Abbreviation]=$B172)*(MData[Report Date]=I$165)*(MData[Preliminary or Updated]=$C$3)*(MData[Final Report]=$C$4),0),MATCH($C$2,MData[#Headers],0))} -> 860826 | J172: {=INDEX(MData[],MATCH(1,(MData[State Abbreviation]=$B172)*(MData[Report Date]=J$165)*(MData[Preliminary or Updated]=$C$3)*(MData[Final Report]=$C$4),0),MATCH($C$2,MData[#Headers],0))} -> 868067 | K172: {=INDEX(MData[],MATCH(1,(MData[State Abbreviation]=$B172)*(MData[Report Date]=K$165)*(MData[Preliminary or Updated]=$C$3)*(MData[Final Report]=$C$4),0),MATCH($C$2,MData[#Headers],0))} -> 874974 | L172: {=INDEX(MData[],MATCH(1,(MData[State Abbreviation]=$B172)*(MData[Report Date]=L$165)*(MData[Preliminary or Updated]=$C$3)*(MData[Final Report]=$C$4),0),MATCH($C$2,MData[#Headers],0))} -> 885365 | M172: {=INDEX(MData[],MATCH(1,(MData[State Abbreviation]=$B172)*(MData[Report Date]=M$165)*(MData[Preliminary or Updated]=$C$3)*(MData[Final Report]=$C$4),0),MATCH($C$2,MData[#Headers],0))} -> 893114 | ... Q172: {=INDEX(MData[],MATCH(1,(MData[State Abbreviation]=$B172)*(MData[Report Date]=Q$165)*(MData[Preliminary or Updated]=$C$3)*(MData[Final Report]=$C$4),0),MATCH($C$2,MData[#Headers],0))} -> 927770 | R172: =AVERAGE(F172:Q172) -> 881289.75
A173: 8 | B173: DE | C173: Delaware | D173: {=INDEX(MData[],MATCH(1,(MData[State Abbreviation]=$B173)*(MData[Report Date]=D$6)*(MData[Preliminary or Updated]=$C$3)*(MData[Final Report]=$C$4),0),MATCH($D$5,MData[#Headers],0))} -> Y | E173: {=INDEX(MData[],MATCH(1,(MData[State Abbreviation]=$B173)*(MData[Report Date]=E$6)*(MData[Preliminary or Updated]=$C$3)*(MData[Final Report]=$C$4),0),MATCH($D$5,MData[#Headers],0))} -> Y | F173: {=INDEX(MData[],MATCH(1,(MData[State Abbreviation]=$B173)*(MData[Report Date]=F$165)*(MData[Preliminary or Updated]=$C$3)*(MData[Final Report]=$C$4),0),MATCH($C$2,MData[#Headers],0))} -> 231455 | G173: {=INDEX(MData[],MATCH(1,(MData[State Abbreviation]=$B173)*(MData[Report Date]=G$165)*(MData[Preliminary or Updated]=$C$3)*(MData[Final Report]=$C$4),0),MATCH($C$2,MData[#Headers],0))} -> 231742 | H173: {=INDEX(MData[],MATCH(1,(MData[State Abbreviation]=$B173)*(MData[Report Date]=H$165)*(MData[Preliminary or Updated]=$C$3)*(MData[Final Report]=$C$4),0),MATCH($C$2,MData[#Headers],0))} -> 231862 | I173: {=INDEX(MData[],MATCH(1,(MData[State Abbreviation]=$B173)*(MData[Report Date]=I$165)*(MData[Preliminary or Updated]=$C$3)*(MData[Final Report]=$C$4),0),MATCH($C$2,MData[#Headers],0))} -> 235286 | J173: {=INDEX(MData[],MATCH(1,(MData[State Abbreviation]=$B173)*(MData[Report Date]=J$165)*(MData[Preliminary or Updated]=$C$3)*(MData[Final Report]=$C$4),0),MATCH($C$2,MData[#Headers],0))} -> 238113 | K173: {=INDEX(MData[],MATCH(1,(MData[State Abbreviation]=$B173)*(MData[Report Date]=K$165)*(MData[Preliminary or Updated]=$C$3)*(MData[Final Report]=$C$4),0),MATCH($C$2,MData[#Headers],0))} -> 240476 | L173: {=INDEX(MData[],MATCH(1,(MData[State Abbreviation]=$B173)*(MData[Report Date]=L$165)*(MData[Preliminary or Updated]=$C$3)*(MData[Final Report]=$C$4),0),MATCH($C$2,MData[#Headers],0))} -> 243349 | M173: {=INDEX(MData[],MATCH(1,(MData[State Abbreviation]=$B173)*(MData[Report Date]=M$165)*(MData[Preliminary or Updated]=$C$3)*(MData[Final Report]=$C$4),0),MATCH($C$2,MData[#Headers],0))} -> 246249 | ... Q173: {=INDEX(MData[],MATCH(1,(MData[State Abbreviation]=$B173)*(MData[Report Date]=Q$165)*(MData[Preliminary or Updated]=$C$3)*(MData[Final Report]=$C$4),0),MATCH($C$2,MData[#Headers],0))} -> 258025 | R173: =AVERAGE(F173:Q173) -> 242623.25
A174: 9 | B174: DC | C174: District of Columbia | D174: {=INDEX(MData[],MATCH(1,(MData[State Abbreviation]=$B174)*(MData[Report Date]=D$6)*(MData[Preliminary or Updated]=$C$3)*(MData[Final Report]=$C$4),0),MATCH($D$5,MData[#Headers],0))} -> Y | E174: {=INDEX(MData[],MATCH(1,(MData[State Abbreviation]=$B174)*(MData[Report Date]=E$6)*(MData[Preliminary or Updated]=$C$3)*(MData[Final Report]=$C$4),0),MATCH($D$5,MData[#Headers],0))} -> Y | F174: {=INDEX(MData[],MATCH(1,(MData[State Abbreviation]=$B174)*(MData[Report Date]=F$165)*(MData[Preliminary or Updated]=$C$3)*(MData[Final Report]=$C$4),0),MATCH($C$2,MData[#Headers],0))} -> 253265 | G174: {=INDEX(MData[],MATCH(1,(MData[State Abbreviation]=$B174)*(MData[Report Date]=G$165)*(MData[Preliminary or Updated]=$C$3)*(MData[Final Report]=$C$4),0),MATCH($C$2,MData[#Headers],0))} -> 241674 | H174: {=INDEX(MData[],MATCH(1,(MData[State Abbreviation]=$B174)*(MData[Report Date]=H$165)*(MData[Preliminary or Updated]=$C$3)*(MData[Final Report]=$C$4),0),MATCH($C$2,MData[#Headers],0))} -> 243503 | I174: {=INDEX(MData[],MATCH(1,(MData[State Abbreviation]=$B174)*(MData[Report Date]=I$165)*(MData[Preliminary or Updated]=$C$3)*(MData[Final Report]=$C$4),0),MATCH($C$2,MData[#Headers],0))} -> 246464 | J174: {=INDEX(MData[],MATCH(1,(MData[State Abbreviation]=$B174)*(MData[Report Date]=J$165)*(MData[Preliminary or Updated]=$C$3)*(MData[Final Report]=$C$4),0),MATCH($C$2,MData[#Headers],0))} -> 248554 | K174: {=INDEX(MData[],MATCH(1,(MData[State Abbreviation]=$B174)*(MData[Report Date]=K$165)*(MData[Preliminary or Updated]=$C$3)*(MData[Final Report]=$C$4),0),MATCH($C$2,MData[#Headers],0))} -> 250860 | L174: {=INDEX(MData[],MATCH(1,(MData[State Abbreviation]=$B174)*(MData[Report Date]=L$165)*(MData[Preliminary or Updated]=$C$3)*(MData[Final Report]=$C$4),0),MATCH($C$2,MData[#Headers],0))} -> 253009 | M174: {=INDEX(MData[],MATCH(1,(MData[State Abbreviation]=$B174)*(MData[Report Date]=M$165)*(MData[Preliminary or Updated]=$C$3)*(MData[Final Report]=$C$4),0),MATCH($C$2,MData[#Headers],0))} -> 254885 | ... Q174: {=INDEX(MData[],MATCH(1,(MData[State Abbreviation]=$B174)*(MData[Report Date]=Q$165)*(MData[Preliminary or Updated]=$C$3)*(MData[Final Report]=$C$4),0),MATCH($C$2,MData[#Headers],0))} -> 262327 | R174: =AVERAGE(F174:Q174) -> 252392.33
A175: 10 | B175: FL | C175: Florida | D175: {=INDEX(MData[],MATCH(1,(MData[State Abbreviation]=$B175)*(MData[Report Date]=D$6)*(MData[Preliminary or Updated]=$C$3)*(MData[Final Report]=$C$4),0),MATCH($D$5,MData[#Headers],0))} -> N | E175: {=INDEX(MData[],MATCH(1,(MData[State Abbreviation]=$B175)*(MData[Report Date]=E$6)*(MData[Preliminary or Updated]=$C$3)*(MData[Final Report]=$C$4),0),MATCH($D$5,MData[#Headers],0))} -> N | F175: {=INDEX(MData[],MATCH(1,(MData[State Abbreviation]=$B175)*(MData[Report Date]=F$165)*(MData[Preliminary or Updated]=$C$3)*(MData[Final Report]=$C$4),0),MATCH($C$2,MData[#Headers],0))} -> 3601113 | G175: {=INDEX(MData[],MATCH(1,(MData[State Abbreviation]=$B175)*(MData[Report Date]=G$165)*(MData[Preliminary or Updated]=$C$3)*(MData[Final Report]=$C$4),0),MATCH($C$2,MData[#Headers],0))} -> 3600457 | H175: {=INDEX(MData[],MATCH(1,(MData[State Abbreviation]=$B175)*(MData[Report Date]=H$165)*(MData[Preliminary or Updated]=$C$3)*(MData[Final Report]=$C$4),0),MATCH($C$2,MData[#Headers],0))} -> 3605857 | I175: {=INDEX(MData[],MATCH(1,(MData[State Abbreviation]=$B175)*(MData[Report Date]=I$165)*(MData[Preliminary or Updated]=$C$3)*(MData[Final Report]=$C$4),0),MATCH($C$2,MData[#Headers],0))} -> 3694863 | J175: {=INDEX(MData[],MATCH(1,(MData[State Abbreviation]=$B175)*(MData[Report Date]=J$165)*(MData[Preliminary or Updated]=$C$3)*(MData[Final Report]=$C$4),0),MATCH($C$2,MData[#Headers],0))} -> 3823393 | K175: {=INDEX(MData[],MATCH(1,(MData[State Abbreviation]=$B175)*(MData[Report Date]=K$165)*(MData[Preliminary or Updated]=$C$3)*(MData[Final Report]=$C$4),0),MATCH($C$2,MData[#Headers],0))} -> 3892552 | L175: {=INDEX(MData[],MATCH(1,(MData[State Abbreviation]=$B175)*(MData[Report Date]=L$165)*(MData[Preliminary or Updated]=$C$3)*(MData[Final Report]=$C$4),0),MATCH($C$2,MData[#Headers],0))} -> 3930734 | M175: {=INDEX(MData[],MATCH(1,(MData[State Abbreviation]=$B175)*(MData[Report Date]=M$165)*(MData[Preliminary or Updated]=$C$3)*(MData[Final Report]=$C$4),0),MATCH($C$2,MData[#Headers],0))} -> 3977970 | ... Q175: {=INDEX(MData[],MATCH(1,(MData[State Abbreviation]=$B175)*(MData[Report Date]=Q$165)*(MData[Preliminary or Updated]=$C$3)*(MData[Final Report]=$C$4),0),MATCH($C$2,MData[#Headers],0))} -> 4104699 | R175: =AVERAGE(F175:Q175) -> 3862766.8
A176: 11 | B176: GA | C176: Georgia | D176: {=INDEX(MData[],MATCH(1,(MData[State Abbreviation]=$B176)*(MData[Report Date]=D$6)*(MData[Preliminary or Updated]=$C$3)*(MData[Final Report]=$C$4),0),MATCH($D$5,MData[#Headers],0))} -> N | E176: {=INDEX(MData[],MATCH(1,(MData[State Abbreviation]=$B176)*(MData[Report Date]=E$6)*(MData[Preliminary or Updated]=$C$3)*(MData[Final Report]=$C$4),0),MATCH($D$5,MData[#Headers],0))} -> N | F176: {=INDEX(MData[],MATCH(1,(MData[State Abbreviation]=$B176)*(MData[Report Date]=F$165)*(MData[Preliminary or Updated]=$C$3)*(MData[Final Report]=$C$4),0),MATCH($C$2,MData[#Headers],0))} -> 1830095 | G176: {=INDEX(MData[],MATCH(1,(MData[State Abbreviation]=$B176)*(MData[Report Date]=G$165)*(MData[Preliminary or Updated]=$C$3)*(MData[Final Report]=$C$4),0),MATCH($C$2,MData[#Headers],0))} -> 1833759 | H176: {=INDEX(MData[],MATCH(1,(MData[State Abbreviation]=$B176)*(MData[Report Date]=H$165)*(MData[Preliminary or Updated]=$C$3)*(MData[Final Report]=$C$4),0),MATCH($C$2,MData[#Headers],0))} -> 1853679 | I176: {=INDEX(MData[],MATCH(1,(MData[State Abbreviation]=$B176)*(MData[Report Date]=I$165)*(MData[Preliminary or Updated]=$C$3)*(MData[Final Report]=$C$4),0),MATCH($C$2,MData[#Headers],0))} -> 1895954 | J176: {=INDEX(MData[],MATCH(1,(MData[State Abbreviation]=$B176)*(MData[Report Date]=J$165)*(MData[Preliminary or Updated]=$C$3)*(MData[Final Report]=$C$4),0),MATCH($C$2,MData[#Headers],0))} -> 1929582 | K176: {=INDEX(MData[],MATCH(1,(MData[State Abbreviation]=$B176)*(MData[Report Date]=K$165)*(MData[Preliminary or Updated]=$C$3)*(MData[Final Report]=$C$4),0),MATCH($C$2,MData[#Headers],0))} -> 1945955 | L176: {=INDEX(MData[],MATCH(1,(MData[State Abbreviation]=$B176)*(MData[Report Date]=L$165)*(MData[Preliminary or Updated]=$C$3)*(MData[Final Report]=$C$4),0),MATCH($C$2,MData[#Headers],0))} -> 1970507 | M176: {=INDEX(MData[],MATCH(1,(MData[State Abbreviation]=$B176)*(MData[Report Date]=M$165)*(MData[Preliminary or Updated]=$C$3)*(MData[Final Report]=$C$4),0),MATCH($C$2,MData[#Headers],0))} -> 1998686 | ... Q176: {=INDEX(MData[],MATCH(1,(MData[State Abbreviation]=$B176)*(MData[Report Date]=Q$165)*(MData[Preliminary or Updated]=$C$3)*(MData[Final Report]=$C$4),0),MATCH($C$2,MData[#Headers],0))} -> 2093853 | R176: =AVERAGE(F176:Q176) -> 1957007.3
A177: 12 | B177: HI | C177: Hawaii | D177: {=INDEX(MData[],MATCH(1,(MData[State Abbreviation]=$B177)*(MData[Report Date]=D$6)*(MData[Preliminary or Updated]=$C$3)*(MData[Final Report]=$C$4),0),MATCH($D$5,MData[#Headers],0))} -> Y | E177: {=INDEX(MData[],MATCH(1,(MData[State Abbreviation]=$B177)*(MData[Report Date]=E$6)*(MData[Preliminary or Updated]=$C$3)*(MData[Final Report]=$C$4),0),MATCH($D$5,MData[#Headers],0))} -> Y | F177: {=INDEX(MData[],MATCH(1,(MData[State Abbreviation]=$B177)*(MData[Report Date]=F$165)*(MData[Preliminary or Updated]=$C$3)*(MData[Final Report]=$C$4),0),MATCH($C$2,MData[#Headers],0))} -> 325833 | G177: {=INDEX(MData[],MATCH(1,(MData[State Abbreviation]=$B177)*(MData[Report Date]=G$165)*(MData[Preliminary or Updated]=$C$3)*(MData[Final Report]=$C$4),0),MATCH($C$2,MData[#Headers],0))} -> 325667 | H177: {=INDEX(MData[],MATCH(1,(MData[State Abbreviation]=$B177)*(MData[Report Date]=H$165)*(MData[Preliminary or Updated]=$C$3)*(MData[Final Report]=$C$4),0),MATCH($C$2,MData[#Headers],0))} -> 329194 | I177: {=INDEX(MData[],MATCH(1,(MData[State Abbreviation]=$B177)*(MData[Report Date]=I$165)*(MData[Preliminary or Updated]=$C$3)*(MData[Final Report]=$C$4),0),MATCH($C$2,MData[#Headers],0))} -> 344318 | J177: {=INDEX(MData[],MATCH(1,(MData[State Abbreviation]=$B177)*(MData[Report Date]=J$165)*(MData[Preliminary or Updated]=$C$3)*(MData[Final Report]=$C$4),0),MATCH($C$2,MData[#Headers],0))} -> 352120 | K177: {=INDEX(MData[],MATCH(1,(MData[State Abbreviation]=$B177)*(MData[Report Date]=K$165)*(MData[Preliminary or Updated]=$C$3)*(MData[Final Report]=$C$4),0),MATCH($C$2,MData[#Headers],0))} -> 356887 | L177: {=INDEX(MData[],MATCH(1,(MData[State Abbreviation]=$B177)*(MData[Report Date]=L$165)*(MData[Preliminary or Updated]=$C$3)*(MData[Final Report]=$C$4),0),MATCH($C$2,MData[#Headers],0))} -> 363958 | M177: {=INDEX(MData[],MATCH(1,(MData[State Abbreviation]=$B177)*(MData[Report Date]=M$165)*(MData[Preliminary or Updated]=$C$3)*(MData[Final Report]=$C$4),0),MATCH($C$2,MData[#Headers],0))} -> 369661 | ... Q177: {=INDEX(MData[],MATCH(1,(MData[State Abbreviation]=$B177)*(MData[Report Date]=Q$165)*(MData[Preliminary or Updated]=$C$3)*(MData[Final Report]=$C$4),0),MATCH($C$2,MData[#Headers],0))} -> 395172 | R177: =AVERAGE(F177:Q177) -> 359002.67
... A216: 51 | B216: WY | C216: Wyoming | D216: {=INDEX(MData[],MATCH(1,(MData[State Abbreviation]=$B216)*(MData[Report Date]=D$6)*(MData[Preliminary or Updated]=$C$3)*(MData[Final Report]=$C$4),0),MATCH($D$5,MData[#Headers],0))} -> N | E216: {=INDEX(MData[],MATCH(1,(MData[State Abbreviation]=$B216)*(MData[Report Date]=E$6)*(MData[Preliminary or Updated]=$C$3)*(MData[Final Report]=$C$4),0),MATCH($D$5,MData[#Headers],0))} -> N | F216: {=INDEX(MData[],MATCH(1,(MData[State Abbreviation]=$B216)*(MData[Report Date]=F$165)*(MData[Preliminary or Updated]=$C$3)*(MData[Final Report]=$C$4),0),MATCH($C$2,MData[#Headers],0))} -> 56199 | G216: {=INDEX(MData[],MATCH(1,(MData[State Abbreviation]=$B216)*(MData[Report Date]=G$165)*(MData[Preliminary or Updated]=$C$3)*(MData[Final Report]=$C$4),0),MATCH($C$2,MData[#Headers],0))} -> 56082 | H216: {=INDEX(MData[],MATCH(1,(MData[State Abbreviation]=$B216)*(MData[Report Date]=H$165)*(MData[Preliminary or Updated]=$C$3)*(MData[Final Report]=$C$4),0),MATCH($C$2,MData[#Headers],0))} -> 56111 | I216: {=INDEX(MData[],MATCH(1,(MData[State Abbreviation]=$B216)*(MData[Report Date]=I$165)*(MData[Preliminary or Updated]=$C$3)*(MData[Final Report]=$C$4),0),MATCH($C$2,MData[#Headers],0))} -> 57817 | J216: {=INDEX(MData[],MATCH(1,(MData[State Abbreviation]=$B216)*(MData[Report Date]=J$165)*(MData[Preliminary or Updated]=$C$3)*(MData[Final Report]=$C$4),0),MATCH($C$2,MData[#Headers],0))} -> 58764 | K216: {=INDEX(MData[],MATCH(1,(MData[State Abbreviation]=$B216)*(MData[Report Date]=K$165)*(MData[Preliminary or Updated]=$C$3)*(MData[Final Report]=$C$4),0),MATCH($C$2,MData[#Headers],0))} -> 60261 | L216: {=INDEX(MData[],MATCH(1,(MData[State Abbreviation]=$B216)*(MData[Report Date]=L$165)*(MData[Preliminary or Updated]=$C$3)*(MData[Final Report]=$C$4),0),MATCH($C$2,MData[#Headers],0))} -> 61603 | M216: {=INDEX(MData[],MATCH(1,(MData[State Abbreviation]=$B216)*(MData[Report Date]=M$165)*(MData[Preliminary or Updated]=$C$3)*(MData[Final Report]=$C$4),0),MATCH($C$2,MData[#Headers],0))} -> 62437 | ... Q216: {=INDEX(MData[],MATCH(1,(MData[State Abbreviation]=$B216)*(MData[Report Date]=Q$165)*(MData[Preliminary or Updated]=$C$3)*(MData[Final Report]=$C$4),0),MATCH($C$2,MData[#Headers],0))} -> 64559 | R216: =AVERAGE(F216:Q216) -> 60378.167
D217: State Expanded Medicaid
B218: Post Code | C218: State | D218: 43466 | E218: 43800 | F218: 43466 | G218: 43497 | H218: 43525 | I218: 43556 | J218: 43586 | K218: 43617 | L218: 43647 | M218: 43678 | N218: 43709 | O218: 43739 | P218: 43770 | Q218: 43800 | R218: average
A219: 1 | B219: AL | C219: Alabama | D219: {=INDEX(MData[],MATCH(1,(MData[State Abbreviation]=$B219)*(MData[Report Date]=D$6)*(MData[Preliminary or Updated]=$C$3)*(MData[Final Report]=$C$4),0),MATCH($D$5,MData[#Headers],0))} -> N | E219: {=INDEX(MData[],MATCH(1,(MData[State Abbreviation]=$B219)*(MData[Report Date]=E$6)*(MData[Preliminary or Updated]=$C$3)*(MData[Final Report]=$C$4),0),MATCH($D$5,MData[#Headers],0))} -> N | F219: {=INDEX(MData[],MATCH(1,(MData[State Abbreviation]=$B219)*(MData[Report Date]=F$218)*(MData[Preliminary or Updated]=$C$3)*(MData[Final Report]=$C$4),0),MATCH($C$2,MData[#Headers],0))} -> 910087 | G219: {=INDEX(MData[],MATCH(1,(MData[State Abbreviation]=$B219)*(MData[Report Date]=G$218)*(MData[Preliminary or Updated]=$C$3)*(MData[Final Report]=$C$4),0),MATCH($C$2,MData[#Headers],0))} -> 912951 | H219: {=INDEX(MData[],MATCH(1,(MData[State Abbreviation]=$B219)*(MData[Report Date]=H$218)*(MData[Preliminary or Updated]=$C$3)*(MData[Final Report]=$C$4),0),MATCH($C$2,MData[#Headers],0))} -> 912015 | I219: {=INDEX(MData[],MATCH(1,(MData[State Abbreviation]=$B219)*(MData[Report Date]=I$218)*(MData[Preliminary or Updated]=$C$3)*(MData[Final Report]=$C$4),0),MATCH($C$2,MData[#Headers],0))} -> 909189 | J219: {=INDEX(MData[],MATCH(1,(MData[State Abbreviation]=$B219)*(MData[Report Date]=J$218)*(MData[Preliminary or Updated]=$C$3)*(MData[Final Report]=$C$4),0),MATCH($C$2,MData[#Headers],0))} -> 908668 | K219: {=INDEX(MData[],MATCH(1,(MData[State Abbreviation]=$B219)*(MData[Report Date]=K$218)*(MData[Preliminary or Updated]=$C$3)*(MData[Final Report]=$C$4),0),MATCH($C$2,MData[#Headers],0))} -> 911855 | L219: {=INDEX(MData[],MATCH(1,(MData[State Abbreviation]=$B219)*(MData[Report Date]=L$218)*(MData[Preliminary or Updated]=$C$3)*(MData[Final Report]=$C$4),0),MATCH($C$2,MData[#Headers],0))} -> 915545 | M219: {=INDEX(MData[],MATCH(1,(MData[State Abbreviation]=$B219)*(MData[Report Date]=M$218)*(MData[Preliminary or Updated]=$C$3)*(MData[Final Report]=$C$4),0),MATCH($C$2,MData[#Headers],0))} -> 918316 | ... Q219: {=INDEX(MData[],MATCH(1,(MData[State Abbreviation]=$B219)*(MData[Report Date]=Q$218)*(MData[Preliminary or Updated]=$C$3)*(MData[Final Report]=$C$4),0),MATCH($C$2,MData[#Headers],0))} -> 921100 | R219: =AVERAGE(F219:Q219) -> 915097
A220: 2 | B220: AK | C220: Alaska | D220: {=INDEX(MData[],MATCH(1,(MData[State Abbreviation]=$B220)*(MData[Report Date]=D$6)*(MData[Preliminary or Updated]=$C$3)*(MData[Final Report]=$C$4),0),MATCH($D$5,MData[#Headers],0))} -> Y | E220: {=INDEX(MData[],MATCH(1,(MData[State Abbreviation]=$B220)*(MData[Report Date]=E$6)*(MData[Preliminary or Updated]=$C$3)*(MData[Final Report]=$C$4),0),MATCH($D$5,MData[#Headers],0))} -> Y | F220: {=INDEX(MData[],MATCH(1,(MData[State Abbreviation]=$B220)*(MData[Report Date]=F$218)*(MData[Preliminary or Updated]=$C$3)*(MData[Final Report]=$C$4),0),MATCH($C$2,MData[#Headers],0))} -> 216175 | G220: {=INDEX(MData[],MATCH(1,(MData[State Abbreviation]=$B220)*(MData[Report Date]=G$218)*(MData[Preliminary or Updated]=$C$3)*(MData[Final Report]=$C$4),0),MATCH($C$2,MData[#Headers],0))} -> 217468 | H220: {=INDEX(MData[],MATCH(1,(MData[State Abbreviation]=$B220)*(MData[Report Date]=H$218)*(MData[Preliminary or Updated]=$C$3)*(MData[Final Report]=$C$4),0),MATCH($C$2,MData[#Headers],0))} -> 217793 | I220: {=INDEX(MData[],MATCH(1,(MData[State Abbreviation]=$B220)*(MData[Report Date]=I$218)*(MData[Preliminary or Updated]=$C$3)*(MData[Final Report]=$C$4),0),MATCH($C$2,MData[#Headers],0))} -> 218972 | J220: {=INDEX(MData[],MATCH(1,(MData[State Abbreviation]=$B220)*(MData[Report Date]=J$218)*(MData[Preliminary or Updated]=$C$3)*(MData[Final Report]=$C$4),0),MATCH($C$2,MData[#Headers],0))} -> 220384 | K220: {=INDEX(MData[],MATCH(1,(MData[State Abbreviation]=$B220)*(MData[Report Date]=K$218)*(MData[Preliminary or Updated]=$C$3)*(MData[Final Report]=$C$4),0),MATCH($C$2,MData[#Headers],0))} -> 221746 | L220: {=INDEX(MData[],MATCH(1,(MData[State Abbreviation]=$B220)*(MData[Report Date]=L$218)*(MData[Preliminary or Updated]=$C$3)*(MData[Final Report]=$C$4),0),MATCH($C$2,MData[#Headers],0))} -> 223117 | M220: {=INDEX(MData[],MATCH(1,(MData[State Abbreviation]=$B220)*(MData[Report Date]=M$218)*(MData[Preliminary or Updated]=$C$3)*(MData[Final Report]=$C$4),0),MATCH($C$2,MData[#Headers],0))} -> 221946 | ... Q220: {=INDEX(MData[],MATCH(1,(MData[State Abbreviation]=$B220)*(MData[Report Date]=Q$218)*(MData[Preliminary or Updated]=$C$3)*(MData[Final Report]=$C$4),0),MATCH($C$2,MData[#Headers],0))} -> 223065 | R220: =AVERAGE(F220:Q220) -> 220535.5
A221: 3 | B221: AZ | C221: Arizona | D221: {=INDEX(MData[],MATCH(1,(MData[State Abbreviation]=$B221)*(MData[Report Date]=D$6)*(MData[Preliminary or Updated]=$C$3)*(MData[Final Report]=$C$4),0),MATCH($D$5,MData[#Headers],0))} -> Y | E221: {=INDEX(MData[],MATCH(1,(MData[State Abbreviation]=$B221)*(MData[Report Date]=E$6)*(MData[Preliminary or Updated]=$C$3)*(MData[Final Report]=$C$4),0),MATCH($D$5,MData[#Headers],0))} -> Y | F221: {=INDEX(MData[],MATCH(1,(MData[State Abbreviation]=$B221)*(MData[Report Date]=F$218)*(MData[Preliminary or Updated]=$C$3)*(MData[Final Report]=$C$4),0),MATCH($C$2,MData[#Headers],0))} -> 1701450 | G221: {=INDEX(MData[],MATCH(1,(MData[State Abbreviation]=$B221)*(MData[Report Date]=G$218)*(MData[Preliminary or Updated]=$C$3)*(MData[Final Report]=$C$4),0),MATCH($C$2,MData[#Headers],0))} -> 1701411 | H221: {=INDEX(MData[],MATCH(1,(MData[State Abbreviation]=$B221)*(MData[Report Date]=H$218)*(MData[Preliminary or Updated]=$C$3)*(MData[Final Report]=$C$4),0),MATCH($C$2,MData[#Headers],0))} -> 1703074 | I221: {=INDEX(MData[],MATCH(1,(MData[State Abbreviation]=$B221)*(MData[Report Date]=I$218)*(MData[Preliminary or Updated]=$C$3)*(MData[Final Report]=$C$4),0),MATCH($C$2,MData[#Headers],0))} -> 1702739 | J221: {=INDEX(MData[],MATCH(1,(MData[State Abbreviation]=$B221)*(MData[Report Date]=J$218)*(MData[Preliminary or Updated]=$C$3)*(MData[Final Report]=$C$4),0),MATCH($C$2,MData[#Headers],0))} -> 1697945 | K221: {=INDEX(MData[],MATCH(1,(MData[State Abbreviation]=$B221)*(MData[Report Date]=K$218)*(MData[Preliminary or Updated]=$C$3)*(MData[Final Report]=$C$4),0),MATCH($C$2,MData[#Headers],0))} -> 1705679 | L221: {=INDEX(MData[],MATCH(1,(MData[State Abbreviation]=$B221)*(MData[Report Date]=L$218)*(MData[Preliminary or Updated]=$C$3)*(MData[Final Report]=$C$4),0),MATCH($C$2,MData[#Headers],0))} -> 1715655 | M221: {=INDEX(MData[],MATCH(1,(MData[State Abbreviation]=$B221)*(MData[Report Date]=M$218)*(MData[Preliminary or Updated]=$C$3)*(MData[Final Report]=$C$4),0),MATCH($C$2,MData[#Headers],0))} -> 1722540 | ... Q221: {=INDEX(MData[],MATCH(1,(MData[State Abbreviation]=$B221)*(MData[Report Date]=Q$218)*(MData[Preliminary or Updated]=$C$3)*(MData[Final Report]=$C$4),0),MATCH($C$2,MData[#Headers],0))} -> 1708073 | R221: =AVERAGE(F221:Q221) -> 1710038.3
A222: 4 | B222: AR | C222: Arkansas | D222: {=INDEX(MData[],MATCH(1,(MData[State Abbreviation]=$B222)*(MData[Report Date]=D$6)*(MData[Preliminary or Updated]=$C$3)*(MData[Final Report]=$C$4),0),MATCH($D$5,MData[#Headers],0))} -> Y | E222: {=INDEX(MData[],MATCH(1,(MData[State Abbreviation]=$B222)*(MData[Report Date]=E$6)*(MData[Preliminary or Updated]=$C$3)*(MData[Final Report]=$C$4),0),MATCH($D$5,MData[#Headers],0))} -> Y | F222: {=INDEX(MData[],MATCH(1,(MData[State Abbreviation]=$B222)*(MData[Report Date]=F$218)*(MData[Preliminary or Updated]=$C$3)*(MData[Final Report]=$C$4),0),MATCH($C$2,MData[#Headers],0))} -> 791648 | G222: {=INDEX(MData[],MATCH(1,(MData[State Abbreviation]=$B222)*(MData[Report Date]=G$218)*(MData[Preliminary or Updated]=$C$3)*(MData[Final Report]=$C$4),0),MATCH($C$2,MData[#Headers],0))} -> 790831 | H222: {=INDEX(MData[],MATCH(1,(MData[State Abbreviation]=$B222)*(MData[Report Date]=H$218)*(MData[Preliminary or Updated]=$C$3)*(MData[Final Report]=$C$4),0),MATCH($C$2,MData[#Headers],0))} -> 793914 | I222: {=INDEX(MData[],MATCH(1,(MData[State Abbreviation]=$B222)*(MData[Report Date]=I$218)*(MData[Preliminary or Updated]=$C$3)*(MData[Final Report]=$C$4),0),MATCH($C$2,MData[#Headers],0))} -> 798105 | J222: {=INDEX(MData[],MATCH(1,(MData[State Abbreviation]=$B222)*(MData[Report Date]=J$218)*(MData[Preliminary or Updated]=$C$3)*(MData[Final Report]=$C$4),0),MATCH($C$2,MData[#Headers],0))} -> 795017 | K222: {=INDEX(MData[],MATCH(1,(MData[State Abbreviation]=$B222)*(MData[Report Date]=K$218)*(MData[Preliminary or Updated]=$C$3)*(MData[Final Report]=$C$4),0),MATCH($C$2,MData[#Headers],0))} -> 794025 | L222: {=INDEX(MData[],MATCH(1,(MData[State Abbreviation]=$B222)*(MData[Report Date]=L$218)*(MData[Preliminary or Updated]=$C$3)*(MData[Final Report]=$C$4),0),MATCH($C$2,MData[#Headers],0))} -> 798044 | M222: {=INDEX(MData[],MATCH(1,(MData[State Abbreviation]=$B222)*(MData[Report Date]=M$218)*(MData[Preliminary or Updated]=$C$3)*(MData[Final Report]=$C$4),0),MATCH($C$2,MData[#Headers],0))} -> 798839 | ... Q222: {=INDEX(MData[],MATCH(1,(MData[State Abbreviation]=$B222)*(MData[Report Date]=Q$218)*(MData[Preliminary or Updated]=$C$3)*(MData[Final Report]=$C$4),0),MATCH($C$2,MData[#Headers],0))} -> 811360 | R222: =AVERAGE(F222:Q222) -> 798309.75
A223: 5 | B223: CA | C223: California | D223: {=INDEX(MData[],MATCH(1,(MData[State Abbreviation]=$B223)*(MData[Report Date]=D$6)*(MData[Preliminary or Updated]=$C$3)*(MData[Final Report]=$C$4),0),MATCH($D$5,MData[#Headers],0))} -> Y | E223: {=INDEX(MData[],MATCH(1,(MData[State Abbreviation]=$B223)*(MData[Report Date]=E$6)*(MData[Preliminary or Updated]=$C$3)*(MData[Final Report]=$C$4),0),MATCH($D$5,MData[#Headers],0))} -> Y | F223: {=INDEX(MData[],MATCH(1,(MData[State Abbreviation]=$B223)*(MData[Report Date]=F$218)*(MData[Preliminary or Updated]=$C$3)*(MData[Final Report]=$C$4),0),MATCH($C$2,MData[#Headers],0))} -> 11914394 | G223: {=INDEX(MData[],MATCH(1,(MData[State Abbreviation]=$B223)*(MData[Report Date]=G$218)*(MData[Preliminary or Updated]=$C$3)*(MData[Final Report]=$C$4),0),MATCH($C$2,MData[#Headers],0))} -> 11884268 | H223: {=INDEX(MData[],MATCH(1,(MData[State Abbreviation]=$B223)*(MData[Report Date]=H$218)*(MData[Preliminary or Updated]=$C$3)*(MData[Final Report]=$C$4),0),MATCH($C$2,MData[#Headers],0))} -> 11874143 | I223: {=INDEX(MData[],MATCH(1,(MData[State Abbreviation]=$B223)*(MData[Report Date]=I$218)*(MData[Preliminary or Updated]=$C$3)*(MData[Final Report]=$C$4),0),MATCH($C$2,MData[#Headers],0))} -> 11824373 | J223: {=INDEX(MData[],MATCH(1,(MData[State Abbreviation]=$B223)*(MData[Report Date]=J$218)*(MData[Preliminary or Updated]=$C$3)*(MData[Final Report]=$C$4),0),MATCH($C$2,MData[#Headers],0))} -> 11798654 | K223: {=INDEX(MData[],MATCH(1,(MData[State Abbreviation]=$B223)*(MData[Report Date]=K$218)*(MData[Preliminary or Updated]=$C$3)*(MData[Final Report]=$C$4),0),MATCH($C$2,MData[#Headers],0))} -> 11744007 | L223: {=INDEX(MData[],MATCH(1,(MData[State Abbreviation]=$B223)*(MData[Report Date]=L$218)*(MData[Preliminary or Updated]=$C$3)*(MData[Final Report]=$C$4),0),MATCH($C$2,MData[#Headers],0))} -> 11743500 | M223: {=INDEX(MData[],MATCH(1,(MData[State Abbreviation]=$B223)*(MData[Report Date]=M$218)*(MData[Preliminary or Updated]=$C$3)*(MData[Final Report]=$C$4),0),MATCH($C$2,MData[#Headers],0))} -> 11752681 | ... Q223: {=INDEX(MData[],MATCH(1,(MData[State Abbreviation]=$B223)*(MData[Report Date]=Q$218)*(MData[Preliminary or Updated]=$C$3)*(MData[Final Report]=$C$4),0),MATCH($C$2,MData[#Headers],0))} -> 11588323 | R223: =AVERAGE(F223:Q223) -> 11764380
A224: 6 | B224: CO | C224: Colorado | D224: {=INDEX(MData[],MATCH(1,(MData[State Abbreviation]=$B224)*(MData[Report Date]=D$6)*(MData[Preliminary or Updated]=$C$3)*(MData[Final Report]=$C$4),0),MATCH($D$5,MData[#Headers],0))} -> Y | E224: {=INDEX(MData[],MATCH(1,(MData[State Abbreviation]=$B224)*(MData[Report Date]=E$6)*(MData[Preliminary or Updated]=$C$3)*(MData[Final Report]=$C$4),0),MATCH($D$5,MData[#Headers],0))} -> Y | F224: {=INDEX(MData[],MATCH(1,(MData[State Abbreviation]=$B224)*(MData[Report Date]=F$218)*(MData[Preliminary or Updated]=$C$3)*(MData[Final Report]=$C$4),0),MATCH($C$2,MData[#Headers],0))} -> 1310744 | G224: {=INDEX(MData[],MATCH(1,(MData[State Abbreviation]=$B224)*(MData[Report Date]=G$218)*(MData[Preliminary or Updated]=$C$3)*(MData[Final Report]=$C$4),0),MATCH($C$2,MData[#Headers],0))} -> 1308718 | H224: {=INDEX(MData[],MATCH(1,(MData[State Abbreviation]=$B224)*(MData[Report Date]=H$218)*(MData[Preliminary or Updated]=$C$3)*(MData[Final Report]=$C$4),0),MATCH($C$2,MData[#Headers],0))} -> 1301526 | I224: {=INDEX(MData[],MATCH(1,(MData[State Abbreviation]=$B224)*(MData[Report Date]=I$218)*(MData[Preliminary or Updated]=$C$3)*(MData[Final Report]=$C$4),0),MATCH($C$2,MData[#Headers],0))} -> 1290326 | J224: {=INDEX(MData[],MATCH(1,(MData[State Abbreviation]=$B224)*(MData[Report Date]=J$218)*(MData[Preliminary or Updated]=$C$3)*(MData[Final Report]=$C$4),0),MATCH($C$2,MData[#Headers],0))} -> 1290573 | K224: {=INDEX(MData[],MATCH(1,(MData[State Abbreviation]=$B224)*(MData[Report Date]=K$218)*(MData[Preliminary or Updated]=$C$3)*(MData[Final Report]=$C$4),0),MATCH($C$2,MData[#Headers],0))} -> 1287236 | L224: {=INDEX(MData[],MATCH(1,(MData[State Abbreviation]=$B224)*(MData[Report Date]=L$218)*(MData[Preliminary or Updated]=$C$3)*(MData[Final Report]=$C$4),0),MATCH($C$2,MData[#Headers],0))} -> 1280142 | M224: {=INDEX(MData[],MATCH(1,(MData[State Abbreviation]=$B224)*(MData[Report Date]=M$218)*(MData[Preliminary or Updated]=$C$3)*(MData[Final Report]=$C$4),0),MATCH($C$2,MData[#Headers],0))} -> 1282442 | ... Q224: {=INDEX(MData[],MATCH(1,(MData[State Abbreviation]=$B224)*(MData[Report Date]=Q$218)*(MData[Preliminary or Updated]=$C$3)*(MData[Final Report]=$C$4),0),MATCH($C$2,MData[#Headers],0))} -> 1275430 | R224: =AVERAGE(F224:Q224) -> 1289215.4
A225: 7 | B225: CT | C225: Connecticut | D225: {=INDEX(MData[],MATCH(1,(MData[State Abbreviation]=$B225)*(MData[Report Date]=D$6)*(MData[Preliminary or Updated]=$C$3)*(MData[Final Report]=$C$4),0),MATCH($D$5,MData[#Headers],0))} -> Y | E225: {=INDEX(MData[],MATCH(1,(MData[State Abbreviation]=$B225)*(MData[Report Date]=E$6)*(MData[Preliminary or Updated]=$C$3)*(MData[Final Report]=$C$4),0),MATCH($D$5,MData[#Headers],0))} -> Y | F225: {=INDEX(MData[],MATCH(1,(MData[State Abbreviation]=$B225)*(MData[Report Date]=F$218)*(MData[Preliminary or Updated]=$C$3)*(MData[Final Report]=$C$4),0),MATCH($C$2,MData[#Headers],0))} -> 861977 | G225: {=INDEX(MData[],MATCH(1,(MData[State Abbreviation]=$B225)*(MData[Report Date]=G$218)*(MData[Preliminary or Updated]=$C$3)*(MData[Final Report]=$C$4),0),MATCH($C$2,MData[#Headers],0))} -> 862725 | H225: {=INDEX(MData[],MATCH(1,(MData[State Abbreviation]=$B225)*(MData[Report Date]=H$218)*(MData[Preliminary or Updated]=$C$3)*(MData[Final Report]=$C$4),0),MATCH($C$2,MData[#Headers],0))} -> 867305 | I225: {=INDEX(MData[],MATCH(1,(MData[State Abbreviation]=$B225)*(MData[Report Date]=I$218)*(MData[Preliminary or Updated]=$C$3)*(MData[Final Report]=$C$4),0),MATCH($C$2,MData[#Headers],0))} -> 863051 | J225: {=INDEX(MData[],MATCH(1,(MData[State Abbreviation]=$B225)*(MData[Report Date]=J$218)*(MData[Preliminary or Updated]=$C$3)*(MData[Final Report]=$C$4),0),MATCH($C$2,MData[#Headers],0))} -> 862405 | K225: {=INDEX(MData[],MATCH(1,(MData[State Abbreviation]=$B225)*(MData[Report Date]=K$218)*(MData[Preliminary or Updated]=$C$3)*(MData[Final Report]=$C$4),0),MATCH($C$2,MData[#Headers],0))} -> 858543 | L225: {=INDEX(MData[],MATCH(1,(MData[State Abbreviation]=$B225)*(MData[Report Date]=L$218)*(MData[Preliminary or Updated]=$C$3)*(MData[Final Report]=$C$4),0),MATCH($C$2,MData[#Headers],0))} -> 857415 | M225: {=INDEX(MData[],MATCH(1,(MData[State Abbreviation]=$B225)*(MData[Report Date]=M$218)*(MData[Preliminary or Updated]=$C$3)*(MData[Final Report]=$C$4),0),MATCH($C$2,MData[#Headers],0))} -> 855505 | ... Q225: {=INDEX(MData[],MATCH(1,(MData[State Abbreviation]=$B225)*(MData[Report Date]=Q$218)*(MData[Preliminary or Updated]=$C$3)*(MData[Final Report]=$C$4),0),MATCH($C$2,MData[#Headers],0))} -> 850657 | R225: =AVERAGE(F225:Q225) -> 857778.42
A226: 8 | B226: DE | C226: Delaware | D226: {=INDEX(MData[],MATCH(1,(MData[State Abbreviation]=$B226)*(MData[Report Date]=D$6)*(MData[Preliminary or Updated]=$C$3)*(MData[Final Report]=$C$4),0),MATCH($D$5,MData[#Headers],0))} -> Y | E226: {=INDEX(MData[],MATCH(1,(MData[State Abbreviation]=$B226)*(MData[Report Date]=E$6)*(MData[Preliminary or Updated]=$C$3)*(MData[Final Report]=$C$4),0),MATCH($D$5,MData[#Headers],0))} -> Y | F226: {=INDEX(MData[],MATCH(1,(MData[State Abbreviation]=$B226)*(MData[Report Date]=F$218)*(MData[Preliminary or Updated]=$C$3)*(MData[Final Report]=$C$4),0),MATCH($C$2,MData[#Headers],0))} -> 232614 | G226: {=INDEX(MData[],MATCH(1,(MData[State Abbreviation]=$B226)*(MData[Report Date]=G$218)*(MData[Preliminary or Updated]=$C$3)*(MData[Final Report]=$C$4),0),MATCH($C$2,MData[#Headers],0))} -> 232772 | H226: {=INDEX(MData[],MATCH(1,(MData[State Abbreviation]=$B226)*(MData[Report Date]=H$218)*(MData[Preliminary or Updated]=$C$3)*(MData[Final Report]=$C$4),0),MATCH($C$2,MData[#Headers],0))} -> 232357 | I226: {=INDEX(MData[],MATCH(1,(MData[State Abbreviation]=$B226)*(MData[Report Date]=I$218)*(MData[Preliminary or Updated]=$C$3)*(MData[Final Report]=$C$4),0),MATCH($C$2,MData[#Headers],0))} -> 231788 | J226: {=INDEX(MData[],MATCH(1,(MData[State Abbreviation]=$B226)*(MData[Report Date]=J$218)*(MData[Preliminary or Updated]=$C$3)*(MData[Final Report]=$C$4),0),MATCH($C$2,MData[#Headers],0))} -> 231598 | K226: {=INDEX(MData[],MATCH(1,(MData[State Abbreviation]=$B226)*(MData[Report Date]=K$218)*(MData[Preliminary or Updated]=$C$3)*(MData[Final Report]=$C$4),0),MATCH($C$2,MData[#Headers],0))} -> 230930 | L226: {=INDEX(MData[],MATCH(1,(MData[State Abbreviation]=$B226)*(MData[Report Date]=L$218)*(MData[Preliminary or Updated]=$C$3)*(MData[Final Report]=$C$4),0),MATCH($C$2,MData[#Headers],0))} -> 231586 | M226: {=INDEX(MData[],MATCH(1,(MData[State Abbreviation]=$B226)*(MData[Report Date]=M$218)*(MData[Preliminary or Updated]=$C$3)*(MData[Final Report]=$C$4),0),MATCH($C$2,MData[#Headers],0))} -> 231674 | ... Q226: {=INDEX(MData[],MATCH(1,(MData[State Abbreviation]=$B226)*(MData[Report Date]=Q$218)*(MData[Preliminary or Updated]=$C$3)*(MData[Final Report]=$C$4),0),MATCH($C$2,MData[#Headers],0))} -> 231285 | R226: =AVERAGE(F226:Q226) -> 231654.17
A227: 9 | B227: DC | C227: District of Columbia | D227: {=INDEX(MData[],MATCH(1,(MData[State Abbreviation]=$B227)*(MData[Report Date]=D$6)*(MData[Preliminary or Updated]=$C$3)*(MData[Final Report]=$C$4),0),MATCH($D$5,MData[#Headers],0))} -> Y | E227: {=INDEX(MData[],MATCH(1,(MData[State Abbreviation]=$B227)*(MData[Report Date]=E$6)*(MData[Preliminary or Updated]=$C$3)*(MData[Final Report]=$C$4),0),MATCH($D$5,MData[#Headers],0))} -> Y | F227: {=INDEX(MData[],MATCH(1,(MData[State Abbreviation]=$B227)*(MData[Report Date]=F$218)*(MData[Preliminary or Updated]=$C$3)*(MData[Final Report]=$C$4),0),MATCH($C$2,MData[#Headers],0))} -> 253658 | G227: {=INDEX(MData[],MATCH(1,(MData[State Abbreviation]=$B227)*(MData[Report Date]=G$218)*(MData[Preliminary or Updated]=$C$3)*(MData[Final Report]=$C$4),0),MATCH($C$2,MData[#Headers],0))} -> 253823 | H227: {=INDEX(MData[],MATCH(1,(MData[State Abbreviation]=$B227)*(MData[Report Date]=H$218)*(MData[Preliminary or Updated]=$C$3)*(MData[Final Report]=$C$4),0),MATCH($C$2,MData[#Headers],0))} -> 254384 | I227: {=INDEX(MData[],MATCH(1,(MData[State Abbreviation]=$B227)*(MData[Report Date]=I$218)*(MData[Preliminary or Updated]=$C$3)*(MData[Final Report]=$C$4),0),MATCH($C$2,MData[#Headers],0))} -> 254683 | J227: {=INDEX(MData[],MATCH(1,(MData[State Abbreviation]=$B227)*(MData[Report Date]=J$218)*(MData[Preliminary or Updated]=$C$3)*(MData[Final Report]=$C$4),0),MATCH($C$2,MData[#Headers],0))} -> 254935 | K227: {=INDEX(MData[],MATCH(1,(MData[State Abbreviation]=$B227)*(MData[Report Date]=K$218)*(MData[Preliminary or Updated]=$C$3)*(MData[Final Report]=$C$4),0),MATCH($C$2,MData[#Headers],0))} -> 254774 | L227: {=INDEX(MData[],MATCH(1,(MData[State Abbreviation]=$B227)*(MData[Report Date]=L$218)*(MData[Preliminary or Updated]=$C$3)*(MData[Final Report]=$C$4),0),MATCH($C$2,MData[#Headers],0))} -> 256101 | M227: {=INDEX(MData[],MATCH(1,(MData[State Abbreviation]=$B227)*(MData[Report Date]=M$218)*(MData[Preliminary or Updated]=$C$3)*(MData[Final Report]=$C$4),0),MATCH($C$2,MData[#Headers],0))} -> 255952 | ... Q227: {=INDEX(MData[],MATCH(1,(MData[State Abbreviation]=$B227)*(MData[Report Date]=Q$218)*(MData[Preliminary or Updated]=$C$3)*(MData[Final Report]=$C$4),0),MATCH($C$2,MData[#Headers],0))} -> 253546 | R227: =AVERAGE(F227:Q227) -> 254316.17
A228: 10 | B228: FL | C228: Florida | D228: {=INDEX(MData[],MATCH(1,(MData[State Abbreviation]=$B228)*(MData[Report Date]=D$6)*(MData[Preliminary or Updated]=$C$3)*(MData[Final Report]=$C$4),0),MATCH($D$5,MData[#Headers],0))} -> N | E228: {=INDEX(MData[],MATCH(1,(MData[State Abbreviation]=$B228)*(MData[Report Date]=E$6)*(MData[Preliminary or Updated]=$C$3)*(MData[Final Report]=$C$4),0),MATCH($D$5,MData[#Headers],0))} -> N | F228: {=INDEX(MData[],MATCH(1,(MData[State Abbreviation]=$B228)*(MData[Report Date]=F$218)*(MData[Preliminary or Updated]=$C$3)*(MData[Final Report]=$C$4),0),MATCH($C$2,MData[#Headers],0))} -> 3679990 | G228: {=INDEX(MData[],MATCH(1,(MData[State Abbreviation]=$B228)*(MData[Report Date]=G$218)*(MData[Preliminary or Updated]=$C$3)*(MData[Final Report]=$C$4),0),MATCH($C$2,MData[#Headers],0))} -> 3678155 | H228: {=INDEX(MData[],MATCH(1,(MData[State Abbreviation]=$B228)*(MData[Report Date]=H$218)*(MData[Preliminary or Updated]=$C$3)*(MData[Final Report]=$C$4),0),MATCH($C$2,MData[#Headers],0))} -> 3655668 | I228: {=INDEX(MData[],MATCH(1,(MData[State Abbreviation]=$B228)*(MData[Report Date]=I$218)*(MData[Preliminary or Updated]=$C$3)*(MData[Final Report]=$C$4),0),MATCH($C$2,MData[#Headers],0))} -> 3662149 | J228: {=INDEX(MData[],MATCH(1,(MData[State Abbreviation]=$B228)*(MData[Report Date]=J$218)*(MData[Preliminary or Updated]=$C$3)*(MData[Final Report]=$C$4),0),MATCH($C$2,MData[#Headers],0))} -> 3654076 | K228: {=INDEX(MData[],MATCH(1,(MData[State Abbreviation]=$B228)*(MData[Report Date]=K$218)*(MData[Preliminary or Updated]=$C$3)*(MData[Final Report]=$C$4),0),MATCH($C$2,MData[#Headers],0))} -> 3650441 | L228: {=INDEX(MData[],MATCH(1,(MData[State Abbreviation]=$B228)*(MData[Report Date]=L$218)*(MData[Preliminary or Updated]=$C$3)*(MData[Final Report]=$C$4),0),MATCH($C$2,MData[#Headers],0))} -> 3657394 | M228: {=INDEX(MData[],MATCH(1,(MData[State Abbreviation]=$B228)*(MData[Report Date]=M$218)*(MData[Preliminary or Updated]=$C$3)*(MData[Final Report]=$C$4),0),MATCH($C$2,MData[#Headers],0))} -> 3652059 | ... Q228: {=INDEX(MData[],MATCH(1,(MData[State Abbreviation]=$B228)*(MData[Report Date]=Q$218)*(MData[Preliminary or Updated]=$C$3)*(MData[Final Report]=$C$4),0),MATCH($C$2,MData[#Headers],0))} -> 3613005 | R228: =AVERAGE(F228:Q228) -> 3651035
A229: 11 | B229: GA | C229: Georgia | D229: {=INDEX(MData[],MATCH(1,(MData[State Abbreviation]=$B229)*(MData[Report Date]=D$6)*(MData[Preliminary or Updated]=$C$3)*(MData[Final Report]=$C$4),0),MATCH($D$5,MData[#Headers],0))} -> N | E229: {=INDEX(MData[],MATCH(1,(MData[State Abbreviation]=$B229)*(MData[Report Date]=E$6)*(MData[Preliminary or Updated]=$C$3)*(MData[Final Report]=$C$4),0),MATCH($D$5,MData[#Headers],0))} -> N | F229: {=INDEX(MData[],MATCH(1,(MData[State Abbreviation]=$B229)*(MData[Report Date]=F$218)*(MData[Preliminary or Updated]=$C$3)*(MData[Final Report]=$C$4),0),MATCH($C$2,MData[#Headers],0))} -> 1838259 | G229: {=INDEX(MData[],MATCH(1,(MData[State Abbreviation]=$B229)*(MData[Report Date]=G$218)*(MData[Preliminary or Updated]=$C$3)*(MData[Final Report]=$C$4),0),MATCH($C$2,MData[#Headers],0))} -> 1835052 | H229: {=INDEX(MData[],MATCH(1,(MData[State Abbreviation]=$B229)*(MData[Report Date]=H$218)*(MData[Preliminary or Updated]=$C$3)*(MData[Final Report]=$C$4),0),MATCH($C$2,MData[#Headers],0))} -> 1832021 | I229: {=INDEX(MData[],MATCH(1,(MData[State Abbreviation]=$B229)*(MData[Report Date]=I$218)*(MData[Preliminary or Updated]=$C$3)*(MData[Final Report]=$C$4),0),MATCH($C$2,MData[#Headers],0))} -> 1837180 | J229: {=INDEX(MData[],MATCH(1,(MData[State Abbreviation]=$B229)*(MData[Report Date]=J$218)*(MData[Preliminary or Updated]=$C$3)*(MData[Final Report]=$C$4),0),MATCH($C$2,MData[#Headers],0))} -> 1837888 | K229: {=INDEX(MData[],MATCH(1,(MData[State Abbreviation]=$B229)*(MData[Report Date]=K$218)*(MData[Preliminary or Updated]=$C$3)*(MData[Final Report]=$C$4),0),MATCH($C$2,MData[#Headers],0))} -> 1841182 | L229: {=INDEX(MData[],MATCH(1,(MData[State Abbreviation]=$B229)*(MData[Report Date]=L$218)*(MData[Preliminary or Updated]=$C$3)*(MData[Final Report]=$C$4),0),MATCH($C$2,MData[#Headers],0))} -> 1848553 | M229: {=INDEX(MData[],MATCH(1,(MData[State Abbreviation]=$B229)*(MData[Report Date]=M$218)*(MData[Preliminary or Updated]=$C$3)*(MData[Final Report]=$C$4),0),MATCH($C$2,MData[#Headers],0))} -> 1851137 | ... Q229: {=INDEX(MData[],MATCH(1,(MData[State Abbreviation]=$B229)*(MData[Report Date]=Q$218)*(MData[Preliminary or Updated]=$C$3)*(MData[Final Report]=$C$4),0),MATCH($C$2,MData[#Headers],0))} -> 1816358 | R229: =AVERAGE(F229:Q229) -> 1839434
A230: 12 | B230: HI | C230: Hawaii | D230: {=INDEX(MData[],MATCH(1,(MData[State Abbreviation]=$B230)*(MData[Report Date]=D$6)*(MData[Preliminary or Updated]=$C$3)*(MData[Final Report]=$C$4),0),MATCH($D$5,MData[#Headers],0))} -> Y | E230: {=INDEX(MData[],MATCH(1,(MData[State Abbreviation]=$B230)*(MData[Report Date]=E$6)*(MData[Preliminary or Updated]=$C$3)*(MData[Final Report]=$C$4),0),MATCH($D$5,MData[#Headers],0))} -> Y | F230: {=INDEX(MData[],MATCH(1,(MData[State Abbreviation]=$B230)*(MData[Report Date]=F$218)*(MData[Preliminary or Updated]=$C$3)*(MData[Final Report]=$C$4),0),MATCH($C$2,MData[#Headers],0))} -> 330410 | G230: {=INDEX(MData[],MATCH(1,(MData[State Abbreviation]=$B230)*(MData[Report Date]=G$218)*(MData[Preliminary or Updated]=$C$3)*(MData[Final Report]=$C$4),0),MATCH($C$2,MData[#Headers],0))} -> 331889 | H230: {=INDEX(MData[],MATCH(1,(MData[State Abbreviation]=$B230)*(MData[Report Date]=H$218)*(MData[Preliminary or Updated]=$C$3)*(MData[Final Report]=$C$4),0),MATCH($C$2,MData[#Headers],0))} -> 329688 | I230: {=INDEX(MData[],MATCH(1,(MData[State Abbreviation]=$B230)*(MData[Report Date]=I$218)*(MData[Preliminary or Updated]=$C$3)*(MData[Final Report]=$C$4),0),MATCH($C$2,MData[#Headers],0))} -> 329868 | J230: {=INDEX(MData[],MATCH(1,(MData[State Abbreviation]=$B230)*(MData[Report Date]=J$218)*(MData[Preliminary or Updated]=$C$3)*(MData[Final Report]=$C$4),0),MATCH($C$2,MData[#Headers],0))} -> 329422 | K230: {=INDEX(MData[],MATCH(1,(MData[State Abbreviation]=$B230)*(MData[Report Date]=K$218)*(MData[Preliminary or Updated]=$C$3)*(MData[Final Report]=$C$4),0),MATCH($C$2,MData[#Headers],0))} -> 329106 | L230: {=INDEX(MData[],MATCH(1,(MData[State Abbreviation]=$B230)*(MData[Report Date]=L$218)*(MData[Preliminary or Updated]=$C$3)*(MData[Final Report]=$C$4),0),MATCH($C$2,MData[#Headers],0))} -> 328393 | M230: {=INDEX(MData[],MATCH(1,(MData[State Abbreviation]=$B230)*(MData[Report Date]=M$218)*(MData[Preliminary or Updated]=$C$3)*(MData[Final Report]=$C$4),0),MATCH($C$2,MData[#Headers],0))} -> 328923 | ... Q230: {=INDEX(MData[],MATCH(1,(MData[State Abbreviation]=$B230)*(MData[Report Date]=Q$218)*(MData[Preliminary or Updated]=$C$3)*(MData[Final Report]=$C$4),0),MATCH($C$2,MData[#Headers],0))} -> 326337 | R230: =AVERAGE(F230:Q230) -> 328810.83
... A269: 51 | B269: WY | C269: Wyoming | D269: {=INDEX(MData[],MATCH(1,(MData[State Abbreviation]=$B269)*(MData[Report Date]=D$6)*(MData[Preliminary or Updated]=$C$3)*(MData[Final Report]=$C$4),0),MATCH($D$5,MData[#Headers],0))} -> N | E269: {=INDEX(MData[],MATCH(1,(MData[State Abbreviation]=$B269)*(MData[Report Date]=E$6)*(MData[Preliminary or Updated]=$C$3)*(MData[Final Report]=$C$4),0),MATCH($D$5,MData[#Headers],0))} -> N | F269: {=INDEX(MData[],MATCH(1,(MData[State Abbreviation]=$B269)*(MData[Report Date]=F$218)*(MData[Preliminary or Updated]=$C$3)*(MData[Final Report]=$C$4),0),MATCH($C$2,MData[#Headers],0))} -> 58059 | G269: {=INDEX(MData[],MATCH(1,(MData[State Abbreviation]=$B269)*(MData[Report Date]=G$218)*(MData[Preliminary or Updated]=$C$3)*(MData[Final Report]=$C$4),0),MATCH($C$2,MData[#Headers],0))} -> 57594 | H269: {=INDEX(MData[],MATCH(1,(MData[State Abbreviation]=$B269)*(MData[Report Date]=H$218)*(MData[Preliminary or Updated]=$C$3)*(MData[Final Report]=$C$4),0),MATCH($C$2,MData[#Headers],0))} -> 57835 | I269: {=INDEX(MData[],MATCH(1,(MData[State Abbreviation]=$B269)*(MData[Report Date]=I$218)*(MData[Preliminary or Updated]=$C$3)*(MData[Final Report]=$C$4),0),MATCH($C$2,MData[#Headers],0))} -> 58027 | J269: {=INDEX(MData[],MATCH(1,(MData[State Abbreviation]=$B269)*(MData[Report Date]=J$218)*(MData[Preliminary or Updated]=$C$3)*(MData[Final Report]=$C$4),0),MATCH($C$2,MData[#Headers],0))} -> 56608 | K269: {=INDEX(MData[],MATCH(1,(MData[State Abbreviation]=$B269)*(MData[Report Date]=K$218)*(MData[Preliminary or Updated]=$C$3)*(MData[Final Report]=$C$4),0),MATCH($C$2,MData[#Headers],0))} -> 56047 | L269: {=INDEX(MData[],MATCH(1,(MData[State Abbreviation]=$B269)*(MData[Report Date]=L$218)*(MData[Preliminary or Updated]=$C$3)*(MData[Final Report]=$C$4),0),MATCH($C$2,MData[#Headers],0))} -> 55904 | M269: {=INDEX(MData[],MATCH(1,(MData[State Abbreviation]=$B269)*(MData[Report Date]=M$218)*(MData[Preliminary or Updated]=$C$3)*(MData[Final Report]=$C$4),0),MATCH($C$2,MData[#Headers],0))} -> 55368 | ... Q269: {=INDEX(MData[],MATCH(1,(MData[State Abbreviation]=$B269)*(MData[Report Date]=Q$218)*(MData[Preliminary or Updated]=$C$3)*(MData[Final Report]=$C$4),0),MATCH($C$2,MData[#Headers],0))} -> 55974 | R269: =AVERAGE(F269:Q269) -> 56579.667

Sheet Enrollment
A1: Last downloaded July 31, 2024
A3: Fields | B3: State Abbreviation | C3: State Name | D3: Report Date | E3: State Expanded Medicaid | F3: Preliminary or Updated | G3: Final Report | H3: New Applications Submitted to Medicaid and CHIP Agencies | I3: New Applications Submitted to Medicaid and CHIP Agencies - footnotes | J3: Applications for Financial Assistance Submitted to the State Based Marketplace | K3: Applications for Financial Assistance Submitted to the State Based Marketplace- footnotes | L3: Total Applications Received | M3: Total Applications Received- footnotess | N3: Individuals Determined Eligible for Medicaid at Application | O3: Individuals Determined Eligible for Medicaid at Application- footnotes | P3: Individuals Determined Eligible for CHIP at Application | Q3: Individuals Determined Eligible for CHIP at Application- footnotes | R3: Total Medicaid and CHIP Determinations | S3: Total Medicaid and CHIP Determinations- footnotes | T3: Medicaid and CHIP Child Enrollment | U3: Medicaid and CHIP Child Enrollment- footnotes | V3: Total Medicaid and CHIP Enrollment | W3: Total Medicaid and CHIP Enrollment- footnotes | X3: Total Medicaid Enrollment | Y3: Total Medicaid Enrollment- footnotes | Z3: Total CHIP Enrollment | AA3: Total CHIP Enrollment - footnotes
A4: Check | B4: =B3=B6 -> TRUE | C4: =C3=C6 -> TRUE | D4: =D3=D6 -> TRUE | E4: =E3=E6 -> TRUE | F4: =F3=F6 -> TRUE | G4: =G3=G6 -> TRUE | H4: =H3=H6 -> TRUE | I4: =I3=I6 -> TRUE | ... AA4: =AA3=AA6 -> TRUE
B6: State Abbreviation | C6: State Name | D6: Report Date | E6: State Expanded Medicaid | F6: Preliminary or Updated | G6: Final Report | H6: New Applications Submitted to Medicaid and CHIP Agencies | I6: New Applications Submitted to Medicaid and CHIP Agencies - footnotes | J6: Applications for Financial Assistance Submitted to the State Based Marketplace | K6: Applications for Financial Assistance Submitted to the State Based Marketplace- footnotes | L6: Total Applications Received | M6: Total Applications Received- footnotess | N6: Individuals Determined Eligible for Medicaid at Application | O6: Individuals Determined Eligible for Medicaid at Application- footnotes | P6: Individuals Determined Eligible for CHIP at Application | Q6: Individuals Determined Eligible for CHIP at Application- footnotes | R6: Total Medicaid and CHIP Determinations | S6: Total Medicaid and CHIP Determinations- footnotes | T6: Medicaid and CHIP Child Enrollment | U6: Medicaid and CHIP Child Enrollment- footnotes | V6: Total Medicaid and CHIP Enrollment | W6: Total Medicaid and CHIP Enrollment- footnotes | X6: Total Medicaid Enrollment | Y6: Total Medicaid Enrollment- footnotes | Z6: Total CHIP Enrollment | AA6: Total CHIP Enrollment - footnotes
B7: AL | C7: Alabama | D7: 41518 | E7: N | F7: U | G7: Y | V7: 799176
B8: AL | C8: Alabama | D8: 42887 | E8: N | F8: P | G8: N | H8: 16449 | J8: 0 | L8: 16449 | N8: 25370 | P8: 3264 | R8: 28634 | T8: 629763 | V8: 888314 | X8: 731915 | Z8: 156399
B9: AL | C9: Alabama | D9: 42887 | E9: N | F9: U | G9: Y | H9: 16449 | J9: 0 | L9: 16449 | N9: 25370 | P9: 3264 | R9: 28634 | T9: 629763 | V9: 888314 | X9: 731915 | Z9: 156399
B10: AL | C10: Alabama | D10: 42917 | E10: N | F10: P | G10: N | H10: 17118 | J10: 0 | L10: 17118 | N10: 25311 | P10: 3352 | R10: 28663 | T10: 632822 | V10: 893193 | X10: 735619 | Z10: 157574
B11: AL | C11: Alabama | D11: 42917 | E11: N | F11: U | G11: Y | H11: 17118 | J11: 0 | L11: 17118 | N11: 25313 | P11: 3352 | R11: 28665 | T11: 632822 | V11: 893193 | X11: 735619 | Z11: 157574
B12: AL | C12: Alabama | D12: 42948 | E12: N | F12: P | G12: N | H12: 20055 | J12: 0 | L12: 20055 | N12: 30256 | P12: 4205 | R12: 34461 | T12: 633050 | V12: 893261 | X12: 734933 | Z12: 158328
B13: AL | C13: Alabama | D13: 42948 | E13: N | F13: U | G13: Y | H13: 20055 | J13: 0 | L13: 20055 | N13: 30256 | P13: 4205 | R13: 34461 | T13: 633050 | V13: 893262 | X13: 734934 | Z13: 158328
B14: AL | C14: Alabama | D14: 42979 | E14: N | F14: P | G14: N | H14: 18308 | J14: 0 | L14: 18308 | N14: 27798 | P14: 3592 | R14: 31390 | T14: 632920 | V14: 892651 | X14: 734507 | Z14: 158144
B15: AL | C15: Alabama | D15: 42979 | E15: N | F15: U | G15: Y | H15: 18308 | J15: 0 | L15: 18308 | N15: 27798 | P15: 3592 | R15: 31390 | T15: 632920 | V15: 892651 | X15: 734507 | Z15: 158144
B16: AL | C16: Alabama | D16: 43009 | E16: N | F16: P | G16: N | H16: 18913 | J16: 0 | L16: 18913 | N16: 28167 | P16: 4200 | R16: 32367 | T16: 634304 | V16: 894251 | X16: 735171 | Z16: 159080
B17: AL | C17: Alabama | D17: 43009 | E17: N | F17: U | G17: Y | H17: 18913 | J17: 0 | L17: 18913 | N17: 28167 | P17: 4200 | R17: 32367 | T17: 634304 | V17: 894251 | X17: 735171 | Z17: 159080
B18: AL | C18: Alabama | D18: 43040 | E18: N | F18: P | G18: N | H18: 17690 | J18: 0 | L18: 17690 | N18: 25298 | P18: 3781 | R18: 29079 | T18: 635937 | V18: 895732 | X18: 723068 | Z18: 172664
B19: AL | C19: Alabama | D19: 43040 | E19: N | F19: U | G19: Y | H19: 17690 | J19: 0 | L19: 17690 | N19: 25298 | P19: 3781 | R19: 29079 | T19: 635937 | V19: 895732 | X19: 723068 | Z19: 172664
... B170: AL | C170: Alabama | D170: 45352 | E170: N | F170: P | G170: N | H170: 10666 | J170: 0 | L170: 10666 | N170: 12146 | P170: 7041 | R170: 19187 | T170: 706838 | V170: 1037164 | X170: 855165 | Z170: 181999
B171: AK | C171: Alaska | D171: 41518 | E171: Y | F171: U | G171: Y | V171: 122334
B172: AK | C172: Alaska | D172: 42887 | E172: Y | F172: P | G172: N | H172: 3017 | I172: Includes Renewals and/or Redeterminations | J172: 0 | L172: 3017 | M172: Includes Renewals and/or Redeterminations | N172: 3422 | O172: Includes Renewals and/or Redeterminations; Includes CHIP | P172: 0 | R172: 3422 | S172: Includes Renewals and/or Redeterminations | T172: 88766 | V172: 191171 | X172: 179001 | Z172: 12170
B173: AK | C173: Alaska | D173: 42887 | E173: Y | F173: U | G173: Y | H173: 3069 | I173: Includes Renewals and/or Redeterminations | J173: 0 | L173: 3069 | M173: Includes Renewals and/or Redeterminations | N173: 3422 | O173: Includes Renewals and/or Redeterminations; Includes CHIP | P173: 0 | R173: 3422 | S173: Includes Renewals and/or Redeterminations | T173: 90081 | V173: 194534 | X173: 182080 | Z173: 12454
B174: AK | C174: Alaska | D174: 42917 | E174: Y | F174: U | G174: Y | H174: 3265 | I174: Includes Renewals and/or Redeterminations | J174: 0 | L174: 3265 | M174: Includes Renewals and/or Redeterminations | N174: 3159 | O174: Includes Renewals and/or Redeterminations; Includes CHIP | P174: 0 | R174: 3159 | S174: Includes Renewals and/or Redeterminations | T174: 90562 | V174: 196121 | X174: 183516 | Z174: 12605
B175: AK | C175: Alaska | D175: 42917 | E175: Y | F175: P | G175: N | H175: 3187 | I175: Includes Renewals and/or Redeterminations | J175: 0 | L175: 3187 | M175: Includes Renewals and/or Redeterminations | N175: 3159 | O175: Includes Renewals and/or Redeterminations; Includes CHIP | P175: 0 | R175: 3159 | S175: Includes Renewals and/or Redeterminations | T175: 89358 | V175: 193019 | X175: 180641 | Z175: 12378
B176: AK | C176: Alaska | D176: 42948 | E176: Y | F176: P | G176: N | H176: 3911 | I176: Includes Renewals and/or Redeterminations | J176: 0 | L176: 3911 | M176: Includes Renewals and/or Redeterminations | N176: 3187 | O176: Includes Renewals and/or Redeterminations; Includes CHIP | P176: 0 | R176: 3187 | S176: Includes Renewals and/or Redeterminations | T176: 90085 | V176: 194909 | X176: 182349 | Z176: 12560
B177: AK | C177: Alaska | D177: 42948 | E177: Y | F177: U | G177: Y | H177: 3967 | I177: Includes Renewals and/or Redeterminations | J177: 0 | L177: 3967 | M177: Includes Renewals and/or Redeterminations | N177: 3187 | O177: Includes Renewals and/or Redeterminations; Includes CHIP | P177: 0 | R177: 3187 | S177: Includes Renewals and/or Redeterminations | T177: 91294 | V177: 197834 | X177: 185071 | Z177: 12763
B178: AK | C178: Alaska | D178: 42979 | E178: Y | F178: U | G178: Y | H178: 3553 | I178: Includes Renewals and/or Redeterminations | J178: 0 | L178: 3553 | M178: Includes Renewals and/or Redeterminations | N178: 2664 | O178: Includes Renewals and/or Redeterminations; Includes CHIP | P178: 0 | R178: 2664 | S178: Includes Renewals and/or Redeterminations | T178: 91550 | V178: 198742 | X178: 185974 | Z178: 12768
B179: AK | C179: Alaska | D179: 42979 | E179: Y | F179: P | G179: N | H179: 3492 | I179: Includes Renewals and/or Redeterminations | J179: 0 | L179: 3492 | M179: Includes Renewals and/or Redeterminations | N179: 2664 | O179: Includes Renewals and/or Redeterminations; Includes CHIP | P179: 0 | R179: 2664 | S179: Includes Renewals and/or Redeterminations | T179: 90439 | V179: 195913 | X179: 183311 | Z179: 12602
B180: AK | C180: Alaska | D180: 43009 | E180: Y | F180: P | G180: N | H180: 3497 | I180: Includes Renewals and/or Redeterminations | J180: 0 | L180: 3497 | M180: Includes Renewals and/or Redeterminations | N180: 2961 | O180: Includes Renewals and/or Redeterminations; Includes CHIP | P180: 0 | R180: 2961 | S180: Includes Renewals and/or Redeterminations | T180: 90933 | V180: 197433 | X180: 184678 | Z180: 12755
B181: AK | C181: Alaska | D181: 43009 | E181: Y | F181: U | G181: Y | H181: 3574 | J181: 0 | L181: 3574 | N181: 2961 | P181: 0 | R181: 2961 | T181: 92122 | V181: 200627 | X181: 187664 | Z181: 12963
B182: AK | C182: Alaska | D182: 43040 | E182: Y | F182: P | G182: N | H182: 4320 | J182: 0 | L182: 4320 | N182: 3337 | P182: 0 | R182: 3337 | T182: 91254 | V182: 198880 | X182: 186078 | Z182: 12802
B183: AK | C183: Alaska | D183: 43040 | E183: Y | F183: U | G183: Y | H183: 4320 | J183: 0 | L183: 4320 | N183: 3337 | P183: 0 | R183: 3337 | T183: 92203 | V183: 201672 | X183: 188630 | Z183: 13042
B184: AK | C184: Alaska | D184: 43070 | E184: Y | F184: U | G184: Y | H184: 3446 | J184: 0 | L184: 3446 | N184: 3825 | P184: 0 | R184: 3825 | T184: 91360 | V184: 200369 | X184: 187450 | Z184: 12919
B185: AK | C185: Alaska | D185: 43070 | E185: Y | F185: P | G185: N | H185: 3854 | J185: 0 | L185: 3854 | N185: 3825 | P185: 0 | R185: 3825 | T185: 91516 | V185: 200185 | X185: 187272 | Z185: 12913
B186: AK | C186: Alaska | D186: 43101 | E186: Y | F186: U | G186: Y | H186: 3735 | J186: 0 | L186: 3735 | N186: 2838 | P186: 0 | R186: 2838 | T186: 92495 | V186: 203654 | X186: 190513 | Z186: 13141
B187: AK | C187: Alaska | D187: 43101 | E187: Y | F187: P | G187: N | H187: 3735 | J187: 0 | L187: 3735 | N187: 2838 | P187: 0 | R187: 2838 | T187: 92260 | V187: 202912 | X187: 189696 | Z187: 13216
B188: AK | C188: Alaska | D188: 43132 | E188: Y | F188: P | G188: N | H188: 3052 | J188: 0 | L188: 3052 | N188: 2334 | P188: 0 | R188: 2334 | T188: 92415 | V188: 203672 | X188: 190509 | Z188: 13163
B189: AK | C189: Alaska | D189: 43132 | E189: Y | F189: U | G189: Y | H189: 3052 | J189: 0 | L189: 3052 | N189: 2334 | P189: 0 | R189: 2334 | T189: 92649 | V189: 204311 | X189: 191133 | Z189: 13178
B190: AK | C190: Alaska | D190: 43160 | E190: Y | F190: U | G190: Y | H190: 3373 | I190: Includes Renewals and/or Redeterminations | J190: 0 | L190: 3373 | M190: Includes Renewals and/or Redeterminations | N190: 2584 | O190: Includes Renewals and/or Redeterminations; Includes CHIP | P190: 0 | R190: 2584 | S190: Includes Renewals and/or Redeterminations | T190: 93203 | V190: 205761 | X190: 192481 | Z190: 13280
B191: AK | C191: Alaska | D191: 43160 | E191: Y | F191: P | G191: N | H191: 3373 | I191: Includes Renewals and/or Redeterminations | J191: 0 | L191: 3373 | M191: Includes Renewals and/or Redeterminations | N191: 2584 | O191: Includes Renewals and/or Redeterminations; Includes CHIP | P191: 0 | R191: 2584 | S191: Includes Renewals and/or Redeterminations | T191: 93019 | V191: 205234 | X191: 191959 | Z191: 13275
B192: AK | C192: Alaska | D192: 43191 | E192: Y | F192: P | G192: N | H192: 3046 | I192: Includes Renewals and/or Redeterminations | J192: 0 | L192: 3046 | M192: Includes Renewals and/or Redeterminations | N192: 2315 | O192: Includes Renewals and/or Redeterminations; Includes CHIP | P192: 0 | R192: 2315 | S192: Includes Renewals and/or Redeterminations | T192: 93511 | V192: 206808 | X192: 193515 | Z192: 13293
B193: AK | C193: Alaska | D193: 43191 | E193: Y | F193: U | G193: Y | H193: 3352 | I193: Includes Renewals and/or Redeterminations | J193: 0 | L193: 3352 | M193: Includes Renewals and/or Redeterminations | N193: 2315 | O193: Includes Renewals and/or Redeterminations; Includes CHIP | P193: 0 | R193: 2315 | S193: Includes Renewals and/or Redeterminations | T193: 93680 | V193: 207337 | X193: 194039 | Z193: 13298
B194: AK | C194: Alaska | D194: 43221 | E194: Y | F194: U | G194: Y | H194: 3549 | I194: Includes Renewals and/or Redeterminations | J194: 0 | L194: 3549 | M194: Includes Renewals and/or Redeterminations | N194: 2312 | O194: Includes Renewals and/or Redeterminations; Includes CHIP | P194: 0 | R194: 2312 | S194: Includes Renewals and/or Redeterminations | T194: 93840 | V194: 207771 | X194: 194367 | Z194: 13404
B195: AK | C195: Alaska | D195: 43221 | E195: Y | F195: P | G195: N | H195: 3549 | I195: Includes Renewals and/or Redeterminations | J195: 0 | L195: 3549 | M195: Includes Renewals and/or Redeterminations | N195: 2312 | O195: Includes Renewals and/or Redeterminations; Includes CHIP | P195: 0 | R195: 2312 | S195: Includes Renewals and/or Redeterminations | T195: 93834 | V195: 207765 | X195: 194362 | Z195: 13403
B196: AK | C196: Alaska | D196: 43252 | E196: Y | F196: U | G196: Y | H196: 3239 | I196: Includes Renewals and/or Redeterminations | J196: 0 | L196: 3239 | M196: Includes Renewals and/or Redeterminations | N196: 2245 | O196: Includes Renewals and/or Redeterminations; Includes CHIP | P196: 0 | R196: 2245 | S196: Includes Renewals and/or Redeterminations | T196: 95006 | V196: 211054 | X196: 197325 | Z196: 13729
B197: AK | C197: Alaska | D197: 43252 | E197: Y | F197: P | G197: N | H197: 3239 | I197: Includes Renewals and/or Redeterminations | J197: 0 | L197: 3239 | M197: Includes Renewals and/or Redeterminations | N197: 2245 | O197: Includes Renewals and/or Redeterminations; Includes CHIP | P197: 0 | R197: 2245 | S197: Includes Renewals and/or Redeterminations | T197: 93416 | V197: 206727 | X197: 193286 | Z197: 13441
B198: AK | C198: Alaska | D198: 43282 | E198: Y | F198: U | G198: Y | H198: 2911 | I198: Includes Renewals and/or Redeterminations | J198: 0 | L198: 2911 | M198: Includes Renewals and/or Redeterminations | N198: 2232 | O198: Includes Renewals and/or Redeterminations; Includes CHIP | P198: 0 | R198: 2232 | S198: Includes Renewals and/or Redeterminations | T198: 95035 | V198: 211609 | X198: 197806 | Z198: 13803
B199: AK | C199: Alaska | D199: 43282 | E199: Y | F199: P | G199: N | H199: 2911 | I199: Includes Renewals and/or Redeterminations | J199: 0 | L199: 2911 | M199: Includes Renewals and/or Redeterminations | N199: 2232 | O199: Includes Renewals and/or Redeterminations; Includes CHIP | P199: 0 | R199: 2232 | S199: Includes Renewals and/or Redeterminations | T199: 94270 | V199: 209491 | X199: 195832 | Z199: 13659
B200: AK | C200: Alaska | D200: 43313 | E200: Y | F200: U | G200: Y | H200: 3216 | I200: Includes Renewals and/or Redeterminations | J200: 0 | L200: 3216 | M200: Includes Renewals and/or Redeterminations | N200: 2409 | O200: Includes Renewals and/or Redeterminations; Includes CHIP | P200: 0 | R200: 2409 | S200: Includes Renewals and/or Redeterminations | T200: 95080 | V200: 211945 | X200: 197981 | Z200: 13964
B201: AK | C201: Alaska | D201: 43313 | E201: Y | F201: P | G201: N | H201: 3216 | I201: Includes Renewals and/or Redeterminations | J201: 0 | L201: 3216 | M201: Includes Renewals and/or Redeterminations | N201: 2409 | O201: Includes Renewals and/or Redeterminations; Includes CHIP | P201: 0 | R201: 2409 | S201: Includes Renewals and/or Redeterminations | T201: 94422 | V201: 210217 | X201: 196460 | Z201: 13757
... B242: AK | C242: Alaska | D242: 43952 | E242: Y | F242: U | G242: Y | H242: 2497 | I242: Includes Renewals and/or Redeterminations | J242: 0 | L242: 2497 | M242: Includes Renewals and/or Redeterminations | N242: 3407 | O242: Includes Renewals and/or Redeterminations; Includes CHIP | P242: 213 | R242: 3620 | S242: Includes Renewals and/or Redeterminations | T242: 98912 | V242: 230043 | X242: 214692 | Z242: 15351
B243: AK | C243: Alaska | D243: 43952 | E243: Y | F243: P | G243: N | H243: 2497 | J243: 0 | L243: 2497 | N243: 3407 | P243: 213 | R243: 3620 | T243: 98912 | V243: 230043 | X243: 214692 | Z243: 15351
B244: AK | C244: Alaska | D244: 43983 | E244: Y | F244: P | G244: N | H244: 2844 | I244: Includes Renewals and/or Redeterminations | J244: 0 | L244: 2844 | M244: Includes Renewals and/or Redeterminations | N244: 3238 | O244: Includes Renewals and/or Redeterminations; Includes CHIP | P244: 231 | R244: 3469 | S244: Includes Renewals and/or Redeterminations | T244: 98484 | V244: 231145 | X244: 216568 | Z244: 14577
B245: AK | C245: Alaska | D245: 43983 | E245: Y | F245: U | G245: Y | H245: 2844 | I245: Includes Renewals and/or Redeterminations | J245: 0 | L245: 2844 | M245: Includes Renewals and/or Redeterminations | N245: 3238 | O245: Includes Renewals and/or Redeterminations; Includes CHIP | P245: 231 | R245: 3469 | S245: Includes Renewals and/or Redeterminations | T245: 98792 | V245: 232069 | X245: 217484 | Z245: 14585
B246: AK | C246: Alaska | D246: 44013 | E246: Y | F246: U | G246: Y | H246: 2402 | I246: Includes Renewals and/or Redeterminations | J246: 0 | L246: 2402 | M246: Includes Renewals and/or Redeterminations | N246: 2081 | O246: Includes Renewals and/or Redeterminations; Includes CHIP | P246: 127 | R246: 2208 | S246: Includes Renewals and/or Redeterminations | T246: 98580 | V246: 233334 | X246: 219239 | Z246: 14095
B247: AK | C247: Alaska | D247: 44013 | E247: Y | F247: P | G247: N | H247: 2402 | I247: Includes Renewals and/or Redeterminations | J247: 0 | L247: 2402 | M247: Includes Renewals and/or Redeterminations | N247: 2081 | O247: Includes Renewals and/or Redeterminations; Includes CHIP | P247: 127 | R247: 2208 | S247: Includes Renewals and/or Redeterminations | T247: 98287 | V247: 232578 | X247: 218487 | Z247: 14091
B248: AK | C248: Alaska | D248: 44044 | E248: Y | F248: P | G248: N | H248: 2737 | I248: Includes Renewals and/or Redeterminations | J248: 0 | L248: 2737 | M248: Includes Renewals and/or Redeterminations | N248: 1950 | O248: Includes Renewals and/or Redeterminations; Includes CHIP | P248: 93 | R248: 2043 | S248: Includes Renewals and/or Redeterminations | T248: 98556 | V248: 234622 | X248: 220778 | Z248: 13844
B249: AK | C249: Alaska | D249: 44044 | E249: Y | F249: U | G249: Y | H249: 2737 | I249: Includes Renewals and/or Redeterminations | J249: 0 | L249: 2737 | M249: Includes Renewals and/or Redeterminations | N249: 1950 | O249: Includes Renewals and/or Redeterminations; Includes CHIP | P249: 93 | R249: 2043 | S249: Includes Renewals and/or Redeterminations | T249: 98804 | V249: 235261 | X249: 221414 | Z249: 13847
B250: AK | C250: Alaska | D250: 44075 | E250: Y | F250: P | G250: N | H250: 2657 | I250: Includes Renewals and/or Redeterminations | J250: 0 | L250: 2657 | M250: Includes Renewals and/or Redeterminations | N250: 1944 | O250: Includes Renewals and/or Redeterminations; Includes CHIP | P250: 95 | R250: 2039 | S250: Includes Renewals and/or Redeterminations | T250: 98788 | V250: 235600 | X250: 221926 | Z250: 13674
B251: AK | C251: Alaska | D251: 44075 | E251: Y | F251: U | G251: Y | H251: 2657 | I251: Includes Renewals and/or Redeterminations | J251: 0 | L251: 2657 | M251: Includes Renewals and/or Redeterminations | N251: 1944 | O251: Includes Renewals and/or Redeterminations; Includes CHIP | P251: 95 | R251: 2039 | S251: Includes Renewals and/or Redeterminations | T251: 99035 | V251: 236362 | X251: 222686 | Z251: 13676
B252: AK | C252: Alaska | D252: 44105 | E252: Y | F252: P | G252: N | H252: 2849 | I252: Includes Renewals and/or Redeterminations | J252: 0 | L252: 2849 | M252: Includes Renewals and/or Redeterminations | N252: 2001 | O252: Includes Renewals and/or Redeterminations; Includes CHIP | P252: 79 | R252: 2080 | S252: Includes Renewals and/or Redeterminations | T252: 99143 | V252: 236719 | X252: 223272 | Z252: 13447
B253: AK | C253: Alaska | D253: 44105 | E253: Y | F253: U | G253: Y | H253: 2849 | I253: Includes Renewals and/or Redeterminations | J253: 0 | L253: 2849 | M253: Includes Renewals and/or Redeterminations | N253: 2001 | O253: Includes Renewals and/or Redeterminations; Includes CHIP | P253: 79 | R253: 2080 | S253: Includes Renewals and/or Redeterminations | T253: 99443 | V253: 237786 | X253: 224338 | Z253: 13448
B254: AK | C254: Alaska | D254: 44136 | E254: Y | F254: P | G254: N | H254: 3756 | I254: Includes Renewals and/or Redeterminations | J254: 0 | L254: 3756 | M254: Includes Renewals and/or Redeterminations | N254: 1976 | O254: Includes Renewals and/or Redeterminations; Includes CHIP | P254: 120 | R254: 2096 | S254: Includes Renewals and/or Redeterminations | T254: 99352 | V254: 237622 | X254: 224273 | Z254: 13349
B255: AK | C255: Alaska | D255: 44136 | E255: Y | F255: U | G255: Y | H255: 3756 | I255: Includes Renewals and/or Redeterminations | J255: 0 | L255: 3756 | M255: Includes Renewals and/or Redeterminations | N255: 1976 | O255: Includes Renewals and/or Redeterminations; Includes CHIP | P255: 120 | R255: 2096 | S255: Includes Renewals and/or Redeterminations | T255: 99655 | V255: 238873 | X255: 225513 | Z255: 13360
... B268: AK | C268: Alaska | D268: 44348 | E268: Y | F268: P | G268: N | H268: 2484 | I268: Includes Renewals and/or Redeterminations | J268: 0 | L268: 2484 | M268: Includes Renewals and/or Redeterminations | N268: 1782 | O268: Includes Renewals and/or Redeterminations; Includes CHIP | P268: 75 | R268: 1857 | S268: Includes Renewals and/or Redeterminations | T268: 102218 | V268: 249502 | X268: 236720 | Z268: 12782
B269: AK | C269: Alaska | D269: 44348 | E269: Y | F269: U | G269: Y | H269: 0 | J269: 0 | L269: 0 | N269: 0 | P269: 0 | R269: 0 | T269: 102501 | V269: 250285 | X269: 237500 | Z269: 12785
B270: AK | C270: Alaska | D270: 44378 | E270: Y | F270: P | G270: N | H270: 2214 | J270: 0 | L270: 2214 | N270: 1519 | P270: 76 | R270: 1595 | T270: 102312 | V270: 250151 | X270: 237497 | Z270: 12654
B271: AK | C271: Alaska | D271: 44378 | E271: Y | F271: U | G271: Y | H271: 2214 | J271: 0 | L271: 2214 | N271: 1519 | P271: 76 | R271: 1595 | T271: 102632 | V271: 251024 | X271: 238365 | Z271: 12659
B272: AK | C272: Alaska | D272: 44409 | E272: Y | F272: P | G272: N | H272: 2379 | J272: 0 | L272: 2379 | N272: 1726 | P272: 70 | R272: 1796 | T272: 101831 | V272: 249781 | X272: 237271 | Z272: 12510
B273: AK | C273: Alaska | D273: 44409 | E273: Y | F273: U | G273: Y | H273: 2379 | J273: 0 | L273: 2379 | N273: 1726 | P273: 70 | R273: 1796 | T273: 102819 | V273: 251977 | X273: 239402 | Z273: 12575
B274: AK | C274: Alaska | D274: 44440 | E274: Y | F274: P | G274: N | H274: 2208 | J274: 0 | L274: 2208 | N274: 1500 | P274: 68 | R274: 1568 | T274: 102778 | V274: 252090 | X274: 239595 | Z274: 12495
B275: AK | C275: Alaska | D275: 44440 | E275: Y | F275: U | G275: Y | H275: 2208 | J275: 0 | L275: 2208 | N275: 1500 | P275: 68 | R275: 1568 | T275: 102993 | V275: 252736 | X275: 240240 | Z275: 12496
B276: AK | C276: Alaska | D276: 44470 | E276: Y | F276: P | G276: N | H276: 2430 | J276: 0 | L276: 2430 | N276: 1432 | P276: 54 | R276: 1486 | T276: 102942 | V276: 252935 | X276: 240527 | Z276: 12408
B277: AK | C277: Alaska | D277: 44470 | E277: Y | F277: U | G277: Y | H277: 2430 | J277: 0 | L277: 2430 | N277: 1432 | P277: 54 | R277: 1486 | T277: 103391 | V277: 254169 | X277: 241822 | Z277: 12347
B278: AK | C278: Alaska | D278: 44501 | E278: Y | F278: P | G278: N | H278: 2396 | J278: 0 | L278: 2396 | N278: 1696 | P278: 84 | R278: 1780 | T278: 103143 | V278: 253841 | X278: 241504 | Z278: 12337
B279: AK | C279: Alaska | D279: 44501 | E279: Y | F279: U | G279: Y | H279: 2396 | J279: 0 | L279: 2396 | N279: 1696 | P279: 84 | R279: 1780 | T279: 103632 | V279: 255230 | X279: 242946 | Z279: 12284
B280: AK | C280: Alaska | D280: 44531 | E280: Y | F280: P | G280: N | H280: 2216 | J280: 0 | L280: 2216 | N280: 1865 | P280: 93 | R280: 1958 | T280: 103473 | V280: 255009 | X280: 242720 | Z280: 12289
... B322: AK | C322: Alaska | D322: 45170 | E322: Y | F322: P | G322: N | H322: 2840 | J322: 0 | L322: 2840 | N322: 1586 | P322: 101 | R322: 1687 | T322: 97433 | V322: 247112 | X322: 234194 | Z322: 12918
B323: AK | C323: Alaska | D323: 45170 | E323: Y | F323: U | G323: Y | H323: 2840 | J323: 0 | L323: 2840 | N323: 1586 | P323: 101 | R323: 1687 | T323: 97359 | U323: Does Not Include All Full-Benefit MAGI Child enrollees | V323: 246817 | W323: Does Not Include All Full-Benefit Non-MAGI enrollees | X323: 233372 | Y323: Does Not Include All Full-Benefit Non-MAGI enrollees | Z323: 13445
B324: AK | C324: Alaska | D324: 45200 | E324: Y | F324: P | G324: N | H324: 2807 | J324: 0 | L324: 2807 | N324: 1494 | P324: 71 | R324: 1565 | T324: 96454 | U324: Does Not Include All Full-Benefit MAGI Child enrollees | V324: 244425 | W324: Does Not Include All Full-Benefit Non-MAGI enrollees | X324: 231257 | Y324: Does Not Include All Full-Benefit Non-MAGI enrollees | Z324: 13168
