Workbook
Name ACTC: '[1]State Comparison Data'!#REF!
Name ACTC: #REF!
Name ActiveState: [1]Calc1!$D$3
Name ActiveState: #REF!
Name Adjusted_Gross_Income: #REF!:INDEX(#REF!,COUNTIF(#REF!,”<>”&””))
Name Adjusted_Gross_Income: #REF!:INDEX(#REF!,COUNTIF(#REF!,”<>”&””))
Name Adjusted_Gross_Income: [1]Calc1!$R$58:INDEX([1]Calc1!$R$58:$HJ$58,COUNTIF([1]Calc1!$R$58:$HJ$58,”<>”&””))
Name Adjusted_Gross_Income: #REF!:INDEX(#REF!,COUNTIF(#REF!,”<>”&””))
Name Adjusted_Gross_Income: #REF!:INDEX(#REF!,COUNTIF(#REF!,”<>”&””))
Name Adjusted_Gross_Income: #REF!:INDEX(#REF!,COUNTIF(#REF!,”<>”&””))
Name AgeAdult: #REF!
Name AgeAdult: [1]Lists!$F$10:$F$59
Name AgeAdult: #REF!
Name AgeAdult: #REF!
Name AgeChild: #REF!
Name AgeChild: [1]Lists!$H$10:$H$33
Name AgeChild: #REF!
Name AgeChild: #REF!
Name Apply: [1]MarriagePenalties!$B$30
Name Apply: #REF!
Name CalculatorNewHours: [1]Inputs!$R$7
Name CalculatorNewHours: #REF!
Name CalculatorNewWage: [1]Inputs!$Q$7
Name CalculatorNewWage: #REF!
Name CCA_RateCategoryEntireCol: INDEX(#REF!,,CA!CCA_RateCategoryStateColNum)
Name CCA_RateCategoryEntireCol: INDEX(#REF!,,CTC!CCA_RateCategoryStateColNum)
Name CCA_RateCategoryEntireCol: INDEX([1]!CCA_RateCategoryStates[#Data],,EITC!CCA_RateCategoryStateColNum)
Name CCA_RateCategoryEntireCol: INDEX(#REF!,,Weights!CCA_RateCategoryStateColNum)
Name CCA_RateCategoryEntireCol: INDEX(#REF!,,CCA_RateCategoryStateColNum)
Name CCA_RateCategoryLookup: INDEX(#REF!,1,CA!CCA_RateCategoryStateColNum):INDEX(#REF!,COUNTA(CA!CCA_RateCategoryEntireCol),CA!CCA_RateCategoryStateColNum)
Name CCA_RateCategoryLookup: INDEX(#REF!,1,CTC!CCA_RateCategoryStateColNum):INDEX(#REF!,COUNTA(CTC!CCA_RateCategoryEntireCol),CTC!CCA_RateCategoryStateColNum)
Name CCA_RateCategoryLookup: INDEX([1]!CCA_RateCategoryStates[#Data],1,EITC!CCA_RateCategoryStateColNum):INDEX([1]!CCA_RateCategoryStates[#Data],COUNTA(EITC!CCA_RateCategoryEntireCol),EITC!CCA_RateCategoryStateColNum)
Name CCA_RateCategoryLookup: INDEX(#REF!,1,Weights!CCA_RateCategoryStateColNum):INDEX(#REF!,COUNTA(Weights!CCA_RateCategoryEntireCol),Weights!CCA_RateCategoryStateColNum)
Name CCA_RateCategoryLookup: INDEX(#REF!,1,CCA_RateCategoryStateColNum):INDEX(#REF!,COUNTA(CCA_RateCategoryEntireCol),CCA_RateCategoryStateColNum)
Name CCA_RateCategoryStateColNum: MATCH(CA!InputStateName,#REF!,0)
Name CCA_RateCategoryStateColNum: MATCH(InputStateName,#REF!,0)
Name CCA_RateCategoryStateColNum: MATCH(EITC!InputStateName,[1]!CCA_RateCategoryStates[#Headers],0)
Name CCA_RateCategoryStateColNum: MATCH(Weights!InputStateName,#REF!,0)
Name CCA_RateCategoryStateColNum: MATCH(InputStateName,#REF!,0)
Name CCA_RateCategoryStatesEntireCol: INDEX(#REF!,,CTC!CCA_RateCategoryStatesStateColNum)
Name CCA_RateCategoryStatesEntireCol: INDEX([1]!CCA_RateCategoryStates[#Data],,EITC!CCA_RateCategoryStatesStateColNum)
Name CCA_RateCategoryStatesEntireCol: INDEX(#REF!,,CCA_RateCategoryStatesStateColNum)
Name CCA_RateCategoryStatesLookup: OFFSET(INDEX(#REF!,MATCH(1,(#REF!=#REF!)*(#REF!=#REF!),0)),0,0,COUNTIFS(#REF!,#REF!,#REF!,#REF!,#REF!,#REF!))
Name CCA_RateCategoryStatesStateColNum: MATCH(InputStateName,#REF!,0)
Name CCA_RateCategoryStatesStateColNum: MATCH(EITC!InputStateName,[1]!CCA_RateCategoryStates[#Headers],0)
Name CCA_RateCategoryStatesStateColNum: MATCH(InputStateName,#REF!,0)
Name CCA_SettingsEntireCol: INDEX(#REF!,,CA!CCA_SettingsStateColNum)
Name CCA_SettingsEntireCol: INDEX(#REF!,,CTC!CCA_SettingsStateColNum)
Name CCA_SettingsEntireCol: INDEX([1]!CCA_SettingsStates[#Data],,EITC!CCA_SettingsStateColNum)
Name CCA_SettingsEntireCol: INDEX(#REF!,,Weights!CCA_SettingsStateColNum)
Name CCA_SettingsEntireCol: INDEX(#REF!,,CCA_SettingsStateColNum)
Name CCA_SettingsLookup: INDEX(#REF!,1,CA!CCA_SettingsStateColNum):INDEX(#REF!,COUNTA(CA!CCA_SettingsEntireCol),CA!CCA_SettingsStateColNum)
Name CCA_SettingsLookup: INDEX(#REF!,1,CTC!CCA_SettingsStateColNum):INDEX(#REF!,COUNTA(CTC!CCA_SettingsEntireCol),CTC!CCA_SettingsStateColNum)
Name CCA_SettingsLookup: INDEX([1]!CCA_SettingsStates[#Data],1,EITC!CCA_SettingsStateColNum):INDEX([1]!CCA_SettingsStates[#Data],COUNTA(EITC!CCA_SettingsEntireCol),EITC!CCA_SettingsStateColNum)
Name CCA_SettingsLookup: INDEX(#REF!,1,Weights!CCA_SettingsStateColNum):INDEX(#REF!,COUNTA(Weights!CCA_SettingsEntireCol),Weights!CCA_SettingsStateColNum)
Name CCA_SettingsLookup: INDEX(#REF!,1,CCA_SettingsStateColNum):INDEX(#REF!,COUNTA(CCA_SettingsEntireCol),CCA_SettingsStateColNum)
Name CCA_SettingsStateColNum: MATCH(CA!InputStateName,#REF!,0)
Name CCA_SettingsStateColNum: MATCH(InputStateName,#REF!,0)
Name CCA_SettingsStateColNum: MATCH(EITC!InputStateName,[1]!CCA_SettingsStates[#Headers],0)
Name CCA_SettingsStateColNum: MATCH(Weights!InputStateName,#REF!,0)

Sheet Sources
B2: Tax Foundation
C3: State Individual Income Tax Rates and Brackets, 2023
C4: 44978
C5: Timothy Vermeer
C6: Accessed August 22, 2024
C7: https://taxfoundation.org/data/all/state/state-income-tax-rates-2023/
B9: The Federation of Tax Administrators, January 2022.
B10: http://www.taxadmin.org/current-tax-rates
C11: members with links to state members: | G11: https://taxadmin.org/fta-members/
B13: National Conference of State Legislatures
C14: Earned Income Tax Credit Enactments
C15: Updated May 3, 2024
C16: https://www.ncsl.org/human-services/eitc-enactments#:~:text=Thirty-one%20states%2C%20the%20District%20of%20Columbia%2C%20Guam%20and,the%20EITC%20and%20how%20to%20file%20for%20it.
C18: Overview, including table
C19: https://www.ncsl.org/human-services/earned-income-tax-credit-overview
C21: State Tax Actions Database | F21: https://www.ncsl.org/fiscal/state-tax-actions-database
B23: Internal Revenue Service
C24: Statistics for Tax Returns with the Earned Income Tax Credit (EITC)
C25: https://www.eitc.irs.gov/eitc-central/statistics-for-tax-returns-with-eitc/statistics-for-tax-returns-with-the-earned-income#2020%20Tax%20Returns%20by%20State%20with%20EITC%20Claims
C27: 2022 EITC Tax Returns by State Processed in 2023
B29: Alabama Dapartment of Revenue
C30: https://www.revenue.alabama.gov/
C31: Instructions | D31: https://www.revenue.alabama.gov/ultraviewer/viewer/basic_viewer/index.html?form=2024/01/23f40bk.pdf
C32: Form 40 | D32: https://www.revenue.alabama.gov/ultraviewer/viewer/basic_viewer/index.html?form=2024/01/23f40.pdf
B34: California Frachise Tax Board
C35: Eligibility and credit informationCalEITC
C36: Home about ftb > newsroom > caleitc > eligibility and credit information
C37: https://www.ftb.ca.gov/about-ftb/newsroom/caleitc/eligibility-and-credit-information.html
C38: accessed August 22, 2024
C39: Found on Booklet:
C40: Tax year 2023 maximum income and credit amounts for CalEITC and related tax credits
C42: 2021 CA S 201 | D42: https://custom.statenet.com/public/resources.cgi?id=ID:bill:CA2021000S201&ciq=ncsl&client_md=5874d7eb0a684501c54a4245da63b1b6&mode=current_text
B44: Maryland Comptroller | D44: https://www.marylandtaxes.gov/
C45: Form 502 2023 | D45: https://www.marylandtaxes.gov/forms/current_forms/502.pdf
C46: 2023 State & Local Tax Forms & Instructions | D46: https://www.marylandtaxes.gov/forms/23_forms/Resident-Booklet.pdf
B48: Minnesota Department of Revenue
C49: 2023 Schedule M1CWFC, Minnesota Child and Working Family Credits
C50: https://www.revenue.state.mn.us/sites/default/files/2024-01/m1cwfc-23_1.pdf
B51: Minnesota House Research
C52: The Working Family Credit and Federal Earned Income Credit August 2022. Fact Sheet
C53: https://www.house.mn.gov/hrd/pubs/ss/sseitcwfc.pdf
B55: Missouri Department of Revenue
C56: What's New? Includes 2023 Indivdiual Income Tax Year Changes and information on 2023 tax credits | D56: What's New? Includes 2023 Indivdiual Income Tax Year Changes and information on 2023 tax credits
C57: Home » Taxation » Individual » Tax Types » Income » Year Changes | D57: Home » Taxation » Individual » Tax Types » Income » Year Changes
C58: https://dor.mo.gov/taxation/individual/tax-types/income/year-changes/ | D58: https://dor.mo.gov/taxation/individual/tax-types/income/year-changes/
C59: Accessed August 22, 2024 | D59: Accessed August 22, 2025
B61: Montana Department of Revenue
C62: https://mtrevenue.gov/
C63: individual Income Tax | D63: https://mtrevenue.gov/taxes/#IndividualIncomeTax
C64: Form Instructions | D64: https://mtrevenue.gov/download/83160/?tmstv=1724947562
C65: Form 2 | D65: https://mtrevenue.gov/publications/montana-individual-income-tax-return-form-2/
D67: https://www.ftb.ca.gov/about-ftb/newsroom/caleitc/eligibility-and-credit-information.html
B69: Utah Taxes
C70: Utah Individual Income Tax Return
C71: 2023 Utah TC-40 Individual Income Tax Return
C72: https://tax.utah.gov/forms/current/tc-40.pdf
B74: Washington State Department of Commerce
C75: https://www.commerce.wa.gov/serving-communities/community-opportunities/earned-income-tax-credit/#:~:text=New%20Washington%20Working%20Families%20Tax%20Credit%20In%202023%2C,the%20Working%20Families%20Credit%20website%20or%20call%20360-763-7300.
C77: Earned Income Tax Credit
C78: New Washington Working Families Tax Credit In 2023, The Washington State Working Families Tax Credit (WFTC) can provide up to $1,200 back in addition to the EITC. To apply and learn more, visit the Working Families Credit website or call 360-763-7300.
C80: Working Families Tax Credit Website
D81: https://workingfamiliescredit.wa.gov/

Sheet Final Results
O1: Non negative | Q1: Live | R1: Live | S1: Live | U1: Single | V1: Single | W1: HOH 1 | X1: HOH 1 | Y1: HOH 2 | Z1: HOH 2 | AA1: HOH 3 | AB1: HOH 3 | AC1: HOH 4 | AD1: HOH 4 | AE1: MFJ 0 | AF1: MFJ 0 | AG1: MFJ 1 | AH1: MFJ 1 | AI1: MFJ 2 | AJ1: MFJ 2 | AK1: MFJ 3 | AL1: MFJ 3 | AM1: MFJ 4 | AN1: MFJ 4
A2: Tax Calculations | G2: Federal | H2: CC Costs | I2: DCCEC | J2: check | K2: CTC | L2: ACTC | M2: EITC | N2: Final Fed | O2: Final Fed Ded | Q2: State Income Taxes | R2: stateEITC | S2: Plus if children under 3 | U2: stateTax | V2: stateEITC | W2: stateTax | X2: stateEITC | Y2: stateTax | Z2: stateEITC | AA2: stateTax | AB2: stateEITC | AC2: stateTax | AD2: stateEITC | AE2: stateTax | AF2: stateEITC | AG2: stateTax | AH2: stateEITC | AI2: stateTax | AJ2: stateEITC | AK2: stateTax | AL2: stateEITC | AM2: stateTax | AN2: stateEITC
E3: Federal | F3: Weights | S3: Conclusion: Neglible
B4: Select Inputs | D4: Phase-In % | E4: Standared Ded | G4: {=INDEX(FedStDeductLookup[],MATCH($B$8,FedStDeductLookup[Status],0),MATCH($B$5,VALUE(FedStDeductLookup[#Headers]),0))} -> 13850 | I4: Rate* | M4: {=INDEX(EITCpercents[],MATCH(1,(EITCpercents[Name]="Phase In Percent")*(EITCpercents[Children]=$B$15),0),MATCH("Percent",EITCpercents[#Headers],0))} -> 0.0765
A5: Tax Year | B5: 2023 | D5: Phase-Out % | E5: Credit Per Child | I5: CCCosts | K5: 2000 | L5: 1600 | M5: {=INDEX(EITCpercents[],MATCH(1,(EITCpercents[Name]="Phase Out Percent")*(EITCpercents[Children]=$B$15),0),MATCH("Percent",EITCpercents[#Headers],0))} -> 0.0765
D6: Threshold | E6: Income Limit | K6: {=INDEX(CTCFactors[],MATCH(1,(CTCFactors[Name]=$B$9)*(CTCFactors[Phaseout Phase]=1)*(CTCFactors[Year]=$B$5)*(CTCFactors[Note]="Income Threshold"),0),MATCH("Value",CTCFactors[#Headers],0))} -> 75000.01 | M6: {=INDEX(EITCPhaseIn[],MATCH(1,(EITCPhaseIn[Name]="Phase In Threshold")*(EITCPhaseIn[Children]=$B$15),0),MATCH($B$5,VALUE(EITCPhaseIn[#Headers]),0))} -> 7840
D7: Max Credit | E7: Decrease by | K7: {=INDEX(CTCFactors[],MATCH(1,(CTCFactors[Name]=$B$9)*(CTCFactors[Phaseout Phase]=1)*(CTCFactors[Year]=$B$5),0),MATCH("Credit Decrease per Income Increment",CTCFactors[#Headers],0))} -> 50 | M7: {=INDEX(EITCPhaseIn[],MATCH(1,(EITCPhaseIn[Name]="Maximum Credit")*(EITCPhaseIn[Children]=$B$15),0),MATCH($B$5,VALUE(EITCPhaseIn[#Headers]),0))} -> 600
A8: Tax Filing Status | B8: Single | D8: Start Phase Out | E8: Per Income Increment | K8: {=INDEX(CTCFactors[],MATCH(1,(CTCFactors[Name]=$B$9)*(CTCFactors[Phaseout Phase]=1)*(CTCFactors[Year]=$B$5),0),MATCH("Income Increment for Phaseout Decrease",CTCFactors[#Headers],0))} -> 1000 | M8: {=_xlfn.IFNA(INDEX(EITCPhaseOut[],MATCH(1,(EITCPhaseOut[Status]=$B$9)*(EITCPhaseOut[Name]="Start Phase Out")*(EITCPhaseOut[Children]=$B$15),0),MATCH($B$5,VALUE(EITCPhaseOut[#Headers]),0)),0)} -> 9800
A9: Description | B9: =VLOOKUP(B8,$A$19:$B$21,2,FALSE) -> Single | D9: Stop Credit | E9: Income Disregard | L9: 2500 | M9: {=_xlfn.IFNA(INDEX(EITCPhaseOut[],MATCH(1,(EITCPhaseOut[Status]=$B$9)*(EITCPhaseOut[Name]="Stop Credit")*(EITCPhaseOut[Children]=$B$15),0),MATCH($B$5,VALUE(EITCPhaseOut[#Headers]),0)),0)} -> 17640
E10: Rate applied to earnings | L10: 0.15
A12: # Tax filer & Spouse: | B12: 1 | E12: Bracket 1 | F12: Over | G12: {=INDEX(FedTaxRateTable[],MATCH(1,(FedTaxRateTable[StatusAbb]=$B$8)*(FedTaxRateTable[Bracket]=$E12)*(FedTaxRateTable[Condition]=$F12),0),MATCH($B$5,VALUE(FedTaxRateTable[#Headers]),0))} -> 0
A13: Dependents | B13: 0 | E13: Bracket 2 | F13: Over | G13: {=INDEX(FedTaxRateTable[],MATCH(1,(FedTaxRateTable[StatusAbb]=$B$8)*(FedTaxRateTable[Bracket]=$E13)*(FedTaxRateTable[Condition]=$F13),0),MATCH($B$5,VALUE(FedTaxRateTable[#Headers]),0))} -> 11000
E14: Bracket 3 | F14: Over | G14: {=INDEX(FedTaxRateTable[],MATCH(1,(FedTaxRateTable[StatusAbb]=$B$8)*(FedTaxRateTable[Bracket]=$E14)*(FedTaxRateTable[Condition]=$F14),0),MATCH($B$5,VALUE(FedTaxRateTable[#Headers]),0))} -> 44725
A15: EITC Children | B15: =IF(B13<3,B13,"3 or more") -> 0 | E15: Bracket 4 | F15: Over | G15: {=INDEX(FedTaxRateTable[],MATCH(1,(FedTaxRateTable[StatusAbb]=$B$8)*(FedTaxRateTable[Bracket]=$E15)*(FedTaxRateTable[Condition]=$F15),0),MATCH($B$5,VALUE(FedTaxRateTable[#Headers]),0))} -> 95375
E17: Bracket 1 | F17: Rate | G17: {=INDEX(FedTaxRateTable[],MATCH(1,(FedTaxRateTable[StatusAbb]=$B$8)*(FedTaxRateTable[Bracket]=$E17)*(FedTaxRateTable[Condition]=$F17),0),MATCH($B$5,VALUE(FedTaxRateTable[#Headers]),0))} -> 0.1
A18: Tax Status List | E18: Bracket 2 | F18: Rate | G18: {=INDEX(FedTaxRateTable[],MATCH(1,(FedTaxRateTable[StatusAbb]=$B$8)*(FedTaxRateTable[Bracket]=$E18)*(FedTaxRateTable[Condition]=$F18),0),MATCH($B$5,VALUE(FedTaxRateTable[#Headers]),0))} -> 0.12
A19: Single | B19: Single | E19: Bracket 3 | F19: Rate | G19: {=INDEX(FedTaxRateTable[],MATCH(1,(FedTaxRateTable[StatusAbb]=$B$8)*(FedTaxRateTable[Bracket]=$E19)*(FedTaxRateTable[Condition]=$F19),0),MATCH($B$5,VALUE(FedTaxRateTable[#Headers]),0))} -> 0.22
A20: HOH | B20: Head of Household | E20: Bracket 4 | F20: Rate | G20: {=INDEX(FedTaxRateTable[],MATCH(1,(FedTaxRateTable[StatusAbb]=$B$8)*(FedTaxRateTable[Bracket]=$E20)*(FedTaxRateTable[Condition]=$F20),0),MATCH($B$5,VALUE(FedTaxRateTable[#Headers]),0))} -> 0.24
A21: MFJ | B21: Married Filing Jointly
E22: Bracket 1 | F22: Plus | G22: {=INDEX(FedTaxRateTable[],MATCH(1,(FedTaxRateTable[StatusAbb]=$B$8)*(FedTaxRateTable[Bracket]=$E22)*(FedTaxRateTable[Condition]=$F22),0),MATCH($B$5,VALUE(FedTaxRateTable[#Headers]),0))} -> 0
A23: Number People List | E23: Bracket 2 | F23: Plus | G23: {=INDEX(FedTaxRateTable[],MATCH(1,(FedTaxRateTable[StatusAbb]=$B$8)*(FedTaxRateTable[Bracket]=$E23)*(FedTaxRateTable[Condition]=$F23),0),MATCH($B$5,VALUE(FedTaxRateTable[#Headers]),0))} -> 1100
A24: 0 | E24: Bracket 3 | F24: Plus | G24: {=INDEX(FedTaxRateTable[],MATCH(1,(FedTaxRateTable[StatusAbb]=$B$8)*(FedTaxRateTable[Bracket]=$E24)*(FedTaxRateTable[Condition]=$F24),0),MATCH($B$5,VALUE(FedTaxRateTable[#Headers]),0))} -> 5147
A25: 1 | E25: Bracket 4 | F25: Plus | G25: {=INDEX(FedTaxRateTable[],MATCH(1,(FedTaxRateTable[StatusAbb]=$B$8)*(FedTaxRateTable[Bracket]=$E25)*(FedTaxRateTable[Condition]=$F25),0),MATCH($B$5,VALUE(FedTaxRateTable[#Headers]),0))} -> 16290
A26: 2 | U26: =SUM(U34:U234) -> -254800 | W26: =SUM(W34:W234) -> -239314 | Y26: =SUM(Y34:Y234) -> -225994 | AA26: =SUM(AA34:AA234) -> -213620 | AC26: =SUM(AC34:AC234) -> -202071 | AE26: =SUM(AE34:AE234) -> -176092 | AG26: =SUM(AG34:AG234) -> -165645 | AI26: =SUM(AI34:AI234) -> -156380 | AK26: =SUM(AK34:AK234) -> -148217 | AM26: =SUM(AM34:AM234) -> -140990
A27: 3 | E27: Total Pre Rate Deductions | G27: =G4 -> 13850 | V27: =SUM(V34:V234) -> 3100 | X27: =SUM(X34:X234) -> 26827 | Z27: =SUM(Z34:Z234) -> 46843 | AB27: =SUM(AB34:AB234) -> 59385 | AD27: =SUM(AD34:AD234) -> 62667 | AF27: =SUM(AF34:AF234) -> 3832 | AH27: =SUM(AH34:AH234) -> 30886 | AJ27: =SUM(AJ34:AJ234) -> 53826 | AL27: =SUM(AL34:AL234) -> 67753 | AN27: =SUM(AN34:AN234) -> 71340
A28: 4 | E28: Post Tax Rate Deductions
E30: Income | F30: EITC rounding
E31: 15250 | F31: =IF(E31<1,0,_xlfn.FLOOR.MATH(E31,50)+25) -> 15275 | G31: =-ROUND(INDEX(G$17:G$20,MATCH(MAX($E31-G$27,0),G$12:G$15,1))*(MAX($E31-G$27,0)-INDEX(G$12:G$15,MATCH(MAX($E31-G$27,0),G$12:G$15,1)))+INDEX(G$22:G$25,MATCH(MAX($E31-G$27,0),G$12:G$15,1)),0) -> -140 | I31: =ROUND(INDEX(CCareExpDecimal[],MATCH(E31,CCareExpDecimal[Income At Least],1),2)*H31,0) -> 0 | K31: =MIN(-G31,K$5*$B$13) -> 0 | L31: =ROUND(MAX(MIN(L$10*($E31-L$9),L$5*$B$13-K31),0),0) -> 0 | M31: =ROUND(IF($F31<M$6,$F31*M$4,0)+IF(AND($F31>=M$6,$F31<M$8),M$7,0)+IF(AND($F31>M$8,$F31<M$9),M$7 - (($F31-M$8)*M$5),0),0) -> 181 | N31: =SUM(G31,I31,K31,L31,M31) -> 41 | O31: =MAX(-N31,0) -> 0 | Q31: =Calc!W90 -> -154 | R31: =Calc!X90 -> 41 | S31: =Calc!Y90 -> 0 | U31: -154 | V31: 157 | W31: -118 | X31: 487 | Y31: -94 | Z31: 686 | AA31: -80 | AB31: 794 | AC31: -69 | AD31: 815 | AE31: -56 | AF31: 78 | AG31: -49 | AH31: 402 | AI31: -43 | AJ31: 669 | AK31: -36 | AL31: 792 | AM31: -30 | AN31: 813
E32: 45000 | F32: =IF(E32<1,0,_xlfn.FLOOR.MATH(E32,50)+25) -> 45025 | G32: =-ROUND(INDEX(G$17:G$20,MATCH(MAX($E32-G$27,0),G$12:G$15,1))*(MAX($E32-G$27,0)-INDEX(G$12:G$15,MATCH(MAX($E32-G$27,0),G$12:G$15,1)))+INDEX(G$22:G$25,MATCH(MAX($E32-G$27,0),G$12:G$15,1)),0) -> -3518 | I32: =ROUND(INDEX(CCareExpDecimal[],MATCH(E32,CCareExpDecimal[Income At Least],1),2)*H32,0) -> 0 | K32: =MIN(-G32,K$5*$B$13) -> 0 | L32: =ROUND(MAX(MIN(L$10*($E32-L$9),L$5*$B$13-K32),0),0) -> 0 | M32: =ROUND(IF($F32<M$6,$F32*M$4,0)+IF(AND($F32>=M$6,$F32<M$8),M$7,0)+IF(AND($F32>M$8,$F32<M$9),M$7 - (($F32-M$8)*M$5),0),0) -> 0 | N32: =SUM(G32,I32,K32,L32,M32) -> -3518 | O32: =MAX(-N32,0) -> 3518 | Q32: =Calc!W91 -> -1006 | R32: =Calc!X91 -> 5 | S32: =Calc!Y91 -> 0 | U32: -1006 | V32: 5 | W32: -913 | X32: 42 | Y32: -821 | Z32: 212 | AA32: -766 | AB32: 312 | AC32: -718 | AD32: 326 | AE32: -604 | AF32: 5 | AG32: -562 | AH32: 148 | AI32: -518 | AJ32: 323 | AK32: -475 | AL32: 428 | AM32: -436 | AN32: 446
E34: 0 | F34: =IF(E34<1,0,_xlfn.FLOOR.MATH(E34,50)+25) -> 0 | G34: =-ROUND(INDEX(G$17:G$20,MATCH(MAX($E34-G$27,0),G$12:G$15,1))*(MAX($E34-G$27,0)-INDEX(G$12:G$15,MATCH(MAX($E34-G$27,0),G$12:G$15,1)))+INDEX(G$22:G$25,MATCH(MAX($E34-G$27,0),G$12:G$15,1)),0) -> 0 | H34: 0 | I34: =ROUND(INDEX(CCareExpDecimal[],MATCH(E34,CCareExpDecimal[Income At Least],1),2)*H34,0) -> 0 | J34: 0 | K34: =MIN(-G34,K$5*$B$13) -> 0 | L34: =ROUND(MAX(MIN(L$10*($E34-L$9),L$5*$B$13-K34),0),0) -> 0 | M34: =ROUND(IF($F34<M$6,$F34*M$4,0)+IF(AND($F34>=M$6,$F34<M$8),M$7,0)+IF(AND($F34>M$8,$F34<M$9),M$7 - (($F34-M$8)*M$5),0),0) -> 0 | N34: =SUM(G34,I34,K34,L34,M34) -> 0 | O34: =MAX(-N34,0) -> 0 | Q34: =Calc!W93 -> 0 | R34: =Calc!X93 -> 5 | S34: =Calc!Y93 -> 0 | U34: 0 | V34: 5 | W34: 0 | X34: 31 | Y34: 0 | Z34: 57 | AA34: 0 | AB34: 83 | AC34: 0 | AD34: 105 | AE34: 0 | AF34: 5 | AG34: 0 | AH34: 31 | AI34: 0 | AJ34: 57 | AK34: 0 | AL34: 83 | AM34: 0 | AN34: 105
E35: 500 | F35: =IF(E35<1,0,_xlfn.FLOOR.MATH(E35,50)+25) -> 525 | G35: =-ROUND(INDEX(G$17:G$20,MATCH(MAX($E35-G$27,0),G$12:G$15,1))*(MAX($E35-G$27,0)-INDEX(G$12:G$15,MATCH(MAX($E35-G$27,0),G$12:G$15,1)))+INDEX(G$22:G$25,MATCH(MAX($E35-G$27,0),G$12:G$15,1)),0) -> 0 | H35: 0 | I35: =ROUND(INDEX(CCareExpDecimal[],MATCH(E35,CCareExpDecimal[Income At Least],1),2)*H35,0) -> 0 | J35: 0 | K35: =MIN(-G35,K$5*$B$13) -> 0 | L35: =ROUND(MAX(MIN(L$10*($E35-L$9),L$5*$B$13-K35),0),0) -> 0 | M35: =ROUND(IF($F35<M$6,$F35*M$4,0)+IF(AND($F35>=M$6,$F35<M$8),M$7,0)+IF(AND($F35>M$8,$F35<M$9),M$7 - (($F35-M$8)*M$5),0),0) -> 40 | N35: =SUM(G35,I35,K35,L35,M35) -> 40 | O35: =MAX(-N35,0) -> 0 | Q35: =Calc!W94 -> 0 | R35: =Calc!X94 -> 12 | S35: =Calc!Y94 -> 0 | U35: 0 | V35: 12 | W35: 0 | X35: 60 | Y35: 0 | Z35: 91 | AA35: 0 | AB35: 123 | AC35: 0 | AD35: 144 | AE35: 0 | AF35: 12 | AG35: 0 | AH35: 60 | AI35: 0 | AJ35: 91 | AK35: 0 | AL35: 123 | AM35: 0 | AN35: 144
E36: 1000 | F36: =IF(E36<1,0,_xlfn.FLOOR.MATH(E36,50)+25) -> 1025 | G36: =-ROUND(INDEX(G$17:G$20,MATCH(MAX($E36-G$27,0),G$12:G$15,1))*(MAX($E36-G$27,0)-INDEX(G$12:G$15,MATCH(MAX($E36-G$27,0),G$12:G$15,1)))+INDEX(G$22:G$25,MATCH(MAX($E36-G$27,0),G$12:G$15,1)),0) -> 0 | H36: 0 | I36: =ROUND(INDEX(CCareExpDecimal[],MATCH(E36,CCareExpDecimal[Income At Least],1),2)*H36,0) -> 0 | J36: 0 | K36: =MIN(-G36,K$5*$B$13) -> 0 | L36: =ROUND(MAX(MIN(L$10*($E36-L$9),L$5*$B$13-K36),0),0) -> 0 | M36: =ROUND(IF($F36<M$6,$F36*M$4,0)+IF(AND($F36>=M$6,$F36<M$8),M$7,0)+IF(AND($F36>M$8,$F36<M$9),M$7 - (($F36-M$8)*M$5),0),0) -> 78 | N36: =SUM(G36,I36,K36,L36,M36) -> 78 | O36: =MAX(-N36,0) -> 0 | Q36: =Calc!W95 -> -1 | R36: =Calc!X95 -> 19 | S36: =Calc!Y95 -> 0 | U36: -1 | V36: 19 | W36: -1 | X36: 89 | Y36: -1 | Z36: 126 | AA36: -1 | AB36: 162 | AC36: -1 | AD36: 183 | AE36: -1 | AF36: 19 | AG36: -1 | AH36: 89 | AI36: -1 | AJ36: 126 | AK36: -1 | AL36: 162 | AM36: -1 | AN36: 183
E37: 1500 | F37: =IF(E37<1,0,_xlfn.FLOOR.MATH(E37,50)+25) -> 1525 | G37: =-ROUND(INDEX(G$17:G$20,MATCH(MAX($E37-G$27,0),G$12:G$15,1))*(MAX($E37-G$27,0)-INDEX(G$12:G$15,MATCH(MAX($E37-G$27,0),G$12:G$15,1)))+INDEX(G$22:G$25,MATCH(MAX($E37-G$27,0),G$12:G$15,1)),0) -> 0 | H37: 0 | I37: =ROUND(INDEX(CCareExpDecimal[],MATCH(E37,CCareExpDecimal[Income At Least],1),2)*H37,0) -> 0 | J37: 0 | K37: =MIN(-G37,K$5*$B$13) -> 0 | L37: =ROUND(MAX(MIN(L$10*($E37-L$9),L$5*$B$13-K37),0),0) -> 0 | M37: =ROUND(IF($F37<M$6,$F37*M$4,0)+IF(AND($F37>=M$6,$F37<M$8),M$7,0)+IF(AND($F37>M$8,$F37<M$9),M$7 - (($F37-M$8)*M$5),0),0) -> 117 | N37: =SUM(G37,I37,K37,L37,M37) -> 117 | O37: =MAX(-N37,0) -> 0 | Q37: =Calc!W96 -> -2 | R37: =Calc!X96 -> 26 | S37: =Calc!Y96 -> 0 | U37: -2 | V37: 26 | W37: -1 | X37: 118 | Y37: -1 | Z37: 160 | AA37: -1 | AB37: 201 | AC37: -1 | AD37: 222 | AE37: -1 | AF37: 26 | AG37: -1 | AH37: 118 | AI37: -1 | AJ37: 160 | AK37: -1 | AL37: 201 | AM37: -1 | AN37: 222
E38: 2000 | F38: =IF(E38<1,0,_xlfn.FLOOR.MATH(E38,50)+25) -> 2025 | G38: =-ROUND(INDEX(G$17:G$20,MATCH(MAX($E38-G$27,0),G$12:G$15,1))*(MAX($E38-G$27,0)-INDEX(G$12:G$15,MATCH(MAX($E38-G$27,0),G$12:G$15,1)))+INDEX(G$22:G$25,MATCH(MAX($E38-G$27,0),G$12:G$15,1)),0) -> 0 | H38: 0 | I38: =ROUND(INDEX(CCareExpDecimal[],MATCH(E38,CCareExpDecimal[Income At Least],1),2)*H38,0) -> 0 | J38: 0 | K38: =MIN(-G38,K$5*$B$13) -> 0 | L38: =ROUND(MAX(MIN(L$10*($E38-L$9),L$5*$B$13-K38),0),0) -> 0 | M38: =ROUND(IF($F38<M$6,$F38*M$4,0)+IF(AND($F38>=M$6,$F38<M$8),M$7,0)+IF(AND($F38>M$8,$F38<M$9),M$7 - (($F38-M$8)*M$5),0),0) -> 155 | N38: =SUM(G38,I38,K38,L38,M38) -> 155 | O38: =MAX(-N38,0) -> 0 | Q38: =Calc!W97 -> -3 | R38: =Calc!X97 -> 33 | S38: =Calc!Y97 -> 0 | U38: -3 | V38: 33 | W38: -2 | X38: 147 | Y38: -2 | Z38: 194 | AA38: -2 | AB38: 240 | AC38: -2 | AD38: 262 | AE38: -2 | AF38: 33 | AG38: -2 | AH38: 147 | AI38: -2 | AJ38: 194 | AK38: -2 | AL38: 240 | AM38: -2 | AN38: 262
E39: 2500 | F39: =IF(E39<1,0,_xlfn.FLOOR.MATH(E39,50)+25) -> 2525 | G39: =-ROUND(INDEX(G$17:G$20,MATCH(MAX($E39-G$27,0),G$12:G$15,1))*(MAX($E39-G$27,0)-INDEX(G$12:G$15,MATCH(MAX($E39-G$27,0),G$12:G$15,1)))+INDEX(G$22:G$25,MATCH(MAX($E39-G$27,0),G$12:G$15,1)),0) -> 0 | H39: 0 | I39: =ROUND(INDEX(CCareExpDecimal[],MATCH(E39,CCareExpDecimal[Income At Least],1),2)*H39,0) -> 0 | J39: 0 | K39: =MIN(-G39,K$5*$B$13) -> 0 | L39: =ROUND(MAX(MIN(L$10*($E39-L$9),L$5*$B$13-K39),0),0) -> 0 | M39: =ROUND(IF($F39<M$6,$F39*M$4,0)+IF(AND($F39>=M$6,$F39<M$8),M$7,0)+IF(AND($F39>M$8,$F39<M$9),M$7 - (($F39-M$8)*M$5),0),0) -> 193 | N39: =SUM(G39,I39,K39,L39,M39) -> 193 | O39: =MAX(-N39,0) -> 0 | Q39: =Calc!W98 -> -4 | R39: =Calc!X98 -> 40 | S39: =Calc!Y98 -> 0 | U39: -4 | V39: 40 | W39: -3 | X39: 176 | Y39: -2 | Z39: 229 | AA39: -2 | AB39: 280 | AC39: -2 | AD39: 301 | AE39: -2 | AF39: 40 | AG39: -2 | AH39: 176 | AI39: -2 | AJ39: 229 | AK39: -2 | AL39: 280 | AM39: -2 | AN39: 301
E40: 3000 | F40: =IF(E40<1,0,_xlfn.FLOOR.MATH(E40,50)+25) -> 3025 | G40: =-ROUND(INDEX(G$17:G$20,MATCH(MAX($E40-G$27,0),G$12:G$15,1))*(MAX($E40-G$27,0)-INDEX(G$12:G$15,MATCH(MAX($E40-G$27,0),G$12:G$15,1)))+INDEX(G$22:G$25,MATCH(MAX($E40-G$27,0),G$12:G$15,1)),0) -> 0 | H40: 0 | I40: =ROUND(INDEX(CCareExpDecimal[],MATCH(E40,CCareExpDecimal[Income At Least],1),2)*H40,0) -> 0 | J40: 0 | K40: =MIN(-G40,K$5*$B$13) -> 0 | L40: =ROUND(MAX(MIN(L$10*($E40-L$9),L$5*$B$13-K40),0),0) -> 0 | M40: =ROUND(IF($F40<M$6,$F40*M$4,0)+IF(AND($F40>=M$6,$F40<M$8),M$7,0)+IF(AND($F40>M$8,$F40<M$9),M$7 - (($F40-M$8)*M$5),0),0) -> 231 | N40: =SUM(G40,I40,K40,L40,M40) -> 231 | O40: =MAX(-N40,0) -> 0 | Q40: =Calc!W99 -> -6 | R40: =Calc!X99 -> 47 | S40: =Calc!Y99 -> 0 | U40: -6 | V40: 47 | W40: -4 | X40: 205 | Y40: -3 | Z40: 263 | AA40: -3 | AB40: 319 | AC40: -3 | AD40: 340 | AE40: -3 | AF40: 47 | AG40: -3 | AH40: 205 | AI40: -3 | AJ40: 263 | AK40: -3 | AL40: 319 | AM40: -3 | AN40: 340
E41: 3500 | F41: =IF(E41<1,0,_xlfn.FLOOR.MATH(E41,50)+25) -> 3525 | G41: =-ROUND(INDEX(G$17:G$20,MATCH(MAX($E41-G$27,0),G$12:G$15,1))*(MAX($E41-G$27,0)-INDEX(G$12:G$15,MATCH(MAX($E41-G$27,0),G$12:G$15,1)))+INDEX(G$22:G$25,MATCH(MAX($E41-G$27,0),G$12:G$15,1)),0) -> 0 | H41: 0 | I41: =ROUND(INDEX(CCareExpDecimal[],MATCH(E41,CCareExpDecimal[Income At Least],1),2)*H41,0) -> 0 | J41: 0 | K41: =MIN(-G41,K$5*$B$13) -> 0 | L41: =ROUND(MAX(MIN(L$10*($E41-L$9),L$5*$B$13-K41),0),0) -> 0 | M41: =ROUND(IF($F41<M$6,$F41*M$4,0)+IF(AND($F41>=M$6,$F41<M$8),M$7,0)+IF(AND($F41>M$8,$F41<M$9),M$7 - (($F41-M$8)*M$5),0),0) -> 270 | N41: =SUM(G41,I41,K41,L41,M41) -> 270 | O41: =MAX(-N41,0) -> 0 | Q41: =Calc!W100 -> -8 | R41: =Calc!X100 -> 54 | S41: =Calc!Y100 -> 0 | U41: -8 | V41: 54 | W41: -5 | X41: 234 | Y41: -4 | Z41: 297 | AA41: -4 | AB41: 358 | AC41: -4 | AD41: 379 | AE41: -3 | AF41: 54 | AG41: -3 | AH41: 234 | AI41: -3 | AJ41: 297 | AK41: -3 | AL41: 358 | AM41: -3 | AN41: 379
E42: 4000 | F42: =IF(E42<1,0,_xlfn.FLOOR.MATH(E42,50)+25) -> 4025 | G42: =-ROUND(INDEX(G$17:G$20,MATCH(MAX($E42-G$27,0),G$12:G$15,1))*(MAX($E42-G$27,0)-INDEX(G$12:G$15,MATCH(MAX($E42-G$27,0),G$12:G$15,1)))+INDEX(G$22:G$25,MATCH(MAX($E42-G$27,0),G$12:G$15,1)),0) -> 0 | H42: 0 | I42: =ROUND(INDEX(CCareExpDecimal[],MATCH(E42,CCareExpDecimal[Income At Least],1),2)*H42,0) -> 0 | J42: 0 | K42: =MIN(-G42,K$5*$B$13) -> 0 | L42: =ROUND(MAX(MIN(L$10*($E42-L$9),L$5*$B$13-K42),0),0) -> 0 | M42: =ROUND(IF($F42<M$6,$F42*M$4,0)+IF(AND($F42>=M$6,$F42<M$8),M$7,0)+IF(AND($F42>M$8,$F42<M$9),M$7 - (($F42-M$8)*M$5),0),0) -> 308 | N42: =SUM(G42,I42,K42,L42,M42) -> 308 | O42: =MAX(-N42,0) -> 0 | Q42: =Calc!W101 -> -11 | R42: =Calc!X101 -> 62 | S42: =Calc!Y101 -> 0 | U42: -11 | V42: 62 | W42: -7 | X42: 263 | Y42: -6 | Z42: 332 | AA42: -5 | AB42: 398 | AC42: -5 | AD42: 419 | AE42: -4 | AF42: 62 | AG42: -4 | AH42: 263 | AI42: -4 | AJ42: 332 | AK42: -4 | AL42: 398 | AM42: -4 | AN42: 419
E43: 4500 | F43: =IF(E43<1,0,_xlfn.FLOOR.MATH(E43,50)+25) -> 4525 | G43: =-ROUND(INDEX(G$17:G$20,MATCH(MAX($E43-G$27,0),G$12:G$15,1))*(MAX($E43-G$27,0)-INDEX(G$12:G$15,MATCH(MAX($E43-G$27,0),G$12:G$15,1)))+INDEX(G$22:G$25,MATCH(MAX($E43-G$27,0),G$12:G$15,1)),0) -> 0 | H43: 0 | I43: =ROUND(INDEX(CCareExpDecimal[],MATCH(E43,CCareExpDecimal[Income At Least],1),2)*H43,0) -> 0 | J43: 0 | K43: =MIN(-G43,K$5*$B$13) -> 0 | L43: =ROUND(MAX(MIN(L$10*($E43-L$9),L$5*$B$13-K43),0),0) -> 0 | M43: =ROUND(IF($F43<M$6,$F43*M$4,0)+IF(AND($F43>=M$6,$F43<M$8),M$7,0)+IF(AND($F43>M$8,$F43<M$9),M$7 - (($F43-M$8)*M$5),0),0) -> 346 | N43: =SUM(G43,I43,K43,L43,M43) -> 346 | O43: =MAX(-N43,0) -> 0 | Q43: =Calc!W102 -> -13 | R43: =Calc!X102 -> 67 | S43: =Calc!Y102 -> 0 | U43: -13 | V43: 67 | W43: -8 | X43: 292 | Y43: -7 | Z43: 366 | AA43: -6 | AB43: 437 | AC43: -5 | AD43: 458 | AE43: -5 | AF43: 67 | AG43: -4 | AH43: 292 | AI43: -4 | AJ43: 366 | AK43: -4 | AL43: 437 | AM43: -4 | AN43: 458
E44: 5000 | F44: =IF(E44<1,0,_xlfn.FLOOR.MATH(E44,50)+25) -> 5025 | G44: =-ROUND(INDEX(G$17:G$20,MATCH(MAX($E44-G$27,0),G$12:G$15,1))*(MAX($E44-G$27,0)-INDEX(G$12:G$15,MATCH(MAX($E44-G$27,0),G$12:G$15,1)))+INDEX(G$22:G$25,MATCH(MAX($E44-G$27,0),G$12:G$15,1)),0) -> 0 | H44: 0 | I44: =ROUND(INDEX(CCareExpDecimal[],MATCH(E44,CCareExpDecimal[Income At Least],1),2)*H44,0) -> 0 | J44: 0 | K44: =MIN(-G44,K$5*$B$13) -> 0 | L44: =ROUND(MAX(MIN(L$10*($E44-L$9),L$5*$B$13-K44),0),0) -> 0 | M44: =ROUND(IF($F44<M$6,$F44*M$4,0)+IF(AND($F44>=M$6,$F44<M$8),M$7,0)+IF(AND($F44>M$8,$F44<M$9),M$7 - (($F44-M$8)*M$5),0),0) -> 384 | N44: =SUM(G44,I44,K44,L44,M44) -> 384 | O44: =MAX(-N44,0) -> 0 | Q44: =Calc!W103 -> -16 | R44: =Calc!X103 -> 67 | S44: =Calc!Y103 -> 0 | U44: -16 | V44: 67 | W44: -10 | X44: 322 | Y44: -8 | Z44: 400 | AA44: -7 | AB44: 476 | AC44: -6 | AD44: 497 | AE44: -6 | AF44: 67 | AG44: -5 | AH44: 322 | AI44: -5 | AJ44: 400 | AK44: -5 | AL44: 476 | AM44: -5 | AN44: 497
E45: 5500 | F45: =IF(E45<1,0,_xlfn.FLOOR.MATH(E45,50)+25) -> 5525 | G45: =-ROUND(INDEX(G$17:G$20,MATCH(MAX($E45-G$27,0),G$12:G$15,1))*(MAX($E45-G$27,0)-INDEX(G$12:G$15,MATCH(MAX($E45-G$27,0),G$12:G$15,1)))+INDEX(G$22:G$25,MATCH(MAX($E45-G$27,0),G$12:G$15,1)),0) -> 0 | H45: 0 | I45: =ROUND(INDEX(CCareExpDecimal[],MATCH(E45,CCareExpDecimal[Income At Least],1),2)*H45,0) -> 0 | J45: 0 | K45: =MIN(-G45,K$5*$B$13) -> 0 | L45: =ROUND(MAX(MIN(L$10*($E45-L$9),L$5*$B$13-K45),0),0) -> 0 | M45: =ROUND(IF($F45<M$6,$F45*M$4,0)+IF(AND($F45>=M$6,$F45<M$8),M$7,0)+IF(AND($F45>M$8,$F45<M$9),M$7 - (($F45-M$8)*M$5),0),0) -> 423 | N45: =SUM(G45,I45,K45,L45,M45) -> 423 | O45: =MAX(-N45,0) -> 0 | Q45: =Calc!W104 -> -19 | R45: =Calc!X104 -> 70 | S45: =Calc!Y104 -> 0 | U45: -19 | V45: 70 | W45: -12 | X45: 351 | Y45: -10 | Z45: 435 | AA45: -8 | AB45: 515 | AC45: -8 | AD45: 537 | AE45: -7 | AF45: 70 | AG45: -6 | AH45: 351 | AI45: -5 | AJ45: 435 | AK45: -5 | AL45: 515 | AM45: -5 | AN45: 537
... E334: 150000 | F334: =IF(E334<1,0,_xlfn.FLOOR.MATH(E334,50)+25) -> 150025 | G334: =-ROUND(INDEX(G$17:G$20,MATCH(MAX($E334-G$27,0),G$12:G$15,1))*(MAX($E334-G$27,0)-INDEX(G$12:G$15,MATCH(MAX($E334-G$27,0),G$12:G$15,1)))+INDEX(G$22:G$25,MATCH(MAX($E334-G$27,0),G$12:G$15,1)),0) -> -26076 | H334: 0 | I334: =ROUND(INDEX(CCareExpDecimal[],MATCH(E334,CCareExpDecimal[Income At Least],1),2)*H334,0) -> 0 | J334: 1200 | K334: =MIN(-G334,K$5*$B$13) -> 0 | L334: =ROUND(MAX(MIN(L$10*($E334-L$9),L$5*$B$13-K334),0),0) -> 0 | M334: =ROUND(IF($F334<M$6,$F334*M$4,0)+IF(AND($F334>=M$6,$F334<M$8),M$7,0)+IF(AND($F334>M$8,$F334<M$9),M$7 - (($F334-M$8)*M$5),0),0) -> 0 | N334: =SUM(G334,I334,K334,L334,M334) -> -26076 | O334: =MAX(-N334,0) -> 26076 | Q334: =Calc!W393 -> -4990 | R334: =Calc!X393 -> 5 | S334: =Calc!Y393 -> 0 | U334: -4990 | V334: 5 | W334: -4886 | X334: 10 | Y334: -4790 | Z334: 15 | AA334: -4693 | AB334: 20 | AC334: -4597 | AD334: 20 | AE334: -4161 | AF334: 5 | AG334: -4067 | AH334: 10 | AI334: -3973 | AJ334: 15 | AK334: -3878 | AL334: 20 | AM334: -3784 | AN334: 20

Sheet Calc
A1: Tax Calculations | E1: =COUNTA(AE1:DC1) -> 60 | H1: Federal | I1: Check | J1: CC Costs | K1: DCCEC | L1: check | M1: CTC | N1: Check1 | O1: Check2 | P1: ACTC | Q1: Check1 | R1: Check2 | S1: EITC | U1: Final Fed Ded | W1: State Income Taxes | X1: stateEITC | Y1: Plus if children under 3 | AD1: Alabama | AE1: Check | AF1: Alaska | AH1: Arizona | AL1: Arkansas | AM1: Chcek | AO1: California | AP1: Colorado | AR1: Connecticut | AS1: Delaware | AT1: District of Columbia | AU1: Florida | AV1: Georgia | AW1: Check | AX1: Hawaii | AY1: Idaho | BA1: Illinois | BB1: Indiana | BC1: Iowa | BD1: Kansas | BE1: Kentucky | BF1: Louisiana | BG1: Check | BH1: Maine | BJ1: Maryland | BK1: Massachusetts | BL1: Michigan | BN1: Minnesota | BO1: Mississippi | BP1: Check | BQ1: Missouri | BR1: Check | BT1: Montana | BU1: Nebraska | BV1: Nevada | BW1: New Hampshire | BX1: New Jersey | BY1: New Mexico | BZ1: New York | CA1: North Carolina | CB1: Check | CC1: North Dakota | CE1: Ohio | CF1: Oklahoma | CH1: Oregon | CI1: Pennsylvania | CK1: Rhode Island | CL1: South Carolina | CM1: Check | CN1: South Dakota | CO1: Tennessee | CP1: Texas | CR1: Utah | CS1: Check | CU1: Vermont | CV1: Virginia | CW1: Washington | CX1: West Virginia | CZ1: Check | DB1: Wisconsin | DC1: Wyoming | DF1: Albama | DG1: Arkansas | DH1: Florida | DI1: Georgia | DJ1: Louisiana | DK1: Mississippi | DL1: Missouri | DM1: North Carolina | DN1: South Carolina | DO1: Tennessee | DP1: Texas | DQ1: Utah | DR1: West Virginia | DW1: EITC | DX1: Alabama | DY1: Alaska | DZ1: Arizona | EA1: Arkansas | EB1: California | EC1: Colorado | ED1: Connecticut | EE1: Delaware | EF1: District of Columbia | EG1: Florida | EH1: Georgia | EI1: Hawaii | EJ1: Idaho | EK1: Illinois | EL1: Indiana | EM1: Iowa | EN1: Kansas | EO1: Kentucky | EP1: Louisiana | EQ1: Maine | ER1: Maryland | ES1: Massachusetts | ET1: Michigan | EU1: Minnesota | EV1: Mississippi | EW1: Missouri | EX1: Montana | EY1: Nebraska | EZ1: Nevada | FA1: New Hampshire | FB1: New Jersey | FC1: New Mexico | FD1: New York | FE1: North Carolina | FF1: North Dakota | FG1: Ohio | FH1: Oklahoma | FI1: Oregon | FJ1: Pennsylvania | FK1: Rhode Island | FL1: South Carolina | FM1: South Dakota | FN1: Tennessee | FO1: Texas | FP1: Utah | FQ1: Vermont | FR1: Virginia | FS1: Washington | FT1: West Virginia | FU1: Wisconsin | FV1: Wyoming
F2: Federal | G2: Weights | V2: Total Weight = | W2: =SUM(AD2:DC2) -> 22628000 | AD2: =_xlfn.IFNA(VLOOKUP(AD1,Weights,2,FALSE),0) -> 422000 | AE2: =_xlfn.IFNA(VLOOKUP(AE1,Weights,2,FALSE),0) -> 0 | AF2: =_xlfn.IFNA(VLOOKUP(AF1,Weights,2,FALSE),0) -> 37000 | AG2: =_xlfn.IFNA(VLOOKUP(AG1,Weights,2,FALSE),0) -> 0 | AH2: =_xlfn.IFNA(VLOOKUP(AH1,Weights,2,FALSE),0) -> 491000 | AI2: =_xlfn.IFNA(VLOOKUP(AI1,Weights,2,FALSE),0) -> 0 | AJ2: =_xlfn.IFNA(VLOOKUP(AJ1,Weights,2,FALSE),0) -> 0 | AK2: =_xlfn.IFNA(VLOOKUP(AK1,Weights,2,FALSE),0) -> 0 | ... DC2: =_xlfn.IFNA(VLOOKUP(DC1,Weights,2,FALSE),0) -> 31000 | DF2: =COLUMN(AM2) -> 39 | DX2: =VLOOKUP(DX1,Weights,2,FALSE) -> 422000 | DY2: =VLOOKUP(DY1,Weights,2,FALSE) -> 37000 | DZ2: =VLOOKUP(DZ1,Weights,2,FALSE) -> 491000 | EA2: =VLOOKUP(EA1,Weights,2,FALSE) -> 257000 | EB2: =VLOOKUP(EB1,Weights,2,FALSE) -> 2400000 | EC2: =VLOOKUP(EC1,Weights,2,FALSE) -> 287000 | ED2: =VLOOKUP(ED1,Weights,2,FALSE) -> 193000 | EE2: =VLOOKUP(EE1,Weights,2,FALSE) -> 65000 | ... FV2: =VLOOKUP(FV1,Weights,2,FALSE) -> 31000
A3: Select Inputs on WS("Final Results") | D3: Phase-In % | E3: Standard | F3: Standared Ded | H3: {=INDEX(FedStDeductLookup[],MATCH($B$7,FedStDeductLookup[Status],0),MATCH($B$4,VALUE(FedStDeductLookup[#Headers]),0))} -> 13850 | K3: Rate* | S3: {=INDEX(EITCpercents[],MATCH(1,(EITCpercents[Name]="Phase In Percent")*(EITCpercents[Children]=$B$14),0),MATCH("Percent",EITCpercents[#Headers],0))} -> 0.0765 | AD3: {=INDEX(stateTaxData[],MATCH(1,(stateTaxData[stateName]=AD$1)*(stateTaxData[taxYear]=$B$4)*(stateTaxData[FilingStatusFlag]=$B$8),0),MATCH($E3,stateTaxData[#Headers],0))} -> 3000 | AF3: {=INDEX(stateTaxData[],MATCH(1,(stateTaxData[stateName]=AF$1)*(stateTaxData[taxYear]=$B$4)*(stateTaxData[FilingStatusFlag]=$B$8),0),MATCH($E3,stateTaxData[#Headers],0))} -> 0 | AH3: {=INDEX(stateTaxData[],MATCH(1,(stateTaxData[stateName]=AH$1)*(stateTaxData[taxYear]=$B$4)*(stateTaxData[FilingStatusFlag]=$B$8),0),MATCH($E3,stateTaxData[#Headers],0))} -> 13850 | AJ3: =AK3 -> 2340 | AK3: =AL3 -> 2340 | AL3: {=INDEX(stateTaxData[],MATCH(1,(stateTaxData[stateName]=AL$1)*(stateTaxData[taxYear]=$B$4)*(stateTaxData[FilingStatusFlag]=$B$8),0),MATCH($E3,stateTaxData[#Headers],0))} -> 2340 | AO3: {=INDEX(stateTaxData[],MATCH(1,(stateTaxData[stateName]=AO$1)*(stateTaxData[taxYear]=$B$4)*(stateTaxData[FilingStatusFlag]=$B$8),0),MATCH($E3,stateTaxData[#Headers],0))} -> 5202 | AP3: {=INDEX(stateTaxData[],MATCH(1,(stateTaxData[stateName]=AP$1)*(stateTaxData[taxYear]=$B$4)*(stateTaxData[FilingStatusFlag]=$B$8),0),MATCH($E3,stateTaxData[#Headers],0))} -> 13850 | AR3: {=INDEX(stateTaxData[],MATCH(1,(stateTaxData[stateName]=AR$1)*(stateTaxData[taxYear]=$B$4)*(stateTaxData[FilingStatusFlag]=$B$8),0),MATCH($E3,stateTaxData[#Headers],0))} -> 0 | AS3: {=INDEX(stateTaxData[],MATCH(1,(stateTaxData[stateName]=AS$1)*(stateTaxData[taxYear]=$B$4)*(stateTaxData[FilingStatusFlag]=$B$8),0),MATCH($E3,stateTaxData[#Headers],0))} -> 3250 | AT3: {=INDEX(stateTaxData[],MATCH(1,(stateTaxData[stateName]=AT$1)*(stateTaxData[taxYear]=$B$4)*(stateTaxData[FilingStatusFlag]=$B$8),0),MATCH($E3,stateTaxData[#Headers],0))} -> 13850 | AU3: {=INDEX(stateTaxData[],MATCH(1,(stateTaxData[stateName]=AU$1)*(stateTaxData[taxYear]=$B$4)*(stateTaxData[FilingStatusFlag]=$B$8),0),MATCH($E3,stateTaxData[#Headers],0))} -> 0 | AV3: {=INDEX(stateTaxData[],MATCH(1,(stateTaxData[stateName]=AV$1)*(stateTaxData[taxYear]=$B$4)*(stateTaxData[FilingStatusFlag]=$B$8),0),MATCH($E3,stateTaxData[#Headers],0))} -> 5400 | AX3: {=INDEX(stateTaxData[],MATCH(1,(stateTaxData[stateName]=AX$1)*(stateTaxData[taxYear]=$B$4)*(stateTaxData[FilingStatusFlag]=$B$8),0),MATCH($E3,stateTaxData[#Headers],0))} -> 2200 | AY3: {=INDEX(stateTaxData[],MATCH(1,(stateTaxData[stateName]=AY$1)*(stateTaxData[taxYear]=$B$4)*(stateTaxData[FilingStatusFlag]=$B$8),0),MATCH($E3,stateTaxData[#Headers],0))} -> 13850 | BA3: {=INDEX(stateTaxData[],MATCH(1,(stateTaxData[stateName]=BA$1)*(stateTaxData[taxYear]=$B$4)*(stateTaxData[FilingStatusFlag]=$B$8),0),MATCH($E3,stateTaxData[#Headers],0))} -> 0 | BB3: {=INDEX(stateTaxData[],MATCH(1,(stateTaxData[stateName]=BB$1)*(stateTaxData[taxYear]=$B$4)*(stateTaxData[FilingStatusFlag]=$B$8),0),MATCH($E3,stateTaxData[#Headers],0))} -> 0 | BC3: {=INDEX(stateTaxData[],MATCH(1,(stateTaxData[stateName]=BC$1)*(stateTaxData[taxYear]=$B$4)*(stateTaxData[FilingStatusFlag]=$B$8),0),MATCH($E3,stateTaxData[#Headers],0))} -> 0 | BD3: {=INDEX(stateTaxData[],MATCH(1,(stateTaxData[stateName]=BD$1)*(stateTaxData[taxYear]=$B$4)*(stateTaxData[FilingStatusFlag]=$B$8),0),MATCH($E3,stateTaxData[#Headers],0))} -> 3500 | BE3: {=INDEX(stateTaxData[],MATCH(1,(stateTaxData[stateName]=BE$1)*(stateTaxData[taxYear]=$B$4)*(stateTaxData[FilingStatusFlag]=$B$8),0),MATCH($E3,stateTaxData[#Headers],0))} -> 2980 | BF3: {=INDEX(stateTaxData[],MATCH(1,(stateTaxData[stateName]=BF$1)*(stateTaxData[taxYear]=$B$4)*(stateTaxData[FilingStatusFlag]=$B$8),0),MATCH($E3,stateTaxData[#Headers],0))} -> 0 | BH3: {=INDEX(stateTaxData[],MATCH(1,(stateTaxData[stateName]=BH$1)*(stateTaxData[taxYear]=$B$4)*(stateTaxData[FilingStatusFlag]=$B$8),0),MATCH($E3,stateTaxData[#Headers],0))} -> 13850 | BK3: {=INDEX(stateTaxData[],MATCH(1,(stateTaxData[stateName]=BK$1)*(stateTaxData[taxYear]=$B$4)*(stateTaxData[FilingStatusFlag]=$B$8),0),MATCH($E3,stateTaxData[#Headers],0))} -> 0 | BL3: {=INDEX(stateTaxData[],MATCH(1,(stateTaxData[stateName]=BL$1)*(stateTaxData[taxYear]=$B$4)*(stateTaxData[FilingStatusFlag]=$B$8),0),MATCH($E3,stateTaxData[#Headers],0))} -> 0 | BN3: {=INDEX(stateTaxData[],MATCH(1,(stateTaxData[stateName]=BN$1)*(stateTaxData[taxYear]=$B$4)*(stateTaxData[FilingStatusFlag]=$B$8),0),MATCH($E3,stateTaxData[#Headers],0))} -> 13825 | BO3: {=INDEX(stateTaxData[],MATCH(1,(stateTaxData[stateName]=BO$1)*(stateTaxData[taxYear]=$B$4)*(stateTaxData[FilingStatusFlag]=$B$8),0),MATCH($E3,stateTaxData[#Headers],0))} -> 2300 | BQ3: {=INDEX(stateTaxData[],MATCH(1,(stateTaxData[stateName]=BQ$1)*(stateTaxData[taxYear]=$B$4)*(stateTaxData[FilingStatusFlag]=$B$8),0),MATCH($E3,stateTaxData[#Headers],0))} -> 13850 | BU3: {=INDEX(stateTaxData[],MATCH(1,(stateTaxData[stateName]=BU$1)*(stateTaxData[taxYear]=$B$4)*(stateTaxData[FilingStatusFlag]=$B$8),0),MATCH($E3,stateTaxData[#Headers],0))} -> 7900 | BV3: {=INDEX(stateTaxData[],MATCH(1,(stateTaxData[stateName]=BV$1)*(stateTaxData[taxYear]=$B$4)*(stateTaxData[FilingStatusFlag]=$B$8),0),MATCH($E3,stateTaxData[#Headers],0))} -> 0 | BW3: {=INDEX(stateTaxData[],MATCH(1,(stateTaxData[stateName]=BW$1)*(stateTaxData[taxYear]=$B$4)*(stateTaxData[FilingStatusFlag]=$B$8),0),MATCH($E3,stateTaxData[#Headers],0))} -> 0 | BX3: {=INDEX(stateTaxData[],MATCH(1,(stateTaxData[stateName]=BX$1)*(stateTaxData[taxYear]=$B$4)*(stateTaxData[FilingStatusFlag]=$B$8),0),MATCH($E3,stateTaxData[#Headers],0))} -> 0 | BY3: {=INDEX(stateTaxData[],MATCH(1,(stateTaxData[stateName]=BY$1)*(stateTaxData[taxYear]=$B$4)*(stateTaxData[FilingStatusFlag]=$B$8),0),MATCH($E3,stateTaxData[#Headers],0))} -> 13850 | BZ3: {=INDEX(stateTaxData[],MATCH(1,(stateTaxData[stateName]=BZ$1)*(stateTaxData[taxYear]=$B$4)*(stateTaxData[FilingStatusFlag]=$B$8),0),MATCH($E3,stateTaxData[#Headers],0))} -> 8000 | CA3: {=INDEX(stateTaxData[],MATCH(1,(stateTaxData[stateName]=CA$1)*(stateTaxData[taxYear]=$B$4)*(stateTaxData[FilingStatusFlag]=$B$8),0),MATCH($E3,stateTaxData[#Headers],0))} -> 12750 | CC3: {=INDEX(stateTaxData[],MATCH(1,(stateTaxData[stateName]=CC$1)*(stateTaxData[taxYear]=$B$4)*(stateTaxData[FilingStatusFlag]=$B$8),0),MATCH($E3,stateTaxData[#Headers],0))} -> 13850 | CE3: {=INDEX(stateTaxData[],MATCH(1,(stateTaxData[stateName]=CE$1)*(stateTaxData[taxYear]=$B$4)*(stateTaxData[FilingStatusFlag]=$B$8),0),MATCH($E3,stateTaxData[#Headers],0))} -> 0 | CF3: {=INDEX(stateTaxData[],MATCH(1,(stateTaxData[stateName]=CF$1)*(stateTaxData[taxYear]=$B$4)*(stateTaxData[FilingStatusFlag]=$B$8),0),MATCH($E3,stateTaxData[#Headers],0))} -> 6350 | CH3: {=INDEX(stateTaxData[],MATCH(1,(stateTaxData[stateName]=CH$1)*(stateTaxData[taxYear]=$B$4)*(stateTaxData[FilingStatusFlag]=$B$8),0),MATCH($E3,stateTaxData[#Headers],0))} -> 2605 | CI3: {=INDEX(stateTaxData[],MATCH(1,(stateTaxData[stateName]=CI$1)*(stateTaxData[taxYear]=$B$4)*(stateTaxData[FilingStatusFlag]=$B$8),0),MATCH($E3,stateTaxData[#Headers],0))} -> 0 | CK3: {=INDEX(stateTaxData[],MATCH(1,(stateTaxData[stateName]=CK$1)*(stateTaxData[taxYear]=$B$4)*(stateTaxData[FilingStatusFlag]=$B$8),0),MATCH($E3,stateTaxData[#Headers],0))} -> 10000 | CL3: {=INDEX(stateTaxData[],MATCH(1,(stateTaxData[stateName]=CL$1)*(stateTaxData[taxYear]=$B$4)*(stateTaxData[FilingStatusFlag]=$B$8),0),MATCH($E3,stateTaxData[#Headers],0))} -> 13850 | CN3: {=INDEX(stateTaxData[],MATCH(1,(stateTaxData[stateName]=CN$1)*(stateTaxData[taxYear]=$B$4)*(stateTaxData[FilingStatusFlag]=$B$8),0),MATCH($E3,stateTaxData[#Headers],0))} -> 0 | CO3: {=INDEX(stateTaxData[],MATCH(1,(stateTaxData[stateName]=CO$1)*(stateTaxData[taxYear]=$B$4)*(stateTaxData[FilingStatusFlag]=$B$8),0),MATCH($E3,stateTaxData[#Headers],0))} -> 0 | CP3: {=INDEX(stateTaxData[],MATCH(1,(stateTaxData[stateName]=CP$1)*(stateTaxData[taxYear]=$B$4)*(stateTaxData[FilingStatusFlag]=$B$8),0),MATCH($E3,stateTaxData[#Headers],0))} -> 0 | CR3: {=INDEX(stateTaxData[],MATCH(1,(stateTaxData[stateName]=CR$1)*(stateTaxData[taxYear]=$B$4)*(stateTaxData[FilingStatusFlag]=$B$8),0),MATCH($E3,stateTaxData[#Headers],0))} -> 0 | CU3: {=INDEX(stateTaxData[],MATCH(1,(stateTaxData[stateName]=CU$1)*(stateTaxData[taxYear]=$B$4)*(stateTaxData[FilingStatusFlag]=$B$8),0),MATCH($E3,stateTaxData[#Headers],0))} -> 6500 | CV3: {=INDEX(stateTaxData[],MATCH(1,(stateTaxData[stateName]=CV$1)*(stateTaxData[taxYear]=$B$4)*(stateTaxData[FilingStatusFlag]=$B$8),0),MATCH($E3,stateTaxData[#Headers],0))} -> 8000 | CW3: {=INDEX(stateTaxData[],MATCH(1,(stateTaxData[stateName]=CW$1)*(stateTaxData[taxYear]=$B$4)*(stateTaxData[FilingStatusFlag]=$B$8),0),MATCH($E3,stateTaxData[#Headers],0))} -> 250000 | CX3: {=INDEX(stateTaxData[],MATCH(1,(stateTaxData[stateName]=CX$1)*(stateTaxData[taxYear]=$B$4)*(stateTaxData[FilingStatusFlag]=$B$8),0),MATCH($E3,stateTaxData[#Headers],0))} -> 0 | DB3: {=INDEX(stateTaxData[],MATCH(1,(stateTaxData[stateName]=DB$1)*(stateTaxData[taxYear]=$B$4)*(stateTaxData[FilingStatusFlag]=$B$8),0),MATCH($E3,stateTaxData[#Headers],0))} -> 12760 | DC3: {=INDEX(stateTaxData[],MATCH(1,(stateTaxData[stateName]=DC$1)*(stateTaxData[taxYear]=$B$4)*(stateTaxData[FilingStatusFlag]=$B$8),0),MATCH($E3,stateTaxData[#Headers],0))} -> 0 | DD3: =ROUND(AVERAGE(AD3,AF3,AH3,AL3,AO3,AP3,AR3,AS3,AT3,AU3,AV3,AX3,AY3,BA3,BB3,BC3,BD3,BE3,BF3,BH3,BJ3,BK3,BL3,BN3,BO3,BQ3,BT3,BU3,BV3,BW3,BX3,BY3,BZ3,CA3,CC3,CE3,CF3,CH3,CI3,CK3,CL3,CN3,CO3,CP3,CR3,CU3,CV3,CW3,CX3,DB3,DC3),0) -> 10072 | DW3: Rate of Federal Benefit by | EB3: Own
A4: Tax Year | B4: ='Final Results'!B5 -> 2023 | D4: Phase-Out % | E4: PersonalExemption | F4: Credit Per Child | K4: CCCosts | M4: 2000 | P4: 1600 | S4: {=INDEX(EITCpercents[],MATCH(1,(EITCpercents[Name]="Phase Out Percent")*(EITCpercents[Children]=$B$14),0),MATCH("Percent",EITCpercents[#Headers],0))} -> 0.0765 | W4: Sampling Error | X4: 0.09 | AD4: {=INDEX(stateTaxData[],MATCH(1,(stateTaxData[stateName]=AD$1)*(stateTaxData[taxYear]=$B$4)*(stateTaxData[FilingStatusFlag]=$B$8),0),MATCH($E4,stateTaxData[#Headers],0))} -> 1500 | AF4: {=INDEX(stateTaxData[],MATCH(1,(stateTaxData[stateName]=AF$1)*(stateTaxData[taxYear]=$B$4)*(stateTaxData[FilingStatusFlag]=$B$8),0),MATCH($E4,stateTaxData[#Headers],0))} -> 0 | AH4: {=INDEX(stateTaxData[],MATCH(1,(stateTaxData[stateName]=AH$1)*(stateTaxData[taxYear]=$B$4)*(stateTaxData[FilingStatusFlag]=$B$8),0),MATCH($E4,stateTaxData[#Headers],0))} -> 0 | AJ4: =AK4 -> 29 | AK4: =AL4 -> 29 | AL4: {=INDEX(stateTaxData[],MATCH(1,(stateTaxData[stateName]=AL$1)*(stateTaxData[taxYear]=$B$4)*(stateTaxData[FilingStatusFlag]=$B$8),0),MATCH($E4,stateTaxData[#Headers],0))} -> 29 | AO4: {=INDEX(stateTaxData[],MATCH(1,(stateTaxData[stateName]=AO$1)*(stateTaxData[taxYear]=$B$4)*(stateTaxData[FilingStatusFlag]=$B$8),0),MATCH($E4,stateTaxData[#Headers],0))} -> 140 | AP4: {=INDEX(stateTaxData[],MATCH(1,(stateTaxData[stateName]=AP$1)*(stateTaxData[taxYear]=$B$4)*(stateTaxData[FilingStatusFlag]=$B$8),0),MATCH($E4,stateTaxData[#Headers],0))} -> 0 | AR4: {=INDEX(stateTaxData[],MATCH(1,(stateTaxData[stateName]=AR$1)*(stateTaxData[taxYear]=$B$4)*(stateTaxData[FilingStatusFlag]=$B$8),0),MATCH($E4,stateTaxData[#Headers],0))} -> 15000 | AS4: {=INDEX(stateTaxData[],MATCH(1,(stateTaxData[stateName]=AS$1)*(stateTaxData[taxYear]=$B$4)*(stateTaxData[FilingStatusFlag]=$B$8),0),MATCH($E4,stateTaxData[#Headers],0))} -> 110 | AT4: {=INDEX(stateTaxData[],MATCH(1,(stateTaxData[stateName]=AT$1)*(stateTaxData[taxYear]=$B$4)*(stateTaxData[FilingStatusFlag]=$B$8),0),MATCH($E4,stateTaxData[#Headers],0))} -> 0 | AU4: {=INDEX(stateTaxData[],MATCH(1,(stateTaxData[stateName]=AU$1)*(stateTaxData[taxYear]=$B$4)*(stateTaxData[FilingStatusFlag]=$B$8),0),MATCH($E4,stateTaxData[#Headers],0))} -> 0 | AV4: {=INDEX(stateTaxData[],MATCH(1,(stateTaxData[stateName]=AV$1)*(stateTaxData[taxYear]=$B$4)*(stateTaxData[FilingStatusFlag]=$B$8),0),MATCH($E4,stateTaxData[#Headers],0))} -> 2700 | AX4: {=INDEX(stateTaxData[],MATCH(1,(stateTaxData[stateName]=AX$1)*(stateTaxData[taxYear]=$B$4)*(stateTaxData[FilingStatusFlag]=$B$8),0),MATCH($E4,stateTaxData[#Headers],0))} -> 1144 | AY4: {=INDEX(stateTaxData[],MATCH(1,(stateTaxData[stateName]=AY$1)*(stateTaxData[taxYear]=$B$4)*(stateTaxData[FilingStatusFlag]=$B$8),0),MATCH($E4,stateTaxData[#Headers],0))} -> 0 | BA4: {=INDEX(stateTaxData[],MATCH(1,(stateTaxData[stateName]=BA$1)*(stateTaxData[taxYear]=$B$4)*(stateTaxData[FilingStatusFlag]=$B$8),0),MATCH($E4,stateTaxData[#Headers],0))} -> 2425 | BB4: {=INDEX(stateTaxData[],MATCH(1,(stateTaxData[stateName]=BB$1)*(stateTaxData[taxYear]=$B$4)*(stateTaxData[FilingStatusFlag]=$B$8),0),MATCH($E4,stateTaxData[#Headers],0))} -> 1000 | BC4: {=INDEX(stateTaxData[],MATCH(1,(stateTaxData[stateName]=BC$1)*(stateTaxData[taxYear]=$B$4)*(stateTaxData[FilingStatusFlag]=$B$8),0),MATCH($E4,stateTaxData[#Headers],0))} -> 40 | BD4: {=INDEX(stateTaxData[],MATCH(1,(stateTaxData[stateName]=BD$1)*(stateTaxData[taxYear]=$B$4)*(stateTaxData[FilingStatusFlag]=$B$8),0),MATCH($E4,stateTaxData[#Headers],0))} -> 2250 | BE4: {=INDEX(stateTaxData[],MATCH(1,(stateTaxData[stateName]=BE$1)*(stateTaxData[taxYear]=$B$4)*(stateTaxData[FilingStatusFlag]=$B$8),0),MATCH($E4,stateTaxData[#Headers],0))} -> 0 | BF4: {=INDEX(stateTaxData[],MATCH(1,(stateTaxData[stateName]=BF$1)*(stateTaxData[taxYear]=$B$4)*(stateTaxData[FilingStatusFlag]=$B$8),0),MATCH($E4,stateTaxData[#Headers],0))} -> 4500 | BH4: {=INDEX(stateTaxData[],MATCH(1,(stateTaxData[stateName]=BH$1)*(stateTaxData[taxYear]=$B$4)*(stateTaxData[FilingStatusFlag]=$B$8),0),MATCH($E4,stateTaxData[#Headers],0))} -> 4700 | BJ4: {=INDEX(stateTaxData[],MATCH(1,(stateTaxData[stateName]=BJ$1)*(stateTaxData[taxYear]=$B$4)*(stateTaxData[FilingStatusFlag]=$B$8),0),MATCH($E4,stateTaxData[#Headers],0))} -> 3200 | BK4: {=INDEX(stateTaxData[],MATCH(1,(stateTaxData[stateName]=BK$1)*(stateTaxData[taxYear]=$B$4)*(stateTaxData[FilingStatusFlag]=$B$8),0),MATCH($E4,stateTaxData[#Headers],0))} -> 4400 | BL4: {=INDEX(stateTaxData[],MATCH(1,(stateTaxData[stateName]=BL$1)*(stateTaxData[taxYear]=$B$4)*(stateTaxData[FilingStatusFlag]=$B$8),0),MATCH($E4,stateTaxData[#Headers],0))} -> 5400 | BN4: {=INDEX(stateTaxData[],MATCH(1,(stateTaxData[stateName]=BN$1)*(stateTaxData[taxYear]=$B$4)*(stateTaxData[FilingStatusFlag]=$B$8),0),MATCH($E4,stateTaxData[#Headers],0))} -> 0 | BO4: {=INDEX(stateTaxData[],MATCH(1,(stateTaxData[stateName]=BO$1)*(stateTaxData[taxYear]=$B$4)*(stateTaxData[FilingStatusFlag]=$B$8),0),MATCH($E4,stateTaxData[#Headers],0))} -> 6000 | BQ4: {=INDEX(stateTaxData[],MATCH(1,(stateTaxData[stateName]=BQ$1)*(stateTaxData[taxYear]=$B$4)*(stateTaxData[FilingStatusFlag]=$B$8),0),MATCH($E4,stateTaxData[#Headers],0))} -> 0 | BT4: {=INDEX(stateTaxData[],MATCH(1,(stateTaxData[stateName]=BT$1)*(stateTaxData[taxYear]=$B$4)*(stateTaxData[FilingStatusFlag]=$B$8),0),MATCH($E4,stateTaxData[#Headers],0))} -> 2960 | BU4: {=INDEX(stateTaxData[],MATCH(1,(stateTaxData[stateName]=BU$1)*(stateTaxData[taxYear]=$B$4)*(stateTaxData[FilingStatusFlag]=$B$8),0),MATCH($E4,stateTaxData[#Headers],0))} -> 157 | BV4: {=INDEX(stateTaxData[],MATCH(1,(stateTaxData[stateName]=BV$1)*(stateTaxData[taxYear]=$B$4)*(stateTaxData[FilingStatusFlag]=$B$8),0),MATCH($E4,stateTaxData[#Headers],0))} -> 0 | BW4: {=INDEX(stateTaxData[],MATCH(1,(stateTaxData[stateName]=BW$1)*(stateTaxData[taxYear]=$B$4)*(stateTaxData[FilingStatusFlag]=$B$8),0),MATCH($E4,stateTaxData[#Headers],0))} -> 2400 | BX4: {=INDEX(stateTaxData[],MATCH(1,(stateTaxData[stateName]=BX$1)*(stateTaxData[taxYear]=$B$4)*(stateTaxData[FilingStatusFlag]=$B$8),0),MATCH($E4,stateTaxData[#Headers],0))} -> 1000 | BY4: {=INDEX(stateTaxData[],MATCH(1,(stateTaxData[stateName]=BY$1)*(stateTaxData[taxYear]=$B$4)*(stateTaxData[FilingStatusFlag]=$B$8),0),MATCH($E4,stateTaxData[#Headers],0))} -> 0 | BZ4: {=INDEX(stateTaxData[],MATCH(1,(stateTaxData[stateName]=BZ$1)*(stateTaxData[taxYear]=$B$4)*(stateTaxData[FilingStatusFlag]=$B$8),0),MATCH($E4,stateTaxData[#Headers],0))} -> 0 | CA4: {=INDEX(stateTaxData[],MATCH(1,(stateTaxData[stateName]=CA$1)*(stateTaxData[taxYear]=$B$4)*(stateTaxData[FilingStatusFlag]=$B$8),0),MATCH($E4,stateTaxData[#Headers],0))} -> 0 | CC4: {=INDEX(stateTaxData[],MATCH(1,(stateTaxData[stateName]=CC$1)*(stateTaxData[taxYear]=$B$4)*(stateTaxData[FilingStatusFlag]=$B$8),0),MATCH($E4,stateTaxData[#Headers],0))} -> 0 | CE4: {=INDEX(stateTaxData[],MATCH(1,(stateTaxData[stateName]=CE$1)*(stateTaxData[taxYear]=$B$4)*(stateTaxData[FilingStatusFlag]=$B$8),0),MATCH($E4,stateTaxData[#Headers],0))} -> 2400 | CF4: {=INDEX(stateTaxData[],MATCH(1,(stateTaxData[stateName]=CF$1)*(stateTaxData[taxYear]=$B$4)*(stateTaxData[FilingStatusFlag]=$B$8),0),MATCH($E4,stateTaxData[#Headers],0))} -> 1000 | CH4: {=INDEX(stateTaxData[],MATCH(1,(stateTaxData[stateName]=CH$1)*(stateTaxData[taxYear]=$B$4)*(stateTaxData[FilingStatusFlag]=$B$8),0),MATCH($E4,stateTaxData[#Headers],0))} -> 236 | CI4: {=INDEX(stateTaxData[],MATCH(1,(stateTaxData[stateName]=CI$1)*(stateTaxData[taxYear]=$B$4)*(stateTaxData[FilingStatusFlag]=$B$8),0),MATCH($E4,stateTaxData[#Headers],0))} -> 0 | CK4: {=INDEX(stateTaxData[],MATCH(1,(stateTaxData[stateName]=CK$1)*(stateTaxData[taxYear]=$B$4)*(stateTaxData[FilingStatusFlag]=$B$8),0),MATCH($E4,stateTaxData[#Headers],0))} -> 4700 | CL4: {=INDEX(stateTaxData[],MATCH(1,(stateTaxData[stateName]=CL$1)*(stateTaxData[taxYear]=$B$4)*(stateTaxData[FilingStatusFlag]=$B$8),0),MATCH($E4,stateTaxData[#Headers],0))} -> 0 | CN4: {=INDEX(stateTaxData[],MATCH(1,(stateTaxData[stateName]=CN$1)*(stateTaxData[taxYear]=$B$4)*(stateTaxData[FilingStatusFlag]=$B$8),0),MATCH($E4,stateTaxData[#Headers],0))} -> 0 | CO4: {=INDEX(stateTaxData[],MATCH(1,(stateTaxData[stateName]=CO$1)*(stateTaxData[taxYear]=$B$4)*(stateTaxData[FilingStatusFlag]=$B$8),0),MATCH($E4,stateTaxData[#Headers],0))} -> 0 | CP4: {=INDEX(stateTaxData[],MATCH(1,(stateTaxData[stateName]=CP$1)*(stateTaxData[taxYear]=$B$4)*(stateTaxData[FilingStatusFlag]=$B$8),0),MATCH($E4,stateTaxData[#Headers],0))} -> 0 | CR4: 0 | CU4: {=INDEX(stateTaxData[],MATCH(1,(stateTaxData[stateName]=CU$1)*(stateTaxData[taxYear]=$B$4)*(stateTaxData[FilingStatusFlag]=$B$8),0),MATCH($E4,stateTaxData[#Headers],0))} -> 4500 | CV4: {=INDEX(stateTaxData[],MATCH(1,(stateTaxData[stateName]=CV$1)*(stateTaxData[taxYear]=$B$4)*(stateTaxData[FilingStatusFlag]=$B$8),0),MATCH($E4,stateTaxData[#Headers],0))} -> 930 | CW4: {=INDEX(stateTaxData[],MATCH(1,(stateTaxData[stateName]=CW$1)*(stateTaxData[taxYear]=$B$4)*(stateTaxData[FilingStatusFlag]=$B$8),0),MATCH($E4,stateTaxData[#Headers],0))} -> 0 | CX4: {=INDEX(stateTaxData[],MATCH(1,(stateTaxData[stateName]=CX$1)*(stateTaxData[taxYear]=$B$4)*(stateTaxData[FilingStatusFlag]=$B$8),0),MATCH($E4,stateTaxData[#Headers],0))} -> 2000 | DB4: {=INDEX(stateTaxData[],MATCH(1,(stateTaxData[stateName]=DB$1)*(stateTaxData[taxYear]=$B$4)*(stateTaxData[FilingStatusFlag]=$B$8),0),MATCH($E4,stateTaxData[#Headers],0))} -> 700 | DC4: {=INDEX(stateTaxData[],MATCH(1,(stateTaxData[stateName]=DC$1)*(stateTaxData[taxYear]=$B$4)*(stateTaxData[FilingStatusFlag]=$B$8),0),MATCH($E4,stateTaxData[#Headers],0))} -> 0 | DD4: =ROUND(AVERAGE(AD4,AF4,AH4,AL4,AO4,AP4,AR4,AS4,AT4,AU4,AV4,AX4,AY4,BA4,BB4,BC4,BD4,BE4,BF4,BH4,BJ4,BK4,BL4,BN4,BO4,BQ4,BT4,BU4,BV4,BW4,BX4,BY4,BZ4,CA4,CC4,CE4,CF4,CH4,CI4,CK4,CL4,CN4,CO4,CP4,CR4,CU4,CV4,CW4,CX4,DB4,DC4),0) -> 1520 | DW4: Number Children
D5: Threshold | E5: PersonalExemptionAsCredit | F5: Income Limit | M5: {=INDEX(CTCFactors[],MATCH(1,(CTCFactors[Name]=$B$8)*(CTCFactors[Phaseout Phase]=1)*(CTCFactors[Year]=$B$4)*(CTCFactors[Note]="Income Threshold"),0),MATCH("Value",CTCFactors[#Headers],0))} -> 75000.01 | S5: {=INDEX(EITCPhaseIn[],MATCH(1,(EITCPhaseIn[Name]="Phase In Threshold")*(EITCPhaseIn[Children]=$B$14),0),MATCH($B$4,VALUE(EITCPhaseIn[#Headers]),0))} -> 7840 | W5: Adjustment | X5: =1/(1+X4) -> 0.91743119 | AD5: {=INDEX(stateTaxData[],MATCH(1,(stateTaxData[stateName]=AD$1)*(stateTaxData[taxYear]=$B$4)*(stateTaxData[FilingStatusFlag]=$B$8),0),MATCH($E5,stateTaxData[#Headers],0))} -> No | AF5: {=INDEX(stateTaxData[],MATCH(1,(stateTaxData[stateName]=AF$1)*(stateTaxData[taxYear]=$B$4)*(stateTaxData[FilingStatusFlag]=$B$8),0),MATCH($E5,stateTaxData[#Headers],0))} -> No | AH5: {=INDEX(stateTaxData[],MATCH(1,(stateTaxData[stateName]=AH$1)*(stateTaxData[taxYear]=$B$4)*(stateTaxData[FilingStatusFlag]=$B$8),0),MATCH($E5,stateTaxData[#Headers],0))} -> No | AJ5: =AK5 -> Yes | AK5: =AL5 -> Yes | AL5: {=INDEX(stateTaxData[],MATCH(1,(stateTaxData[stateName]=AL$1)*(stateTaxData[taxYear]=$B$4)*(stateTaxData[FilingStatusFlag]=$B$8),0),MATCH($E5,stateTaxData[#Headers],0))} -> Yes | AO5: {=INDEX(stateTaxData[],MATCH(1,(stateTaxData[stateName]=AO$1)*(stateTaxData[taxYear]=$B$4)*(stateTaxData[FilingStatusFlag]=$B$8),0),MATCH($E5,stateTaxData[#Headers],0))} -> Yes | AP5: {=INDEX(stateTaxData[],MATCH(1,(stateTaxData[stateName]=AP$1)*(stateTaxData[taxYear]=$B$4)*(stateTaxData[FilingStatusFlag]=$B$8),0),MATCH($E5,stateTaxData[#Headers],0))} -> No | AR5: {=INDEX(stateTaxData[],MATCH(1,(stateTaxData[stateName]=AR$1)*(stateTaxData[taxYear]=$B$4)*(stateTaxData[FilingStatusFlag]=$B$8),0),MATCH($E5,stateTaxData[#Headers],0))} -> No | AS5: {=INDEX(stateTaxData[],MATCH(1,(stateTaxData[stateName]=AS$1)*(stateTaxData[taxYear]=$B$4)*(stateTaxData[FilingStatusFlag]=$B$8),0),MATCH($E5,stateTaxData[#Headers],0))} -> Yes | AT5: {=INDEX(stateTaxData[],MATCH(1,(stateTaxData[stateName]=AT$1)*(stateTaxData[taxYear]=$B$4)*(stateTaxData[FilingStatusFlag]=$B$8),0),MATCH($E5,stateTaxData[#Headers],0))} -> No | AU5: {=INDEX(stateTaxData[],MATCH(1,(stateTaxData[stateName]=AU$1)*(stateTaxData[taxYear]=$B$4)*(stateTaxData[FilingStatusFlag]=$B$8),0),MATCH($E5,stateTaxData[#Headers],0))} -> No | AV5: {=INDEX(stateTaxData[],MATCH(1,(stateTaxData[stateName]=AV$1)*(stateTaxData[taxYear]=$B$4)*(stateTaxData[FilingStatusFlag]=$B$8),0),MATCH($E5,stateTaxData[#Headers],0))} -> No | AX5: {=INDEX(stateTaxData[],MATCH(1,(stateTaxData[stateName]=AX$1)*(stateTaxData[taxYear]=$B$4)*(stateTaxData[FilingStatusFlag]=$B$8),0),MATCH($E5,stateTaxData[#Headers],0))} -> No | AY5: {=INDEX(stateTaxData[],MATCH(1,(stateTaxData[stateName]=AY$1)*(stateTaxData[taxYear]=$B$4)*(stateTaxData[FilingStatusFlag]=$B$8),0),MATCH($E5,stateTaxData[#Headers],0))} -> No | BA5: {=INDEX(stateTaxData[],MATCH(1,(stateTaxData[stateName]=BA$1)*(stateTaxData[taxYear]=$B$4)*(stateTaxData[FilingStatusFlag]=$B$8),0),MATCH($E5,stateTaxData[#Headers],0))} -> No | BB5: {=INDEX(stateTaxData[],MATCH(1,(stateTaxData[stateName]=BB$1)*(stateTaxData[taxYear]=$B$4)*(stateTaxData[FilingStatusFlag]=$B$8),0),MATCH($E5,stateTaxData[#Headers],0))} -> No | BC5: {=INDEX(stateTaxData[],MATCH(1,(stateTaxData[stateName]=BC$1)*(stateTaxData[taxYear]=$B$4)*(stateTaxData[FilingStatusFlag]=$B$8),0),MATCH($E5,stateTaxData[#Headers],0))} -> Yes | BD5: {=INDEX(stateTaxData[],MATCH(1,(stateTaxData[stateName]=BD$1)*(stateTaxData[taxYear]=$B$4)*(stateTaxData[FilingStatusFlag]=$B$8),0),MATCH($E5,stateTaxData[#Headers],0))} -> No | BE5: {=INDEX(stateTaxData[],MATCH(1,(stateTaxData[stateName]=BE$1)*(stateTaxData[taxYear]=$B$4)*(stateTaxData[FilingStatusFlag]=$B$8),0),MATCH($E5,stateTaxData[#Headers],0))} -> No | BF5: {=INDEX(stateTaxData[],MATCH(1,(stateTaxData[stateName]=BF$1)*(stateTaxData[taxYear]=$B$4)*(stateTaxData[FilingStatusFlag]=$B$8),0),MATCH($E5,stateTaxData[#Headers],0))} -> No | BH5: {=INDEX(stateTaxData[],MATCH(1,(stateTaxData[stateName]=BH$1)*(stateTaxData[taxYear]=$B$4)*(stateTaxData[FilingStatusFlag]=$B$8),0),MATCH($E5,stateTaxData[#Headers],0))} -> No | BJ5: {=INDEX(stateTaxData[],MATCH(1,(stateTaxData[stateName]=BJ$1)*(stateTaxData[taxYear]=$B$4)*(stateTaxData[FilingStatusFlag]=$B$8),0),MATCH($E5,stateTaxData[#Headers],0))} -> No | BK5: {=INDEX(stateTaxData[],MATCH(1,(stateTaxData[stateName]=BK$1)*(stateTaxData[taxYear]=$B$4)*(stateTaxData[FilingStatusFlag]=$B$8),0),MATCH($E5,stateTaxData[#Headers],0))} -> No | BL5: {=INDEX(stateTaxData[],MATCH(1,(stateTaxData[stateName]=BL$1)*(stateTaxData[taxYear]=$B$4)*(stateTaxData[FilingStatusFlag]=$B$8),0),MATCH($E5,stateTaxData[#Headers],0))} -> No | BN5: {=INDEX(stateTaxData[],MATCH(1,(stateTaxData[stateName]=BN$1)*(stateTaxData[taxYear]=$B$4)*(stateTaxData[FilingStatusFlag]=$B$8),0),MATCH($E5,stateTaxData[#Headers],0))} -> No | BO5: {=INDEX(stateTaxData[],MATCH(1,(stateTaxData[stateName]=BO$1)*(stateTaxData[taxYear]=$B$4)*(stateTaxData[FilingStatusFlag]=$B$8),0),MATCH($E5,stateTaxData[#Headers],0))} -> No | BQ5: {=INDEX(stateTaxData[],MATCH(1,(stateTaxData[stateName]=BQ$1)*(stateTaxData[taxYear]=$B$4)*(stateTaxData[FilingStatusFlag]=$B$8),0),MATCH($E5,stateTaxData[#Headers],0))} -> No | BT5: {=INDEX(stateTaxData[],MATCH(1,(stateTaxData[stateName]=BT$1)*(stateTaxData[taxYear]=$B$4)*(stateTaxData[FilingStatusFlag]=$B$8),0),MATCH($E5,stateTaxData[#Headers],0))} -> No | BU5: {=INDEX(stateTaxData[],MATCH(1,(stateTaxData[stateName]=BU$1)*(stateTaxData[taxYear]=$B$4)*(stateTaxData[FilingStatusFlag]=$B$8),0),MATCH($E5,stateTaxData[#Headers],0))} -> Yes | BV5: {=INDEX(stateTaxData[],MATCH(1,(stateTaxData[stateName]=BV$1)*(stateTaxData[taxYear]=$B$4)*(stateTaxData[FilingStatusFlag]=$B$8),0),MATCH($E5,stateTaxData[#Headers],0))} -> No | BW5: {=INDEX(stateTaxData[],MATCH(1,(stateTaxData[stateName]=BW$1)*(stateTaxData[taxYear]=$B$4)*(stateTaxData[FilingStatusFlag]=$B$8),0),MATCH($E5,stateTaxData[#Headers],0))} -> No | BX5: {=INDEX(stateTaxData[],MATCH(1,(stateTaxData[stateName]=BX$1)*(stateTaxData[taxYear]=$B$4)*(stateTaxData[FilingStatusFlag]=$B$8),0),MATCH($E5,stateTaxData[#Headers],0))} -> No | BY5: {=INDEX(stateTaxData[],MATCH(1,(stateTaxData[stateName]=BY$1)*(stateTaxData[taxYear]=$B$4)*(stateTaxData[FilingStatusFlag]=$B$8),0),MATCH($E5,stateTaxData[#Headers],0))} -> No | BZ5: {=INDEX(stateTaxData[],MATCH(1,(stateTaxData[stateName]=BZ$1)*(stateTaxData[taxYear]=$B$4)*(stateTaxData[FilingStatusFlag]=$B$8),0),MATCH($E5,stateTaxData[#Headers],0))} -> No | CA5: {=INDEX(stateTaxData[],MATCH(1,(stateTaxData[stateName]=CA$1)*(stateTaxData[taxYear]=$B$4)*(stateTaxData[FilingStatusFlag]=$B$8),0),MATCH($E5,stateTaxData[#Headers],0))} -> No | CC5: {=INDEX(stateTaxData[],MATCH(1,(stateTaxData[stateName]=CC$1)*(stateTaxData[taxYear]=$B$4)*(stateTaxData[FilingStatusFlag]=$B$8),0),MATCH($E5,stateTaxData[#Headers],0))} -> No | CE5: {=INDEX(stateTaxData[],MATCH(1,(stateTaxData[stateName]=CE$1)*(stateTaxData[taxYear]=$B$4)*(stateTaxData[FilingStatusFlag]=$B$8),0),MATCH($E5,stateTaxData[#Headers],0))} -> No | CF5: {=INDEX(stateTaxData[],MATCH(1,(stateTaxData[stateName]=CF$1)*(stateTaxData[taxYear]=$B$4)*(stateTaxData[FilingStatusFlag]=$B$8),0),MATCH($E5,stateTaxData[#Headers],0))} -> No | CH5: {=INDEX(stateTaxData[],MATCH(1,(stateTaxData[stateName]=CH$1)*(stateTaxData[taxYear]=$B$4)*(stateTaxData[FilingStatusFlag]=$B$8),0),MATCH($E5,stateTaxData[#Headers],0))} -> Yes | CI5: {=INDEX(stateTaxData[],MATCH(1,(stateTaxData[stateName]=CI$1)*(stateTaxData[taxYear]=$B$4)*(stateTaxData[FilingStatusFlag]=$B$8),0),MATCH($E5,stateTaxData[#Headers],0))} -> No | CK5: {=INDEX(stateTaxData[],MATCH(1,(stateTaxData[stateName]=CK$1)*(stateTaxData[taxYear]=$B$4)*(stateTaxData[FilingStatusFlag]=$B$8),0),MATCH($E5,stateTaxData[#Headers],0))} -> No | CL5: {=INDEX(stateTaxData[],MATCH(1,(stateTaxData[stateName]=CL$1)*(stateTaxData[taxYear]=$B$4)*(stateTaxData[FilingStatusFlag]=$B$8),0),MATCH($E5,stateTaxData[#Headers],0))} -> No | CN5: {=INDEX(stateTaxData[],MATCH(1,(stateTaxData[stateName]=CN$1)*(stateTaxData[taxYear]=$B$4)*(stateTaxData[FilingStatusFlag]=$B$8),0),MATCH($E5,stateTaxData[#Headers],0))} -> No | CO5: {=INDEX(stateTaxData[],MATCH(1,(stateTaxData[stateName]=CO$1)*(stateTaxData[taxYear]=$B$4)*(stateTaxData[FilingStatusFlag]=$B$8),0),MATCH($E5,stateTaxData[#Headers],0))} -> No | CP5: {=INDEX(stateTaxData[],MATCH(1,(stateTaxData[stateName]=CP$1)*(stateTaxData[taxYear]=$B$4)*(stateTaxData[FilingStatusFlag]=$B$8),0),MATCH($E5,stateTaxData[#Headers],0))} -> No | CR5: {=INDEX(stateTaxData[],MATCH(1,(stateTaxData[stateName]=CR$1)*(stateTaxData[taxYear]=$B$4)*(stateTaxData[FilingStatusFlag]=$B$8),0),MATCH($E5,stateTaxData[#Headers],0))} -> Yes | CU5: {=INDEX(stateTaxData[],MATCH(1,(stateTaxData[stateName]=CU$1)*(stateTaxData[taxYear]=$B$4)*(stateTaxData[FilingStatusFlag]=$B$8),0),MATCH($E5,stateTaxData[#Headers],0))} -> No | CV5: {=INDEX(stateTaxData[],MATCH(1,(stateTaxData[stateName]=CV$1)*(stateTaxData[taxYear]=$B$4)*(stateTaxData[FilingStatusFlag]=$B$8),0),MATCH($E5,stateTaxData[#Headers],0))} -> No | CW5: {=INDEX(stateTaxData[],MATCH(1,(stateTaxData[stateName]=CW$1)*(stateTaxData[taxYear]=$B$4)*(stateTaxData[FilingStatusFlag]=$B$8),0),MATCH($E5,stateTaxData[#Headers],0))} -> No | CX5: {=INDEX(stateTaxData[],MATCH(1,(stateTaxData[stateName]=CX$1)*(stateTaxData[taxYear]=$B$4)*(stateTaxData[FilingStatusFlag]=$B$8),0),MATCH($E5,stateTaxData[#Headers],0))} -> No | DB5: {=INDEX(stateTaxData[],MATCH(1,(stateTaxData[stateName]=DB$1)*(stateTaxData[taxYear]=$B$4)*(stateTaxData[FilingStatusFlag]=$B$8),0),MATCH($E5,stateTaxData[#Headers],0))} -> No | DC5: {=INDEX(stateTaxData[],MATCH(1,(stateTaxData[stateName]=DC$1)*(stateTaxData[taxYear]=$B$4)*(stateTaxData[FilingStatusFlag]=$B$8),0),MATCH($E5,stateTaxData[#Headers],0))} -> No | DW5: 0 | EC5: 0.5 | ED5: 0.4 | EE5: 0.045 | EF5: 0.55 | EI5: 0.4 | EK5: 0.2 | EL5: 0.1 | EM5: 0.15 | EN5: 0.17 | EP5: 0.05 | EQ5: 0.5 | ER5: 1 | ES5: 0.3 | ET5: 0.3 | EU5: 0.04 | EW5: 0.1 | EX5: 0.1 | EY5: 0.1 | FB5: 0.4 | FC5: 0.25 | FD5: 0.3 | FG5: 0.3 | FH5: 0.05 | FI5: 0.09 | FK5: 0.16 | FL5: 1.25 | FP5: 0.2 | FQ5: 0.38 | FR5: 0.2
D6: Max Credit | E6: DependentExemption | F6: Decrease by | M6: {=INDEX(CTCFactors[],MATCH(1,(CTCFactors[Name]=$B$8)*(CTCFactors[Phaseout Phase]=1)*(CTCFactors[Year]=$B$4),0),MATCH("Credit Decrease per Income Increment",CTCFactors[#Headers],0))} -> 50 | S6: {=INDEX(EITCPhaseIn[],MATCH(1,(EITCPhaseIn[Name]="Maximum Credit")*(EITCPhaseIn[Children]=$B$14),0),MATCH($B$4,VALUE(EITCPhaseIn[#Headers]),0))} -> 600 | AD6: {=INDEX(stateTaxData[],MATCH(1,(stateTaxData[stateName]=AD$1)*(stateTaxData[taxYear]=$B$4)*(stateTaxData[FilingStatusFlag]=$B$8),0),MATCH($E6,stateTaxData[#Headers],0))} -> 1000 | AF6: {=INDEX(stateTaxData[],MATCH(1,(stateTaxData[stateName]=AF$1)*(stateTaxData[taxYear]=$B$4)*(stateTaxData[FilingStatusFlag]=$B$8),0),MATCH($E6,stateTaxData[#Headers],0))} -> 0 | AH6: {=INDEX(stateTaxData[],MATCH(1,(stateTaxData[stateName]=AH$1)*(stateTaxData[taxYear]=$B$4)*(stateTaxData[FilingStatusFlag]=$B$8),0),MATCH($E6,stateTaxData[#Headers],0))} -> 100 | AJ6: =AK6 -> 29 | AK6: =AL6 -> 29 | AL6: {=INDEX(stateTaxData[],MATCH(1,(stateTaxData[stateName]=AL$1)*(stateTaxData[taxYear]=$B$4)*(stateTaxData[FilingStatusFlag]=$B$8),0),MATCH($E6,stateTaxData[#Headers],0))} -> 29 | AO6: {=INDEX(stateTaxData[],MATCH(1,(stateTaxData[stateName]=AO$1)*(stateTaxData[taxYear]=$B$4)*(stateTaxData[FilingStatusFlag]=$B$8),0),MATCH($E6,stateTaxData[#Headers],0))} -> 433 | AP6: {=INDEX(stateTaxData[],MATCH(1,(stateTaxData[stateName]=AP$1)*(stateTaxData[taxYear]=$B$4)*(stateTaxData[FilingStatusFlag]=$B$8),0),MATCH($E6,stateTaxData[#Headers],0))} -> 0 | AR6: {=INDEX(stateTaxData[],MATCH(1,(stateTaxData[stateName]=AR$1)*(stateTaxData[taxYear]=$B$4)*(stateTaxData[FilingStatusFlag]=$B$8),0),MATCH($E6,stateTaxData[#Headers],0))} -> 0 | AS6: {=INDEX(stateTaxData[],MATCH(1,(stateTaxData[stateName]=AS$1)*(stateTaxData[taxYear]=$B$4)*(stateTaxData[FilingStatusFlag]=$B$8),0),MATCH($E6,stateTaxData[#Headers],0))} -> 110 | AT6: {=INDEX(stateTaxData[],MATCH(1,(stateTaxData[stateName]=AT$1)*(stateTaxData[taxYear]=$B$4)*(stateTaxData[FilingStatusFlag]=$B$8),0),MATCH($E6,stateTaxData[#Headers],0))} -> 0 | AU6: {=INDEX(stateTaxData[],MATCH(1,(stateTaxData[stateName]=AU$1)*(stateTaxData[taxYear]=$B$4)*(stateTaxData[FilingStatusFlag]=$B$8),0),MATCH($E6,stateTaxData[#Headers],0))} -> 0 | AV6: {=INDEX(stateTaxData[],MATCH(1,(stateTaxData[stateName]=AV$1)*(stateTaxData[taxYear]=$B$4)*(stateTaxData[FilingStatusFlag]=$B$8),0),MATCH($E6,stateTaxData[#Headers],0))} -> 3000 | AX6: {=INDEX(stateTaxData[],MATCH(1,(stateTaxData[stateName]=AX$1)*(stateTaxData[taxYear]=$B$4)*(stateTaxData[FilingStatusFlag]=$B$8),0),MATCH($E6,stateTaxData[#Headers],0))} -> 1144 | AY6: {=INDEX(stateTaxData[],MATCH(1,(stateTaxData[stateName]=AY$1)*(stateTaxData[taxYear]=$B$4)*(stateTaxData[FilingStatusFlag]=$B$8),0),MATCH($E6,stateTaxData[#Headers],0))} -> 0 | BA6: {=INDEX(stateTaxData[],MATCH(1,(stateTaxData[stateName]=BA$1)*(stateTaxData[taxYear]=$B$4)*(stateTaxData[FilingStatusFlag]=$B$8),0),MATCH($E6,stateTaxData[#Headers],0))} -> 2425 | BB6: {=INDEX(stateTaxData[],MATCH(1,(stateTaxData[stateName]=BB$1)*(stateTaxData[taxYear]=$B$4)*(stateTaxData[FilingStatusFlag]=$B$8),0),MATCH($E6,stateTaxData[#Headers],0))} -> 1000 | BC6: {=INDEX(stateTaxData[],MATCH(1,(stateTaxData[stateName]=BC$1)*(stateTaxData[taxYear]=$B$4)*(stateTaxData[FilingStatusFlag]=$B$8),0),MATCH($E6,stateTaxData[#Headers],0))} -> 40 | BD6: {=INDEX(stateTaxData[],MATCH(1,(stateTaxData[stateName]=BD$1)*(stateTaxData[taxYear]=$B$4)*(stateTaxData[FilingStatusFlag]=$B$8),0),MATCH($E6,stateTaxData[#Headers],0))} -> 2250 | BE6: {=INDEX(stateTaxData[],MATCH(1,(stateTaxData[stateName]=BE$1)*(stateTaxData[taxYear]=$B$4)*(stateTaxData[FilingStatusFlag]=$B$8),0),MATCH($E6,stateTaxData[#Headers],0))} -> 0 | BF6: {=INDEX(stateTaxData[],MATCH(1,(stateTaxData[stateName]=BF$1)*(stateTaxData[taxYear]=$B$4)*(stateTaxData[FilingStatusFlag]=$B$8),0),MATCH($E6,stateTaxData[#Headers],0))} -> 1000 | BH6: {=INDEX(stateTaxData[],MATCH(1,(stateTaxData[stateName]=BH$1)*(stateTaxData[taxYear]=$B$4)*(stateTaxData[FilingStatusFlag]=$B$8),0),MATCH($E6,stateTaxData[#Headers],0))} -> 300 | BJ6: {=INDEX(stateTaxData[],MATCH(1,(stateTaxData[stateName]=BJ$1)*(stateTaxData[taxYear]=$B$4)*(stateTaxData[FilingStatusFlag]=$B$8),0),MATCH($E6,stateTaxData[#Headers],0))} -> 3200 | BK6: {=INDEX(stateTaxData[],MATCH(1,(stateTaxData[stateName]=BK$1)*(stateTaxData[taxYear]=$B$4)*(stateTaxData[FilingStatusFlag]=$B$8),0),MATCH($E6,stateTaxData[#Headers],0))} -> 1000 | BL6: {=INDEX(stateTaxData[],MATCH(1,(stateTaxData[stateName]=BL$1)*(stateTaxData[taxYear]=$B$4)*(stateTaxData[FilingStatusFlag]=$B$8),0),MATCH($E6,stateTaxData[#Headers],0))} -> 5400 | BN6: {=INDEX(stateTaxData[],MATCH(1,(stateTaxData[stateName]=BN$1)*(stateTaxData[taxYear]=$B$4)*(stateTaxData[FilingStatusFlag]=$B$8),0),MATCH($E6,stateTaxData[#Headers],0))} -> 4800 | BO6: {=INDEX(stateTaxData[],MATCH(1,(stateTaxData[stateName]=BO$1)*(stateTaxData[taxYear]=$B$4)*(stateTaxData[FilingStatusFlag]=$B$8),0),MATCH($E6,stateTaxData[#Headers],0))} -> 1500 | BQ6: {=INDEX(stateTaxData[],MATCH(1,(stateTaxData[stateName]=BQ$1)*(stateTaxData[taxYear]=$B$4)*(stateTaxData[FilingStatusFlag]=$B$8),0),MATCH($E6,stateTaxData[#Headers],0))} -> 0 | BT6: {=INDEX(stateTaxData[],MATCH(1,(stateTaxData[stateName]=BT$1)*(stateTaxData[taxYear]=$B$4)*(stateTaxData[FilingStatusFlag]=$B$8),0),MATCH($E6,stateTaxData[#Headers],0))} -> 2960 | BU6: {=INDEX(stateTaxData[],MATCH(1,(stateTaxData[stateName]=BU$1)*(stateTaxData[taxYear]=$B$4)*(stateTaxData[FilingStatusFlag]=$B$8),0),MATCH($E6,stateTaxData[#Headers],0))} -> 157 | BV6: {=INDEX(stateTaxData[],MATCH(1,(stateTaxData[stateName]=BV$1)*(stateTaxData[taxYear]=$B$4)*(stateTaxData[FilingStatusFlag]=$B$8),0),MATCH($E6,stateTaxData[#Headers],0))} -> 0 | BW6: {=INDEX(stateTaxData[],MATCH(1,(stateTaxData[stateName]=BW$1)*(stateTaxData[taxYear]=$B$4)*(stateTaxData[FilingStatusFlag]=$B$8),0),MATCH($E6,stateTaxData[#Headers],0))} -> 0 | BX6: {=INDEX(stateTaxData[],MATCH(1,(stateTaxData[stateName]=BX$1)*(stateTaxData[taxYear]=$B$4)*(stateTaxData[FilingStatusFlag]=$B$8),0),MATCH($E6,stateTaxData[#Headers],0))} -> 1500 | BY6: {=INDEX(stateTaxData[],MATCH(1,(stateTaxData[stateName]=BY$1)*(stateTaxData[taxYear]=$B$4)*(stateTaxData[FilingStatusFlag]=$B$8),0),MATCH($E6,stateTaxData[#Headers],0))} -> 4000 | BZ6: {=INDEX(stateTaxData[],MATCH(1,(stateTaxData[stateName]=BZ$1)*(stateTaxData[taxYear]=$B$4)*(stateTaxData[FilingStatusFlag]=$B$8),0),MATCH($E6,stateTaxData[#Headers],0))} -> 1000 | CA6: {=INDEX(stateTaxData[],MATCH(1,(stateTaxData[stateName]=CA$1)*(stateTaxData[taxYear]=$B$4)*(stateTaxData[FilingStatusFlag]=$B$8),0),MATCH($E6,stateTaxData[#Headers],0))} -> 0 | CC6: {=INDEX(stateTaxData[],MATCH(1,(stateTaxData[stateName]=CC$1)*(stateTaxData[taxYear]=$B$4)*(stateTaxData[FilingStatusFlag]=$B$8),0),MATCH($E6,stateTaxData[#Headers],0))} -> 0 | CE6: {=INDEX(stateTaxData[],MATCH(1,(stateTaxData[stateName]=CE$1)*(stateTaxData[taxYear]=$B$4)*(stateTaxData[FilingStatusFlag]=$B$8),0),MATCH($E6,stateTaxData[#Headers],0))} -> 2400 | CF6: {=INDEX(stateTaxData[],MATCH(1,(stateTaxData[stateName]=CF$1)*(stateTaxData[taxYear]=$B$4)*(stateTaxData[FilingStatusFlag]=$B$8),0),MATCH($E6,stateTaxData[#Headers],0))} -> 1000 | CH6: {=INDEX(stateTaxData[],MATCH(1,(stateTaxData[stateName]=CH$1)*(stateTaxData[taxYear]=$B$4)*(stateTaxData[FilingStatusFlag]=$B$8),0),MATCH($E6,stateTaxData[#Headers],0))} -> 236 | CI6: {=INDEX(stateTaxData[],MATCH(1,(stateTaxData[stateName]=CI$1)*(stateTaxData[taxYear]=$B$4)*(stateTaxData[FilingStatusFlag]=$B$8),0),MATCH($E6,stateTaxData[#Headers],0))} -> 0 | CK6: {=INDEX(stateTaxData[],MATCH(1,(stateTaxData[stateName]=CK$1)*(stateTaxData[taxYear]=$B$4)*(stateTaxData[FilingStatusFlag]=$B$8),0),MATCH($E6,stateTaxData[#Headers],0))} -> 4700 | CL6: {=INDEX(stateTaxData[],MATCH(1,(stateTaxData[stateName]=CL$1)*(stateTaxData[taxYear]=$B$4)*(stateTaxData[FilingStatusFlag]=$B$8),0),MATCH($E6,stateTaxData[#Headers],0))} -> 4610 | CN6: {=INDEX(stateTaxData[],MATCH(1,(stateTaxData[stateName]=CN$1)*(stateTaxData[taxYear]=$B$4)*(stateTaxData[FilingStatusFlag]=$B$8),0),MATCH($E6,stateTaxData[#Headers],0))} -> 0 | CO6: {=INDEX(stateTaxData[],MATCH(1,(stateTaxData[stateName]=CO$1)*(stateTaxData[taxYear]=$B$4)*(stateTaxData[FilingStatusFlag]=$B$8),0),MATCH($E6,stateTaxData[#Headers],0))} -> 0 | CP6: {=INDEX(stateTaxData[],MATCH(1,(stateTaxData[stateName]=CP$1)*(stateTaxData[taxYear]=$B$4)*(stateTaxData[FilingStatusFlag]=$B$8),0),MATCH($E6,stateTaxData[#Headers],0))} -> 0 | CR6: 0 | CU6: {=INDEX(stateTaxData[],MATCH(1,(stateTaxData[stateName]=CU$1)*(stateTaxData[taxYear]=$B$4)*(stateTaxData[FilingStatusFlag]=$B$8),0),MATCH($E6,stateTaxData[#Headers],0))} -> 4500 | CV6: {=INDEX(stateTaxData[],MATCH(1,(stateTaxData[stateName]=CV$1)*(stateTaxData[taxYear]=$B$4)*(stateTaxData[FilingStatusFlag]=$B$8),0),MATCH($E6,stateTaxData[#Headers],0))} -> 930 | CW6: {=INDEX(stateTaxData[],MATCH(1,(stateTaxData[stateName]=CW$1)*(stateTaxData[taxYear]=$B$4)*(stateTaxData[FilingStatusFlag]=$B$8),0),MATCH($E6,stateTaxData[#Headers],0))} -> 0 | CX6: {=INDEX(stateTaxData[],MATCH(1,(stateTaxData[stateName]=CX$1)*(stateTaxData[taxYear]=$B$4)*(stateTaxData[FilingStatusFlag]=$B$8),0),MATCH($E6,stateTaxData[#Headers],0))} -> 2000 | DB6: {=INDEX(stateTaxData[],MATCH(1,(stateTaxData[stateName]=DB$1)*(stateTaxData[taxYear]=$B$4)*(stateTaxData[FilingStatusFlag]=$B$8),0),MATCH($E6,stateTaxData[#Headers],0))} -> 700 | DC6: {=INDEX(stateTaxData[],MATCH(1,(stateTaxData[stateName]=DC$1)*(stateTaxData[taxYear]=$B$4)*(stateTaxData[FilingStatusFlag]=$B$8),0),MATCH($E6,stateTaxData[#Headers],0))} -> 0 | DD6: =ROUND(AVERAGE(AD6,AF6,AH6,AL6,AO6,AP6,AR6,AS6,AT6,AU6,AV6,AX6,AY6,BA6,BB6,BC6,BD6,BE6,BF6,BH6,BJ6,BK6,BL6,BN6,BO6,BQ6,BT6,BU6,BV6,BW6,BX6,BY6,BZ6,CA6,CC6,CE6,CF6,CH6,CI6,CK6,CL6,CN6,CO6,CP6,CR6,CU6,CV6,CW6,CX6,DB6,DC6),0) -> 1165 | DW6: 1 | EC6: 0.5 | ED6: 0.4 | EE6: 0.045 | EF6: 0.55 | EI6: 0.4 | EK6: 0.2 | EL6: 0.1 | EM6: 0.15 | EN6: 0.17 | EP6: 0.05 | EQ6: 0.25 | ER6: 0.45 | ES6: 0.3 | ET6: 0.3 | EU6: 0.04 | EW6: 0.1 | EX6: 0.1 | EY6: 0.1 | FB6: 0.4 | FC6: 0.25 | FD6: 0.3 | FG6: 0.3 | FH6: 0.05 | FI6: 0.09 | FK6: 0.16 | FL6: 1.25 | FP6: 0.2 | FQ6: 0.38 | FR6: 0.2 | FU6: 0.04
A7: Tax Filing Status | B7: ='Final Results'!B8 -> Single | D7: Start Phase Out | E7: DependExemptionAsCredit | F7: Per Income Increment | M7: {=INDEX(CTCFactors[],MATCH(1,(CTCFactors[Name]=$B$8)*(CTCFactors[Phaseout Phase]=1)*(CTCFactors[Year]=$B$4),0),MATCH("Income Increment for Phaseout Decrease",CTCFactors[#Headers],0))} -> 1000 | S7: {=_xlfn.IFNA(INDEX(EITCPhaseOut[],MATCH(1,(EITCPhaseOut[Status]=$B$8)*(EITCPhaseOut[Name]="Start Phase Out")*(EITCPhaseOut[Children]=$B$14),0),MATCH($B$4,VALUE(EITCPhaseOut[#Headers]),0)),0)} -> 9800 | W7: Oregon | Y7: =VLOOKUP(W7,Weights,2,FALSE) -> 218000 | AD7: {=INDEX(stateTaxData[],MATCH(1,(stateTaxData[stateName]=AD$1)*(stateTaxData[taxYear]=$B$4)*(stateTaxData[FilingStatusFlag]=$B$8),0),MATCH($E7,stateTaxData[#Headers],0))} -> No | AF7: {=INDEX(stateTaxData[],MATCH(1,(stateTaxData[stateName]=AF$1)*(stateTaxData[taxYear]=$B$4)*(stateTaxData[FilingStatusFlag]=$B$8),0),MATCH($E7,stateTaxData[#Headers],0))} -> No | AH7: {=INDEX(stateTaxData[],MATCH(1,(stateTaxData[stateName]=AH$1)*(stateTaxData[taxYear]=$B$4)*(stateTaxData[FilingStatusFlag]=$B$8),0),MATCH($E7,stateTaxData[#Headers],0))} -> Yes | AJ7: =AK7 -> Yes | AK7: =AL7 -> Yes | AL7: {=INDEX(stateTaxData[],MATCH(1,(stateTaxData[stateName]=AL$1)*(stateTaxData[taxYear]=$B$4)*(stateTaxData[FilingStatusFlag]=$B$8),0),MATCH($E7,stateTaxData[#Headers],0))} -> Yes | AO7: {=INDEX(stateTaxData[],MATCH(1,(stateTaxData[stateName]=AO$1)*(stateTaxData[taxYear]=$B$4)*(stateTaxData[FilingStatusFlag]=$B$8),0),MATCH($E7,stateTaxData[#Headers],0))} -> Yes | AP7: {=INDEX(stateTaxData[],MATCH(1,(stateTaxData[stateName]=AP$1)*(stateTaxData[taxYear]=$B$4)*(stateTaxData[FilingStatusFlag]=$B$8),0),MATCH($E7,stateTaxData[#Headers],0))} -> No | AR7: {=INDEX(stateTaxData[],MATCH(1,(stateTaxData[stateName]=AR$1)*(stateTaxData[taxYear]=$B$4)*(stateTaxData[FilingStatusFlag]=$B$8),0),MATCH($E7,stateTaxData[#Headers],0))} -> No | AS7: {=INDEX(stateTaxData[],MATCH(1,(stateTaxData[stateName]=AS$1)*(stateTaxData[taxYear]=$B$4)*(stateTaxData[FilingStatusFlag]=$B$8),0),MATCH($E7,stateTaxData[#Headers],0))} -> Yes | AT7: {=INDEX(stateTaxData[],MATCH(1,(stateTaxData[stateName]=AT$1)*(stateTaxData[taxYear]=$B$4)*(stateTaxData[FilingStatusFlag]=$B$8),0),MATCH($E7,stateTaxData[#Headers],0))} -> No | AU7: {=INDEX(stateTaxData[],MATCH(1,(stateTaxData[stateName]=AU$1)*(stateTaxData[taxYear]=$B$4)*(stateTaxData[FilingStatusFlag]=$B$8),0),MATCH($E7,stateTaxData[#Headers],0))} -> No | AV7: {=INDEX(stateTaxData[],MATCH(1,(stateTaxData[stateName]=AV$1)*(stateTaxData[taxYear]=$B$4)*(stateTaxData[FilingStatusFlag]=$B$8),0),MATCH($E7,stateTaxData[#Headers],0))} -> No | AX7: {=INDEX(stateTaxData[],MATCH(1,(stateTaxData[stateName]=AX$1)*(stateTaxData[taxYear]=$B$4)*(stateTaxData[FilingStatusFlag]=$B$8),0),MATCH($E7,stateTaxData[#Headers],0))} -> No | AY7: {=INDEX(stateTaxData[],MATCH(1,(stateTaxData[stateName]=AY$1)*(stateTaxData[taxYear]=$B$4)*(stateTaxData[FilingStatusFlag]=$B$8),0),MATCH($E7,stateTaxData[#Headers],0))} -> No | BA7: {=INDEX(stateTaxData[],MATCH(1,(stateTaxData[stateName]=BA$1)*(stateTaxData[taxYear]=$B$4)*(stateTaxData[FilingStatusFlag]=$B$8),0),MATCH($E7,stateTaxData[#Headers],0))} -> No | BB7: {=INDEX(stateTaxData[],MATCH(1,(stateTaxData[stateName]=BB$1)*(stateTaxData[taxYear]=$B$4)*(stateTaxData[FilingStatusFlag]=$B$8),0),MATCH($E7,stateTaxData[#Headers],0))} -> No | BC7: {=INDEX(stateTaxData[],MATCH(1,(stateTaxData[stateName]=BC$1)*(stateTaxData[taxYear]=$B$4)*(stateTaxData[FilingStatusFlag]=$B$8),0),MATCH($E7,stateTaxData[#Headers],0))} -> Yes | BD7: {=INDEX(stateTaxData[],MATCH(1,(stateTaxData[stateName]=BD$1)*(stateTaxData[taxYear]=$B$4)*(stateTaxData[FilingStatusFlag]=$B$8),0),MATCH($E7,stateTaxData[#Headers],0))} -> No | BE7: {=INDEX(stateTaxData[],MATCH(1,(stateTaxData[stateName]=BE$1)*(stateTaxData[taxYear]=$B$4)*(stateTaxData[FilingStatusFlag]=$B$8),0),MATCH($E7,stateTaxData[#Headers],0))} -> No | BF7: {=INDEX(stateTaxData[],MATCH(1,(stateTaxData[stateName]=BF$1)*(stateTaxData[taxYear]=$B$4)*(stateTaxData[FilingStatusFlag]=$B$8),0),MATCH($E7,stateTaxData[#Headers],0))} -> No | BH7: {=INDEX(stateTaxData[],MATCH(1,(stateTaxData[stateName]=BH$1)*(stateTaxData[taxYear]=$B$4)*(stateTaxData[FilingStatusFlag]=$B$8),0),MATCH($E7,stateTaxData[#Headers],0))} -> Yes | BJ7: {=INDEX(stateTaxData[],MATCH(1,(stateTaxData[stateName]=BJ$1)*(stateTaxData[taxYear]=$B$4)*(stateTaxData[FilingStatusFlag]=$B$8),0),MATCH($E7,stateTaxData[#Headers],0))} -> No | BK7: {=INDEX(stateTaxData[],MATCH(1,(stateTaxData[stateName]=BK$1)*(stateTaxData[taxYear]=$B$4)*(stateTaxData[FilingStatusFlag]=$B$8),0),MATCH($E7,stateTaxData[#Headers],0))} -> No | BL7: {=INDEX(stateTaxData[],MATCH(1,(stateTaxData[stateName]=BL$1)*(stateTaxData[taxYear]=$B$4)*(stateTaxData[FilingStatusFlag]=$B$8),0),MATCH($E7,stateTaxData[#Headers],0))} -> No | BN7: {=INDEX(stateTaxData[],MATCH(1,(stateTaxData[stateName]=BN$1)*(stateTaxData[taxYear]=$B$4)*(stateTaxData[FilingStatusFlag]=$B$8),0),MATCH($E7,stateTaxData[#Headers],0))} -> No | BO7: {=INDEX(stateTaxData[],MATCH(1,(stateTaxData[stateName]=BO$1)*(stateTaxData[taxYear]=$B$4)*(stateTaxData[FilingStatusFlag]=$B$8),0),MATCH($E7,stateTaxData[#Headers],0))} -> No | BQ7: {=INDEX(stateTaxData[],MATCH(1,(stateTaxData[stateName]=BQ$1)*(stateTaxData[taxYear]=$B$4)*(stateTaxData[FilingStatusFlag]=$B$8),0),MATCH($E7,stateTaxData[#Headers],0))} -> No | BT7: {=INDEX(stateTaxData[],MATCH(1,(stateTaxData[stateName]=BT$1)*(stateTaxData[taxYear]=$B$4)*(stateTaxData[FilingStatusFlag]=$B$8),0),MATCH($E7,stateTaxData[#Headers],0))} -> No | BU7: {=INDEX(stateTaxData[],MATCH(1,(stateTaxData[stateName]=BU$1)*(stateTaxData[taxYear]=$B$4)*(stateTaxData[FilingStatusFlag]=$B$8),0),MATCH($E7,stateTaxData[#Headers],0))} -> Yes | BV7: {=INDEX(stateTaxData[],MATCH(1,(stateTaxData[stateName]=BV$1)*(stateTaxData[taxYear]=$B$4)*(stateTaxData[FilingStatusFlag]=$B$8),0),MATCH($E7,stateTaxData[#Headers],0))} -> No | BW7: {=INDEX(stateTaxData[],MATCH(1,(stateTaxData[stateName]=BW$1)*(stateTaxData[taxYear]=$B$4)*(stateTaxData[FilingStatusFlag]=$B$8),0),MATCH($E7,stateTaxData[#Headers],0))} -> No | BX7: {=INDEX(stateTaxData[],MATCH(1,(stateTaxData[stateName]=BX$1)*(stateTaxData[taxYear]=$B$4)*(stateTaxData[FilingStatusFlag]=$B$8),0),MATCH($E7,stateTaxData[#Headers],0))} -> No | BY7: {=INDEX(stateTaxData[],MATCH(1,(stateTaxData[stateName]=BY$1)*(stateTaxData[taxYear]=$B$4)*(stateTaxData[FilingStatusFlag]=$B$8),0),MATCH($E7,stateTaxData[#Headers],0))} -> No | BZ7: {=INDEX(stateTaxData[],MATCH(1,(stateTaxData[stateName]=BZ$1)*(stateTaxData[taxYear]=$B$4)*(stateTaxData[FilingStatusFlag]=$B$8),0),MATCH($E7,stateTaxData[#Headers],0))} -> No | CA7: {=INDEX(stateTaxData[],MATCH(1,(stateTaxData[stateName]=CA$1)*(stateTaxData[taxYear]=$B$4)*(stateTaxData[FilingStatusFlag]=$B$8),0),MATCH($E7,stateTaxData[#Headers],0))} -> No | CC7: {=INDEX(stateTaxData[],MATCH(1,(stateTaxData[stateName]=CC$1)*(stateTaxData[taxYear]=$B$4)*(stateTaxData[FilingStatusFlag]=$B$8),0),MATCH($E7,stateTaxData[#Headers],0))} -> No | CE7: {=INDEX(stateTaxData[],MATCH(1,(stateTaxData[stateName]=CE$1)*(stateTaxData[taxYear]=$B$4)*(stateTaxData[FilingStatusFlag]=$B$8),0),MATCH($E7,stateTaxData[#Headers],0))} -> No | CF7: {=INDEX(stateTaxData[],MATCH(1,(stateTaxData[stateName]=CF$1)*(stateTaxData[taxYear]=$B$4)*(stateTaxData[FilingStatusFlag]=$B$8),0),MATCH($E7,stateTaxData[#Headers],0))} -> No | CH7: {=INDEX(stateTaxData[],MATCH(1,(stateTaxData[stateName]=CH$1)*(stateTaxData[taxYear]=$B$4)*(stateTaxData[FilingStatusFlag]=$B$8),0),MATCH($E7,stateTaxData[#Headers],0))} -> Yes | CI7: {=INDEX(stateTaxData[],MATCH(1,(stateTaxData[stateName]=CI$1)*(stateTaxData[taxYear]=$B$4)*(stateTaxData[FilingStatusFlag]=$B$8),0),MATCH($E7,stateTaxData[#Headers],0))} -> No | CK7: {=INDEX(stateTaxData[],MATCH(1,(stateTaxData[stateName]=CK$1)*(stateTaxData[taxYear]=$B$4)*(stateTaxData[FilingStatusFlag]=$B$8),0),MATCH($E7,stateTaxData[#Headers],0))} -> No | CL7: {=INDEX(stateTaxData[],MATCH(1,(stateTaxData[stateName]=CL$1)*(stateTaxData[taxYear]=$B$4)*(stateTaxData[FilingStatusFlag]=$B$8),0),MATCH($E7,stateTaxData[#Headers],0))} -> No | CN7: {=INDEX(stateTaxData[],MATCH(1,(stateTaxData[stateName]=CN$1)*(stateTaxData[taxYear]=$B$4)*(stateTaxData[FilingStatusFlag]=$B$8),0),MATCH($E7,stateTaxData[#Headers],0))} -> No | CO7: {=INDEX(stateTaxData[],MATCH(1,(stateTaxData[stateName]=CO$1)*(stateTaxData[taxYear]=$B$4)*(stateTaxData[FilingStatusFlag]=$B$8),0),MATCH($E7,stateTaxData[#Headers],0))} -> No | CP7: {=INDEX(stateTaxData[],MATCH(1,(stateTaxData[stateName]=CP$1)*(stateTaxData[taxYear]=$B$4)*(stateTaxData[FilingStatusFlag]=$B$8),0),MATCH($E7,stateTaxData[#Headers],0))} -> No | CR7: {=INDEX(stateTaxData[],MATCH(1,(stateTaxData[stateName]=CR$1)*(stateTaxData[taxYear]=$B$4)*(stateTaxData[FilingStatusFlag]=$B$8),0),MATCH($E7,stateTaxData[#Headers],0))} -> Yes | CU7: {=INDEX(stateTaxData[],MATCH(1,(stateTaxData[stateName]=CU$1)*(stateTaxData[taxYear]=$B$4)*(stateTaxData[FilingStatusFlag]=$B$8),0),MATCH($E7,stateTaxData[#Headers],0))} -> No | CV7: {=INDEX(stateTaxData[],MATCH(1,(stateTaxData[stateName]=CV$1)*(stateTaxData[taxYear]=$B$4)*(stateTaxData[FilingStatusFlag]=$B$8),0),MATCH($E7,stateTaxData[#Headers],0))} -> No | CW7: {=INDEX(stateTaxData[],MATCH(1,(stateTaxData[stateName]=CW$1)*(stateTaxData[taxYear]=$B$4)*(stateTaxData[FilingStatusFlag]=$B$8),0),MATCH($E7,stateTaxData[#Headers],0))} -> No | CX7: {=INDEX(stateTaxData[],MATCH(1,(stateTaxData[stateName]=CX$1)*(stateTaxData[taxYear]=$B$4)*(stateTaxData[FilingStatusFlag]=$B$8),0),MATCH($E7,stateTaxData[#Headers],0))} -> No | DB7: {=INDEX(stateTaxData[],MATCH(1,(stateTaxData[stateName]=DB$1)*(stateTaxData[taxYear]=$B$4)*(stateTaxData[FilingStatusFlag]=$B$8),0),MATCH($E7,stateTaxData[#Headers],0))} -> No | DC7: {=INDEX(stateTaxData[],MATCH(1,(stateTaxData[stateName]=DC$1)*(stateTaxData[taxYear]=$B$4)*(stateTaxData[FilingStatusFlag]=$B$8),0),MATCH($E7,stateTaxData[#Headers],0))} -> No | DW7: 2 | EC7: 0.5 | ED7: 0.4 | EE7: 0.045 | EF7: 0.55 | EI7: 0.4 | EK7: 0.2 | EL7: 0.1 | EM7: 0.15 | EN7: 0.17 | EP7: 0.05 | EQ7: 0.25 | ER7: 0.45 | ES7: 0.3 | ET7: 0.3 | EU7: 0.04 | EW7: 0.1 | EX7: 0.1 | EY7: 0.1 | FB7: 0.4 | FC7: 0.25 | FD7: 0.3 | FG7: 0.3 | FH7: 0.05 | FI7: 0.09 | FK7: 0.16 | FL7: 1.25 | FP7: 0.2 | FQ7: 0.38 | FR7: 0.2 | FU7: 0.11
A8: Description | B8: =VLOOKUP(B7,$A$18:$B$20,2,FALSE) -> Single | D8: Stop Credit | E8: FederalIncomeTaxDeductible | F8: Income Disregard | P8: 2500 | S8: {=_xlfn.IFNA(INDEX(EITCPhaseOut[],MATCH(1,(EITCPhaseOut[Status]=$B$8)*(EITCPhaseOut[Name]="Stop Credit")*(EITCPhaseOut[Children]=$B$14),0),MATCH($B$4,VALUE(EITCPhaseOut[#Headers]),0)),0)} -> 17640 | W8: Weight | Y8: =Y7/W2 -> 0.0096340817 | AD8: {=INDEX(stateTaxData[],MATCH(1,(stateTaxData[stateName]=AD$1)*(stateTaxData[taxYear]=$B$4)*(stateTaxData[FilingStatusFlag]=$B$8),0),MATCH($E8,stateTaxData[#Headers],0))} -> Yes | AF8: {=INDEX(stateTaxData[],MATCH(1,(stateTaxData[stateName]=AF$1)*(stateTaxData[taxYear]=$B$4)*(stateTaxData[FilingStatusFlag]=$B$8),0),MATCH($E8,stateTaxData[#Headers],0))} -> No | AH8: {=INDEX(stateTaxData[],MATCH(1,(stateTaxData[stateName]=AH$1)*(stateTaxData[taxYear]=$B$4)*(stateTaxData[FilingStatusFlag]=$B$8),0),MATCH($E8,stateTaxData[#Headers],0))} -> No | AJ8: =AK8 -> No | AK8: =AL8 -> No | AL8: {=INDEX(stateTaxData[],MATCH(1,(stateTaxData[stateName]=AL$1)*(stateTaxData[taxYear]=$B$4)*(stateTaxData[FilingStatusFlag]=$B$8),0),MATCH($E8,stateTaxData[#Headers],0))} -> No | AO8: {=INDEX(stateTaxData[],MATCH(1,(stateTaxData[stateName]=AO$1)*(stateTaxData[taxYear]=$B$4)*(stateTaxData[FilingStatusFlag]=$B$8),0),MATCH($E8,stateTaxData[#Headers],0))} -> No | AP8: {=INDEX(stateTaxData[],MATCH(1,(stateTaxData[stateName]=AP$1)*(stateTaxData[taxYear]=$B$4)*(stateTaxData[FilingStatusFlag]=$B$8),0),MATCH($E8,stateTaxData[#Headers],0))} -> No | AR8: {=INDEX(stateTaxData[],MATCH(1,(stateTaxData[stateName]=AR$1)*(stateTaxData[taxYear]=$B$4)*(stateTaxData[FilingStatusFlag]=$B$8),0),MATCH($E8,stateTaxData[#Headers],0))} -> No | AS8: {=INDEX(stateTaxData[],MATCH(1,(stateTaxData[stateName]=AS$1)*(stateTaxData[taxYear]=$B$4)*(stateTaxData[FilingStatusFlag]=$B$8),0),MATCH($E8,stateTaxData[#Headers],0))} -> No | AT8: {=INDEX(stateTaxData[],MATCH(1,(stateTaxData[stateName]=AT$1)*(stateTaxData[taxYear]=$B$4)*(stateTaxData[FilingStatusFlag]=$B$8),0),MATCH($E8,stateTaxData[#Headers],0))} -> No | AU8: {=INDEX(stateTaxData[],MATCH(1,(stateTaxData[stateName]=AU$1)*(stateTaxData[taxYear]=$B$4)*(stateTaxData[FilingStatusFlag]=$B$8),0),MATCH($E8,stateTaxData[#Headers],0))} -> No | AV8: {=INDEX(stateTaxData[],MATCH(1,(stateTaxData[stateName]=AV$1)*(stateTaxData[taxYear]=$B$4)*(stateTaxData[FilingStatusFlag]=$B$8),0),MATCH($E8,stateTaxData[#Headers],0))} -> No | AX8: {=INDEX(stateTaxData[],MATCH(1,(stateTaxData[stateName]=AX$1)*(stateTaxData[taxYear]=$B$4)*(stateTaxData[FilingStatusFlag]=$B$8),0),MATCH($E8,stateTaxData[#Headers],0))} -> No | AY8: {=INDEX(stateTaxData[],MATCH(1,(stateTaxData[stateName]=AY$1)*(stateTaxData[taxYear]=$B$4)*(stateTaxData[FilingStatusFlag]=$B$8),0),MATCH($E8,stateTaxData[#Headers],0))} -> No | BA8: {=INDEX(stateTaxData[],MATCH(1,(stateTaxData[stateName]=BA$1)*(stateTaxData[taxYear]=$B$4)*(stateTaxData[FilingStatusFlag]=$B$8),0),MATCH($E8,stateTaxData[#Headers],0))} -> No | BB8: {=INDEX(stateTaxData[],MATCH(1,(stateTaxData[stateName]=BB$1)*(stateTaxData[taxYear]=$B$4)*(stateTaxData[FilingStatusFlag]=$B$8),0),MATCH($E8,stateTaxData[#Headers],0))} -> No | BC8: {=INDEX(stateTaxData[],MATCH(1,(stateTaxData[stateName]=BC$1)*(stateTaxData[taxYear]=$B$4)*(stateTaxData[FilingStatusFlag]=$B$8),0),MATCH($E8,stateTaxData[#Headers],0))} -> Yes | BD8: {=INDEX(stateTaxData[],MATCH(1,(stateTaxData[stateName]=BD$1)*(stateTaxData[taxYear]=$B$4)*(stateTaxData[FilingStatusFlag]=$B$8),0),MATCH($E8,stateTaxData[#Headers],0))} -> No | BE8: {=INDEX(stateTaxData[],MATCH(1,(stateTaxData[stateName]=BE$1)*(stateTaxData[taxYear]=$B$4)*(stateTaxData[FilingStatusFlag]=$B$8),0),MATCH($E8,stateTaxData[#Headers],0))} -> No | BF8: {=INDEX(stateTaxData[],MATCH(1,(stateTaxData[stateName]=BF$1)*(stateTaxData[taxYear]=$B$4)*(stateTaxData[FilingStatusFlag]=$B$8),0),MATCH($E8,stateTaxData[#Headers],0))} -> No | BH8: {=INDEX(stateTaxData[],MATCH(1,(stateTaxData[stateName]=BH$1)*(stateTaxData[taxYear]=$B$4)*(stateTaxData[FilingStatusFlag]=$B$8),0),MATCH($E8,stateTaxData[#Headers],0))} -> No | BJ8: {=INDEX(stateTaxData[],MATCH(1,(stateTaxData[stateName]=BJ$1)*(stateTaxData[taxYear]=$B$4)*(stateTaxData[FilingStatusFlag]=$B$8),0),MATCH($E8,stateTaxData[#Headers],0))} -> No | BK8: {=INDEX(stateTaxData[],MATCH(1,(stateTaxData[stateName]=BK$1)*(stateTaxData[taxYear]=$B$4)*(stateTaxData[FilingStatusFlag]=$B$8),0),MATCH($E8,stateTaxData[#Headers],0))} -> No | BL8: {=INDEX(stateTaxData[],MATCH(1,(stateTaxData[stateName]=BL$1)*(stateTaxData[taxYear]=$B$4)*(stateTaxData[FilingStatusFlag]=$B$8),0),MATCH($E8,stateTaxData[#Headers],0))} -> No | BN8: {=INDEX(stateTaxData[],MATCH(1,(stateTaxData[stateName]=BN$1)*(stateTaxData[taxYear]=$B$4)*(stateTaxData[FilingStatusFlag]=$B$8),0),MATCH($E8,stateTaxData[#Headers],0))} -> No | BO8: {=INDEX(stateTaxData[],MATCH(1,(stateTaxData[stateName]=BO$1)*(stateTaxData[taxYear]=$B$4)*(stateTaxData[FilingStatusFlag]=$B$8),0),MATCH($E8,stateTaxData[#Headers],0))} -> No | BQ8: {=INDEX(stateTaxData[],MATCH(1,(stateTaxData[stateName]=BQ$1)*(stateTaxData[taxYear]=$B$4)*(stateTaxData[FilingStatusFlag]=$B$8),0),MATCH($E8,stateTaxData[#Headers],0))} -> Yes | BT8: {=INDEX(stateTaxData[],MATCH(1,(stateTaxData[stateName]=BT$1)*(stateTaxData[taxYear]=$B$4)*(stateTaxData[FilingStatusFlag]=$B$8),0),MATCH($E8,stateTaxData[#Headers],0))} -> Yes | BU8: {=INDEX(stateTaxData[],MATCH(1,(stateTaxData[stateName]=BU$1)*(stateTaxData[taxYear]=$B$4)*(stateTaxData[FilingStatusFlag]=$B$8),0),MATCH($E8,stateTaxData[#Headers],0))} -> No | BV8: {=INDEX(stateTaxData[],MATCH(1,(stateTaxData[stateName]=BV$1)*(stateTaxData[taxYear]=$B$4)*(stateTaxData[FilingStatusFlag]=$B$8),0),MATCH($E8,stateTaxData[#Headers],0))} -> No | BW8: {=INDEX(stateTaxData[],MATCH(1,(stateTaxData[stateName]=BW$1)*(stateTaxData[taxYear]=$B$4)*(stateTaxData[FilingStatusFlag]=$B$8),0),MATCH($E8,stateTaxData[#Headers],0))} -> No | BX8: {=INDEX(stateTaxData[],MATCH(1,(stateTaxData[stateName]=BX$1)*(stateTaxData[taxYear]=$B$4)*(stateTaxData[FilingStatusFlag]=$B$8),0),MATCH($E8,stateTaxData[#Headers],0))} -> No | BY8: {=INDEX(stateTaxData[],MATCH(1,(stateTaxData[stateName]=BY$1)*(stateTaxData[taxYear]=$B$4)*(stateTaxData[FilingStatusFlag]=$B$8),0),MATCH($E8,stateTaxData[#Headers],0))} -> No | BZ8: {=INDEX(stateTaxData[],MATCH(1,(stateTaxData[stateName]=BZ$1)*(stateTaxData[taxYear]=$B$4)*(stateTaxData[FilingStatusFlag]=$B$8),0),MATCH($E8,stateTaxData[#Headers],0))} -> No | CA8: {=INDEX(stateTaxData[],MATCH(1,(stateTaxData[stateName]=CA$1)*(stateTaxData[taxYear]=$B$4)*(stateTaxData[FilingStatusFlag]=$B$8),0),MATCH($E8,stateTaxData[#Headers],0))} -> No | CC8: {=INDEX(stateTaxData[],MATCH(1,(stateTaxData[stateName]=CC$1)*(stateTaxData[taxYear]=$B$4)*(stateTaxData[FilingStatusFlag]=$B$8),0),MATCH($E8,stateTaxData[#Headers],0))} -> No | CE8: {=INDEX(stateTaxData[],MATCH(1,(stateTaxData[stateName]=CE$1)*(stateTaxData[taxYear]=$B$4)*(stateTaxData[FilingStatusFlag]=$B$8),0),MATCH($E8,stateTaxData[#Headers],0))} -> No | CF8: {=INDEX(stateTaxData[],MATCH(1,(stateTaxData[stateName]=CF$1)*(stateTaxData[taxYear]=$B$4)*(stateTaxData[FilingStatusFlag]=$B$8),0),MATCH($E8,stateTaxData[#Headers],0))} -> No | CH8: {=INDEX(stateTaxData[],MATCH(1,(stateTaxData[stateName]=CH$1)*(stateTaxData[taxYear]=$B$4)*(stateTaxData[FilingStatusFlag]=$B$8),0),MATCH($E8,stateTaxData[#Headers],0))} -> Yes | CI8: {=INDEX(stateTaxData[],MATCH(1,(stateTaxData[stateName]=CI$1)*(stateTaxData[taxYear]=$B$4)*(stateTaxData[FilingStatusFlag]=$B$8),0),MATCH($E8,stateTaxData[#Headers],0))} -> No | CK8: {=INDEX(stateTaxData[],MATCH(1,(stateTaxData[stateName]=CK$1)*(stateTaxData[taxYear]=$B$4)*(stateTaxData[FilingStatusFlag]=$B$8),0),MATCH($E8,stateTaxData[#Headers],0))} -> No | CL8: {=INDEX(stateTaxData[],MATCH(1,(stateTaxData[stateName]=CL$1)*(stateTaxData[taxYear]=$B$4)*(stateTaxData[FilingStatusFlag]=$B$8),0),MATCH($E8,stateTaxData[#Headers],0))} -> No | CN8: {=INDEX(stateTaxData[],MATCH(1,(stateTaxData[stateName]=CN$1)*(stateTaxData[taxYear]=$B$4)*(stateTaxData[FilingStatusFlag]=$B$8),0),MATCH($E8,stateTaxData[#Headers],0))} -> No | CO8: {=INDEX(stateTaxData[],MATCH(1,(stateTaxData[stateName]=CO$1)*(stateTaxData[taxYear]=$B$4)*(stateTaxData[FilingStatusFlag]=$B$8),0),MATCH($E8,stateTaxData[#Headers],0))} -> No | CP8: {=INDEX(stateTaxData[],MATCH(1,(stateTaxData[stateName]=CP$1)*(stateTaxData[taxYear]=$B$4)*(stateTaxData[FilingStatusFlag]=$B$8),0),MATCH($E8,stateTaxData[#Headers],0))} -> No | CR8: {=INDEX(stateTaxData[],MATCH(1,(stateTaxData[stateName]=CR$1)*(stateTaxData[taxYear]=$B$4)*(stateTaxData[FilingStatusFlag]=$B$8),0),MATCH($E8,stateTaxData[#Headers],0))} -> No | CU8: {=INDEX(stateTaxData[],MATCH(1,(stateTaxData[stateName]=CU$1)*(stateTaxData[taxYear]=$B$4)*(stateTaxData[FilingStatusFlag]=$B$8),0),MATCH($E8,stateTaxData[#Headers],0))} -> No | CV8: {=INDEX(stateTaxData[],MATCH(1,(stateTaxData[stateName]=CV$1)*(stateTaxData[taxYear]=$B$4)*(stateTaxData[FilingStatusFlag]=$B$8),0),MATCH($E8,stateTaxData[#Headers],0))} -> No | CW8: {=INDEX(stateTaxData[],MATCH(1,(stateTaxData[stateName]=CW$1)*(stateTaxData[taxYear]=$B$4)*(stateTaxData[FilingStatusFlag]=$B$8),0),MATCH($E8,stateTaxData[#Headers],0))} -> No | CX8: {=INDEX(stateTaxData[],MATCH(1,(stateTaxData[stateName]=CX$1)*(stateTaxData[taxYear]=$B$4)*(stateTaxData[FilingStatusFlag]=$B$8),0),MATCH($E8,stateTaxData[#Headers],0))} -> No | DB8: {=INDEX(stateTaxData[],MATCH(1,(stateTaxData[stateName]=DB$1)*(stateTaxData[taxYear]=$B$4)*(stateTaxData[FilingStatusFlag]=$B$8),0),MATCH($E8,stateTaxData[#Headers],0))} -> No | DC8: {=INDEX(stateTaxData[],MATCH(1,(stateTaxData[stateName]=DC$1)*(stateTaxData[taxYear]=$B$4)*(stateTaxData[FilingStatusFlag]=$B$8),0),MATCH($E8,stateTaxData[#Headers],0))} -> No | DW8: 3 | EC8: 0.5 | ED8: 0.4 | EE8: 0.045 | EF8: 0.55 | EI8: 0.4 | EK8: 0.2 | EL8: 0.1 | EM8: 0.15 | EN8: 0.17 | EP8: 0.05 | EQ8: 0.25 | ER8: 0.45 | ES8: 0.3 | ET8: 0.3 | EU8: 0.04 | EW8: 0.1 | EX8: 0.1 | EY8: 0.1 | FB8: 0.4 | FC8: 0.25 | FD8: 0.3 | FG8: 0.3 | FH8: 0.05 | FI8: 0.09 | FK8: 0.16 | FL8: 1.25 | FP8: 0.2 | FQ8: 0.38 | FR8: 0.2 | FU8: 0.34
E9: FedIncTaxLimit | F9: Rate applied to earnings | P9: 0.15 | W9: Percent | Y9: 0.03 | AD9: {=INDEX(stateTaxData[],MATCH(1,(stateTaxData[stateName]=AD$1)*(stateTaxData[taxYear]=$B$4)*(stateTaxData[FilingStatusFlag]=$B$8),0),MATCH($E9,stateTaxData[#Headers],0))} -> 0 | AF9: {=INDEX(stateTaxData[],MATCH(1,(stateTaxData[stateName]=AF$1)*(stateTaxData[taxYear]=$B$4)*(stateTaxData[FilingStatusFlag]=$B$8),0),MATCH($E9,stateTaxData[#Headers],0))} -> 0 | AH9: {=INDEX(stateTaxData[],MATCH(1,(stateTaxData[stateName]=AH$1)*(stateTaxData[taxYear]=$B$4)*(stateTaxData[FilingStatusFlag]=$B$8),0),MATCH($E9,stateTaxData[#Headers],0))} -> 0 | AJ9: =AK9 -> 0 | AK9: =AL9 -> 0 | AL9: {=INDEX(stateTaxData[],MATCH(1,(stateTaxData[stateName]=AL$1)*(stateTaxData[taxYear]=$B$4)*(stateTaxData[FilingStatusFlag]=$B$8),0),MATCH($E9,stateTaxData[#Headers],0))} -> 0 | AO9: {=INDEX(stateTaxData[],MATCH(1,(stateTaxData[stateName]=AO$1)*(stateTaxData[taxYear]=$B$4)*(stateTaxData[FilingStatusFlag]=$B$8),0),MATCH($E9,stateTaxData[#Headers],0))} -> 0 | AP9: {=INDEX(stateTaxData[],MATCH(1,(stateTaxData[stateName]=AP$1)*(stateTaxData[taxYear]=$B$4)*(stateTaxData[FilingStatusFlag]=$B$8),0),MATCH($E9,stateTaxData[#Headers],0))} -> 0 | AR9: {=INDEX(stateTaxData[],MATCH(1,(stateTaxData[stateName]=AR$1)*(stateTaxData[taxYear]=$B$4)*(stateTaxData[FilingStatusFlag]=$B$8),0),MATCH($E9,stateTaxData[#Headers],0))} -> 0 | AS9: {=INDEX(stateTaxData[],MATCH(1,(stateTaxData[stateName]=AS$1)*(stateTaxData[taxYear]=$B$4)*(stateTaxData[FilingStatusFlag]=$B$8),0),MATCH($E9,stateTaxData[#Headers],0))} -> 0 | AT9: {=INDEX(stateTaxData[],MATCH(1,(stateTaxData[stateName]=AT$1)*(stateTaxData[taxYear]=$B$4)*(stateTaxData[FilingStatusFlag]=$B$8),0),MATCH($E9,stateTaxData[#Headers],0))} -> 0 | AU9: {=INDEX(stateTaxData[],MATCH(1,(stateTaxData[stateName]=AU$1)*(stateTaxData[taxYear]=$B$4)*(stateTaxData[FilingStatusFlag]=$B$8),0),MATCH($E9,stateTaxData[#Headers],0))} -> 0 | AV9: {=INDEX(stateTaxData[],MATCH(1,(stateTaxData[stateName]=AV$1)*(stateTaxData[taxYear]=$B$4)*(stateTaxData[FilingStatusFlag]=$B$8),0),MATCH($E9,stateTaxData[#Headers],0))} -> 0 | AX9: {=INDEX(stateTaxData[],MATCH(1,(stateTaxData[stateName]=AX$1)*(stateTaxData[taxYear]=$B$4)*(stateTaxData[FilingStatusFlag]=$B$8),0),MATCH($E9,stateTaxData[#Headers],0))} -> 0 | AY9: {=INDEX(stateTaxData[],MATCH(1,(stateTaxData[stateName]=AY$1)*(stateTaxData[taxYear]=$B$4)*(stateTaxData[FilingStatusFlag]=$B$8),0),MATCH($E9,stateTaxData[#Headers],0))} -> 0 | BA9: {=INDEX(stateTaxData[],MATCH(1,(stateTaxData[stateName]=BA$1)*(stateTaxData[taxYear]=$B$4)*(stateTaxData[FilingStatusFlag]=$B$8),0),MATCH($E9,stateTaxData[#Headers],0))} -> 0 | BB9: {=INDEX(stateTaxData[],MATCH(1,(stateTaxData[stateName]=BB$1)*(stateTaxData[taxYear]=$B$4)*(stateTaxData[FilingStatusFlag]=$B$8),0),MATCH($E9,stateTaxData[#Headers],0))} -> 0 | BC9: {=INDEX(stateTaxData[],MATCH(1,(stateTaxData[stateName]=BC$1)*(stateTaxData[taxYear]=$B$4)*(stateTaxData[FilingStatusFlag]=$B$8),0),MATCH($E9,stateTaxData[#Headers],0))} -> 0 | BD9: {=INDEX(stateTaxData[],MATCH(1,(stateTaxData[stateName]=BD$1)*(stateTaxData[taxYear]=$B$4)*(stateTaxData[FilingStatusFlag]=$B$8),0),MATCH($E9,stateTaxData[#Headers],0))} -> 0 | BE9: {=INDEX(stateTaxData[],MATCH(1,(stateTaxData[stateName]=BE$1)*(stateTaxData[taxYear]=$B$4)*(stateTaxData[FilingStatusFlag]=$B$8),0),MATCH($E9,stateTaxData[#Headers],0))} -> 0 | BF9: {=INDEX(stateTaxData[],MATCH(1,(stateTaxData[stateName]=BF$1)*(stateTaxData[taxYear]=$B$4)*(stateTaxData[FilingStatusFlag]=$B$8),0),MATCH($E9,stateTaxData[#Headers],0))} -> 0 | BH9: {=INDEX(stateTaxData[],MATCH(1,(stateTaxData[stateName]=BH$1)*(stateTaxData[taxYear]=$B$4)*(stateTaxData[FilingStatusFlag]=$B$8),0),MATCH($E9,stateTaxData[#Headers],0))} -> 0 | BJ9: {=INDEX(stateTaxData[],MATCH(1,(stateTaxData[stateName]=BJ$1)*(stateTaxData[taxYear]=$B$4)*(stateTaxData[FilingStatusFlag]=$B$8),0),MATCH($E9,stateTaxData[#Headers],0))} -> 0 | BK9: {=INDEX(stateTaxData[],MATCH(1,(stateTaxData[stateName]=BK$1)*(stateTaxData[taxYear]=$B$4)*(stateTaxData[FilingStatusFlag]=$B$8),0),MATCH($E9,stateTaxData[#Headers],0))} -> 0 | BL9: {=INDEX(stateTaxData[],MATCH(1,(stateTaxData[stateName]=BL$1)*(stateTaxData[taxYear]=$B$4)*(stateTaxData[FilingStatusFlag]=$B$8),0),MATCH($E9,stateTaxData[#Headers],0))} -> 0 | BN9: {=INDEX(stateTaxData[],MATCH(1,(stateTaxData[stateName]=BN$1)*(stateTaxData[taxYear]=$B$4)*(stateTaxData[FilingStatusFlag]=$B$8),0),MATCH($E9,stateTaxData[#Headers],0))} -> 0 | BO9: {=INDEX(stateTaxData[],MATCH(1,(stateTaxData[stateName]=BO$1)*(stateTaxData[taxYear]=$B$4)*(stateTaxData[FilingStatusFlag]=$B$8),0),MATCH($E9,stateTaxData[#Headers],0))} -> 0 | BQ9: {=INDEX(stateTaxData[],MATCH(1,(stateTaxData[stateName]=BQ$1)*(stateTaxData[taxYear]=$B$4)*(stateTaxData[FilingStatusFlag]=$B$8),0),MATCH($E9,stateTaxData[#Headers],0))} -> 5000 | BT9: {=INDEX(stateTaxData[],MATCH(1,(stateTaxData[stateName]=BT$1)*(stateTaxData[taxYear]=$B$4)*(stateTaxData[FilingStatusFlag]=$B$8),0),MATCH($E9,stateTaxData[#Headers],0))} -> 5000 | BU9: {=INDEX(stateTaxData[],MATCH(1,(stateTaxData[stateName]=BU$1)*(stateTaxData[taxYear]=$B$4)*(stateTaxData[FilingStatusFlag]=$B$8),0),MATCH($E9,stateTaxData[#Headers],0))} -> 0 | BV9: {=INDEX(stateTaxData[],MATCH(1,(stateTaxData[stateName]=BV$1)*(stateTaxData[taxYear]=$B$4)*(stateTaxData[FilingStatusFlag]=$B$8),0),MATCH($E9,stateTaxData[#Headers],0))} -> 0 | BW9: {=INDEX(stateTaxData[],MATCH(1,(stateTaxData[stateName]=BW$1)*(stateTaxData[taxYear]=$B$4)*(stateTaxData[FilingStatusFlag]=$B$8),0),MATCH($E9,stateTaxData[#Headers],0))} -> 0 | BX9: {=INDEX(stateTaxData[],MATCH(1,(stateTaxData[stateName]=BX$1)*(stateTaxData[taxYear]=$B$4)*(stateTaxData[FilingStatusFlag]=$B$8),0),MATCH($E9,stateTaxData[#Headers],0))} -> 0 | BY9: {=INDEX(stateTaxData[],MATCH(1,(stateTaxData[stateName]=BY$1)*(stateTaxData[taxYear]=$B$4)*(stateTaxData[FilingStatusFlag]=$B$8),0),MATCH($E9,stateTaxData[#Headers],0))} -> 0 | BZ9: {=INDEX(stateTaxData[],MATCH(1,(stateTaxData[stateName]=BZ$1)*(stateTaxData[taxYear]=$B$4)*(stateTaxData[FilingStatusFlag]=$B$8),0),MATCH($E9,stateTaxData[#Headers],0))} -> 0 | CA9: {=INDEX(stateTaxData[],MATCH(1,(stateTaxData[stateName]=CA$1)*(stateTaxData[taxYear]=$B$4)*(stateTaxData[FilingStatusFlag]=$B$8),0),MATCH($E9,stateTaxData[#Headers],0))} -> 0 | CC9: {=INDEX(stateTaxData[],MATCH(1,(stateTaxData[stateName]=CC$1)*(stateTaxData[taxYear]=$B$4)*(stateTaxData[FilingStatusFlag]=$B$8),0),MATCH($E9,stateTaxData[#Headers],0))} -> 0 | CE9: {=INDEX(stateTaxData[],MATCH(1,(stateTaxData[stateName]=CE$1)*(stateTaxData[taxYear]=$B$4)*(stateTaxData[FilingStatusFlag]=$B$8),0),MATCH($E9,stateTaxData[#Headers],0))} -> 0 | CF9: {=INDEX(stateTaxData[],MATCH(1,(stateTaxData[stateName]=CF$1)*(stateTaxData[taxYear]=$B$4)*(stateTaxData[FilingStatusFlag]=$B$8),0),MATCH($E9,stateTaxData[#Headers],0))} -> 0 | CH9: {=INDEX(stateTaxData[],MATCH(1,(stateTaxData[stateName]=CH$1)*(stateTaxData[taxYear]=$B$4)*(stateTaxData[FilingStatusFlag]=$B$8),0),MATCH($E9,stateTaxData[#Headers],0))} -> 7800 | CI9: {=INDEX(stateTaxData[],MATCH(1,(stateTaxData[stateName]=CI$1)*(stateTaxData[taxYear]=$B$4)*(stateTaxData[FilingStatusFlag]=$B$8),0),MATCH($E9,stateTaxData[#Headers],0))} -> 0 | CK9: {=INDEX(stateTaxData[],MATCH(1,(stateTaxData[stateName]=CK$1)*(stateTaxData[taxYear]=$B$4)*(stateTaxData[FilingStatusFlag]=$B$8),0),MATCH($E9,stateTaxData[#Headers],0))} -> 0 | CL9: {=INDEX(stateTaxData[],MATCH(1,(stateTaxData[stateName]=CL$1)*(stateTaxData[taxYear]=$B$4)*(stateTaxData[FilingStatusFlag]=$B$8),0),MATCH($E9,stateTaxData[#Headers],0))} -> 0 | CN9: {=INDEX(stateTaxData[],MATCH(1,(stateTaxData[stateName]=CN$1)*(stateTaxData[taxYear]=$B$4)*(stateTaxData[FilingStatusFlag]=$B$8),0),MATCH($E9,stateTaxData[#Headers],0))} -> 0 | CO9: {=INDEX(stateTaxData[],MATCH(1,(stateTaxData[stateName]=CO$1)*(stateTaxData[taxYear]=$B$4)*(stateTaxData[FilingStatusFlag]=$B$8),0),MATCH($E9,stateTaxData[#Headers],0))} -> 0 | CP9: {=INDEX(stateTaxData[],MATCH(1,(stateTaxData[stateName]=CP$1)*(stateTaxData[taxYear]=$B$4)*(stateTaxData[FilingStatusFlag]=$B$8),0),MATCH($E9,stateTaxData[#Headers],0))} -> 0 | CR9: {=INDEX(stateTaxData[],MATCH(1,(stateTaxData[stateName]=CR$1)*(stateTaxData[taxYear]=$B$4)*(stateTaxData[FilingStatusFlag]=$B$8),0),MATCH($E9,stateTaxData[#Headers],0))} -> 0 | CU9: {=INDEX(stateTaxData[],MATCH(1,(stateTaxData[stateName]=CU$1)*(stateTaxData[taxYear]=$B$4)*(stateTaxData[FilingStatusFlag]=$B$8),0),MATCH($E9,stateTaxData[#Headers],0))} -> 0 | CV9: {=INDEX(stateTaxData[],MATCH(1,(stateTaxData[stateName]=CV$1)*(stateTaxData[taxYear]=$B$4)*(stateTaxData[FilingStatusFlag]=$B$8),0),MATCH($E9,stateTaxData[#Headers],0))} -> 0 | CW9: {=INDEX(stateTaxData[],MATCH(1,(stateTaxData[stateName]=CW$1)*(stateTaxData[taxYear]=$B$4)*(stateTaxData[FilingStatusFlag]=$B$8),0),MATCH($E9,stateTaxData[#Headers],0))} -> 0 | CX9: {=INDEX(stateTaxData[],MATCH(1,(stateTaxData[stateName]=CX$1)*(stateTaxData[taxYear]=$B$4)*(stateTaxData[FilingStatusFlag]=$B$8),0),MATCH($E9,stateTaxData[#Headers],0))} -> 0 | DB9: {=INDEX(stateTaxData[],MATCH(1,(stateTaxData[stateName]=DB$1)*(stateTaxData[taxYear]=$B$4)*(stateTaxData[FilingStatusFlag]=$B$8),0),MATCH($E9,stateTaxData[#Headers],0))} -> 0 | DC9: {=INDEX(stateTaxData[],MATCH(1,(stateTaxData[stateName]=DC$1)*(stateTaxData[taxYear]=$B$4)*(stateTaxData[FilingStatusFlag]=$B$8),0),MATCH($E9,stateTaxData[#Headers],0))} -> 0 | DD9: =ROUND(AVERAGE(AD9,AF9,AH9,AL9,AO9,AP9,AR9,AS9,AT9,AU9,AV9,AX9,AY9,BA9,BB9,BC9,BD9,BE9,BF9,BH9,BJ9,BK9,BL9,BN9,BO9,BQ9,BT9,BU9,BV9,BW9,BX9,BY9,BZ9,CA9,CC9,CE9,CF9,CH9,CI9,CK9,CL9,CN9,CO9,CP9,CR9,CU9,CV9,CW9,CX9,DB9,DC9),0) -> 349
W10: Factor | Y10: =Y9*Y8 -> 0.00028902245 | DW10: Refundable? | EB10: TRUE | EC10: TRUE | ED10: TRUE | EE10: TRUE | EF10: TRUE | EI10: TRUE | EK10: TRUE | EL10: TRUE | EM10: TRUE | EN10: TRUE | EP10: TRUE | EQ10: TRUE | ER10: BOTH | ES10: TRUE | ET10: TRUE | EU10: TRUE | EW10: FALSE | EX10: TRUE | EY10: TRUE | FB10: TRUE | FC10: TRUE | FD10: TRUE | FG10: FALSE | FH10: TRUE | FI10: TRUE | FK10: TRUE | FL10: FALSE | FP10: FALSE | FQ10: TRUE | FR10: FALSE | FS10: TRUE | FU10: TRUE
A11: # Tax filer & Spouse: | B11: ='Final Results'!B12 -> 1 | W11: Conclusion | Y11: Negligible
A12: Dependents | B12: ='Final Results'!B13 -> 0 | E12: Correct to DataFrame for Bin0 | AD12: 0 | AF12: 0 | AH12: 0 | AL12: 0 | AO12: 0 | AP12: 0 | AR12: 0 | AS12: 0 | AT12: 0 | AU12: 0 | AV12: 0 | AX12: 0 | AY12: 0 | BA12: 0 | BB12: 0 | BC12: 0 | BD12: 0 | BE12: 0 | BF12: 0 | BH12: 0 | BJ12: 0 | BK12: 0 | BL12: 0 | BN12: 0 | BO12: 0 | BQ12: 0 | BT12: 0 | BU12: 0 | BV12: 0 | BW12: 0 | BX12: 0 | BY12: 0 | BZ12: 0 | CA12: 0 | CC12: 0 | CE12: 0 | CF12: 0 | CH12: 0 | CI12: 0 | CK12: 0 | CL12: 0 | DW12: Different Nonrefundable rate (DE) | EE12: TRUE
E13: IncomeBin1Max | F13: Bracket 1 | G13: Over | H13: {=INDEX(FedTaxRateTable[],MATCH(1,(FedTaxRateTable[StatusAbb]=$B$7)*(FedTaxRateTable[Bracket]=$F13)*(FedTaxRateTable[Condition]=$G13),0),MATCH($B$4,VALUE(FedTaxRateTable[#Headers]),0))} -> 0 | AD13: {=INDEX(stateTaxData[],MATCH(1,(stateTaxData[stateName]=AD$1)*(stateTaxData[taxYear]=$B$4)*(stateTaxData[FilingStatusFlag]=$B$8),0),MATCH($E13,stateTaxData[#Headers],0))} -> 0 | AF13: {=INDEX(stateTaxData[],MATCH(1,(stateTaxData[stateName]=AF$1)*(stateTaxData[taxYear]=$B$4)*(stateTaxData[FilingStatusFlag]=$B$8),0),MATCH($E13,stateTaxData[#Headers],0))} -> 0 | AH13: {=INDEX(stateTaxData[],MATCH(1,(stateTaxData[stateName]=AH$1)*(stateTaxData[taxYear]=$B$4)*(stateTaxData[FilingStatusFlag]=$B$8),0),MATCH($E13,stateTaxData[#Headers],0))} -> 0 | AJ13: =AL61 -> 0 | AK13: =AL13 -> 0 | AL13: {=INDEX(stateTaxData[],MATCH(1,(stateTaxData[stateName]=AL$1)*(stateTaxData[taxYear]=$B$4)*(stateTaxData[FilingStatusFlag]=$B$8),0),MATCH($E13,stateTaxData[#Headers],0))} -> 0 | AO13: {=INDEX(stateTaxData[],MATCH(1,(stateTaxData[stateName]=AO$1)*(stateTaxData[taxYear]=$B$4)*(stateTaxData[FilingStatusFlag]=$B$8),0),MATCH($E13,stateTaxData[#Headers],0))} -> 0 | AP13: {=INDEX(stateTaxData[],MATCH(1,(stateTaxData[stateName]=AP$1)*(stateTaxData[taxYear]=$B$4)*(stateTaxData[FilingStatusFlag]=$B$8),0),MATCH($E13,stateTaxData[#Headers],0))} -> 0 | AR13: {=INDEX(stateTaxData[],MATCH(1,(stateTaxData[stateName]=AR$1)*(stateTaxData[taxYear]=$B$4)*(stateTaxData[FilingStatusFlag]=$B$8),0),MATCH($E13,stateTaxData[#Headers],0))} -> 0 | AS13: {=INDEX(stateTaxData[],MATCH(1,(stateTaxData[stateName]=AS$1)*(stateTaxData[taxYear]=$B$4)*(stateTaxData[FilingStatusFlag]=$B$8),0),MATCH($E13,stateTaxData[#Headers],0))} -> 2000 | AT13: {=INDEX(stateTaxData[],MATCH(1,(stateTaxData[stateName]=AT$1)*(stateTaxData[taxYear]=$B$4)*(stateTaxData[FilingStatusFlag]=$B$8),0),MATCH($E13,stateTaxData[#Headers],0))} -> 0 | AU13: {=INDEX(stateTaxData[],MATCH(1,(stateTaxData[stateName]=AU$1)*(stateTaxData[taxYear]=$B$4)*(stateTaxData[FilingStatusFlag]=$B$8),0),MATCH($E13,stateTaxData[#Headers],0))} -> 0 | AV13: {=INDEX(stateTaxData[],MATCH(1,(stateTaxData[stateName]=AV$1)*(stateTaxData[taxYear]=$B$4)*(stateTaxData[FilingStatusFlag]=$B$8),0),MATCH($E13,stateTaxData[#Headers],0))} -> 0 | AX13: {=INDEX(stateTaxData[],MATCH(1,(stateTaxData[stateName]=AX$1)*(stateTaxData[taxYear]=$B$4)*(stateTaxData[FilingStatusFlag]=$B$8),0),MATCH($E13,stateTaxData[#Headers],0))} -> 0 | AY13: {=INDEX(stateTaxData[],MATCH(1,(stateTaxData[stateName]=AY$1)*(stateTaxData[taxYear]=$B$4)*(stateTaxData[FilingStatusFlag]=$B$8),0),MATCH($E13,stateTaxData[#Headers],0))} -> 4489 | BA13: {=INDEX(stateTaxData[],MATCH(1,(stateTaxData[stateName]=BA$1)*(stateTaxData[taxYear]=$B$4)*(stateTaxData[FilingStatusFlag]=$B$8),0),MATCH($E13,stateTaxData[#Headers],0))} -> 0 | BB13: {=INDEX(stateTaxData[],MATCH(1,(stateTaxData[stateName]=BB$1)*(stateTaxData[taxYear]=$B$4)*(stateTaxData[FilingStatusFlag]=$B$8),0),MATCH($E13,stateTaxData[#Headers],0))} -> 0 | BC13: {=INDEX(stateTaxData[],MATCH(1,(stateTaxData[stateName]=BC$1)*(stateTaxData[taxYear]=$B$4)*(stateTaxData[FilingStatusFlag]=$B$8),0),MATCH($E13,stateTaxData[#Headers],0))} -> 0 | BD13: {=INDEX(stateTaxData[],MATCH(1,(stateTaxData[stateName]=BD$1)*(stateTaxData[taxYear]=$B$4)*(stateTaxData[FilingStatusFlag]=$B$8),0),MATCH($E13,stateTaxData[#Headers],0))} -> 0 | BE13: {=INDEX(stateTaxData[],MATCH(1,(stateTaxData[stateName]=BE$1)*(stateTaxData[taxYear]=$B$4)*(stateTaxData[FilingStatusFlag]=$B$8),0),MATCH($E13,stateTaxData[#Headers],0))} -> 0 | BF13: {=INDEX(stateTaxData[],MATCH(1,(stateTaxData[stateName]=BF$1)*(stateTaxData[taxYear]=$B$4)*(stateTaxData[FilingStatusFlag]=$B$8),0),MATCH($E13,stateTaxData[#Headers],0))} -> 0 | BH13: {=INDEX(stateTaxData[],MATCH(1,(stateTaxData[stateName]=BH$1)*(stateTaxData[taxYear]=$B$4)*(stateTaxData[FilingStatusFlag]=$B$8),0),MATCH($E13,stateTaxData[#Headers],0))} -> 0 | BJ13: {=INDEX(stateTaxData[],MATCH(1,(stateTaxData[stateName]=BJ$1)*(stateTaxData[taxYear]=$B$4)*(stateTaxData[FilingStatusFlag]=$B$8),0),MATCH($E13,stateTaxData[#Headers],0))} -> 0 | BK13: {=INDEX(stateTaxData[],MATCH(1,(stateTaxData[stateName]=BK$1)*(stateTaxData[taxYear]=$B$4)*(stateTaxData[FilingStatusFlag]=$B$8),0),MATCH($E13,stateTaxData[#Headers],0))} -> 0 | BL13: {=INDEX(stateTaxData[],MATCH(1,(stateTaxData[stateName]=BL$1)*(stateTaxData[taxYear]=$B$4)*(stateTaxData[FilingStatusFlag]=$B$8),0),MATCH($E13,stateTaxData[#Headers],0))} -> 0 | BN13: {=INDEX(stateTaxData[],MATCH(1,(stateTaxData[stateName]=BN$1)*(stateTaxData[taxYear]=$B$4)*(stateTaxData[FilingStatusFlag]=$B$8),0),MATCH($E13,stateTaxData[#Headers],0))} -> 0 | BO13: {=INDEX(stateTaxData[],MATCH(1,(stateTaxData[stateName]=BO$1)*(stateTaxData[taxYear]=$B$4)*(stateTaxData[FilingStatusFlag]=$B$8),0),MATCH($E13,stateTaxData[#Headers],0))} -> 10000 | BQ13: {=INDEX(stateTaxData[],MATCH(1,(stateTaxData[stateName]=BQ$1)*(stateTaxData[taxYear]=$B$4)*(stateTaxData[FilingStatusFlag]=$B$8),0),MATCH($E13,stateTaxData[#Headers],0))} -> 1207 | BT13: {=INDEX(stateTaxData[],MATCH(1,(stateTaxData[stateName]=BT$1)*(stateTaxData[taxYear]=$B$4)*(stateTaxData[FilingStatusFlag]=$B$8),0),MATCH($E13,stateTaxData[#Headers],0))} -> 0 | BU13: {=INDEX(stateTaxData[],MATCH(1,(stateTaxData[stateName]=BU$1)*(stateTaxData[taxYear]=$B$4)*(stateTaxData[FilingStatusFlag]=$B$8),0),MATCH($E13,stateTaxData[#Headers],0))} -> 0 | BV13: {=INDEX(stateTaxData[],MATCH(1,(stateTaxData[stateName]=BV$1)*(stateTaxData[taxYear]=$B$4)*(stateTaxData[FilingStatusFlag]=$B$8),0),MATCH($E13,stateTaxData[#Headers],0))} -> 0 | BW13: {=INDEX(stateTaxData[],MATCH(1,(stateTaxData[stateName]=BW$1)*(stateTaxData[taxYear]=$B$4)*(stateTaxData[FilingStatusFlag]=$B$8),0),MATCH($E13,stateTaxData[#Headers],0))} -> 0 | BX13: {=INDEX(stateTaxData[],MATCH(1,(stateTaxData[stateName]=BX$1)*(stateTaxData[taxYear]=$B$4)*(stateTaxData[FilingStatusFlag]=$B$8),0),MATCH($E13,stateTaxData[#Headers],0))} -> 0 | BY13: {=INDEX(stateTaxData[],MATCH(1,(stateTaxData[stateName]=BY$1)*(stateTaxData[taxYear]=$B$4)*(stateTaxData[FilingStatusFlag]=$B$8),0),MATCH($E13,stateTaxData[#Headers],0))} -> 0 | BZ13: {=INDEX(stateTaxData[],MATCH(1,(stateTaxData[stateName]=BZ$1)*(stateTaxData[taxYear]=$B$4)*(stateTaxData[FilingStatusFlag]=$B$8),0),MATCH($E13,stateTaxData[#Headers],0))} -> 0 | CA13: {=INDEX(stateTaxData[],MATCH(1,(stateTaxData[stateName]=CA$1)*(stateTaxData[taxYear]=$B$4)*(stateTaxData[FilingStatusFlag]=$B$8),0),MATCH($E13,stateTaxData[#Headers],0))} -> 0 | CC13: {=INDEX(stateTaxData[],MATCH(1,(stateTaxData[stateName]=CC$1)*(stateTaxData[taxYear]=$B$4)*(stateTaxData[FilingStatusFlag]=$B$8),0),MATCH($E13,stateTaxData[#Headers],0))} -> 44725 | CE13: {=INDEX(stateTaxData[],MATCH(1,(stateTaxData[stateName]=CE$1)*(stateTaxData[taxYear]=$B$4)*(stateTaxData[FilingStatusFlag]=$B$8),0),MATCH($E13,stateTaxData[#Headers],0))} -> 26050 | CF13: {=INDEX(stateTaxData[],MATCH(1,(stateTaxData[stateName]=CF$1)*(stateTaxData[taxYear]=$B$4)*(stateTaxData[FilingStatusFlag]=$B$8),0),MATCH($E13,stateTaxData[#Headers],0))} -> 0 | CH13: {=INDEX(stateTaxData[],MATCH(1,(stateTaxData[stateName]=CH$1)*(stateTaxData[taxYear]=$B$4)*(stateTaxData[FilingStatusFlag]=$B$8),0),MATCH($E13,stateTaxData[#Headers],0))} -> 0 | CI13: {=INDEX(stateTaxData[],MATCH(1,(stateTaxData[stateName]=CI$1)*(stateTaxData[taxYear]=$B$4)*(stateTaxData[FilingStatusFlag]=$B$8),0),MATCH($E13,stateTaxData[#Headers],0))} -> 0 | CK13: {=INDEX(stateTaxData[],MATCH(1,(stateTaxData[stateName]=CK$1)*(stateTaxData[taxYear]=$B$4)*(stateTaxData[FilingStatusFlag]=$B$8),0),MATCH($E13,stateTaxData[#Headers],0))} -> 0 | CL13: {=INDEX(stateTaxData[],MATCH(1,(stateTaxData[stateName]=CL$1)*(stateTaxData[taxYear]=$B$4)*(stateTaxData[FilingStatusFlag]=$B$8),0),MATCH($E13,stateTaxData[#Headers],0))} -> 0 | CN13: {=INDEX(stateTaxData[],MATCH(1,(stateTaxData[stateName]=CN$1)*(stateTaxData[taxYear]=$B$4)*(stateTaxData[FilingStatusFlag]=$B$8),0),MATCH($E13,stateTaxData[#Headers],0))} -> 0 | CO13: {=INDEX(stateTaxData[],MATCH(1,(stateTaxData[stateName]=CO$1)*(stateTaxData[taxYear]=$B$4)*(stateTaxData[FilingStatusFlag]=$B$8),0),MATCH($E13,stateTaxData[#Headers],0))} -> 0 | CP13: {=INDEX(stateTaxData[],MATCH(1,(stateTaxData[stateName]=CP$1)*(stateTaxData[taxYear]=$B$4)*(stateTaxData[FilingStatusFlag]=$B$8),0),MATCH($E13,stateTaxData[#Headers],0))} -> 0 | CR13: {=INDEX(stateTaxData[],MATCH(1,(stateTaxData[stateName]=CR$1)*(stateTaxData[taxYear]=$B$4)*(stateTaxData[FilingStatusFlag]=$B$8),0),MATCH($E13,stateTaxData[#Headers],0))} -> 0 | CU13: {=INDEX(stateTaxData[],MATCH(1,(stateTaxData[stateName]=CU$1)*(stateTaxData[taxYear]=$B$4)*(stateTaxData[FilingStatusFlag]=$B$8),0),MATCH($E13,stateTaxData[#Headers],0))} -> 0 | CV13: {=INDEX(stateTaxData[],MATCH(1,(stateTaxData[stateName]=CV$1)*(stateTaxData[taxYear]=$B$4)*(stateTaxData[FilingStatusFlag]=$B$8),0),MATCH($E13,stateTaxData[#Headers],0))} -> 0 | CW13: {=INDEX(stateTaxData[],MATCH(1,(stateTaxData[stateName]=CW$1)*(stateTaxData[taxYear]=$B$4)*(stateTaxData[FilingStatusFlag]=$B$8),0),MATCH($E13,stateTaxData[#Headers],0))} -> 0 | CX13: {=INDEX(stateTaxData[],MATCH(1,(stateTaxData[stateName]=CX$1)*(stateTaxData[taxYear]=$B$4)*(stateTaxData[FilingStatusFlag]=$B$8),0),MATCH($E13,stateTaxData[#Headers],0))} -> 0 | DB13: {=INDEX(stateTaxData[],MATCH(1,(stateTaxData[stateName]=DB$1)*(stateTaxData[taxYear]=$B$4)*(stateTaxData[FilingStatusFlag]=$B$8),0),MATCH($E13,stateTaxData[#Headers],0))} -> 0 | DC13: {=INDEX(stateTaxData[],MATCH(1,(stateTaxData[stateName]=DC$1)*(stateTaxData[taxYear]=$B$4)*(stateTaxData[FilingStatusFlag]=$B$8),0),MATCH($E13,stateTaxData[#Headers],0))} -> 0 | DW13: Nonrfundable rate (DE) | EE13: 0.2
A14: EITC Children | B14: =IF(B12<3,B12,"3 or more") -> 0 | E14: IncomeBin2Max | F14: Bracket 2 | G14: Over | H14: {=INDEX(FedTaxRateTable[],MATCH(1,(FedTaxRateTable[StatusAbb]=$B$7)*(FedTaxRateTable[Bracket]=$F14)*(FedTaxRateTable[Condition]=$G14),0),MATCH($B$4,VALUE(FedTaxRateTable[#Headers]),0))} -> 11000 | AD14: {=IF(AD13=9999999,9999999,INDEX(stateTaxData[],MATCH(1,(stateTaxData[stateName]=AD$1)*(stateTaxData[taxYear]=$B$4)*(stateTaxData[FilingStatusFlag]=$B$8),0),MATCH($E14,stateTaxData[#Headers],0)))} -> 500 | AF14: {=IF(AF13=9999999,9999999,INDEX(stateTaxData[],MATCH(1,(stateTaxData[stateName]=AF$1)*(stateTaxData[taxYear]=$B$4)*(stateTaxData[FilingStatusFlag]=$B$8),0),MATCH($E14,stateTaxData[#Headers],0)))} -> 9999999 | AH14: {=IF(AH13=9999999,9999999,INDEX(stateTaxData[],MATCH(1,(stateTaxData[stateName]=AH$1)*(stateTaxData[taxYear]=$B$4)*(stateTaxData[FilingStatusFlag]=$B$8),0),MATCH($E14,stateTaxData[#Headers],0)))} -> 9999999 | AJ14: =AL62 -> 5000 | AK14: =AL14 -> 4400 | AL14: {=IF(AL13=9999999,9999999,INDEX(stateTaxData[],MATCH(1,(stateTaxData[stateName]=AL$1)*(stateTaxData[taxYear]=$B$4)*(stateTaxData[FilingStatusFlag]=$B$8),0),MATCH($E14,stateTaxData[#Headers],0)))} -> 4400 | AO14: {=IF(AO13=9999999,9999999,INDEX(stateTaxData[],MATCH(1,(stateTaxData[stateName]=AO$1)*(stateTaxData[taxYear]=$B$4)*(stateTaxData[FilingStatusFlag]=$B$8),0),MATCH($E14,stateTaxData[#Headers],0)))} -> 10099 | AP14: {=IF(AP13=9999999,9999999,INDEX(stateTaxData[],MATCH(1,(stateTaxData[stateName]=AP$1)*(stateTaxData[taxYear]=$B$4)*(stateTaxData[FilingStatusFlag]=$B$8),0),MATCH($E14,stateTaxData[#Headers],0)))} -> 9999999 | AR14: {=IF(AR13=9999999,9999999,INDEX(stateTaxData[],MATCH(1,(stateTaxData[stateName]=AR$1)*(stateTaxData[taxYear]=$B$4)*(stateTaxData[FilingStatusFlag]=$B$8),0),MATCH($E14,stateTaxData[#Headers],0)))} -> 10000 | AS14: {=IF(AS13=9999999,9999999,INDEX(stateTaxData[],MATCH(1,(stateTaxData[stateName]=AS$1)*(stateTaxData[taxYear]=$B$4)*(stateTaxData[FilingStatusFlag]=$B$8),0),MATCH($E14,stateTaxData[#Headers],0)))} -> 5000 | AT14: {=IF(AT13=9999999,9999999,INDEX(stateTaxData[],MATCH(1,(stateTaxData[stateName]=AT$1)*(stateTaxData[taxYear]=$B$4)*(stateTaxData[FilingStatusFlag]=$B$8),0),MATCH($E14,stateTaxData[#Headers],0)))} -> 10000 | AU14: {=IF(AU13=9999999,9999999,INDEX(stateTaxData[],MATCH(1,(stateTaxData[stateName]=AU$1)*(stateTaxData[taxYear]=$B$4)*(stateTaxData[FilingStatusFlag]=$B$8),0),MATCH($E14,stateTaxData[#Headers],0)))} -> 9999999 | AV14: {=IF(AV13=9999999,9999999,INDEX(stateTaxData[],MATCH(1,(stateTaxData[stateName]=AV$1)*(stateTaxData[taxYear]=$B$4)*(stateTaxData[FilingStatusFlag]=$B$8),0),MATCH($E14,stateTaxData[#Headers],0)))} -> 750 | AX14: {=IF(AX13=9999999,9999999,INDEX(stateTaxData[],MATCH(1,(stateTaxData[stateName]=AX$1)*(stateTaxData[taxYear]=$B$4)*(stateTaxData[FilingStatusFlag]=$B$8),0),MATCH($E14,stateTaxData[#Headers],0)))} -> 2400 | AY14: {=IF(AY13=9999999,9999999,INDEX(stateTaxData[],MATCH(1,(stateTaxData[stateName]=AY$1)*(stateTaxData[taxYear]=$B$4)*(stateTaxData[FilingStatusFlag]=$B$8),0),MATCH($E14,stateTaxData[#Headers],0)))} -> 9999999 | BA14: {=IF(BA13=9999999,9999999,INDEX(stateTaxData[],MATCH(1,(stateTaxData[stateName]=BA$1)*(stateTaxData[taxYear]=$B$4)*(stateTaxData[FilingStatusFlag]=$B$8),0),MATCH($E14,stateTaxData[#Headers],0)))} -> 9999999 | BB14: {=IF(BB13=9999999,9999999,INDEX(stateTaxData[],MATCH(1,(stateTaxData[stateName]=BB$1)*(stateTaxData[taxYear]=$B$4)*(stateTaxData[FilingStatusFlag]=$B$8),0),MATCH($E14,stateTaxData[#Headers],0)))} -> 9999999 | BC14: {=IF(BC13=9999999,9999999,INDEX(stateTaxData[],MATCH(1,(stateTaxData[stateName]=BC$1)*(stateTaxData[taxYear]=$B$4)*(stateTaxData[FilingStatusFlag]=$B$8),0),MATCH($E14,stateTaxData[#Headers],0)))} -> 6000 | BD14: {=IF(BD13=9999999,9999999,INDEX(stateTaxData[],MATCH(1,(stateTaxData[stateName]=BD$1)*(stateTaxData[taxYear]=$B$4)*(stateTaxData[FilingStatusFlag]=$B$8),0),MATCH($E14,stateTaxData[#Headers],0)))} -> 15000 | BE14: {=IF(BE13=9999999,9999999,INDEX(stateTaxData[],MATCH(1,(stateTaxData[stateName]=BE$1)*(stateTaxData[taxYear]=$B$4)*(stateTaxData[FilingStatusFlag]=$B$8),0),MATCH($E14,stateTaxData[#Headers],0)))} -> 9999999 | BF14: {=IF(BF13=9999999,9999999,INDEX(stateTaxData[],MATCH(1,(stateTaxData[stateName]=BF$1)*(stateTaxData[taxYear]=$B$4)*(stateTaxData[FilingStatusFlag]=$B$8),0),MATCH($E14,stateTaxData[#Headers],0)))} -> 12500 | BH14: {=IF(BH13=9999999,9999999,INDEX(stateTaxData[],MATCH(1,(stateTaxData[stateName]=BH$1)*(stateTaxData[taxYear]=$B$4)*(stateTaxData[FilingStatusFlag]=$B$8),0),MATCH($E14,stateTaxData[#Headers],0)))} -> 24500 | BJ14: {=IF(BJ13=9999999,9999999,INDEX(stateTaxData[],MATCH(1,(stateTaxData[stateName]=BJ$1)*(stateTaxData[taxYear]=$B$4)*(stateTaxData[FilingStatusFlag]=$B$8),0),MATCH($E14,stateTaxData[#Headers],0)))} -> 1000 | BK14: {=IF(BK13=9999999,9999999,INDEX(stateTaxData[],MATCH(1,(stateTaxData[stateName]=BK$1)*(stateTaxData[taxYear]=$B$4)*(stateTaxData[FilingStatusFlag]=$B$8),0),MATCH($E14,stateTaxData[#Headers],0)))} -> 1000000 | BL14: {=IF(BL13=9999999,9999999,INDEX(stateTaxData[],MATCH(1,(stateTaxData[stateName]=BL$1)*(stateTaxData[taxYear]=$B$4)*(stateTaxData[FilingStatusFlag]=$B$8),0),MATCH($E14,stateTaxData[#Headers],0)))} -> 9999999 | BN14: {=IF(BN13=9999999,9999999,INDEX(stateTaxData[],MATCH(1,(stateTaxData[stateName]=BN$1)*(stateTaxData[taxYear]=$B$4)*(stateTaxData[FilingStatusFlag]=$B$8),0),MATCH($E14,stateTaxData[#Headers],0)))} -> 30070 | BO14: {=IF(BO13=9999999,9999999,INDEX(stateTaxData[],MATCH(1,(stateTaxData[stateName]=BO$1)*(stateTaxData[taxYear]=$B$4)*(stateTaxData[FilingStatusFlag]=$B$8),0),MATCH($E14,stateTaxData[#Headers],0)))} -> 9999999 | BQ14: {=IF(BQ13=9999999,9999999,INDEX(stateTaxData[],MATCH(1,(stateTaxData[stateName]=BQ$1)*(stateTaxData[taxYear]=$B$4)*(stateTaxData[FilingStatusFlag]=$B$8),0),MATCH($E14,stateTaxData[#Headers],0)))} -> 2414 | BT14: {=IF(BT13=9999999,9999999,INDEX(stateTaxData[],MATCH(1,(stateTaxData[stateName]=BT$1)*(stateTaxData[taxYear]=$B$4)*(stateTaxData[FilingStatusFlag]=$B$8),0),MATCH($E14,stateTaxData[#Headers],0)))} -> 3600 | BU14: {=IF(BU13=9999999,9999999,INDEX(stateTaxData[],MATCH(1,(stateTaxData[stateName]=BU$1)*(stateTaxData[taxYear]=$B$4)*(stateTaxData[FilingStatusFlag]=$B$8),0),MATCH($E14,stateTaxData[#Headers],0)))} -> 3700 | BV14: {=IF(BV13=9999999,9999999,INDEX(stateTaxData[],MATCH(1,(stateTaxData[stateName]=BV$1)*(stateTaxData[taxYear]=$B$4)*(stateTaxData[FilingStatusFlag]=$B$8),0),MATCH($E14,stateTaxData[#Headers],0)))} -> 9999999 | BW14: {=IF(BW13=9999999,9999999,INDEX(stateTaxData[],MATCH(1,(stateTaxData[stateName]=BW$1)*(stateTaxData[taxYear]=$B$4)*(stateTaxData[FilingStatusFlag]=$B$8),0),MATCH($E14,stateTaxData[#Headers],0)))} -> 9999999 | BX14: {=IF(BX13=9999999,9999999,INDEX(stateTaxData[],MATCH(1,(stateTaxData[stateName]=BX$1)*(stateTaxData[taxYear]=$B$4)*(stateTaxData[FilingStatusFlag]=$B$8),0),MATCH($E14,stateTaxData[#Headers],0)))} -> 20000 | BY14: {=IF(BY13=9999999,9999999,INDEX(stateTaxData[],MATCH(1,(stateTaxData[stateName]=BY$1)*(stateTaxData[taxYear]=$B$4)*(stateTaxData[FilingStatusFlag]=$B$8),0),MATCH($E14,stateTaxData[#Headers],0)))} -> 5500 | BZ14: {=IF(BZ13=9999999,9999999,INDEX(stateTaxData[],MATCH(1,(stateTaxData[stateName]=BZ$1)*(stateTaxData[taxYear]=$B$4)*(stateTaxData[FilingStatusFlag]=$B$8),0),MATCH($E14,stateTaxData[#Headers],0)))} -> 8500 | CA14: {=IF(CA13=9999999,9999999,INDEX(stateTaxData[],MATCH(1,(stateTaxData[stateName]=CA$1)*(stateTaxData[taxYear]=$B$4)*(stateTaxData[FilingStatusFlag]=$B$8),0),MATCH($E14,stateTaxData[#Headers],0)))} -> 9999999 | CC14: {=IF(CC13=9999999,9999999,INDEX(stateTaxData[],MATCH(1,(stateTaxData[stateName]=CC$1)*(stateTaxData[taxYear]=$B$4)*(stateTaxData[FilingStatusFlag]=$B$8),0),MATCH($E14,stateTaxData[#Headers],0)))} -> 225975 | CE14: {=IF(CE13=9999999,9999999,INDEX(stateTaxData[],MATCH(1,(stateTaxData[stateName]=CE$1)*(stateTaxData[taxYear]=$B$4)*(stateTaxData[FilingStatusFlag]=$B$8),0),MATCH($E14,stateTaxData[#Headers],0)))} -> 100000 | CF14: {=IF(CF13=9999999,9999999,INDEX(stateTaxData[],MATCH(1,(stateTaxData[stateName]=CF$1)*(stateTaxData[taxYear]=$B$4)*(stateTaxData[FilingStatusFlag]=$B$8),0),MATCH($E14,stateTaxData[#Headers],0)))} -> 1000 | CH14: {=IF(CH13=9999999,9999999,INDEX(stateTaxData[],MATCH(1,(stateTaxData[stateName]=CH$1)*(stateTaxData[taxYear]=$B$4)*(stateTaxData[FilingStatusFlag]=$B$8),0),MATCH($E14,stateTaxData[#Headers],0)))} -> 4050 | CI14: {=IF(CI13=9999999,9999999,INDEX(stateTaxData[],MATCH(1,(stateTaxData[stateName]=CI$1)*(stateTaxData[taxYear]=$B$4)*(stateTaxData[FilingStatusFlag]=$B$8),0),MATCH($E14,stateTaxData[#Headers],0)))} -> 9999999 | CK14: {=IF(CK13=9999999,9999999,INDEX(stateTaxData[],MATCH(1,(stateTaxData[stateName]=CK$1)*(stateTaxData[taxYear]=$B$4)*(stateTaxData[FilingStatusFlag]=$B$8),0),MATCH($E14,stateTaxData[#Headers],0)))} -> 68200 | CL14: {=IF(CL13=9999999,9999999,INDEX(stateTaxData[],MATCH(1,(stateTaxData[stateName]=CL$1)*(stateTaxData[taxYear]=$B$4)*(stateTaxData[FilingStatusFlag]=$B$8),0),MATCH($E14,stateTaxData[#Headers],0)))} -> 3330 | CN14: {=IF(CN13=9999999,9999999,INDEX(stateTaxData[],MATCH(1,(stateTaxData[stateName]=CN$1)*(stateTaxData[taxYear]=$B$4)*(stateTaxData[FilingStatusFlag]=$B$8),0),MATCH($E14,stateTaxData[#Headers],0)))} -> 9999999 | CO14: {=IF(CO13=9999999,9999999,INDEX(stateTaxData[],MATCH(1,(stateTaxData[stateName]=CO$1)*(stateTaxData[taxYear]=$B$4)*(stateTaxData[FilingStatusFlag]=$B$8),0),MATCH($E14,stateTaxData[#Headers],0)))} -> 9999999 | CP14: {=IF(CP13=9999999,9999999,INDEX(stateTaxData[],MATCH(1,(stateTaxData[stateName]=CP$1)*(stateTaxData[taxYear]=$B$4)*(stateTaxData[FilingStatusFlag]=$B$8),0),MATCH($E14,stateTaxData[#Headers],0)))} -> 9999999 | CR14: {=IF(CR13=9999999,9999999,INDEX(stateTaxData[],MATCH(1,(stateTaxData[stateName]=CR$1)*(stateTaxData[taxYear]=$B$4)*(stateTaxData[FilingStatusFlag]=$B$8),0),MATCH($E14,stateTaxData[#Headers],0)))} -> 9999999 | CU14: {=IF(CU13=9999999,9999999,INDEX(stateTaxData[],MATCH(1,(stateTaxData[stateName]=CU$1)*(stateTaxData[taxYear]=$B$4)*(stateTaxData[FilingStatusFlag]=$B$8),0),MATCH($E14,stateTaxData[#Headers],0)))} -> 42150 | CV14: {=IF(CV13=9999999,9999999,INDEX(stateTaxData[],MATCH(1,(stateTaxData[stateName]=CV$1)*(stateTaxData[taxYear]=$B$4)*(stateTaxData[FilingStatusFlag]=$B$8),0),MATCH($E14,stateTaxData[#Headers],0)))} -> 3000 | CW14: {=IF(CW13=9999999,9999999,INDEX(stateTaxData[],MATCH(1,(stateTaxData[stateName]=CW$1)*(stateTaxData[taxYear]=$B$4)*(stateTaxData[FilingStatusFlag]=$B$8),0),MATCH($E14,stateTaxData[#Headers],0)))} -> 9999999 | CX14: {=IF(CX13=9999999,9999999,INDEX(stateTaxData[],MATCH(1,(stateTaxData[stateName]=CX$1)*(stateTaxData[taxYear]=$B$4)*(stateTaxData[FilingStatusFlag]=$B$8),0),MATCH($E14,stateTaxData[#Headers],0)))} -> 10000 | DB14: {=IF(DB13=9999999,9999999,INDEX(stateTaxData[],MATCH(1,(stateTaxData[stateName]=DB$1)*(stateTaxData[taxYear]=$B$4)*(stateTaxData[FilingStatusFlag]=$B$8),0),MATCH($E14,stateTaxData[#Headers],0)))} -> 13810 | DC14: {=IF(DC13=9999999,9999999,INDEX(stateTaxData[],MATCH(1,(stateTaxData[stateName]=DC$1)*(stateTaxData[taxYear]=$B$4)*(stateTaxData[FilingStatusFlag]=$B$8),0),MATCH($E14,stateTaxData[#Headers],0)))} -> 9999999
E15: IncomeBin3Max | F15: Bracket 3 | G15: Over | H15: {=INDEX(FedTaxRateTable[],MATCH(1,(FedTaxRateTable[StatusAbb]=$B$7)*(FedTaxRateTable[Bracket]=$F15)*(FedTaxRateTable[Condition]=$G15),0),MATCH($B$4,VALUE(FedTaxRateTable[#Headers]),0))} -> 44725 | AD15: {=IF(AD14=9999999,9999999,INDEX(stateTaxData[],MATCH(1,(stateTaxData[stateName]=AD$1)*(stateTaxData[taxYear]=$B$4)*(stateTaxData[FilingStatusFlag]=$B$8),0),MATCH($E15,stateTaxData[#Headers],0)))} -> 3000 | AF15: {=IF(AF14=9999999,9999999,INDEX(stateTaxData[],MATCH(1,(stateTaxData[stateName]=AF$1)*(stateTaxData[taxYear]=$B$4)*(stateTaxData[FilingStatusFlag]=$B$8),0),MATCH($E15,stateTaxData[#Headers],0)))} -> 9999999 | AH15: {=IF(AH14=9999999,9999999,INDEX(stateTaxData[],MATCH(1,(stateTaxData[stateName]=AH$1)*(stateTaxData[taxYear]=$B$4)*(stateTaxData[FilingStatusFlag]=$B$8),0),MATCH($E15,stateTaxData[#Headers],0)))} -> 9999999 | AJ15: =AL63 -> 10000 | AK15: =AL15 -> 8800 | AL15: {=IF(AL14=9999999,9999999,INDEX(stateTaxData[],MATCH(1,(stateTaxData[stateName]=AL$1)*(stateTaxData[taxYear]=$B$4)*(stateTaxData[FilingStatusFlag]=$B$8),0),MATCH($E15,stateTaxData[#Headers],0)))} -> 8800 | AO15: {=IF(AO14=9999999,9999999,INDEX(stateTaxData[],MATCH(1,(stateTaxData[stateName]=AO$1)*(stateTaxData[taxYear]=$B$4)*(stateTaxData[FilingStatusFlag]=$B$8),0),MATCH($E15,stateTaxData[#Headers],0)))} -> 23942 | AP15: {=IF(AP14=9999999,9999999,INDEX(stateTaxData[],MATCH(1,(stateTaxData[stateName]=AP$1)*(stateTaxData[taxYear]=$B$4)*(stateTaxData[FilingStatusFlag]=$B$8),0),MATCH($E15,stateTaxData[#Headers],0)))} -> 9999999 | AR15: {=IF(AR14=9999999,9999999,INDEX(stateTaxData[],MATCH(1,(stateTaxData[stateName]=AR$1)*(stateTaxData[taxYear]=$B$4)*(stateTaxData[FilingStatusFlag]=$B$8),0),MATCH($E15,stateTaxData[#Headers],0)))} -> 50000 | AS15: {=IF(AS14=9999999,9999999,INDEX(stateTaxData[],MATCH(1,(stateTaxData[stateName]=AS$1)*(stateTaxData[taxYear]=$B$4)*(stateTaxData[FilingStatusFlag]=$B$8),0),MATCH($E15,stateTaxData[#Headers],0)))} -> 10000 | AT15: {=IF(AT14=9999999,9999999,INDEX(stateTaxData[],MATCH(1,(stateTaxData[stateName]=AT$1)*(stateTaxData[taxYear]=$B$4)*(stateTaxData[FilingStatusFlag]=$B$8),0),MATCH($E15,stateTaxData[#Headers],0)))} -> 40000 | AU15: {=IF(AU14=9999999,9999999,INDEX(stateTaxData[],MATCH(1,(stateTaxData[stateName]=AU$1)*(stateTaxData[taxYear]=$B$4)*(stateTaxData[FilingStatusFlag]=$B$8),0),MATCH($E15,stateTaxData[#Headers],0)))} -> 9999999 | AV15: {=IF(AV14=9999999,9999999,INDEX(stateTaxData[],MATCH(1,(stateTaxData[stateName]=AV$1)*(stateTaxData[taxYear]=$B$4)*(stateTaxData[FilingStatusFlag]=$B$8),0),MATCH($E15,stateTaxData[#Headers],0)))} -> 2250 | AX15: {=IF(AX14=9999999,9999999,INDEX(stateTaxData[],MATCH(1,(stateTaxData[stateName]=AX$1)*(stateTaxData[taxYear]=$B$4)*(stateTaxData[FilingStatusFlag]=$B$8),0),MATCH($E15,stateTaxData[#Headers],0)))} -> 4800 | AY15: {=IF(AY14=9999999,9999999,INDEX(stateTaxData[],MATCH(1,(stateTaxData[stateName]=AY$1)*(stateTaxData[taxYear]=$B$4)*(stateTaxData[FilingStatusFlag]=$B$8),0),MATCH($E15,stateTaxData[#Headers],0)))} -> 9999999 | BA15: {=IF(BA14=9999999,9999999,INDEX(stateTaxData[],MATCH(1,(stateTaxData[stateName]=BA$1)*(stateTaxData[taxYear]=$B$4)*(stateTaxData[FilingStatusFlag]=$B$8),0),MATCH($E15,stateTaxData[#Headers],0)))} -> 9999999 | BB15: {=IF(BB14=9999999,9999999,INDEX(stateTaxData[],MATCH(1,(stateTaxData[stateName]=BB$1)*(stateTaxData[taxYear]=$B$4)*(stateTaxData[FilingStatusFlag]=$B$8),0),MATCH($E15,stateTaxData[#Headers],0)))} -> 9999999 | BC15: {=IF(BC14=9999999,9999999,INDEX(stateTaxData[],MATCH(1,(stateTaxData[stateName]=BC$1)*(stateTaxData[taxYear]=$B$4)*(stateTaxData[FilingStatusFlag]=$B$8),0),MATCH($E15,stateTaxData[#Headers],0)))} -> 30000 | BD15: {=IF(BD14=9999999,9999999,INDEX(stateTaxData[],MATCH(1,(stateTaxData[stateName]=BD$1)*(stateTaxData[taxYear]=$B$4)*(stateTaxData[FilingStatusFlag]=$B$8),0),MATCH($E15,stateTaxData[#Headers],0)))} -> 30000 | BE15: {=IF(BE14=9999999,9999999,INDEX(stateTaxData[],MATCH(1,(stateTaxData[stateName]=BE$1)*(stateTaxData[taxYear]=$B$4)*(stateTaxData[FilingStatusFlag]=$B$8),0),MATCH($E15,stateTaxData[#Headers],0)))} -> 9999999 | BF15: {=IF(BF14=9999999,9999999,INDEX(stateTaxData[],MATCH(1,(stateTaxData[stateName]=BF$1)*(stateTaxData[taxYear]=$B$4)*(stateTaxData[FilingStatusFlag]=$B$8),0),MATCH($E15,stateTaxData[#Headers],0)))} -> 50000 | BH15: {=IF(BH14=9999999,9999999,INDEX(stateTaxData[],MATCH(1,(stateTaxData[stateName]=BH$1)*(stateTaxData[taxYear]=$B$4)*(stateTaxData[FilingStatusFlag]=$B$8),0),MATCH($E15,stateTaxData[#Headers],0)))} -> 58050 | BJ15: {=IF(BJ14=9999999,9999999,INDEX(stateTaxData[],MATCH(1,(stateTaxData[stateName]=BJ$1)*(stateTaxData[taxYear]=$B$4)*(stateTaxData[FilingStatusFlag]=$B$8),0),MATCH($E15,stateTaxData[#Headers],0)))} -> 2000 | BK15: {=IF(BK14=9999999,9999999,INDEX(stateTaxData[],MATCH(1,(stateTaxData[stateName]=BK$1)*(stateTaxData[taxYear]=$B$4)*(stateTaxData[FilingStatusFlag]=$B$8),0),MATCH($E15,stateTaxData[#Headers],0)))} -> 9999999 | BL15: {=IF(BL14=9999999,9999999,INDEX(stateTaxData[],MATCH(1,(stateTaxData[stateName]=BL$1)*(stateTaxData[taxYear]=$B$4)*(stateTaxData[FilingStatusFlag]=$B$8),0),MATCH($E15,stateTaxData[#Headers],0)))} -> 9999999 | BN15: {=IF(BN14=9999999,9999999,INDEX(stateTaxData[],MATCH(1,(stateTaxData[stateName]=BN$1)*(stateTaxData[taxYear]=$B$4)*(stateTaxData[FilingStatusFlag]=$B$8),0),MATCH($E15,stateTaxData[#Headers],0)))} -> 98760 | BO15: {=IF(BO14=9999999,9999999,INDEX(stateTaxData[],MATCH(1,(stateTaxData[stateName]=BO$1)*(stateTaxData[taxYear]=$B$4)*(stateTaxData[FilingStatusFlag]=$B$8),0),MATCH($E15,stateTaxData[#Headers],0)))} -> 9999999 | BQ15: {=IF(BQ14=9999999,9999999,INDEX(stateTaxData[],MATCH(1,(stateTaxData[stateName]=BQ$1)*(stateTaxData[taxYear]=$B$4)*(stateTaxData[FilingStatusFlag]=$B$8),0),MATCH($E15,stateTaxData[#Headers],0)))} -> 3621 | BT15: {=IF(BT14=9999999,9999999,INDEX(stateTaxData[],MATCH(1,(stateTaxData[stateName]=BT$1)*(stateTaxData[taxYear]=$B$4)*(stateTaxData[FilingStatusFlag]=$B$8),0),MATCH($E15,stateTaxData[#Headers],0)))} -> 6300 | BU15: {=IF(BU14=9999999,9999999,INDEX(stateTaxData[],MATCH(1,(stateTaxData[stateName]=BU$1)*(stateTaxData[taxYear]=$B$4)*(stateTaxData[FilingStatusFlag]=$B$8),0),MATCH($E15,stateTaxData[#Headers],0)))} -> 22170 | BV15: {=IF(BV14=9999999,9999999,INDEX(stateTaxData[],MATCH(1,(stateTaxData[stateName]=BV$1)*(stateTaxData[taxYear]=$B$4)*(stateTaxData[FilingStatusFlag]=$B$8),0),MATCH($E15,stateTaxData[#Headers],0)))} -> 9999999 | BW15: {=IF(BW14=9999999,9999999,INDEX(stateTaxData[],MATCH(1,(stateTaxData[stateName]=BW$1)*(stateTaxData[taxYear]=$B$4)*(stateTaxData[FilingStatusFlag]=$B$8),0),MATCH($E15,stateTaxData[#Headers],0)))} -> 9999999 | BX15: {=IF(BX14=9999999,9999999,INDEX(stateTaxData[],MATCH(1,(stateTaxData[stateName]=BX$1)*(stateTaxData[taxYear]=$B$4)*(stateTaxData[FilingStatusFlag]=$B$8),0),MATCH($E15,stateTaxData[#Headers],0)))} -> 35000 | BY15: {=IF(BY14=9999999,9999999,INDEX(stateTaxData[],MATCH(1,(stateTaxData[stateName]=BY$1)*(stateTaxData[taxYear]=$B$4)*(stateTaxData[FilingStatusFlag]=$B$8),0),MATCH($E15,stateTaxData[#Headers],0)))} -> 11000 | BZ15: {=IF(BZ14=9999999,9999999,INDEX(stateTaxData[],MATCH(1,(stateTaxData[stateName]=BZ$1)*(stateTaxData[taxYear]=$B$4)*(stateTaxData[FilingStatusFlag]=$B$8),0),MATCH($E15,stateTaxData[#Headers],0)))} -> 11700 | CA15: {=IF(CA14=9999999,9999999,INDEX(stateTaxData[],MATCH(1,(stateTaxData[stateName]=CA$1)*(stateTaxData[taxYear]=$B$4)*(stateTaxData[FilingStatusFlag]=$B$8),0),MATCH($E15,stateTaxData[#Headers],0)))} -> 9999999 | CC15: {=IF(CC14=9999999,9999999,INDEX(stateTaxData[],MATCH(1,(stateTaxData[stateName]=CC$1)*(stateTaxData[taxYear]=$B$4)*(stateTaxData[FilingStatusFlag]=$B$8),0),MATCH($E15,stateTaxData[#Headers],0)))} -> 9999999 | CE15: {=IF(CE14=9999999,9999999,INDEX(stateTaxData[],MATCH(1,(stateTaxData[stateName]=CE$1)*(stateTaxData[taxYear]=$B$4)*(stateTaxData[FilingStatusFlag]=$B$8),0),MATCH($E15,stateTaxData[#Headers],0)))} -> 115300 | CF15: {=IF(CF14=9999999,9999999,INDEX(stateTaxData[],MATCH(1,(stateTaxData[stateName]=CF$1)*(stateTaxData[taxYear]=$B$4)*(stateTaxData[FilingStatusFlag]=$B$8),0),MATCH($E15,stateTaxData[#Headers],0)))} -> 2500 | CH15: {=IF(CH14=9999999,9999999,INDEX(stateTaxData[],MATCH(1,(stateTaxData[stateName]=CH$1)*(stateTaxData[taxYear]=$B$4)*(stateTaxData[FilingStatusFlag]=$B$8),0),MATCH($E15,stateTaxData[#Headers],0)))} -> 10200 | CI15: {=IF(CI14=9999999,9999999,INDEX(stateTaxData[],MATCH(1,(stateTaxData[stateName]=CI$1)*(stateTaxData[taxYear]=$B$4)*(stateTaxData[FilingStatusFlag]=$B$8),0),MATCH($E15,stateTaxData[#Headers],0)))} -> 9999999 | CK15: {=IF(CK14=9999999,9999999,INDEX(stateTaxData[],MATCH(1,(stateTaxData[stateName]=CK$1)*(stateTaxData[taxYear]=$B$4)*(stateTaxData[FilingStatusFlag]=$B$8),0),MATCH($E15,stateTaxData[#Headers],0)))} -> 155050 | CL15: {=IF(CL14=9999999,9999999,INDEX(stateTaxData[],MATCH(1,(stateTaxData[stateName]=CL$1)*(stateTaxData[taxYear]=$B$4)*(stateTaxData[FilingStatusFlag]=$B$8),0),MATCH($E15,stateTaxData[#Headers],0)))} -> 16680 | CN15: {=IF(CN14=9999999,9999999,INDEX(stateTaxData[],MATCH(1,(stateTaxData[stateName]=CN$1)*(stateTaxData[taxYear]=$B$4)*(stateTaxData[FilingStatusFlag]=$B$8),0),MATCH($E15,stateTaxData[#Headers],0)))} -> 9999999 | CO15: {=IF(CO14=9999999,9999999,INDEX(stateTaxData[],MATCH(1,(stateTaxData[stateName]=CO$1)*(stateTaxData[taxYear]=$B$4)*(stateTaxData[FilingStatusFlag]=$B$8),0),MATCH($E15,stateTaxData[#Headers],0)))} -> 9999999 | CP15: {=IF(CP14=9999999,9999999,INDEX(stateTaxData[],MATCH(1,(stateTaxData[stateName]=CP$1)*(stateTaxData[taxYear]=$B$4)*(stateTaxData[FilingStatusFlag]=$B$8),0),MATCH($E15,stateTaxData[#Headers],0)))} -> 9999999 | CR15: {=IF(CR14=9999999,9999999,INDEX(stateTaxData[],MATCH(1,(stateTaxData[stateName]=CR$1)*(stateTaxData[taxYear]=$B$4)*(stateTaxData[FilingStatusFlag]=$B$8),0),MATCH($E15,stateTaxData[#Headers],0)))} -> 9999999 | CU15: {=IF(CU14=9999999,9999999,INDEX(stateTaxData[],MATCH(1,(stateTaxData[stateName]=CU$1)*(stateTaxData[taxYear]=$B$4)*(stateTaxData[FilingStatusFlag]=$B$8),0),MATCH($E15,stateTaxData[#Headers],0)))} -> 102200 | CV15: {=IF(CV14=9999999,9999999,INDEX(stateTaxData[],MATCH(1,(stateTaxData[stateName]=CV$1)*(stateTaxData[taxYear]=$B$4)*(stateTaxData[FilingStatusFlag]=$B$8),0),MATCH($E15,stateTaxData[#Headers],0)))} -> 5000 | CW15: {=IF(CW14=9999999,9999999,INDEX(stateTaxData[],MATCH(1,(stateTaxData[stateName]=CW$1)*(stateTaxData[taxYear]=$B$4)*(stateTaxData[FilingStatusFlag]=$B$8),0),MATCH($E15,stateTaxData[#Headers],0)))} -> 9999999 | CX15: {=IF(CX14=9999999,9999999,INDEX(stateTaxData[],MATCH(1,(stateTaxData[stateName]=CX$1)*(stateTaxData[taxYear]=$B$4)*(stateTaxData[FilingStatusFlag]=$B$8),0),MATCH($E15,stateTaxData[#Headers],0)))} -> 25000 | DB15: {=IF(DB14=9999999,9999999,INDEX(stateTaxData[],MATCH(1,(stateTaxData[stateName]=DB$1)*(stateTaxData[taxYear]=$B$4)*(stateTaxData[FilingStatusFlag]=$B$8),0),MATCH($E15,stateTaxData[#Headers],0)))} -> 27630 | DC15: {=IF(DC14=9999999,9999999,INDEX(stateTaxData[],MATCH(1,(stateTaxData[stateName]=DC$1)*(stateTaxData[taxYear]=$B$4)*(stateTaxData[FilingStatusFlag]=$B$8),0),MATCH($E15,stateTaxData[#Headers],0)))} -> 9999999 | DW15: Greater Than (MD) | ER15: TRUE
E16: IncomeBin4Max | F16: Bracket 4 | G16: Over | H16: {=INDEX(FedTaxRateTable[],MATCH(1,(FedTaxRateTable[StatusAbb]=$B$7)*(FedTaxRateTable[Bracket]=$F16)*(FedTaxRateTable[Condition]=$G16),0),MATCH($B$4,VALUE(FedTaxRateTable[#Headers]),0))} -> 95375 | AD16: {=IF(AD15=9999999,9999999,INDEX(stateTaxData[],MATCH(1,(stateTaxData[stateName]=AD$1)*(stateTaxData[taxYear]=$B$4)*(stateTaxData[FilingStatusFlag]=$B$8),0),MATCH($E16,stateTaxData[#Headers],0)))} -> 9999999 | AF16: {=IF(AF15=9999999,9999999,INDEX(stateTaxData[],MATCH(1,(stateTaxData[stateName]=AF$1)*(stateTaxData[taxYear]=$B$4)*(stateTaxData[FilingStatusFlag]=$B$8),0),MATCH($E16,stateTaxData[#Headers],0)))} -> 9999999 | AH16: {=IF(AH15=9999999,9999999,INDEX(stateTaxData[],MATCH(1,(stateTaxData[stateName]=AH$1)*(stateTaxData[taxYear]=$B$4)*(stateTaxData[FilingStatusFlag]=$B$8),0),MATCH($E16,stateTaxData[#Headers],0)))} -> 9999999 | AJ16: =AL64 -> 14300 | AK16: =AL16 -> 9999999 | AL16: {=IF(AL15=9999999,9999999,INDEX(stateTaxData[],MATCH(1,(stateTaxData[stateName]=AL$1)*(stateTaxData[taxYear]=$B$4)*(stateTaxData[FilingStatusFlag]=$B$8),0),MATCH($E16,stateTaxData[#Headers],0)))} -> 9999999 | AO16: {=IF(AO15=9999999,9999999,INDEX(stateTaxData[],MATCH(1,(stateTaxData[stateName]=AO$1)*(stateTaxData[taxYear]=$B$4)*(stateTaxData[FilingStatusFlag]=$B$8),0),MATCH($E16,stateTaxData[#Headers],0)))} -> 37788 | AP16: {=IF(AP15=9999999,9999999,INDEX(stateTaxData[],MATCH(1,(stateTaxData[stateName]=AP$1)*(stateTaxData[taxYear]=$B$4)*(stateTaxData[FilingStatusFlag]=$B$8),0),MATCH($E16,stateTaxData[#Headers],0)))} -> 9999999 | AR16: {=IF(AR15=9999999,9999999,INDEX(stateTaxData[],MATCH(1,(stateTaxData[stateName]=AR$1)*(stateTaxData[taxYear]=$B$4)*(stateTaxData[FilingStatusFlag]=$B$8),0),MATCH($E16,stateTaxData[#Headers],0)))} -> 100000 | AS16: {=IF(AS15=9999999,9999999,INDEX(stateTaxData[],MATCH(1,(stateTaxData[stateName]=AS$1)*(stateTaxData[taxYear]=$B$4)*(stateTaxData[FilingStatusFlag]=$B$8),0),MATCH($E16,stateTaxData[#Headers],0)))} -> 20000 | AT16: {=IF(AT15=9999999,9999999,INDEX(stateTaxData[],MATCH(1,(stateTaxData[stateName]=AT$1)*(stateTaxData[taxYear]=$B$4)*(stateTaxData[FilingStatusFlag]=$B$8),0),MATCH($E16,stateTaxData[#Headers],0)))} -> 60000 | AU16: {=IF(AU15=9999999,9999999,INDEX(stateTaxData[],MATCH(1,(stateTaxData[stateName]=AU$1)*(stateTaxData[taxYear]=$B$4)*(stateTaxData[FilingStatusFlag]=$B$8),0),MATCH($E16,stateTaxData[#Headers],0)))} -> 9999999 | AV16: {=IF(AV15=9999999,9999999,INDEX(stateTaxData[],MATCH(1,(stateTaxData[stateName]=AV$1)*(stateTaxData[taxYear]=$B$4)*(stateTaxData[FilingStatusFlag]=$B$8),0),MATCH($E16,stateTaxData[#Headers],0)))} -> 3750 | AX16: {=IF(AX15=9999999,9999999,INDEX(stateTaxData[],MATCH(1,(stateTaxData[stateName]=AX$1)*(stateTaxData[taxYear]=$B$4)*(stateTaxData[FilingStatusFlag]=$B$8),0),MATCH($E16,stateTaxData[#Headers],0)))} -> 9600 | AY16: {=IF(AY15=9999999,9999999,INDEX(stateTaxData[],MATCH(1,(stateTaxData[stateName]=AY$1)*(stateTaxData[taxYear]=$B$4)*(stateTaxData[FilingStatusFlag]=$B$8),0),MATCH($E16,stateTaxData[#Headers],0)))} -> 9999999 | BA16: {=IF(BA15=9999999,9999999,INDEX(stateTaxData[],MATCH(1,(stateTaxData[stateName]=BA$1)*(stateTaxData[taxYear]=$B$4)*(stateTaxData[FilingStatusFlag]=$B$8),0),MATCH($E16,stateTaxData[#Headers],0)))} -> 9999999 | BB16: {=IF(BB15=9999999,9999999,INDEX(stateTaxData[],MATCH(1,(stateTaxData[stateName]=BB$1)*(stateTaxData[taxYear]=$B$4)*(stateTaxData[FilingStatusFlag]=$B$8),0),MATCH($E16,stateTaxData[#Headers],0)))} -> 9999999 | BC16: {=IF(BC15=9999999,9999999,INDEX(stateTaxData[],MATCH(1,(stateTaxData[stateName]=BC$1)*(stateTaxData[taxYear]=$B$4)*(stateTaxData[FilingStatusFlag]=$B$8),0),MATCH($E16,stateTaxData[#Headers],0)))} -> 75000 | BD16: {=IF(BD15=9999999,9999999,INDEX(stateTaxData[],MATCH(1,(stateTaxData[stateName]=BD$1)*(stateTaxData[taxYear]=$B$4)*(stateTaxData[FilingStatusFlag]=$B$8),0),MATCH($E16,stateTaxData[#Headers],0)))} -> 9999999 | BE16: {=IF(BE15=9999999,9999999,INDEX(stateTaxData[],MATCH(1,(stateTaxData[stateName]=BE$1)*(stateTaxData[taxYear]=$B$4)*(stateTaxData[FilingStatusFlag]=$B$8),0),MATCH($E16,stateTaxData[#Headers],0)))} -> 9999999 | BF16: {=IF(BF15=9999999,9999999,INDEX(stateTaxData[],MATCH(1,(stateTaxData[stateName]=BF$1)*(stateTaxData[taxYear]=$B$4)*(stateTaxData[FilingStatusFlag]=$B$8),0),MATCH($E16,stateTaxData[#Headers],0)))} -> 9999999 | BH16: {=IF(BH15=9999999,9999999,INDEX(stateTaxData[],MATCH(1,(stateTaxData[stateName]=BH$1)*(stateTaxData[taxYear]=$B$4)*(stateTaxData[FilingStatusFlag]=$B$8),0),MATCH($E16,stateTaxData[#Headers],0)))} -> 9999999 | BJ16: {=IF(BJ15=9999999,9999999,INDEX(stateTaxData[],MATCH(1,(stateTaxData[stateName]=BJ$1)*(stateTaxData[taxYear]=$B$4)*(stateTaxData[FilingStatusFlag]=$B$8),0),MATCH($E16,stateTaxData[#Headers],0)))} -> 3000 | BK16: {=IF(BK15=9999999,9999999,INDEX(stateTaxData[],MATCH(1,(stateTaxData[stateName]=BK$1)*(stateTaxData[taxYear]=$B$4)*(stateTaxData[FilingStatusFlag]=$B$8),0),MATCH($E16,stateTaxData[#Headers],0)))} -> 9999999 | BL16: {=IF(BL15=9999999,9999999,INDEX(stateTaxData[],MATCH(1,(stateTaxData[stateName]=BL$1)*(stateTaxData[taxYear]=$B$4)*(stateTaxData[FilingStatusFlag]=$B$8),0),MATCH($E16,stateTaxData[#Headers],0)))} -> 9999999 | BN16: {=IF(BN15=9999999,9999999,INDEX(stateTaxData[],MATCH(1,(stateTaxData[stateName]=BN$1)*(stateTaxData[taxYear]=$B$4)*(stateTaxData[FilingStatusFlag]=$B$8),0),MATCH($E16,stateTaxData[#Headers],0)))} -> 183340 | BO16: {=IF(BO15=9999999,9999999,INDEX(stateTaxData[],MATCH(1,(stateTaxData[stateName]=BO$1)*(stateTaxData[taxYear]=$B$4)*(stateTaxData[FilingStatusFlag]=$B$8),0),MATCH($E16,stateTaxData[#Headers],0)))} -> 9999999 | BQ16: {=IF(BQ15=9999999,9999999,INDEX(stateTaxData[],MATCH(1,(stateTaxData[stateName]=BQ$1)*(stateTaxData[taxYear]=$B$4)*(stateTaxData[FilingStatusFlag]=$B$8),0),MATCH($E16,stateTaxData[#Headers],0)))} -> 4828 | BT16: {=IF(BT15=9999999,9999999,INDEX(stateTaxData[],MATCH(1,(stateTaxData[stateName]=BT$1)*(stateTaxData[taxYear]=$B$4)*(stateTaxData[FilingStatusFlag]=$B$8),0),MATCH($E16,stateTaxData[#Headers],0)))} -> 9700 | BU16: {=IF(BU15=9999999,9999999,INDEX(stateTaxData[],MATCH(1,(stateTaxData[stateName]=BU$1)*(stateTaxData[taxYear]=$B$4)*(stateTaxData[FilingStatusFlag]=$B$8),0),MATCH($E16,stateTaxData[#Headers],0)))} -> 35730 | BV16: {=IF(BV15=9999999,9999999,INDEX(stateTaxData[],MATCH(1,(stateTaxData[stateName]=BV$1)*(stateTaxData[taxYear]=$B$4)*(stateTaxData[FilingStatusFlag]=$B$8),0),MATCH($E16,stateTaxData[#Headers],0)))} -> 9999999 | BW16: {=IF(BW15=9999999,9999999,INDEX(stateTaxData[],MATCH(1,(stateTaxData[stateName]=BW$1)*(stateTaxData[taxYear]=$B$4)*(stateTaxData[FilingStatusFlag]=$B$8),0),MATCH($E16,stateTaxData[#Headers],0)))} -> 9999999 | BX16: {=IF(BX15=9999999,9999999,INDEX(stateTaxData[],MATCH(1,(stateTaxData[stateName]=BX$1)*(stateTaxData[taxYear]=$B$4)*(stateTaxData[FilingStatusFlag]=$B$8),0),MATCH($E16,stateTaxData[#Headers],0)))} -> 40000 | BY16: {=IF(BY15=9999999,9999999,INDEX(stateTaxData[],MATCH(1,(stateTaxData[stateName]=BY$1)*(stateTaxData[taxYear]=$B$4)*(stateTaxData[FilingStatusFlag]=$B$8),0),MATCH($E16,stateTaxData[#Headers],0)))} -> 16000 | BZ16: {=IF(BZ15=9999999,9999999,INDEX(stateTaxData[],MATCH(1,(stateTaxData[stateName]=BZ$1)*(stateTaxData[taxYear]=$B$4)*(stateTaxData[FilingStatusFlag]=$B$8),0),MATCH($E16,stateTaxData[#Headers],0)))} -> 13900 | CA16: {=IF(CA15=9999999,9999999,INDEX(stateTaxData[],MATCH(1,(stateTaxData[stateName]=CA$1)*(stateTaxData[taxYear]=$B$4)*(stateTaxData[FilingStatusFlag]=$B$8),0),MATCH($E16,stateTaxData[#Headers],0)))} -> 9999999 | CC16: {=IF(CC15=9999999,9999999,INDEX(stateTaxData[],MATCH(1,(stateTaxData[stateName]=CC$1)*(stateTaxData[taxYear]=$B$4)*(stateTaxData[FilingStatusFlag]=$B$8),0),MATCH($E16,stateTaxData[#Headers],0)))} -> 9999999 | CE16: {=IF(CE15=9999999,9999999,INDEX(stateTaxData[],MATCH(1,(stateTaxData[stateName]=CE$1)*(stateTaxData[taxYear]=$B$4)*(stateTaxData[FilingStatusFlag]=$B$8),0),MATCH($E16,stateTaxData[#Headers],0)))} -> 9999999 | CF16: {=IF(CF15=9999999,9999999,INDEX(stateTaxData[],MATCH(1,(stateTaxData[stateName]=CF$1)*(stateTaxData[taxYear]=$B$4)*(stateTaxData[FilingStatusFlag]=$B$8),0),MATCH($E16,stateTaxData[#Headers],0)))} -> 3750 | CH16: {=IF(CH15=9999999,9999999,INDEX(stateTaxData[],MATCH(1,(stateTaxData[stateName]=CH$1)*(stateTaxData[taxYear]=$B$4)*(stateTaxData[FilingStatusFlag]=$B$8),0),MATCH($E16,stateTaxData[#Headers],0)))} -> 125000 | CI16: {=IF(CI15=9999999,9999999,INDEX(stateTaxData[],MATCH(1,(stateTaxData[stateName]=CI$1)*(stateTaxData[taxYear]=$B$4)*(stateTaxData[FilingStatusFlag]=$B$8),0),MATCH($E16,stateTaxData[#Headers],0)))} -> 9999999 | CK16: {=IF(CK15=9999999,9999999,INDEX(stateTaxData[],MATCH(1,(stateTaxData[stateName]=CK$1)*(stateTaxData[taxYear]=$B$4)*(stateTaxData[FilingStatusFlag]=$B$8),0),MATCH($E16,stateTaxData[#Headers],0)))} -> 9999999 | CL16: {=IF(CL15=9999999,9999999,INDEX(stateTaxData[],MATCH(1,(stateTaxData[stateName]=CL$1)*(stateTaxData[taxYear]=$B$4)*(stateTaxData[FilingStatusFlag]=$B$8),0),MATCH($E16,stateTaxData[#Headers],0)))} -> 9999999 | CN16: {=IF(CN15=9999999,9999999,INDEX(stateTaxData[],MATCH(1,(stateTaxData[stateName]=CN$1)*(stateTaxData[taxYear]=$B$4)*(stateTaxData[FilingStatusFlag]=$B$8),0),MATCH($E16,stateTaxData[#Headers],0)))} -> 9999999 | CO16: {=IF(CO15=9999999,9999999,INDEX(stateTaxData[],MATCH(1,(stateTaxData[stateName]=CO$1)*(stateTaxData[taxYear]=$B$4)*(stateTaxData[FilingStatusFlag]=$B$8),0),MATCH($E16,stateTaxData[#Headers],0)))} -> 9999999 | CP16: {=IF(CP15=9999999,9999999,INDEX(stateTaxData[],MATCH(1,(stateTaxData[stateName]=CP$1)*(stateTaxData[taxYear]=$B$4)*(stateTaxData[FilingStatusFlag]=$B$8),0),MATCH($E16,stateTaxData[#Headers],0)))} -> 9999999 | CR16: {=IF(CR15=9999999,9999999,INDEX(stateTaxData[],MATCH(1,(stateTaxData[stateName]=CR$1)*(stateTaxData[taxYear]=$B$4)*(stateTaxData[FilingStatusFlag]=$B$8),0),MATCH($E16,stateTaxData[#Headers],0)))} -> 9999999 | CU16: {=IF(CU15=9999999,9999999,INDEX(stateTaxData[],MATCH(1,(stateTaxData[stateName]=CU$1)*(stateTaxData[taxYear]=$B$4)*(stateTaxData[FilingStatusFlag]=$B$8),0),MATCH($E16,stateTaxData[#Headers],0)))} -> 213150 | CV16: {=IF(CV15=9999999,9999999,INDEX(stateTaxData[],MATCH(1,(stateTaxData[stateName]=CV$1)*(stateTaxData[taxYear]=$B$4)*(stateTaxData[FilingStatusFlag]=$B$8),0),MATCH($E16,stateTaxData[#Headers],0)))} -> 17000 | CW16: {=IF(CW15=9999999,9999999,INDEX(stateTaxData[],MATCH(1,(stateTaxData[stateName]=CW$1)*(stateTaxData[taxYear]=$B$4)*(stateTaxData[FilingStatusFlag]=$B$8),0),MATCH($E16,stateTaxData[#Headers],0)))} -> 9999999 | CX16: {=IF(CX15=9999999,9999999,INDEX(stateTaxData[],MATCH(1,(stateTaxData[stateName]=CX$1)*(stateTaxData[taxYear]=$B$4)*(stateTaxData[FilingStatusFlag]=$B$8),0),MATCH($E16,stateTaxData[#Headers],0)))} -> 40000 | DB16: {=IF(DB15=9999999,9999999,INDEX(stateTaxData[],MATCH(1,(stateTaxData[stateName]=DB$1)*(stateTaxData[taxYear]=$B$4)*(stateTaxData[FilingStatusFlag]=$B$8),0),MATCH($E16,stateTaxData[#Headers],0)))} -> 304170 | DC16: {=IF(DC15=9999999,9999999,INDEX(stateTaxData[],MATCH(1,(stateTaxData[stateName]=DC$1)*(stateTaxData[taxYear]=$B$4)*(stateTaxData[FilingStatusFlag]=$B$8),0),MATCH($E16,stateTaxData[#Headers],0)))} -> 9999999 | DW16: Greater Than Rate | ER16: 0.5
A17: Tax Status List | E17: IncomeBin5Max | AD17: {=IF(AD16=9999999,9999999,INDEX(stateTaxData[],MATCH(1,(stateTaxData[stateName]=AD$1)*(stateTaxData[taxYear]=$B$4)*(stateTaxData[FilingStatusFlag]=$B$8),0),MATCH($E17,stateTaxData[#Headers],0)))} -> 9999999 | AF17: {=IF(AF16=9999999,9999999,INDEX(stateTaxData[],MATCH(1,(stateTaxData[stateName]=AF$1)*(stateTaxData[taxYear]=$B$4)*(stateTaxData[FilingStatusFlag]=$B$8),0),MATCH($E17,stateTaxData[#Headers],0)))} -> 9999999 | AH17: {=IF(AH16=9999999,9999999,INDEX(stateTaxData[],MATCH(1,(stateTaxData[stateName]=AH$1)*(stateTaxData[taxYear]=$B$4)*(stateTaxData[FilingStatusFlag]=$B$8),0),MATCH($E17,stateTaxData[#Headers],0)))} -> 9999999 | AJ17: =AL65 -> 23600 | AK17: =AL17 -> 9999999 | AL17: {=IF(AL16=9999999,9999999,INDEX(stateTaxData[],MATCH(1,(stateTaxData[stateName]=AL$1)*(stateTaxData[taxYear]=$B$4)*(stateTaxData[FilingStatusFlag]=$B$8),0),MATCH($E17,stateTaxData[#Headers],0)))} -> 9999999 | AO17: {=IF(AO16=9999999,9999999,INDEX(stateTaxData[],MATCH(1,(stateTaxData[stateName]=AO$1)*(stateTaxData[taxYear]=$B$4)*(stateTaxData[FilingStatusFlag]=$B$8),0),MATCH($E17,stateTaxData[#Headers],0)))} -> 52455 | AP17: {=IF(AP16=9999999,9999999,INDEX(stateTaxData[],MATCH(1,(stateTaxData[stateName]=AP$1)*(stateTaxData[taxYear]=$B$4)*(stateTaxData[FilingStatusFlag]=$B$8),0),MATCH($E17,stateTaxData[#Headers],0)))} -> 9999999 | AR17: {=IF(AR16=9999999,9999999,INDEX(stateTaxData[],MATCH(1,(stateTaxData[stateName]=AR$1)*(stateTaxData[taxYear]=$B$4)*(stateTaxData[FilingStatusFlag]=$B$8),0),MATCH($E17,stateTaxData[#Headers],0)))} -> 200000 | AS17: {=IF(AS16=9999999,9999999,INDEX(stateTaxData[],MATCH(1,(stateTaxData[stateName]=AS$1)*(stateTaxData[taxYear]=$B$4)*(stateTaxData[FilingStatusFlag]=$B$8),0),MATCH($E17,stateTaxData[#Headers],0)))} -> 25000 | AT17: {=IF(AT16=9999999,9999999,INDEX(stateTaxData[],MATCH(1,(stateTaxData[stateName]=AT$1)*(stateTaxData[taxYear]=$B$4)*(stateTaxData[FilingStatusFlag]=$B$8),0),MATCH($E17,stateTaxData[#Headers],0)))} -> 250000 | AU17: {=IF(AU16=9999999,9999999,INDEX(stateTaxData[],MATCH(1,(stateTaxData[stateName]=AU$1)*(stateTaxData[taxYear]=$B$4)*(stateTaxData[FilingStatusFlag]=$B$8),0),MATCH($E17,stateTaxData[#Headers],0)))} -> 9999999 | AV17: {=IF(AV16=9999999,9999999,INDEX(stateTaxData[],MATCH(1,(stateTaxData[stateName]=AV$1)*(stateTaxData[taxYear]=$B$4)*(stateTaxData[FilingStatusFlag]=$B$8),0),MATCH($E17,stateTaxData[#Headers],0)))} -> 5250 | AX17: {=IF(AX16=9999999,9999999,INDEX(stateTaxData[],MATCH(1,(stateTaxData[stateName]=AX$1)*(stateTaxData[taxYear]=$B$4)*(stateTaxData[FilingStatusFlag]=$B$8),0),MATCH($E17,stateTaxData[#Headers],0)))} -> 14400 | AY17: {=IF(AY16=9999999,9999999,INDEX(stateTaxData[],MATCH(1,(stateTaxData[stateName]=AY$1)*(stateTaxData[taxYear]=$B$4)*(stateTaxData[FilingStatusFlag]=$B$8),0),MATCH($E17,stateTaxData[#Headers],0)))} -> 9999999 | BA17: {=IF(BA16=9999999,9999999,INDEX(stateTaxData[],MATCH(1,(stateTaxData[stateName]=BA$1)*(stateTaxData[taxYear]=$B$4)*(stateTaxData[FilingStatusFlag]=$B$8),0),MATCH($E17,stateTaxData[#Headers],0)))} -> 9999999 | BB17: {=IF(BB16=9999999,9999999,INDEX(stateTaxData[],MATCH(1,(stateTaxData[stateName]=BB$1)*(stateTaxData[taxYear]=$B$4)*(stateTaxData[FilingStatusFlag]=$B$8),0),MATCH($E17,stateTaxData[#Headers],0)))} -> 9999999 | BC17: {=IF(BC16=9999999,9999999,INDEX(stateTaxData[],MATCH(1,(stateTaxData[stateName]=BC$1)*(stateTaxData[taxYear]=$B$4)*(stateTaxData[FilingStatusFlag]=$B$8),0),MATCH($E17,stateTaxData[#Headers],0)))} -> 9999999 | BD17: {=IF(BD16=9999999,9999999,INDEX(stateTaxData[],MATCH(1,(stateTaxData[stateName]=BD$1)*(stateTaxData[taxYear]=$B$4)*(stateTaxData[FilingStatusFlag]=$B$8),0),MATCH($E17,stateTaxData[#Headers],0)))} -> 9999999 | BE17: {=IF(BE16=9999999,9999999,INDEX(stateTaxData[],MATCH(1,(stateTaxData[stateName]=BE$1)*(stateTaxData[taxYear]=$B$4)*(stateTaxData[FilingStatusFlag]=$B$8),0),MATCH($E17,stateTaxData[#Headers],0)))} -> 9999999 | BF17: {=IF(BF16=9999999,9999999,INDEX(stateTaxData[],MATCH(1,(stateTaxData[stateName]=BF$1)*(stateTaxData[taxYear]=$B$4)*(stateTaxData[FilingStatusFlag]=$B$8),0),MATCH($E17,stateTaxData[#Headers],0)))} -> 9999999 | BH17: {=IF(BH16=9999999,9999999,INDEX(stateTaxData[],MATCH(1,(stateTaxData[stateName]=BH$1)*(stateTaxData[taxYear]=$B$4)*(stateTaxData[FilingStatusFlag]=$B$8),0),MATCH($E17,stateTaxData[#Headers],0)))} -> 9999999 | BJ17: {=IF(BJ16=9999999,9999999,INDEX(stateTaxData[],MATCH(1,(stateTaxData[stateName]=BJ$1)*(stateTaxData[taxYear]=$B$4)*(stateTaxData[FilingStatusFlag]=$B$8),0),MATCH($E17,stateTaxData[#Headers],0)))} -> 100000 | BK17: {=IF(BK16=9999999,9999999,INDEX(stateTaxData[],MATCH(1,(stateTaxData[stateName]=BK$1)*(stateTaxData[taxYear]=$B$4)*(stateTaxData[FilingStatusFlag]=$B$8),0),MATCH($E17,stateTaxData[#Headers],0)))} -> 9999999 | BL17: {=IF(BL16=9999999,9999999,INDEX(stateTaxData[],MATCH(1,(stateTaxData[stateName]=BL$1)*(stateTaxData[taxYear]=$B$4)*(stateTaxData[FilingStatusFlag]=$B$8),0),MATCH($E17,stateTaxData[#Headers],0)))} -> 9999999 | BN17: {=IF(BN16=9999999,9999999,INDEX(stateTaxData[],MATCH(1,(stateTaxData[stateName]=BN$1)*(stateTaxData[taxYear]=$B$4)*(stateTaxData[FilingStatusFlag]=$B$8),0),MATCH($E17,stateTaxData[#Headers],0)))} -> 9999999 | BO17: {=IF(BO16=9999999,9999999,INDEX(stateTaxData[],MATCH(1,(stateTaxData[stateName]=BO$1)*(stateTaxData[taxYear]=$B$4)*(stateTaxData[FilingStatusFlag]=$B$8),0),MATCH($E17,stateTaxData[#Headers],0)))} -> 9999999 | BQ17: {=IF(BQ16=9999999,9999999,INDEX(stateTaxData[],MATCH(1,(stateTaxData[stateName]=BQ$1)*(stateTaxData[taxYear]=$B$4)*(stateTaxData[FilingStatusFlag]=$B$8),0),MATCH($E17,stateTaxData[#Headers],0)))} -> 6035 | BT17: {=IF(BT16=9999999,9999999,INDEX(stateTaxData[],MATCH(1,(stateTaxData[stateName]=BT$1)*(stateTaxData[taxYear]=$B$4)*(stateTaxData[FilingStatusFlag]=$B$8),0),MATCH($E17,stateTaxData[#Headers],0)))} -> 13000 | BU17: {=IF(BU16=9999999,9999999,INDEX(stateTaxData[],MATCH(1,(stateTaxData[stateName]=BU$1)*(stateTaxData[taxYear]=$B$4)*(stateTaxData[FilingStatusFlag]=$B$8),0),MATCH($E17,stateTaxData[#Headers],0)))} -> 9999999 | BV17: {=IF(BV16=9999999,9999999,INDEX(stateTaxData[],MATCH(1,(stateTaxData[stateName]=BV$1)*(stateTaxData[taxYear]=$B$4)*(stateTaxData[FilingStatusFlag]=$B$8),0),MATCH($E17,stateTaxData[#Headers],0)))} -> 9999999 | BW17: {=IF(BW16=9999999,9999999,INDEX(stateTaxData[],MATCH(1,(stateTaxData[stateName]=BW$1)*(stateTaxData[taxYear]=$B$4)*(stateTaxData[FilingStatusFlag]=$B$8),0),MATCH($E17,stateTaxData[#Headers],0)))} -> 9999999 | BX17: {=IF(BX16=9999999,9999999,INDEX(stateTaxData[],MATCH(1,(stateTaxData[stateName]=BX$1)*(stateTaxData[taxYear]=$B$4)*(stateTaxData[FilingStatusFlag]=$B$8),0),MATCH($E17,stateTaxData[#Headers],0)))} -> 75000 | BY17: {=IF(BY16=9999999,9999999,INDEX(stateTaxData[],MATCH(1,(stateTaxData[stateName]=BY$1)*(stateTaxData[taxYear]=$B$4)*(stateTaxData[FilingStatusFlag]=$B$8),0),MATCH($E17,stateTaxData[#Headers],0)))} -> 210000 | BZ17: {=IF(BZ16=9999999,9999999,INDEX(stateTaxData[],MATCH(1,(stateTaxData[stateName]=BZ$1)*(stateTaxData[taxYear]=$B$4)*(stateTaxData[FilingStatusFlag]=$B$8),0),MATCH($E17,stateTaxData[#Headers],0)))} -> 80650 | CA17: {=IF(CA16=9999999,9999999,INDEX(stateTaxData[],MATCH(1,(stateTaxData[stateName]=CA$1)*(stateTaxData[taxYear]=$B$4)*(stateTaxData[FilingStatusFlag]=$B$8),0),MATCH($E17,stateTaxData[#Headers],0)))} -> 9999999 | CC17: {=IF(CC16=9999999,9999999,INDEX(stateTaxData[],MATCH(1,(stateTaxData[stateName]=CC$1)*(stateTaxData[taxYear]=$B$4)*(stateTaxData[FilingStatusFlag]=$B$8),0),MATCH($E17,stateTaxData[#Headers],0)))} -> 9999999 | CE17: {=IF(CE16=9999999,9999999,INDEX(stateTaxData[],MATCH(1,(stateTaxData[stateName]=CE$1)*(stateTaxData[taxYear]=$B$4)*(stateTaxData[FilingStatusFlag]=$B$8),0),MATCH($E17,stateTaxData[#Headers],0)))} -> 9999999 | CF17: {=IF(CF16=9999999,9999999,INDEX(stateTaxData[],MATCH(1,(stateTaxData[stateName]=CF$1)*(stateTaxData[taxYear]=$B$4)*(stateTaxData[FilingStatusFlag]=$B$8),0),MATCH($E17,stateTaxData[#Headers],0)))} -> 4900 | CH17: {=IF(CH16=9999999,9999999,INDEX(stateTaxData[],MATCH(1,(stateTaxData[stateName]=CH$1)*(stateTaxData[taxYear]=$B$4)*(stateTaxData[FilingStatusFlag]=$B$8),0),MATCH($E17,stateTaxData[#Headers],0)))} -> 9999999 | CI17: {=IF(CI16=9999999,9999999,INDEX(stateTaxData[],MATCH(1,(stateTaxData[stateName]=CI$1)*(stateTaxData[taxYear]=$B$4)*(stateTaxData[FilingStatusFlag]=$B$8),0),MATCH($E17,stateTaxData[#Headers],0)))} -> 9999999 | CK17: {=IF(CK16=9999999,9999999,INDEX(stateTaxData[],MATCH(1,(stateTaxData[stateName]=CK$1)*(stateTaxData[taxYear]=$B$4)*(stateTaxData[FilingStatusFlag]=$B$8),0),MATCH($E17,stateTaxData[#Headers],0)))} -> 9999999 | CL17: {=IF(CL16=9999999,9999999,INDEX(stateTaxData[],MATCH(1,(stateTaxData[stateName]=CL$1)*(stateTaxData[taxYear]=$B$4)*(stateTaxData[FilingStatusFlag]=$B$8),0),MATCH($E17,stateTaxData[#Headers],0)))} -> 9999999 | CN17: {=IF(CN16=9999999,9999999,INDEX(stateTaxData[],MATCH(1,(stateTaxData[stateName]=CN$1)*(stateTaxData[taxYear]=$B$4)*(stateTaxData[FilingStatusFlag]=$B$8),0),MATCH($E17,stateTaxData[#Headers],0)))} -> 9999999 | CO17: {=IF(CO16=9999999,9999999,INDEX(stateTaxData[],MATCH(1,(stateTaxData[stateName]=CO$1)*(stateTaxData[taxYear]=$B$4)*(stateTaxData[FilingStatusFlag]=$B$8),0),MATCH($E17,stateTaxData[#Headers],0)))} -> 9999999 | CP17: {=IF(CP16=9999999,9999999,INDEX(stateTaxData[],MATCH(1,(stateTaxData[stateName]=CP$1)*(stateTaxData[taxYear]=$B$4)*(stateTaxData[FilingStatusFlag]=$B$8),0),MATCH($E17,stateTaxData[#Headers],0)))} -> 9999999 | CR17: {=IF(CR16=9999999,9999999,INDEX(stateTaxData[],MATCH(1,(stateTaxData[stateName]=CR$1)*(stateTaxData[taxYear]=$B$4)*(stateTaxData[FilingStatusFlag]=$B$8),0),MATCH($E17,stateTaxData[#Headers],0)))} -> 9999999 | CU17: {=IF(CU16=9999999,9999999,INDEX(stateTaxData[],MATCH(1,(stateTaxData[stateName]=CU$1)*(stateTaxData[taxYear]=$B$4)*(stateTaxData[FilingStatusFlag]=$B$8),0),MATCH($E17,stateTaxData[#Headers],0)))} -> 9999999 | CV17: {=IF(CV16=9999999,9999999,INDEX(stateTaxData[],MATCH(1,(stateTaxData[stateName]=CV$1)*(stateTaxData[taxYear]=$B$4)*(stateTaxData[FilingStatusFlag]=$B$8),0),MATCH($E17,stateTaxData[#Headers],0)))} -> 9999999 | CW17: {=IF(CW16=9999999,9999999,INDEX(stateTaxData[],MATCH(1,(stateTaxData[stateName]=CW$1)*(stateTaxData[taxYear]=$B$4)*(stateTaxData[FilingStatusFlag]=$B$8),0),MATCH($E17,stateTaxData[#Headers],0)))} -> 9999999 | CX17: {=IF(CX16=9999999,9999999,INDEX(stateTaxData[],MATCH(1,(stateTaxData[stateName]=CX$1)*(stateTaxData[taxYear]=$B$4)*(stateTaxData[FilingStatusFlag]=$B$8),0),MATCH($E17,stateTaxData[#Headers],0)))} -> 60000 | DB17: {=IF(DB16=9999999,9999999,INDEX(stateTaxData[],MATCH(1,(stateTaxData[stateName]=DB$1)*(stateTaxData[taxYear]=$B$4)*(stateTaxData[FilingStatusFlag]=$B$8),0),MATCH($E17,stateTaxData[#Headers],0)))} -> 9999999 | DC17: {=IF(DC16=9999999,9999999,INDEX(stateTaxData[],MATCH(1,(stateTaxData[stateName]=DC$1)*(stateTaxData[taxYear]=$B$4)*(stateTaxData[FilingStatusFlag]=$B$8),0),MATCH($E17,stateTaxData[#Headers],0)))} -> 9999999
A18: Single | B18: Single | E18: IncomeBin6Max | AD18: {=IF(AD17=9999999,9999999,INDEX(stateTaxData[],MATCH(1,(stateTaxData[stateName]=AD$1)*(stateTaxData[taxYear]=$B$4)*(stateTaxData[FilingStatusFlag]=$B$8),0),MATCH($E18,stateTaxData[#Headers],0)))} -> 9999999 | AF18: {=IF(AF17=9999999,9999999,INDEX(stateTaxData[],MATCH(1,(stateTaxData[stateName]=AF$1)*(stateTaxData[taxYear]=$B$4)*(stateTaxData[FilingStatusFlag]=$B$8),0),MATCH($E18,stateTaxData[#Headers],0)))} -> 9999999 | AH18: {=IF(AH17=9999999,9999999,INDEX(stateTaxData[],MATCH(1,(stateTaxData[stateName]=AH$1)*(stateTaxData[taxYear]=$B$4)*(stateTaxData[FilingStatusFlag]=$B$8),0),MATCH($E18,stateTaxData[#Headers],0)))} -> 9999999 | AJ18: =AL66 -> 84500 | AK18: =AL18 -> 9999999 | AL18: {=IF(AL17=9999999,9999999,INDEX(stateTaxData[],MATCH(1,(stateTaxData[stateName]=AL$1)*(stateTaxData[taxYear]=$B$4)*(stateTaxData[FilingStatusFlag]=$B$8),0),MATCH($E18,stateTaxData[#Headers],0)))} -> 9999999 | AO18: {=IF(AO17=9999999,9999999,INDEX(stateTaxData[],MATCH(1,(stateTaxData[stateName]=AO$1)*(stateTaxData[taxYear]=$B$4)*(stateTaxData[FilingStatusFlag]=$B$8),0),MATCH($E18,stateTaxData[#Headers],0)))} -> 66295 | AP18: {=IF(AP17=9999999,9999999,INDEX(stateTaxData[],MATCH(1,(stateTaxData[stateName]=AP$1)*(stateTaxData[taxYear]=$B$4)*(stateTaxData[FilingStatusFlag]=$B$8),0),MATCH($E18,stateTaxData[#Headers],0)))} -> 9999999 | AR18: {=IF(AR17=9999999,9999999,INDEX(stateTaxData[],MATCH(1,(stateTaxData[stateName]=AR$1)*(stateTaxData[taxYear]=$B$4)*(stateTaxData[FilingStatusFlag]=$B$8),0),MATCH($E18,stateTaxData[#Headers],0)))} -> 250000 | AS18: {=IF(AS17=9999999,9999999,INDEX(stateTaxData[],MATCH(1,(stateTaxData[stateName]=AS$1)*(stateTaxData[taxYear]=$B$4)*(stateTaxData[FilingStatusFlag]=$B$8),0),MATCH($E18,stateTaxData[#Headers],0)))} -> 60000 | AT18: {=IF(AT17=9999999,9999999,INDEX(stateTaxData[],MATCH(1,(stateTaxData[stateName]=AT$1)*(stateTaxData[taxYear]=$B$4)*(stateTaxData[FilingStatusFlag]=$B$8),0),MATCH($E18,stateTaxData[#Headers],0)))} -> 500000 | AU18: {=IF(AU17=9999999,9999999,INDEX(stateTaxData[],MATCH(1,(stateTaxData[stateName]=AU$1)*(stateTaxData[taxYear]=$B$4)*(stateTaxData[FilingStatusFlag]=$B$8),0),MATCH($E18,stateTaxData[#Headers],0)))} -> 9999999 | AV18: {=IF(AV17=9999999,9999999,INDEX(stateTaxData[],MATCH(1,(stateTaxData[stateName]=AV$1)*(stateTaxData[taxYear]=$B$4)*(stateTaxData[FilingStatusFlag]=$B$8),0),MATCH($E18,stateTaxData[#Headers],0)))} -> 7000 | AX18: {=IF(AX17=9999999,9999999,INDEX(stateTaxData[],MATCH(1,(stateTaxData[stateName]=AX$1)*(stateTaxData[taxYear]=$B$4)*(stateTaxData[FilingStatusFlag]=$B$8),0),MATCH($E18,stateTaxData[#Headers],0)))} -> 19200 | AY18: {=IF(AY17=9999999,9999999,INDEX(stateTaxData[],MATCH(1,(stateTaxData[stateName]=AY$1)*(stateTaxData[taxYear]=$B$4)*(stateTaxData[FilingStatusFlag]=$B$8),0),MATCH($E18,stateTaxData[#Headers],0)))} -> 9999999 | BA18: {=IF(BA17=9999999,9999999,INDEX(stateTaxData[],MATCH(1,(stateTaxData[stateName]=BA$1)*(stateTaxData[taxYear]=$B$4)*(stateTaxData[FilingStatusFlag]=$B$8),0),MATCH($E18,stateTaxData[#Headers],0)))} -> 9999999 | BB18: {=IF(BB17=9999999,9999999,INDEX(stateTaxData[],MATCH(1,(stateTaxData[stateName]=BB$1)*(stateTaxData[taxYear]=$B$4)*(stateTaxData[FilingStatusFlag]=$B$8),0),MATCH($E18,stateTaxData[#Headers],0)))} -> 9999999 | BC18: {=IF(BC17=9999999,9999999,INDEX(stateTaxData[],MATCH(1,(stateTaxData[stateName]=BC$1)*(stateTaxData[taxYear]=$B$4)*(stateTaxData[FilingStatusFlag]=$B$8),0),MATCH($E18,stateTaxData[#Headers],0)))} -> 9999999 | BD18: {=IF(BD17=9999999,9999999,INDEX(stateTaxData[],MATCH(1,(stateTaxData[stateName]=BD$1)*(stateTaxData[taxYear]=$B$4)*(stateTaxData[FilingStatusFlag]=$B$8),0),MATCH($E18,stateTaxData[#Headers],0)))} -> 9999999 | BE18: {=IF(BE17=9999999,9999999,INDEX(stateTaxData[],MATCH(1,(stateTaxData[stateName]=BE$1)*(stateTaxData[taxYear]=$B$4)*(stateTaxData[FilingStatusFlag]=$B$8),0),MATCH($E18,stateTaxData[#Headers],0)))} -> 9999999 | BF18: {=IF(BF17=9999999,9999999,INDEX(stateTaxData[],MATCH(1,(stateTaxData[stateName]=BF$1)*(stateTaxData[taxYear]=$B$4)*(stateTaxData[FilingStatusFlag]=$B$8),0),MATCH($E18,stateTaxData[#Headers],0)))} -> 9999999 | BH18: {=IF(BH17=9999999,9999999,INDEX(stateTaxData[],MATCH(1,(stateTaxData[stateName]=BH$1)*(stateTaxData[taxYear]=$B$4)*(stateTaxData[FilingStatusFlag]=$B$8),0),MATCH($E18,stateTaxData[#Headers],0)))} -> 9999999 | BJ18: {=IF(BJ17=9999999,9999999,INDEX(stateTaxData[],MATCH(1,(stateTaxData[stateName]=BJ$1)*(stateTaxData[taxYear]=$B$4)*(stateTaxData[FilingStatusFlag]=$B$8),0),MATCH($E18,stateTaxData[#Headers],0)))} -> 125000 | BK18: {=IF(BK17=9999999,9999999,INDEX(stateTaxData[],MATCH(1,(stateTaxData[stateName]=BK$1)*(stateTaxData[taxYear]=$B$4)*(stateTaxData[FilingStatusFlag]=$B$8),0),MATCH($E18,stateTaxData[#Headers],0)))} -> 9999999 | BL18: {=IF(BL17=9999999,9999999,INDEX(stateTaxData[],MATCH(1,(stateTaxData[stateName]=BL$1)*(stateTaxData[taxYear]=$B$4)*(stateTaxData[FilingStatusFlag]=$B$8),0),MATCH($E18,stateTaxData[#Headers],0)))} -> 9999999 | BN18: {=IF(BN17=9999999,9999999,INDEX(stateTaxData[],MATCH(1,(stateTaxData[stateName]=BN$1)*(stateTaxData[taxYear]=$B$4)*(stateTaxData[FilingStatusFlag]=$B$8),0),MATCH($E18,stateTaxData[#Headers],0)))} -> 9999999 | BO18: {=IF(BO17=9999999,9999999,INDEX(stateTaxData[],MATCH(1,(stateTaxData[stateName]=BO$1)*(stateTaxData[taxYear]=$B$4)*(stateTaxData[FilingStatusFlag]=$B$8),0),MATCH($E18,stateTaxData[#Headers],0)))} -> 9999999 | BQ18: {=IF(BQ17=9999999,9999999,INDEX(stateTaxData[],MATCH(1,(stateTaxData[stateName]=BQ$1)*(stateTaxData[taxYear]=$B$4)*(stateTaxData[FilingStatusFlag]=$B$8),0),MATCH($E18,stateTaxData[#Headers],0)))} -> 7242 | BT18: {=IF(BT17=9999999,9999999,INDEX(stateTaxData[],MATCH(1,(stateTaxData[stateName]=BT$1)*(stateTaxData[taxYear]=$B$4)*(stateTaxData[FilingStatusFlag]=$B$8),0),MATCH($E18,stateTaxData[#Headers],0)))} -> 16800 | BU18: {=IF(BU17=9999999,9999999,INDEX(stateTaxData[],MATCH(1,(stateTaxData[stateName]=BU$1)*(stateTaxData[taxYear]=$B$4)*(stateTaxData[FilingStatusFlag]=$B$8),0),MATCH($E18,stateTaxData[#Headers],0)))} -> 9999999 | BV18: {=IF(BV17=9999999,9999999,INDEX(stateTaxData[],MATCH(1,(stateTaxData[stateName]=BV$1)*(stateTaxData[taxYear]=$B$4)*(stateTaxData[FilingStatusFlag]=$B$8),0),MATCH($E18,stateTaxData[#Headers],0)))} -> 9999999 | BW18: {=IF(BW17=9999999,9999999,INDEX(stateTaxData[],MATCH(1,(stateTaxData[stateName]=BW$1)*(stateTaxData[taxYear]=$B$4)*(stateTaxData[FilingStatusFlag]=$B$8),0),MATCH($E18,stateTaxData[#Headers],0)))} -> 9999999 | BX18: {=IF(BX17=9999999,9999999,INDEX(stateTaxData[],MATCH(1,(stateTaxData[stateName]=BX$1)*(stateTaxData[taxYear]=$B$4)*(stateTaxData[FilingStatusFlag]=$B$8),0),MATCH($E18,stateTaxData[#Headers],0)))} -> 500000 | BY18: {=IF(BY17=9999999,9999999,INDEX(stateTaxData[],MATCH(1,(stateTaxData[stateName]=BY$1)*(stateTaxData[taxYear]=$B$4)*(stateTaxData[FilingStatusFlag]=$B$8),0),MATCH($E18,stateTaxData[#Headers],0)))} -> 9999999 | BZ18: {=IF(BZ17=9999999,9999999,INDEX(stateTaxData[],MATCH(1,(stateTaxData[stateName]=BZ$1)*(stateTaxData[taxYear]=$B$4)*(stateTaxData[FilingStatusFlag]=$B$8),0),MATCH($E18,stateTaxData[#Headers],0)))} -> 215400 | CA18: {=IF(CA17=9999999,9999999,INDEX(stateTaxData[],MATCH(1,(stateTaxData[stateName]=CA$1)*(stateTaxData[taxYear]=$B$4)*(stateTaxData[FilingStatusFlag]=$B$8),0),MATCH($E18,stateTaxData[#Headers],0)))} -> 9999999 | CC18: {=IF(CC17=9999999,9999999,INDEX(stateTaxData[],MATCH(1,(stateTaxData[stateName]=CC$1)*(stateTaxData[taxYear]=$B$4)*(stateTaxData[FilingStatusFlag]=$B$8),0),MATCH($E18,stateTaxData[#Headers],0)))} -> 9999999 | CE18: {=IF(CE17=9999999,9999999,INDEX(stateTaxData[],MATCH(1,(stateTaxData[stateName]=CE$1)*(stateTaxData[taxYear]=$B$4)*(stateTaxData[FilingStatusFlag]=$B$8),0),MATCH($E18,stateTaxData[#Headers],0)))} -> 9999999 | CF18: {=IF(CF17=9999999,9999999,INDEX(stateTaxData[],MATCH(1,(stateTaxData[stateName]=CF$1)*(stateTaxData[taxYear]=$B$4)*(stateTaxData[FilingStatusFlag]=$B$8),0),MATCH($E18,stateTaxData[#Headers],0)))} -> 7200 | CH18: {=IF(CH17=9999999,9999999,INDEX(stateTaxData[],MATCH(1,(stateTaxData[stateName]=CH$1)*(stateTaxData[taxYear]=$B$4)*(stateTaxData[FilingStatusFlag]=$B$8),0),MATCH($E18,stateTaxData[#Headers],0)))} -> 9999999 | CI18: {=IF(CI17=9999999,9999999,INDEX(stateTaxData[],MATCH(1,(stateTaxData[stateName]=CI$1)*(stateTaxData[taxYear]=$B$4)*(stateTaxData[FilingStatusFlag]=$B$8),0),MATCH($E18,stateTaxData[#Headers],0)))} -> 9999999 | CK18: {=IF(CK17=9999999,9999999,INDEX(stateTaxData[],MATCH(1,(stateTaxData[stateName]=CK$1)*(stateTaxData[taxYear]=$B$4)*(stateTaxData[FilingStatusFlag]=$B$8),0),MATCH($E18,stateTaxData[#Headers],0)))} -> 9999999 | CL18: {=IF(CL17=9999999,9999999,INDEX(stateTaxData[],MATCH(1,(stateTaxData[stateName]=CL$1)*(stateTaxData[taxYear]=$B$4)*(stateTaxData[FilingStatusFlag]=$B$8),0),MATCH($E18,stateTaxData[#Headers],0)))} -> 9999999 | CN18: {=IF(CN17=9999999,9999999,INDEX(stateTaxData[],MATCH(1,(stateTaxData[stateName]=CN$1)*(stateTaxData[taxYear]=$B$4)*(stateTaxData[FilingStatusFlag]=$B$8),0),MATCH($E18,stateTaxData[#Headers],0)))} -> 9999999 | CO18: {=IF(CO17=9999999,9999999,INDEX(stateTaxData[],MATCH(1,(stateTaxData[stateName]=CO$1)*(stateTaxData[taxYear]=$B$4)*(stateTaxData[FilingStatusFlag]=$B$8),0),MATCH($E18,stateTaxData[#Headers],0)))} -> 9999999 | CP18: {=IF(CP17=9999999,9999999,INDEX(stateTaxData[],MATCH(1,(stateTaxData[stateName]=CP$1)*(stateTaxData[taxYear]=$B$4)*(stateTaxData[FilingStatusFlag]=$B$8),0),MATCH($E18,stateTaxData[#Headers],0)))} -> 9999999 | CR18: {=IF(CR17=9999999,9999999,INDEX(stateTaxData[],MATCH(1,(stateTaxData[stateName]=CR$1)*(stateTaxData[taxYear]=$B$4)*(stateTaxData[FilingStatusFlag]=$B$8),0),MATCH($E18,stateTaxData[#Headers],0)))} -> 9999999 | CU18: {=IF(CU17=9999999,9999999,INDEX(stateTaxData[],MATCH(1,(stateTaxData[stateName]=CU$1)*(stateTaxData[taxYear]=$B$4)*(stateTaxData[FilingStatusFlag]=$B$8),0),MATCH($E18,stateTaxData[#Headers],0)))} -> 9999999 | CV18: {=IF(CV17=9999999,9999999,INDEX(stateTaxData[],MATCH(1,(stateTaxData[stateName]=CV$1)*(stateTaxData[taxYear]=$B$4)*(stateTaxData[FilingStatusFlag]=$B$8),0),MATCH($E18,stateTaxData[#Headers],0)))} -> 9999999 | CW18: {=IF(CW17=9999999,9999999,INDEX(stateTaxData[],MATCH(1,(stateTaxData[stateName]=CW$1)*(stateTaxData[taxYear]=$B$4)*(stateTaxData[FilingStatusFlag]=$B$8),0),MATCH($E18,stateTaxData[#Headers],0)))} -> 9999999 | CX18: {=IF(CX17=9999999,9999999,INDEX(stateTaxData[],MATCH(1,(stateTaxData[stateName]=CX$1)*(stateTaxData[taxYear]=$B$4)*(stateTaxData[FilingStatusFlag]=$B$8),0),MATCH($E18,stateTaxData[#Headers],0)))} -> 9999999 | DB18: {=IF(DB17=9999999,9999999,INDEX(stateTaxData[],MATCH(1,(stateTaxData[stateName]=DB$1)*(stateTaxData[taxYear]=$B$4)*(stateTaxData[FilingStatusFlag]=$B$8),0),MATCH($E18,stateTaxData[#Headers],0)))} -> 9999999 | DC18: {=IF(DC17=9999999,9999999,INDEX(stateTaxData[],MATCH(1,(stateTaxData[stateName]=DC$1)*(stateTaxData[taxYear]=$B$4)*(stateTaxData[FilingStatusFlag]=$B$8),0),MATCH($E18,stateTaxData[#Headers],0)))} -> 9999999 | DW18: Cap on Rate (MN)? | EU18: TRUE
A19: HOH | B19: Head of Household | E19: IncomeBin7Max | AD19: {=IF(AD18=9999999,9999999,INDEX(stateTaxData[],MATCH(1,(stateTaxData[stateName]=AD$1)*(stateTaxData[taxYear]=$B$4)*(stateTaxData[FilingStatusFlag]=$B$8),0),MATCH($E19,stateTaxData[#Headers],0)))} -> 9999999 | AF19: {=IF(AF18=9999999,9999999,INDEX(stateTaxData[],MATCH(1,(stateTaxData[stateName]=AF$1)*(stateTaxData[taxYear]=$B$4)*(stateTaxData[FilingStatusFlag]=$B$8),0),MATCH($E19,stateTaxData[#Headers],0)))} -> 9999999 | AH19: {=IF(AH18=9999999,9999999,INDEX(stateTaxData[],MATCH(1,(stateTaxData[stateName]=AH$1)*(stateTaxData[taxYear]=$B$4)*(stateTaxData[FilingStatusFlag]=$B$8),0),MATCH($E19,stateTaxData[#Headers],0)))} -> 9999999 | AJ19: =AK19 -> 9999999 | AK19: =AL19 -> 9999999 | AL19: {=IF(AL18=9999999,9999999,INDEX(stateTaxData[],MATCH(1,(stateTaxData[stateName]=AL$1)*(stateTaxData[taxYear]=$B$4)*(stateTaxData[FilingStatusFlag]=$B$8),0),MATCH($E19,stateTaxData[#Headers],0)))} -> 9999999 | AO19: {=IF(AO18=9999999,9999999,INDEX(stateTaxData[],MATCH(1,(stateTaxData[stateName]=AO$1)*(stateTaxData[taxYear]=$B$4)*(stateTaxData[FilingStatusFlag]=$B$8),0),MATCH($E19,stateTaxData[#Headers],0)))} -> 338639 | AP19: {=IF(AP18=9999999,9999999,INDEX(stateTaxData[],MATCH(1,(stateTaxData[stateName]=AP$1)*(stateTaxData[taxYear]=$B$4)*(stateTaxData[FilingStatusFlag]=$B$8),0),MATCH($E19,stateTaxData[#Headers],0)))} -> 9999999 | AR19: {=IF(AR18=9999999,9999999,INDEX(stateTaxData[],MATCH(1,(stateTaxData[stateName]=AR$1)*(stateTaxData[taxYear]=$B$4)*(stateTaxData[FilingStatusFlag]=$B$8),0),MATCH($E19,stateTaxData[#Headers],0)))} -> 500000 | AS19: {=IF(AS18=9999999,9999999,INDEX(stateTaxData[],MATCH(1,(stateTaxData[stateName]=AS$1)*(stateTaxData[taxYear]=$B$4)*(stateTaxData[FilingStatusFlag]=$B$8),0),MATCH($E19,stateTaxData[#Headers],0)))} -> 9999999 | AT19: {=IF(AT18=9999999,9999999,INDEX(stateTaxData[],MATCH(1,(stateTaxData[stateName]=AT$1)*(stateTaxData[taxYear]=$B$4)*(stateTaxData[FilingStatusFlag]=$B$8),0),MATCH($E19,stateTaxData[#Headers],0)))} -> 1000000 | AU19: {=IF(AU18=9999999,9999999,INDEX(stateTaxData[],MATCH(1,(stateTaxData[stateName]=AU$1)*(stateTaxData[taxYear]=$B$4)*(stateTaxData[FilingStatusFlag]=$B$8),0),MATCH($E19,stateTaxData[#Headers],0)))} -> 9999999 | AV19: {=IF(AV18=9999999,9999999,INDEX(stateTaxData[],MATCH(1,(stateTaxData[stateName]=AV$1)*(stateTaxData[taxYear]=$B$4)*(stateTaxData[FilingStatusFlag]=$B$8),0),MATCH($E19,stateTaxData[#Headers],0)))} -> 9999999 | AX19: {=IF(AX18=9999999,9999999,INDEX(stateTaxData[],MATCH(1,(stateTaxData[stateName]=AX$1)*(stateTaxData[taxYear]=$B$4)*(stateTaxData[FilingStatusFlag]=$B$8),0),MATCH($E19,stateTaxData[#Headers],0)))} -> 24000 | AY19: {=IF(AY18=9999999,9999999,INDEX(stateTaxData[],MATCH(1,(stateTaxData[stateName]=AY$1)*(stateTaxData[taxYear]=$B$4)*(stateTaxData[FilingStatusFlag]=$B$8),0),MATCH($E19,stateTaxData[#Headers],0)))} -> 9999999 | BA19: {=IF(BA18=9999999,9999999,INDEX(stateTaxData[],MATCH(1,(stateTaxData[stateName]=BA$1)*(stateTaxData[taxYear]=$B$4)*(stateTaxData[FilingStatusFlag]=$B$8),0),MATCH($E19,stateTaxData[#Headers],0)))} -> 9999999 | BB19: {=IF(BB18=9999999,9999999,INDEX(stateTaxData[],MATCH(1,(stateTaxData[stateName]=BB$1)*(stateTaxData[taxYear]=$B$4)*(stateTaxData[FilingStatusFlag]=$B$8),0),MATCH($E19,stateTaxData[#Headers],0)))} -> 9999999 | BC19: {=IF(BC18=9999999,9999999,INDEX(stateTaxData[],MATCH(1,(stateTaxData[stateName]=BC$1)*(stateTaxData[taxYear]=$B$4)*(stateTaxData[FilingStatusFlag]=$B$8),0),MATCH($E19,stateTaxData[#Headers],0)))} -> 9999999 | BD19: {=IF(BD18=9999999,9999999,INDEX(stateTaxData[],MATCH(1,(stateTaxData[stateName]=BD$1)*(stateTaxData[taxYear]=$B$4)*(stateTaxData[FilingStatusFlag]=$B$8),0),MATCH($E19,stateTaxData[#Headers],0)))} -> 9999999 | BE19: {=IF(BE18=9999999,9999999,INDEX(stateTaxData[],MATCH(1,(stateTaxData[stateName]=BE$1)*(stateTaxData[taxYear]=$B$4)*(stateTaxData[FilingStatusFlag]=$B$8),0),MATCH($E19,stateTaxData[#Headers],0)))} -> 9999999 | BF19: {=IF(BF18=9999999,9999999,INDEX(stateTaxData[],MATCH(1,(stateTaxData[stateName]=BF$1)*(stateTaxData[taxYear]=$B$4)*(stateTaxData[FilingStatusFlag]=$B$8),0),MATCH($E19,stateTaxData[#Headers],0)))} -> 9999999 | BH19: {=IF(BH18=9999999,9999999,INDEX(stateTaxData[],MATCH(1,(stateTaxData[stateName]=BH$1)*(stateTaxData[taxYear]=$B$4)*(stateTaxData[FilingStatusFlag]=$B$8),0),MATCH($E19,stateTaxData[#Headers],0)))} -> 9999999 | BJ19: {=IF(BJ18=9999999,9999999,INDEX(stateTaxData[],MATCH(1,(stateTaxData[stateName]=BJ$1)*(stateTaxData[taxYear]=$B$4)*(stateTaxData[FilingStatusFlag]=$B$8),0),MATCH($E19,stateTaxData[#Headers],0)))} -> 150000 | BK19: {=IF(BK18=9999999,9999999,INDEX(stateTaxData[],MATCH(1,(stateTaxData[stateName]=BK$1)*(stateTaxData[taxYear]=$B$4)*(stateTaxData[FilingStatusFlag]=$B$8),0),MATCH($E19,stateTaxData[#Headers],0)))} -> 9999999 | BL19: {=IF(BL18=9999999,9999999,INDEX(stateTaxData[],MATCH(1,(stateTaxData[stateName]=BL$1)*(stateTaxData[taxYear]=$B$4)*(stateTaxData[FilingStatusFlag]=$B$8),0),MATCH($E19,stateTaxData[#Headers],0)))} -> 9999999 | BN19: {=IF(BN18=9999999,9999999,INDEX(stateTaxData[],MATCH(1,(stateTaxData[stateName]=BN$1)*(stateTaxData[taxYear]=$B$4)*(stateTaxData[FilingStatusFlag]=$B$8),0),MATCH($E19,stateTaxData[#Headers],0)))} -> 9999999 | BO19: {=IF(BO18=9999999,9999999,INDEX(stateTaxData[],MATCH(1,(stateTaxData[stateName]=BO$1)*(stateTaxData[taxYear]=$B$4)*(stateTaxData[FilingStatusFlag]=$B$8),0),MATCH($E19,stateTaxData[#Headers],0)))} -> 9999999 | BQ19: {=IF(BQ18=9999999,9999999,INDEX(stateTaxData[],MATCH(1,(stateTaxData[stateName]=BQ$1)*(stateTaxData[taxYear]=$B$4)*(stateTaxData[FilingStatusFlag]=$B$8),0),MATCH($E19,stateTaxData[#Headers],0)))} -> 8449 | BT19: {=IF(BT18=9999999,9999999,INDEX(stateTaxData[],MATCH(1,(stateTaxData[stateName]=BT$1)*(stateTaxData[taxYear]=$B$4)*(stateTaxData[FilingStatusFlag]=$B$8),0),MATCH($E19,stateTaxData[#Headers],0)))} -> 21600 | BU19: {=IF(BU18=9999999,9999999,INDEX(stateTaxData[],MATCH(1,(stateTaxData[stateName]=BU$1)*(stateTaxData[taxYear]=$B$4)*(stateTaxData[FilingStatusFlag]=$B$8),0),MATCH($E19,stateTaxData[#Headers],0)))} -> 9999999 | BV19: {=IF(BV18=9999999,9999999,INDEX(stateTaxData[],MATCH(1,(stateTaxData[stateName]=BV$1)*(stateTaxData[taxYear]=$B$4)*(stateTaxData[FilingStatusFlag]=$B$8),0),MATCH($E19,stateTaxData[#Headers],0)))} -> 9999999 | BW19: {=IF(BW18=9999999,9999999,INDEX(stateTaxData[],MATCH(1,(stateTaxData[stateName]=BW$1)*(stateTaxData[taxYear]=$B$4)*(stateTaxData[FilingStatusFlag]=$B$8),0),MATCH($E19,stateTaxData[#Headers],0)))} -> 9999999 | BX19: {=IF(BX18=9999999,9999999,INDEX(stateTaxData[],MATCH(1,(stateTaxData[stateName]=BX$1)*(stateTaxData[taxYear]=$B$4)*(stateTaxData[FilingStatusFlag]=$B$8),0),MATCH($E19,stateTaxData[#Headers],0)))} -> 1000000 | BY19: {=IF(BY18=9999999,9999999,INDEX(stateTaxData[],MATCH(1,(stateTaxData[stateName]=BY$1)*(stateTaxData[taxYear]=$B$4)*(stateTaxData[FilingStatusFlag]=$B$8),0),MATCH($E19,stateTaxData[#Headers],0)))} -> 9999999 | BZ19: {=IF(BZ18=9999999,9999999,INDEX(stateTaxData[],MATCH(1,(stateTaxData[stateName]=BZ$1)*(stateTaxData[taxYear]=$B$4)*(stateTaxData[FilingStatusFlag]=$B$8),0),MATCH($E19,stateTaxData[#Headers],0)))} -> 1077550 | CA19: {=IF(CA18=9999999,9999999,INDEX(stateTaxData[],MATCH(1,(stateTaxData[stateName]=CA$1)*(stateTaxData[taxYear]=$B$4)*(stateTaxData[FilingStatusFlag]=$B$8),0),MATCH($E19,stateTaxData[#Headers],0)))} -> 9999999 | CC19: {=IF(CC18=9999999,9999999,INDEX(stateTaxData[],MATCH(1,(stateTaxData[stateName]=CC$1)*(stateTaxData[taxYear]=$B$4)*(stateTaxData[FilingStatusFlag]=$B$8),0),MATCH($E19,stateTaxData[#Headers],0)))} -> 9999999 | CE19: {=IF(CE18=9999999,9999999,INDEX(stateTaxData[],MATCH(1,(stateTaxData[stateName]=CE$1)*(stateTaxData[taxYear]=$B$4)*(stateTaxData[FilingStatusFlag]=$B$8),0),MATCH($E19,stateTaxData[#Headers],0)))} -> 9999999 | CF19: {=IF(CF18=9999999,9999999,INDEX(stateTaxData[],MATCH(1,(stateTaxData[stateName]=CF$1)*(stateTaxData[taxYear]=$B$4)*(stateTaxData[FilingStatusFlag]=$B$8),0),MATCH($E19,stateTaxData[#Headers],0)))} -> 9999999 | CH19: {=IF(CH18=9999999,9999999,INDEX(stateTaxData[],MATCH(1,(stateTaxData[stateName]=CH$1)*(stateTaxData[taxYear]=$B$4)*(stateTaxData[FilingStatusFlag]=$B$8),0),MATCH($E19,stateTaxData[#Headers],0)))} -> 9999999 | CI19: {=IF(CI18=9999999,9999999,INDEX(stateTaxData[],MATCH(1,(stateTaxData[stateName]=CI$1)*(stateTaxData[taxYear]=$B$4)*(stateTaxData[FilingStatusFlag]=$B$8),0),MATCH($E19,stateTaxData[#Headers],0)))} -> 9999999 | CK19: {=IF(CK18=9999999,9999999,INDEX(stateTaxData[],MATCH(1,(stateTaxData[stateName]=CK$1)*(stateTaxData[taxYear]=$B$4)*(stateTaxData[FilingStatusFlag]=$B$8),0),MATCH($E19,stateTaxData[#Headers],0)))} -> 9999999 | CL19: {=IF(CL18=9999999,9999999,INDEX(stateTaxData[],MATCH(1,(stateTaxData[stateName]=CL$1)*(stateTaxData[taxYear]=$B$4)*(stateTaxData[FilingStatusFlag]=$B$8),0),MATCH($E19,stateTaxData[#Headers],0)))} -> 9999999 | CN19: {=IF(CN18=9999999,9999999,INDEX(stateTaxData[],MATCH(1,(stateTaxData[stateName]=CN$1)*(stateTaxData[taxYear]=$B$4)*(stateTaxData[FilingStatusFlag]=$B$8),0),MATCH($E19,stateTaxData[#Headers],0)))} -> 9999999 | CO19: {=IF(CO18=9999999,9999999,INDEX(stateTaxData[],MATCH(1,(stateTaxData[stateName]=CO$1)*(stateTaxData[taxYear]=$B$4)*(stateTaxData[FilingStatusFlag]=$B$8),0),MATCH($E19,stateTaxData[#Headers],0)))} -> 9999999 | CP19: {=IF(CP18=9999999,9999999,INDEX(stateTaxData[],MATCH(1,(stateTaxData[stateName]=CP$1)*(stateTaxData[taxYear]=$B$4)*(stateTaxData[FilingStatusFlag]=$B$8),0),MATCH($E19,stateTaxData[#Headers],0)))} -> 9999999 | CR19: {=IF(CR18=9999999,9999999,INDEX(stateTaxData[],MATCH(1,(stateTaxData[stateName]=CR$1)*(stateTaxData[taxYear]=$B$4)*(stateTaxData[FilingStatusFlag]=$B$8),0),MATCH($E19,stateTaxData[#Headers],0)))} -> 9999999 | CU19: {=IF(CU18=9999999,9999999,INDEX(stateTaxData[],MATCH(1,(stateTaxData[stateName]=CU$1)*(stateTaxData[taxYear]=$B$4)*(stateTaxData[FilingStatusFlag]=$B$8),0),MATCH($E19,stateTaxData[#Headers],0)))} -> 9999999 | CV19: {=IF(CV18=9999999,9999999,INDEX(stateTaxData[],MATCH(1,(stateTaxData[stateName]=CV$1)*(stateTaxData[taxYear]=$B$4)*(stateTaxData[FilingStatusFlag]=$B$8),0),MATCH($E19,stateTaxData[#Headers],0)))} -> 9999999 | CW19: {=IF(CW18=9999999,9999999,INDEX(stateTaxData[],MATCH(1,(stateTaxData[stateName]=CW$1)*(stateTaxData[taxYear]=$B$4)*(stateTaxData[FilingStatusFlag]=$B$8),0),MATCH($E19,stateTaxData[#Headers],0)))} -> 9999999 | CX19: {=IF(CX18=9999999,9999999,INDEX(stateTaxData[],MATCH(1,(stateTaxData[stateName]=CX$1)*(stateTaxData[taxYear]=$B$4)*(stateTaxData[FilingStatusFlag]=$B$8),0),MATCH($E19,stateTaxData[#Headers],0)))} -> 9999999 | DB19: {=IF(DB18=9999999,9999999,INDEX(stateTaxData[],MATCH(1,(stateTaxData[stateName]=DB$1)*(stateTaxData[taxYear]=$B$4)*(stateTaxData[FilingStatusFlag]=$B$8),0),MATCH($E19,stateTaxData[#Headers],0)))} -> 9999999 | DC19: {=IF(DC18=9999999,9999999,INDEX(stateTaxData[],MATCH(1,(stateTaxData[stateName]=DC$1)*(stateTaxData[taxYear]=$B$4)*(stateTaxData[FilingStatusFlag]=$B$8),0),MATCH($E19,stateTaxData[#Headers],0)))} -> 9999999 | DW19: Cap (MN) | ET19: 1. Fed AGI
A20: MFJ | B20: Married Filing Jointly | E20: IncomeBin8Max | AD20: {=IF(AD19=9999999,9999999,INDEX(stateTaxData[],MATCH(1,(stateTaxData[stateName]=AD$1)*(stateTaxData[taxYear]=$B$4)*(stateTaxData[FilingStatusFlag]=$B$8),0),MATCH($E20,stateTaxData[#Headers],0)))} -> 9999999 | AF20: {=IF(AF19=9999999,9999999,INDEX(stateTaxData[],MATCH(1,(stateTaxData[stateName]=AF$1)*(stateTaxData[taxYear]=$B$4)*(stateTaxData[FilingStatusFlag]=$B$8),0),MATCH($E20,stateTaxData[#Headers],0)))} -> 9999999 | AH20: {=IF(AH19=9999999,9999999,INDEX(stateTaxData[],MATCH(1,(stateTaxData[stateName]=AH$1)*(stateTaxData[taxYear]=$B$4)*(stateTaxData[FilingStatusFlag]=$B$8),0),MATCH($E20,stateTaxData[#Headers],0)))} -> 9999999 | AJ20: =AK20 -> 9999999 | AK20: =AL20 -> 9999999 | AL20: {=IF(AL19=9999999,9999999,INDEX(stateTaxData[],MATCH(1,(stateTaxData[stateName]=AL$1)*(stateTaxData[taxYear]=$B$4)*(stateTaxData[FilingStatusFlag]=$B$8),0),MATCH($E20,stateTaxData[#Headers],0)))} -> 9999999 | AO20: {=IF(AO19=9999999,9999999,INDEX(stateTaxData[],MATCH(1,(stateTaxData[stateName]=AO$1)*(stateTaxData[taxYear]=$B$4)*(stateTaxData[FilingStatusFlag]=$B$8),0),MATCH($E20,stateTaxData[#Headers],0)))} -> 406364 | AP20: {=IF(AP19=9999999,9999999,INDEX(stateTaxData[],MATCH(1,(stateTaxData[stateName]=AP$1)*(stateTaxData[taxYear]=$B$4)*(stateTaxData[FilingStatusFlag]=$B$8),0),MATCH($E20,stateTaxData[#Headers],0)))} -> 9999999 | AR20: {=IF(AR19=9999999,9999999,INDEX(stateTaxData[],MATCH(1,(stateTaxData[stateName]=AR$1)*(stateTaxData[taxYear]=$B$4)*(stateTaxData[FilingStatusFlag]=$B$8),0),MATCH($E20,stateTaxData[#Headers],0)))} -> 9999999 | AS20: {=IF(AS19=9999999,9999999,INDEX(stateTaxData[],MATCH(1,(stateTaxData[stateName]=AS$1)*(stateTaxData[taxYear]=$B$4)*(stateTaxData[FilingStatusFlag]=$B$8),0),MATCH($E20,stateTaxData[#Headers],0)))} -> 9999999 | AT20: {=IF(AT19=9999999,9999999,INDEX(stateTaxData[],MATCH(1,(stateTaxData[stateName]=AT$1)*(stateTaxData[taxYear]=$B$4)*(stateTaxData[FilingStatusFlag]=$B$8),0),MATCH($E20,stateTaxData[#Headers],0)))} -> 9999999 | AU20: {=IF(AU19=9999999,9999999,INDEX(stateTaxData[],MATCH(1,(stateTaxData[stateName]=AU$1)*(stateTaxData[taxYear]=$B$4)*(stateTaxData[FilingStatusFlag]=$B$8),0),MATCH($E20,stateTaxData[#Headers],0)))} -> 9999999 | AV20: {=IF(AV19=9999999,9999999,INDEX(stateTaxData[],MATCH(1,(stateTaxData[stateName]=AV$1)*(stateTaxData[taxYear]=$B$4)*(stateTaxData[FilingStatusFlag]=$B$8),0),MATCH($E20,stateTaxData[#Headers],0)))} -> 9999999 | AX20: {=IF(AX19=9999999,9999999,INDEX(stateTaxData[],MATCH(1,(stateTaxData[stateName]=AX$1)*(stateTaxData[taxYear]=$B$4)*(stateTaxData[FilingStatusFlag]=$B$8),0),MATCH($E20,stateTaxData[#Headers],0)))} -> 36000 | AY20: {=IF(AY19=9999999,9999999,INDEX(stateTaxData[],MATCH(1,(stateTaxData[stateName]=AY$1)*(stateTaxData[taxYear]=$B$4)*(stateTaxData[FilingStatusFlag]=$B$8),0),MATCH($E20,stateTaxData[#Headers],0)))} -> 9999999 | BA20: {=IF(BA19=9999999,9999999,INDEX(stateTaxData[],MATCH(1,(stateTaxData[stateName]=BA$1)*(stateTaxData[taxYear]=$B$4)*(stateTaxData[FilingStatusFlag]=$B$8),0),MATCH($E20,stateTaxData[#Headers],0)))} -> 9999999 | BB20: {=IF(BB19=9999999,9999999,INDEX(stateTaxData[],MATCH(1,(stateTaxData[stateName]=BB$1)*(stateTaxData[taxYear]=$B$4)*(stateTaxData[FilingStatusFlag]=$B$8),0),MATCH($E20,stateTaxData[#Headers],0)))} -> 9999999 | BC20: {=IF(BC19=9999999,9999999,INDEX(stateTaxData[],MATCH(1,(stateTaxData[stateName]=BC$1)*(stateTaxData[taxYear]=$B$4)*(stateTaxData[FilingStatusFlag]=$B$8),0),MATCH($E20,stateTaxData[#Headers],0)))} -> 9999999 | BD20: {=IF(BD19=9999999,9999999,INDEX(stateTaxData[],MATCH(1,(stateTaxData[stateName]=BD$1)*(stateTaxData[taxYear]=$B$4)*(stateTaxData[FilingStatusFlag]=$B$8),0),MATCH($E20,stateTaxData[#Headers],0)))} -> 9999999 | BE20: {=IF(BE19=9999999,9999999,INDEX(stateTaxData[],MATCH(1,(stateTaxData[stateName]=BE$1)*(stateTaxData[taxYear]=$B$4)*(stateTaxData[FilingStatusFlag]=$B$8),0),MATCH($E20,stateTaxData[#Headers],0)))} -> 9999999 | BF20: {=IF(BF19=9999999,9999999,INDEX(stateTaxData[],MATCH(1,(stateTaxData[stateName]=BF$1)*(stateTaxData[taxYear]=$B$4)*(stateTaxData[FilingStatusFlag]=$B$8),0),MATCH($E20,stateTaxData[#Headers],0)))} -> 9999999 | BH20: {=IF(BH19=9999999,9999999,INDEX(stateTaxData[],MATCH(1,(stateTaxData[stateName]=BH$1)*(stateTaxData[taxYear]=$B$4)*(stateTaxData[FilingStatusFlag]=$B$8),0),MATCH($E20,stateTaxData[#Headers],0)))} -> 9999999 | BJ20: {=IF(BJ19=9999999,9999999,INDEX(stateTaxData[],MATCH(1,(stateTaxData[stateName]=BJ$1)*(stateTaxData[taxYear]=$B$4)*(stateTaxData[FilingStatusFlag]=$B$8),0),MATCH($E20,stateTaxData[#Headers],0)))} -> 250000 | BK20: {=IF(BK19=9999999,9999999,INDEX(stateTaxData[],MATCH(1,(stateTaxData[stateName]=BK$1)*(stateTaxData[taxYear]=$B$4)*(stateTaxData[FilingStatusFlag]=$B$8),0),MATCH($E20,stateTaxData[#Headers],0)))} -> 9999999 | BL20: {=IF(BL19=9999999,9999999,INDEX(stateTaxData[],MATCH(1,(stateTaxData[stateName]=BL$1)*(stateTaxData[taxYear]=$B$4)*(stateTaxData[FilingStatusFlag]=$B$8),0),MATCH($E20,stateTaxData[#Headers],0)))} -> 9999999 | BN20: {=IF(BN19=9999999,9999999,INDEX(stateTaxData[],MATCH(1,(stateTaxData[stateName]=BN$1)*(stateTaxData[taxYear]=$B$4)*(stateTaxData[FilingStatusFlag]=$B$8),0),MATCH($E20,stateTaxData[#Headers],0)))} -> 9999999 | BO20: {=IF(BO19=9999999,9999999,INDEX(stateTaxData[],MATCH(1,(stateTaxData[stateName]=BO$1)*(stateTaxData[taxYear]=$B$4)*(stateTaxData[FilingStatusFlag]=$B$8),0),MATCH($E20,stateTaxData[#Headers],0)))} -> 9999999 | BQ20: {=IF(BQ19=9999999,9999999,INDEX(stateTaxData[],MATCH(1,(stateTaxData[stateName]=BQ$1)*(stateTaxData[taxYear]=$B$4)*(stateTaxData[FilingStatusFlag]=$B$8),0),MATCH($E20,stateTaxData[#Headers],0)))} -> 9999999 | BT20: {=IF(BT19=9999999,9999999,INDEX(stateTaxData[],MATCH(1,(stateTaxData[stateName]=BT$1)*(stateTaxData[taxYear]=$B$4)*(stateTaxData[FilingStatusFlag]=$B$8),0),MATCH($E20,stateTaxData[#Headers],0)))} -> 9999999 | BU20: {=IF(BU19=9999999,9999999,INDEX(stateTaxData[],MATCH(1,(stateTaxData[stateName]=BU$1)*(stateTaxData[taxYear]=$B$4)*(stateTaxData[FilingStatusFlag]=$B$8),0),MATCH($E20,stateTaxData[#Headers],0)))} -> 9999999 | BV20: {=IF(BV19=9999999,9999999,INDEX(stateTaxData[],MATCH(1,(stateTaxData[stateName]=BV$1)*(stateTaxData[taxYear]=$B$4)*(stateTaxData[FilingStatusFlag]=$B$8),0),MATCH($E20,stateTaxData[#Headers],0)))} -> 9999999 | BW20: {=IF(BW19=9999999,9999999,INDEX(stateTaxData[],MATCH(1,(stateTaxData[stateName]=BW$1)*(stateTaxData[taxYear]=$B$4)*(stateTaxData[FilingStatusFlag]=$B$8),0),MATCH($E20,stateTaxData[#Headers],0)))} -> 9999999 | BX20: {=IF(BX19=9999999,9999999,INDEX(stateTaxData[],MATCH(1,(stateTaxData[stateName]=BX$1)*(stateTaxData[taxYear]=$B$4)*(stateTaxData[FilingStatusFlag]=$B$8),0),MATCH($E20,stateTaxData[#Headers],0)))} -> 9999999 | BY20: {=IF(BY19=9999999,9999999,INDEX(stateTaxData[],MATCH(1,(stateTaxData[stateName]=BY$1)*(stateTaxData[taxYear]=$B$4)*(stateTaxData[FilingStatusFlag]=$B$8),0),MATCH($E20,stateTaxData[#Headers],0)))} -> 9999999 | BZ20: {=IF(BZ19=9999999,9999999,INDEX(stateTaxData[],MATCH(1,(stateTaxData[stateName]=BZ$1)*(stateTaxData[taxYear]=$B$4)*(stateTaxData[FilingStatusFlag]=$B$8),0),MATCH($E20,stateTaxData[#Headers],0)))} -> 5000000 | CA20: {=IF(CA19=9999999,9999999,INDEX(stateTaxData[],MATCH(1,(stateTaxData[stateName]=CA$1)*(stateTaxData[taxYear]=$B$4)*(stateTaxData[FilingStatusFlag]=$B$8),0),MATCH($E20,stateTaxData[#Headers],0)))} -> 9999999 | CC20: {=IF(CC19=9999999,9999999,INDEX(stateTaxData[],MATCH(1,(stateTaxData[stateName]=CC$1)*(stateTaxData[taxYear]=$B$4)*(stateTaxData[FilingStatusFlag]=$B$8),0),MATCH($E20,stateTaxData[#Headers],0)))} -> 9999999 | CE20: {=IF(CE19=9999999,9999999,INDEX(stateTaxData[],MATCH(1,(stateTaxData[stateName]=CE$1)*(stateTaxData[taxYear]=$B$4)*(stateTaxData[FilingStatusFlag]=$B$8),0),MATCH($E20,stateTaxData[#Headers],0)))} -> 9999999 | CF20: {=IF(CF19=9999999,9999999,INDEX(stateTaxData[],MATCH(1,(stateTaxData[stateName]=CF$1)*(stateTaxData[taxYear]=$B$4)*(stateTaxData[FilingStatusFlag]=$B$8),0),MATCH($E20,stateTaxData[#Headers],0)))} -> 9999999 | CH20: {=IF(CH19=9999999,9999999,INDEX(stateTaxData[],MATCH(1,(stateTaxData[stateName]=CH$1)*(stateTaxData[taxYear]=$B$4)*(stateTaxData[FilingStatusFlag]=$B$8),0),MATCH($E20,stateTaxData[#Headers],0)))} -> 9999999 | CI20: {=IF(CI19=9999999,9999999,INDEX(stateTaxData[],MATCH(1,(stateTaxData[stateName]=CI$1)*(stateTaxData[taxYear]=$B$4)*(stateTaxData[FilingStatusFlag]=$B$8),0),MATCH($E20,stateTaxData[#Headers],0)))} -> 9999999 | CK20: {=IF(CK19=9999999,9999999,INDEX(stateTaxData[],MATCH(1,(stateTaxData[stateName]=CK$1)*(stateTaxData[taxYear]=$B$4)*(stateTaxData[FilingStatusFlag]=$B$8),0),MATCH($E20,stateTaxData[#Headers],0)))} -> 9999999 | CL20: {=IF(CL19=9999999,9999999,INDEX(stateTaxData[],MATCH(1,(stateTaxData[stateName]=CL$1)*(stateTaxData[taxYear]=$B$4)*(stateTaxData[FilingStatusFlag]=$B$8),0),MATCH($E20,stateTaxData[#Headers],0)))} -> 9999999 | CN20: {=IF(CN19=9999999,9999999,INDEX(stateTaxData[],MATCH(1,(stateTaxData[stateName]=CN$1)*(stateTaxData[taxYear]=$B$4)*(stateTaxData[FilingStatusFlag]=$B$8),0),MATCH($E20,stateTaxData[#Headers],0)))} -> 9999999 | CO20: {=IF(CO19=9999999,9999999,INDEX(stateTaxData[],MATCH(1,(stateTaxData[stateName]=CO$1)*(stateTaxData[taxYear]=$B$4)*(stateTaxData[FilingStatusFlag]=$B$8),0),MATCH($E20,stateTaxData[#Headers],0)))} -> 9999999 | CP20: {=IF(CP19=9999999,9999999,INDEX(stateTaxData[],MATCH(1,(stateTaxData[stateName]=CP$1)*(stateTaxData[taxYear]=$B$4)*(stateTaxData[FilingStatusFlag]=$B$8),0),MATCH($E20,stateTaxData[#Headers],0)))} -> 9999999 | CR20: {=IF(CR19=9999999,9999999,INDEX(stateTaxData[],MATCH(1,(stateTaxData[stateName]=CR$1)*(stateTaxData[taxYear]=$B$4)*(stateTaxData[FilingStatusFlag]=$B$8),0),MATCH($E20,stateTaxData[#Headers],0)))} -> 9999999 | CU20: {=IF(CU19=9999999,9999999,INDEX(stateTaxData[],MATCH(1,(stateTaxData[stateName]=CU$1)*(stateTaxData[taxYear]=$B$4)*(stateTaxData[FilingStatusFlag]=$B$8),0),MATCH($E20,stateTaxData[#Headers],0)))} -> 9999999 | CV20: {=IF(CV19=9999999,9999999,INDEX(stateTaxData[],MATCH(1,(stateTaxData[stateName]=CV$1)*(stateTaxData[taxYear]=$B$4)*(stateTaxData[FilingStatusFlag]=$B$8),0),MATCH($E20,stateTaxData[#Headers],0)))} -> 9999999 | CW20: {=IF(CW19=9999999,9999999,INDEX(stateTaxData[],MATCH(1,(stateTaxData[stateName]=CW$1)*(stateTaxData[taxYear]=$B$4)*(stateTaxData[FilingStatusFlag]=$B$8),0),MATCH($E20,stateTaxData[#Headers],0)))} -> 9999999 | CX20: {=IF(CX19=9999999,9999999,INDEX(stateTaxData[],MATCH(1,(stateTaxData[stateName]=CX$1)*(stateTaxData[taxYear]=$B$4)*(stateTaxData[FilingStatusFlag]=$B$8),0),MATCH($E20,stateTaxData[#Headers],0)))} -> 9999999 | DB20: {=IF(DB19=9999999,9999999,INDEX(stateTaxData[],MATCH(1,(stateTaxData[stateName]=DB$1)*(stateTaxData[taxYear]=$B$4)*(stateTaxData[FilingStatusFlag]=$B$8),0),MATCH($E20,stateTaxData[#Headers],0)))} -> 9999999 | DC20: {=IF(DC19=9999999,9999999,INDEX(stateTaxData[],MATCH(1,(stateTaxData[stateName]=DC$1)*(stateTaxData[taxYear]=$B$4)*(stateTaxData[FilingStatusFlag]=$B$8),0),MATCH($E20,stateTaxData[#Headers],0)))} -> 9999999 | ET20: 2. earnings cap | EU20: 8750
